Workbook

Sheet Read Me
A1: PROJECT NIGHTFALL
A2: AVOD content acquisition valuation model
A3: Prepared by Tanmay Srivastava
A4: Independent analytical case study using synthetic assumptions. Not based on proprietary company information.
A6: THE QUESTION
A7: Should an ad-supported streaming platform acquire Project Nightfall, under what deal structure, and what is the maximum economically supportable bid?
A8: Project Nightfall is a fictional package of five action and thriller features offered on a 24-month exclusive U.S. AVOD licence. All titles, performance assumptions, costs and deal terms are invented for this exercise.
A10: HOW TO USE THE MODEL
A11: 1. Set the scenario on the Scenarios sheet. The selector drives every downstream sheet. Scenarios move operating drivers only; no output is overridden.
A12: 2. Read the answer on the Executive Summary sheet. Price, returns, preferred structure and portfolio risk are all model outputs.
A13: 3. Check the QA Controls sheet before relying on any number. Fourteen automated controls reconcile the model.
A14: 4. Edit inputs only in the blue cells on Assumptions, Title Inputs and the scenario driver table.
A16: SHEET MAP
A17: Assumptions | B17: Term, required return, monetisation and cost globals, and the terms of all three deal structures.
A18: Title Inputs | B18: Twenty-three assumptions for each of the five titles, including judgement overlays.
A19: Monthly Viewing Forecast | B19: Monthly viewers, viewing hours, monetised impressions and gross advertising revenue, by title and scenario.
A20: Title Economics | B20: Monthly incremental revenue, follow-on value, costs and contribution by title and scenario, plus the active-scenario title summary.
A21: Deal Structures | B21: Monthly payment mechanics for the fixed fee, the guarantee plus revenue share, and the performance fee with earn-outs.
A22: Scenarios | B22: Scenario selector, operating drivers, scenario results and the pricing conclusions.
A23: Sensitivities | B23: Two-way sensitivity grids, break-even analysis, title ranking, concentration and the cash flow profile.
A24: Executive Summary | B24: The recommendation and the figures used in the accompanying presentation.
A25: QA Controls | B25: Automated reconciliation controls with PASS or FAIL results.
A27: COLOUR AND FORMATTING CONVENTION
A28: Blue text on a pale fill: a direct input. Edit these.
A29: Black text: a formula calculated on the same sheet.
A30: Green text: a link to another sheet.
A31: Shaded cells: totals and headline outputs.
A33: CORE FORMULAS
A34: Viewing hours = unique viewers x starts per viewer x runtime x completion rate / 60
A35: Monetised ad impressions = viewing hours x ad opportunities per hour x fill rate
A36: Advertising revenue = monetised impressions / 1,000 x net CPM
A37: Incremental advertising revenue = advertising revenue x incrementality rate
A38: Contribution before licence fee = incremental advertising revenue + follow-on engagement value - marketing - delivery and QC - variable serving costs
A39: Contribution after licence fee = contribution before licence fee - allocated licence fee
... A55: Sensitivity grids scale the Base monthly profile uniformly and therefore hold the shape of the decay curve constant.

Sheet Assumptions
A1: PROJECT NIGHTFALL
A2: Global assumptions and deal terms
A3: Independent analytical case study using synthetic assumptions. Not based on proprietary company information.
A5: PACKAGE AND LICENCE TERM
A6: Package name | C6: Project Nightfall
A7: Rights granted | C7: U.S. exclusive AVOD, all devices
A8: Licence term (months) | C8: 24 | E8: Model horizon; no renewal value assumed
A9: Titles in package | C9: 5
A10: Seller initial ask - fixed fee ($) | C10: 2500000 | E10: Opening position quoted by the distributor
A12: RETURN AND DISCOUNTING
A13: Required return (annual, nominal) | C13: 0.12 | E13: Hurdle applied to content acquisition capital
A14: Monthly discount rate | C14: =(1+Assumptions!$C$13)^(1/12)-1 -> 0.0094887929 | E14: Cash flows discounted at end of each month
A15: Target portfolio ROI for pricing test | C15: 0.2 | E15: Second pricing test alongside downside break-even
A16: Opening offer as % of target price | C16: 0.88 | E16: Leaves negotiating room below the target
A18: MONETISATION AND COST GLOBALS
A19: Follow-on engagement value ($ per incremental viewing hour) | C19: 0.045 | E19: Modelled incremental benefit; held separate from attributable ad revenue
A20: Variable serving cost ($ per viewing hour) | C20: 0.019 | E20: CDN, encoding, packaging and DRM
A22: MARKETING SPEND PROFILE (% OF TITLE MARKETING SUPPORT)
A23: Month 1 | C23: 0.55
A24: Month 2 | C24: 0.25
A25: Month 3 | C25: 0.12
A26: Month 4 | C26: 0.08
A27: Check: profile sums to 100% | C27: =SUM(C23:C26) -> 1
A29: FIXED-FEE PAYMENT TERMS (STRUCTURE A)
A30: First instalment (% of fee) | C30: 0.5 | E30: Paid on delivery and acceptance
A31: First instalment month | C31: 1
A32: Second instalment (% of fee) | C32: 0.5 | E32: Paid on the six-month anniversary
A33: Second instalment month | C33: 7
A34: PV factor on one dollar of fixed fee | C34: =Assumptions!$C$30/(1+Assumptions!$C$14)^Assumptions!$C$31+Assumptions!$C$32/(1+Assumptions!$C$14)^Assumptions!$C$33 -> 0.9633149 | E34: Used to convert a headline fee into present value
A36: STRUCTURE B - MINIMUM GUARANTEE PLUS REVENUE SHARE
A37: Minimum guarantee ($) | C37: 950000 | E37: Paid month 1, creditable against revenue share
A38: Licensor share of attributable gross ad revenue | C38: 0.28
A40: STRUCTURE C - PERFORMANCE FEE WITH EARN-OUTS
A41: Base fee ($) | C41: 850000 | E41: Paid month 1 on delivery
A42: Earn-out 1 payment ($) | C42: 250000
A43: Earn-out 1 trigger - cumulative viewing hours by month 12 | C43: 12750000
A44: Earn-out 2 payment ($) | C44: 250000
A45: Earn-out 2 trigger - cumulative viewing hours by month 18 | C45: 14500000
A46: Earn-out 3 payment ($) | C46: 300000
A47: Earn-out 3 trigger - cumulative viewing hours by month 24 | C47: 17000000
A49: All figures are illustrative and constructed for this case study. They are not observed market data.

Sheet Title Inputs
A1: PROJECT NIGHTFALL
A2: Title-level assumptions (five titles)
A3: Independent analytical case study using synthetic assumptions. Not based on proprietary company information.
A5: TITLE PROFILE
A6: Line item | C6: Title 1 | D6: Title 2 | E6: Title 3 | F6: Title 4 | G6: Title 5 | H6: Portfolio | I6: Notes
A7: Fictional title | C7: Nightfall Protocol | D7: Ash Ridge | E7: Cold Harbor | F7: The Quiet Depth | G7: Vector Nine
A8: Genre | C8: Action | D8: Action | E8: Thriller | F8: Thriller | G8: Thriller
A9: Subgenre | C9: Special-ops thriller | D9: Survival action | E9: Espionage thriller | F9: Submarine thriller | G9: Cyber thriller
A10: Release year | C10: 2021 | D10: 2022 | E10: 2019 | F10: 2018 | G10: 2023 | I10: Held as text so it is not formatted as a number
A11: Runtime (minutes) | C11: 118 | D11: 112 | E11: 106 | F11: 124 | G11: 99
A12: Comparable-performance tier | C12: Tier 1 - Wide theatrical | D12: Tier 2 - Limited theatrical | E12: Tier 2 - Limited theatrical | F12: Tier 3 - Direct to streaming | G12: Tier 4 - Festival / niche | I12: Internal tiering of comparable library performance
A14: AUDIENCE AND VIEWING
A15: Projected unique viewers - lifetime, base curve | C15: 3600000 | D15: 3050000 | E15: 2500000 | F15: 1650000 | G15: 850000 | H15: =SUM(C15:G15) -> 11650000 | I15: Lifetime total over the 24-month window at the base decay rate
A16: Starts per viewer | C16: 1.3 | D16: 1.24 | E16: 1.2 | F16: 1.13 | G16: 1.08 | I16: Total starts divided by unique viewers
A17: Repeat viewing rate | C17: =C16-1 -> 0.3 | D17: =D16-1 -> 0.24 | E17: =E16-1 -> 0.2 | F17: =F16-1 -> 0.13 | G17: =G16-1 -> 0.08 | I17: Starts per viewer less one; the share of viewing that is a return visit
A18: Completion rate | C18: 0.64 | D18: 0.61 | E18: 0.59 | F18: 0.51 | G18: 0.45
A19: Average minutes viewed per start | C19: =C11*C18 -> 75.52 | D19: =D11*D18 -> 68.32 | E19: =E11*E18 -> 62.54 | F19: =F11*F18 -> 63.24 | G19: =G11*G18 -> 44.55 | I19: Runtime multiplied by completion rate
A20: Monthly viewing decay rate | C20: 0.115 | D20: 0.12 | E20: 0.128 | F20: 0.14 | G20: 0.15 | I20: Month-on-month decline in unique viewers
A21: Decay curve normaliser (24 months) | C21: =(1-(1-C20)^Assumptions!$C$8)/C20 -> 8.2322686 | D21: =(1-(1-D20)^Assumptions!$C$8)/D20 -> 7.9457163 | E21: =(1-(1-E20)^Assumptions!$C$8)/E20 -> 7.5206325 | F21: =(1-(1-F20)^Assumptions!$C$8)/F20 -> 6.9515044 | G21: =(1-(1-G20)^Assumptions!$C$8)/G20 -> 6.5317819 | I21: Geometric sum of the base decay curve; converts lifetime viewers into a month-1 base
A23: ADVERTISING MONETISATION
A24: Ad opportunities per viewing hour | C24: 16 | D24: 16 | E24: 15.5 | F24: 15 | G24: 15 | I24: 30-second equivalent impressions available per hour
A25: Ad fill rate | C25: 0.82 | D25: 0.81 | E25: 0.8 | F25: 0.77 | G25: 0.75
A26: Net advertising CPM ($) | C26: 25.5 | D26: 24 | E26: 23 | F26: 21 | G26: 19.5 | I26: Net of ad-serving and sales costs
A27: Incrementality rate | C27: 0.62 | D27: 0.58 | E27: 0.55 | F27: 0.47 | G27: 0.4 | I27: Share of viewing not displaced from other owned content
A28: Cannibalisation rate | C28: =1-C27 -> 0.38 | D28: =1-D27 -> 0.42 | E28: =1-E27 -> 0.45 | F28: =1-F27 -> 0.53 | G28: =1-G27 -> 0.6 | I28: One less the incrementality rate
A30: COSTS AND ALLOCATION
A31: Marketing support ($) | C31: 165000 | D31: 130000 | E31: 100000 | F31: 72000 | G31: 58000 | H31: =SUM(C31:G31) -> 525000
A32: Delivery, localisation and QC ($) | C32: 58000 | D32: 52000 | E32: 46000 | F32: 44000 | G32: 40000 | H32: =SUM(C32:G32) -> 240000
A33: Variable serving cost ($ per viewing hour) | C33: =Assumptions!$C$20 -> 0.019 | D33: =Assumptions!$C$20 -> 0.019 | E33: =Assumptions!$C$20 -> 0.019 | F33: =Assumptions!$C$20 -> 0.019 | G33: =Assumptions!$C$20 -> 0.019 | I33: Linked to the global rate on Assumptions
A34: Follow-on engagement value ($ per incremental viewing hour) | C34: =Assumptions!$C$19 -> 0.045 | D34: =Assumptions!$C$19 -> 0.045 | E34: =Assumptions!$C$19 -> 0.045 | F34: =Assumptions!$C$19 -> 0.045 | G34: =Assumptions!$C$19 -> 0.045 | I34: Linked to the global rate on Assumptions; reported separately from ad revenue
A35: Allocated licence fee share of package | C35: 0.32 | D35: 0.26 | E35: 0.2 | F35: 0.13 | G35: 0.09 | H35: =SUM(C35:G35) -> 1 | I35: Negotiated allocation used for title-level economics; must total 100%
A37: JUDGEMENT OVERLAYS
A38: Forecast confidence | C38: High | D38: High | E38: Medium | F38: Medium | G38: Low
A39: Risk rating | C39: Low | D39: Low | E39: Medium | F39: Medium | G39: High
A40: Portfolio role | C40: Anchor | D40: Anchor | E40: Supporting | F40: Filler | G40: Dilutive
A42: Blue cells are direct inputs. Green cells link to another sheet. Black cells are formulas. All values are illustrative.

Sheet Monthly Viewing Forecast
A1: PROJECT NIGHTFALL
A2: Monthly viewing, impressions and gross advertising revenue by title
A3: Independent analytical case study using synthetic assumptions. Not based on proprietary company information.
A4: Scenario | B4: Title | C4: Month | D4: Total | E4: 1 | F4: 2 | G4: 3 | H4: 4 | I4: 5 | J4: 6 | K4: 7 | L4: 8 | M4: 9 | N4: 10 | O4: 11 | P4: 12 | Q4: 13 | R4: 14 | S4: 15 | T4: 16 | U4: 17 | V4: 18 | W4: 19 | X4: 20 | Y4: 21 | Z4: 22 | AA4: 23 | AB4: 24
A6: DOWNSIDE SCENARIO
A7: Downside | B7: Nightfall Protocol | C7: Monthly unique viewers | D7: =SUM(E7:AB7) -> 3334895.1 | E7: =Scenarios!$C$23*(1-Scenarios!$C$22)^(E$4-1) -> 428557.45 | F7: =Scenarios!$C$23*(1-Scenarios!$C$22)^(F$4-1) -> 375844.88 | G7: =Scenarios!$C$23*(1-Scenarios!$C$22)^(G$4-1) -> 329615.96 | H7: =Scenarios!$C$23*(1-Scenarios!$C$22)^(H$4-1) -> 289073.2 | I7: =Scenarios!$C$23*(1-Scenarios!$C$22)^(I$4-1) -> 253517.19 | J7: =Scenarios!$C$23*(1-Scenarios!$C$22)^(J$4-1) -> 222334.58 | K7: =Scenarios!$C$23*(1-Scenarios!$C$22)^(K$4-1) -> 194987.43 | L7: =Scenarios!$C$23*(1-Scenarios!$C$22)^(L$4-1) -> 171003.97 | ... AB7: =Scenarios!$C$23*(1-Scenarios!$C$22)^(AB$4-1) -> 20941.11
C8: Share of modelled lifetime viewers | D8: =SUM(E8:AB8) -> 1 | E8: =E7/$D$7 -> 0.12850703 | F8: =F7/$D$7 -> 0.11270066 | G8: =G7/$D$7 -> 0.09883848 | H8: =H7/$D$7 -> 0.086681347 | I8: =I7/$D$7 -> 0.076019541 | J8: =J7/$D$7 -> 0.066669138 | K8: =K7/$D$7 -> 0.058468834 | L8: =L7/$D$7 -> 0.051277167 | ... AB8: =AB7/$D$7 -> 0.0062793909
C9: Viewing hours | D9: =SUM(E9:AB9) -> 5347642.1 | E9: =E7*'Title Inputs'!$C$16*'Title Inputs'!$C$11*Scenarios!$C$24/60 -> 687209.58 | F9: =F7*'Title Inputs'!$C$16*'Title Inputs'!$C$11*Scenarios!$C$24/60 -> 602682.8 | G9: =G7*'Title Inputs'!$C$16*'Title Inputs'!$C$11*Scenarios!$C$24/60 -> 528552.82 | H9: =H7*'Title Inputs'!$C$16*'Title Inputs'!$C$11*Scenarios!$C$24/60 -> 463540.82 | I9: =I7*'Title Inputs'!$C$16*'Title Inputs'!$C$11*Scenarios!$C$24/60 -> 406525.3 | J9: =J7*'Title Inputs'!$C$16*'Title Inputs'!$C$11*Scenarios!$C$24/60 -> 356522.69 | K9: =K7*'Title Inputs'!$C$16*'Title Inputs'!$C$11*Scenarios!$C$24/60 -> 312670.4 | L9: =L7*'Title Inputs'!$C$16*'Title Inputs'!$C$11*Scenarios!$C$24/60 -> 274211.94 | ... AB9: =AB7*'Title Inputs'!$C$16*'Title Inputs'!$C$11*Scenarios!$C$24/60 -> 33579.935
C10: Monetised ad impressions | D10: =SUM(E10:AB10) -> 68757843 | E10: =E9*'Title Inputs'!$C$24*Scenarios!$C$25 -> 8835865.9 | F10: =F9*'Title Inputs'!$C$24*Scenarios!$C$25 -> 7749054.4 | G10: =G9*'Title Inputs'!$C$24*Scenarios!$C$25 -> 6795920.7 | H10: =H9*'Title Inputs'!$C$24*Scenarios!$C$25 -> 5960022.4 | I10: =I9*'Title Inputs'!$C$24*Scenarios!$C$25 -> 5226939.7 | J10: =J9*'Title Inputs'!$C$24*Scenarios!$C$25 -> 4584026.1 | K10: =K9*'Title Inputs'!$C$24*Scenarios!$C$25 -> 4020190.9 | L10: =L9*'Title Inputs'!$C$24*Scenarios!$C$25 -> 3525707.4 | ... AB10: =AB9*'Title Inputs'!$C$24*Scenarios!$C$25 -> 431757.37
C11: Gross advertising revenue ($) | D11: =SUM(E11:AB11) -> 1683192 | E11: =E10/1000*Scenarios!$C$26 -> 216302 | F11: =F10/1000*Scenarios!$C$26 -> 189696.85 | G11: =G10/1000*Scenarios!$C$26 -> 166364.14 | H11: =H10/1000*Scenarios!$C$26 -> 145901.35 | I11: =I10/1000*Scenarios!$C$26 -> 127955.48 | J11: =J10/1000*Scenarios!$C$26 -> 112216.96 | K11: =K10/1000*Scenarios!$C$26 -> 98414.273 | L11: =L10/1000*Scenarios!$C$26 -> 86309.317 | ... AB11: =AB10/1000*Scenarios!$C$26 -> 10569.42
A13: Downside | B13: Ash Ridge | C13: Monthly unique viewers | D13: =SUM(E13:AB13) -> 2829093.1 | E13: =Scenarios!$D$23*(1-Scenarios!$D$22)^(E$4-1) -> 376177.54 | F13: =Scenarios!$D$23*(1-Scenarios!$D$22)^(F$4-1) -> 328026.81 | G13: =Scenarios!$D$23*(1-Scenarios!$D$22)^(G$4-1) -> 286039.38 | H13: =Scenarios!$D$23*(1-Scenarios!$D$22)^(H$4-1) -> 249426.34 | I13: =Scenarios!$D$23*(1-Scenarios!$D$22)^(I$4-1) -> 217499.77 | J13: =Scenarios!$D$23*(1-Scenarios!$D$22)^(J$4-1) -> 189659.8 | K13: =Scenarios!$D$23*(1-Scenarios!$D$22)^(K$4-1) -> 165383.34 | L13: =Scenarios!$D$23*(1-Scenarios!$D$22)^(L$4-1) -> 144214.28 | ... AB13: =Scenarios!$D$23*(1-Scenarios!$D$22)^(AB$4-1) -> 16116.548
C14: Share of modelled lifetime viewers | D14: =SUM(E14:AB14) -> 1 | E14: =E13/$D$13 -> 0.13296754 | F14: =F13/$D$13 -> 0.11594769 | G14: =G13/$D$13 -> 0.10110639 | H14: =H13/$D$13 -> 0.088164771 | I14: =I13/$D$13 -> 0.076879681 | J14: =J13/$D$13 -> 0.067039081 | K14: =K13/$D$13 -> 0.058458079 | L14: =L13/$D$13 -> 0.050975445 | ... AB14: =AB13/$D$13 -> 0.0056967188
C15: Viewing hours | D15: =SUM(E15:AB15) -> 3914637.9 | E15: =E13*'Title Inputs'!$D$16*'Title Inputs'!$D$11*Scenarios!$D$24/60 -> 520519.77 | F15: =F13*'Title Inputs'!$D$16*'Title Inputs'!$D$11*Scenarios!$D$24/60 -> 453893.24 | G15: =G13*'Title Inputs'!$D$16*'Title Inputs'!$D$11*Scenarios!$D$24/60 -> 395794.91 | H15: =H13*'Title Inputs'!$D$16*'Title Inputs'!$D$11*Scenarios!$D$24/60 -> 345133.16 | I15: =I13*'Title Inputs'!$D$16*'Title Inputs'!$D$11*Scenarios!$D$24/60 -> 300956.11 | J15: =J13*'Title Inputs'!$D$16*'Title Inputs'!$D$11*Scenarios!$D$24/60 -> 262433.73 | K15: =K13*'Title Inputs'!$D$16*'Title Inputs'!$D$11*Scenarios!$D$24/60 -> 228842.21 | L15: =L13*'Title Inputs'!$D$16*'Title Inputs'!$D$11*Scenarios!$D$24/60 -> 199550.41 | ... AB15: =AB13*'Title Inputs'!$D$16*'Title Inputs'!$D$11*Scenarios!$D$24/60 -> 22300.592
C16: Monetised ad impressions | D16: =SUM(E16:AB16) -> 49719033 | E16: =E15*'Title Inputs'!$D$24*Scenarios!$D$25 -> 6611017.5 | F16: =F15*'Title Inputs'!$D$24*Scenarios!$D$25 -> 5764807.3 | G16: =G15*'Title Inputs'!$D$24*Scenarios!$D$25 -> 5026911.9 | H16: =H15*'Title Inputs'!$D$24*Scenarios!$D$25 -> 4383467.2 | I16: =I15*'Title Inputs'!$D$24*Scenarios!$D$25 -> 3822383.4 | J16: =J15*'Title Inputs'!$D$24*Scenarios!$D$25 -> 3333118.3 | K16: =K15*'Title Inputs'!$D$24*Scenarios!$D$25 -> 2906479.2 | L16: =L15*'Title Inputs'!$D$24*Scenarios!$D$25 -> 2534449.8 | ... AB16: =AB15*'Title Inputs'!$D$24*Scenarios!$D$25 -> 283235.35
C17: Gross advertising revenue ($) | D17: =SUM(E17:AB17) -> 1145526.5 | E17: =E16/1000*Scenarios!$D$26 -> 152317.84 | F17: =F16/1000*Scenarios!$D$26 -> 132821.16 | G17: =G16/1000*Scenarios!$D$26 -> 115820.05 | H17: =H16/1000*Scenarios!$D$26 -> 100995.08 | I17: =I16/1000*Scenarios!$D$26 -> 88067.714 | J17: =J16/1000*Scenarios!$D$26 -> 76795.046 | K17: =K16/1000*Scenarios!$D$26 -> 66965.28 | L17: =L16/1000*Scenarios!$D$26 -> 58393.725 | ... AB17: =AB16/1000*Scenarios!$D$26 -> 6525.7425
A19: Downside | B19: Cold Harbor | C19: Monthly unique viewers | D19: =SUM(E19:AB19) -> 2323640.8 | E19: =Scenarios!$E$23*(1-Scenarios!$E$22)^(E$4-1) -> 325770.47 | F19: =Scenarios!$E$23*(1-Scenarios!$E$22)^(F$4-1) -> 281465.69 | G19: =Scenarios!$E$23*(1-Scenarios!$E$22)^(G$4-1) -> 243186.35 | H19: =Scenarios!$E$23*(1-Scenarios!$E$22)^(H$4-1) -> 210113.01 | I19: =Scenarios!$E$23*(1-Scenarios!$E$22)^(I$4-1) -> 181537.64 | J19: =Scenarios!$E$23*(1-Scenarios!$E$22)^(J$4-1) -> 156848.52 | K19: =Scenarios!$E$23*(1-Scenarios!$E$22)^(K$4-1) -> 135517.12 | L19: =Scenarios!$E$23*(1-Scenarios!$E$22)^(L$4-1) -> 117086.79 | ... AB19: =Scenarios!$E$23*(1-Scenarios!$E$22)^(AB$4-1) -> 11290.88
C20: Share of modelled lifetime viewers | D20: =SUM(E20:AB20) -> 1 | E20: =E19/$D$19 -> 0.14019829 | F20: =F19/$D$19 -> 0.12113132 | G20: =G19/$D$19 -> 0.10465746 | H20: =H19/$D$19 -> 0.090424048 | I20: =I19/$D$19 -> 0.078126378 | J20: =J19/$D$19 -> 0.06750119 | K20: =K19/$D$19 -> 0.058321029 | L20: =L19/$D$19 -> 0.050389369 | ... AB20: =AB19/$D$19 -> 0.0048591331
C21: Viewing hours | D21: =SUM(E21:AB21) -> 2848281.7 | E21: =E19*'Title Inputs'!$E$16*'Title Inputs'!$E$11*Scenarios!$E$24/60 -> 399324.23 | F21: =F19*'Title Inputs'!$E$16*'Title Inputs'!$E$11*Scenarios!$E$24/60 -> 345016.13 | G21: =G19*'Title Inputs'!$E$16*'Title Inputs'!$E$11*Scenarios!$E$24/60 -> 298093.94 | H21: =H19*'Title Inputs'!$E$16*'Title Inputs'!$E$11*Scenarios!$E$24/60 -> 257553.16 | I21: =I19*'Title Inputs'!$E$16*'Title Inputs'!$E$11*Scenarios!$E$24/60 -> 222525.93 | J21: =J19*'Title Inputs'!$E$16*'Title Inputs'!$E$11*Scenarios!$E$24/60 -> 192262.41 | K21: =K19*'Title Inputs'!$E$16*'Title Inputs'!$E$11*Scenarios!$E$24/60 -> 166114.72 | L21: =L19*'Title Inputs'!$E$16*'Title Inputs'!$E$11*Scenarios!$E$24/60 -> 143523.12 | ... AB21: =AB19*'Title Inputs'!$E$16*'Title Inputs'!$E$11*Scenarios!$E$24/60 -> 13840.18
C22: Monetised ad impressions | D22: =SUM(E22:AB22) -> 34612319 | E22: =E21*'Title Inputs'!$E$24*Scenarios!$E$25 -> 4852588 | F22: =F21*'Title Inputs'!$E$24*Scenarios!$E$25 -> 4192636.1 | G22: =G21*'Title Inputs'!$E$24*Scenarios!$E$25 -> 3622437.6 | H22: =H21*'Title Inputs'!$E$24*Scenarios!$E$25 -> 3129786.1 | I22: =I21*'Title Inputs'!$E$24*Scenarios!$E$25 -> 2704135.2 | J22: =J21*'Title Inputs'!$E$24*Scenarios!$E$25 -> 2336372.8 | K22: =K21*'Title Inputs'!$E$24*Scenarios!$E$25 -> 2018626.1 | L22: =L21*'Title Inputs'!$E$24*Scenarios!$E$25 -> 1744092.9 | ... AB22: =AB21*'Title Inputs'!$E$24*Scenarios!$E$25 -> 168185.87
C23: Gross advertising revenue ($) | D23: =SUM(E23:AB23) -> 764240.01 | E23: =E22/1000*Scenarios!$E$26 -> 107145.14 | F23: =F22/1000*Scenarios!$E$26 -> 92573.404 | G23: =G22/1000*Scenarios!$E$26 -> 79983.421 | H23: =H22/1000*Scenarios!$E$26 -> 69105.676 | I23: =I22/1000*Scenarios!$E$26 -> 59707.304 | J23: =J22/1000*Scenarios!$E$26 -> 51587.111 | K23: =K22/1000*Scenarios!$E$26 -> 44571.264 | L23: =L22/1000*Scenarios!$E$26 -> 38509.572 | ... AB23: =AB22/1000*Scenarios!$E$26 -> 3713.544
A25: Downside | B25: The Quiet Depth | C25: Monthly unique viewers | D25: =SUM(E25:AB25) -> 1538054.5 | E25: =Scenarios!$F$23*(1-Scenarios!$F$22)^(E$4-1) -> 232611.52 | F25: =Scenarios!$F$23*(1-Scenarios!$F$22)^(F$4-1) -> 198185.02 | G25: =Scenarios!$F$23*(1-Scenarios!$F$22)^(G$4-1) -> 168853.63 | H25: =Scenarios!$F$23*(1-Scenarios!$F$22)^(H$4-1) -> 143863.3 | I25: =Scenarios!$F$23*(1-Scenarios!$F$22)^(I$4-1) -> 122571.53 | J25: =Scenarios!$F$23*(1-Scenarios!$F$22)^(J$4-1) -> 104430.94 | K25: =Scenarios!$F$23*(1-Scenarios!$F$22)^(K$4-1) -> 88975.162 | L25: =Scenarios!$F$23*(1-Scenarios!$F$22)^(L$4-1) -> 75806.838 | ... AB25: =Scenarios!$F$23*(1-Scenarios!$F$22)^(AB$4-1) -> 5844.4265
C26: Share of modelled lifetime viewers | D26: =SUM(E26:AB26) -> 1 | E26: =E25/$D$25 -> 0.1512375 | F26: =F25/$D$25 -> 0.12885435 | G26: =G25/$D$25 -> 0.10978391 | H26: =H25/$D$25 -> 0.093535888 | I26: =I25/$D$25 -> 0.079692577 | J26: =J25/$D$25 -> 0.067898075 | K26: =K25/$D$25 -> 0.05784916 | L26: =L25/$D$25 -> 0.049287484 | ... AB26: =AB25/$D$25 -> 0.0037998825
C27: Viewing hours | D27: =SUM(E27:AB27) -> 1795216.6 | E27: =E25*'Title Inputs'!$F$16*'Title Inputs'!$F$11*Scenarios!$F$24/60 -> 271504.07 | F27: =F25*'Title Inputs'!$F$16*'Title Inputs'!$F$11*Scenarios!$F$24/60 -> 231321.47 | G27: =G25*'Title Inputs'!$F$16*'Title Inputs'!$F$11*Scenarios!$F$24/60 -> 197085.89 | H27: =H25*'Title Inputs'!$F$16*'Title Inputs'!$F$11*Scenarios!$F$24/60 -> 167917.18 | I27: =I25*'Title Inputs'!$F$16*'Title Inputs'!$F$11*Scenarios!$F$24/60 -> 143065.44 | J27: =J25*'Title Inputs'!$F$16*'Title Inputs'!$F$11*Scenarios!$F$24/60 -> 121891.75 | K27: =K25*'Title Inputs'!$F$16*'Title Inputs'!$F$11*Scenarios!$F$24/60 -> 103851.77 | L27: =L25*'Title Inputs'!$F$16*'Title Inputs'!$F$11*Scenarios!$F$24/60 -> 88481.711 | ... AB27: =AB25*'Title Inputs'!$F$16*'Title Inputs'!$F$11*Scenarios!$F$24/60 -> 6821.6123
C28: Monetised ad impressions | D28: =SUM(E28:AB28) -> 20320057 | E28: =E27*'Title Inputs'!$F$24*Scenarios!$F$25 -> 3073154.6 | F28: =F27*'Title Inputs'!$F$24*Scenarios!$F$25 -> 2618327.7 | G28: =G27*'Title Inputs'!$F$24*Scenarios!$F$25 -> 2230815.2 | H28: =H27*'Title Inputs'!$F$24*Scenarios!$F$25 -> 1900654.6 | I28: =I27*'Title Inputs'!$F$24*Scenarios!$F$25 -> 1619357.7 | J28: =J27*'Title Inputs'!$F$24*Scenarios!$F$25 -> 1379692.8 | K28: =K27*'Title Inputs'!$F$24*Scenarios!$F$25 -> 1175498.2 | L28: =L27*'Title Inputs'!$F$24*Scenarios!$F$25 -> 1001524.5 | ... AB28: =AB27*'Title Inputs'!$F$24*Scenarios!$F$25 -> 77213.829
C29: Gross advertising revenue ($) | D29: =SUM(E29:AB29) -> 409652.35 | E29: =E28/1000*Scenarios!$F$26 -> 61954.797 | F29: =F28/1000*Scenarios!$F$26 -> 52785.487 | G29: =G28/1000*Scenarios!$F$26 -> 44973.235 | H29: =H28/1000*Scenarios!$F$26 -> 38317.196 | I29: =I28/1000*Scenarios!$F$26 -> 32646.251 | J29: =J28/1000*Scenarios!$F$26 -> 27814.606 | K29: =K28/1000*Scenarios!$F$26 -> 23698.044 | L29: =L28/1000*Scenarios!$F$26 -> 20190.734 | ... AB29: =AB28/1000*Scenarios!$F$26 -> 1556.6308
A31: Downside | B31: Vector Nine | C31: Monthly unique viewers | D31: =SUM(E31:AB31) -> 794138.63 | E31: =Scenarios!$G$23*(1-Scenarios!$G$22)^(E$4-1) -> 127530.28 | F31: =Scenarios!$G$23*(1-Scenarios!$G$22)^(F$4-1) -> 107380.5 | G31: =Scenarios!$G$23*(1-Scenarios!$G$22)^(G$4-1) -> 90414.38 | H31: =Scenarios!$G$23*(1-Scenarios!$G$22)^(H$4-1) -> 76128.908 | I31: =Scenarios!$G$23*(1-Scenarios!$G$22)^(I$4-1) -> 64100.541 | J31: =Scenarios!$G$23*(1-Scenarios!$G$22)^(J$4-1) -> 53972.655 | K31: =Scenarios!$G$23*(1-Scenarios!$G$22)^(K$4-1) -> 45444.976 | L31: =Scenarios!$G$23*(1-Scenarios!$G$22)^(L$4-1) -> 38264.67 | ... AB31: =Scenarios!$G$23*(1-Scenarios!$G$22)^(AB$4-1) -> 2442.2574
C32: Share of modelled lifetime viewers | D32: =SUM(E32:AB32) -> 1 | E32: =E31/$D$31 -> 0.16058945 | F32: =F31/$D$31 -> 0.13521632 | G32: =G31/$D$31 -> 0.11385214 | H32: =H31/$D$31 -> 0.0958635 | I32: =I31/$D$31 -> 0.080717067 | J32: =J31/$D$31 -> 0.06796377 | K32: =K31/$D$31 -> 0.057225495 | L32: =L31/$D$31 -> 0.048183866 | ... AB32: =AB31/$D$31 -> 0.003075354
C33: Viewing hours | D33: =SUM(E33:AB33) -> 624083.37 | E33: =E31*'Title Inputs'!$G$16*'Title Inputs'!$G$11*Scenarios!$G$24/60 -> 100221.2 | F33: =F31*'Title Inputs'!$G$16*'Title Inputs'!$G$11*Scenarios!$G$24/60 -> 84386.254 | G33: =G31*'Title Inputs'!$G$16*'Title Inputs'!$G$11*Scenarios!$G$24/60 -> 71053.226 | H33: =H31*'Title Inputs'!$G$16*'Title Inputs'!$G$11*Scenarios!$G$24/60 -> 59826.816 | I33: =I31*'Title Inputs'!$G$16*'Title Inputs'!$G$11*Scenarios!$G$24/60 -> 50374.179 | J33: =J31*'Title Inputs'!$G$16*'Title Inputs'!$G$11*Scenarios!$G$24/60 -> 42415.059 | K33: =K31*'Title Inputs'!$G$16*'Title Inputs'!$G$11*Scenarios!$G$24/60 -> 35713.48 | L33: =L31*'Title Inputs'!$G$16*'Title Inputs'!$G$11*Scenarios!$G$24/60 -> 30070.75 | ... AB33: =AB31*'Title Inputs'!$G$16*'Title Inputs'!$G$11*Scenarios!$G$24/60 -> 1919.2773
C34: Monetised ad impressions | D34: =SUM(E34:AB34) -> 6880519.2 | E34: =E33*'Title Inputs'!$G$24*Scenarios!$G$25 -> 1104938.8 | F34: =F33*'Title Inputs'!$G$24*Scenarios!$G$25 -> 930358.45 | G34: =G33*'Title Inputs'!$G$24*Scenarios!$G$25 -> 783361.81 | H34: =H33*'Title Inputs'!$G$24*Scenarios!$G$25 -> 659590.65 | I34: =I33*'Title Inputs'!$G$24*Scenarios!$G$25 -> 555375.33 | J34: =J33*'Title Inputs'!$G$24*Scenarios!$G$25 -> 467626.02 | K34: =K33*'Title Inputs'!$G$24*Scenarios!$G$25 -> 393741.11 | L34: =L33*'Title Inputs'!$G$24*Scenarios!$G$25 -> 331530.02 | ... AB34: =AB33*'Title Inputs'!$G$24*Scenarios!$G$25 -> 21160.032
C35: Gross advertising revenue ($) | D35: =SUM(E35:AB35) -> 128803.32 | E35: =E34/1000*Scenarios!$G$26 -> 20684.454 | F35: =F34/1000*Scenarios!$G$26 -> 17416.31 | G35: =G34/1000*Scenarios!$G$26 -> 14664.533 | H35: =H34/1000*Scenarios!$G$26 -> 12347.537 | I35: =I34/1000*Scenarios!$G$26 -> 10396.626 | J35: =J34/1000*Scenarios!$G$26 -> 8753.9592 | K35: =K34/1000*Scenarios!$G$26 -> 7370.8336 | L35: =L34/1000*Scenarios!$G$26 -> 6206.2419 | ... AB35: =AB34/1000*Scenarios!$G$26 -> 396.1158
B37: PORTFOLIO | C37: Portfolio unique viewers | D37: =$D$7+$D$13+$D$19+$D$25+$D$31 -> 10819822 | E37: =E7+E13+E19+E25+E31 -> 1490647.3 | F37: =F7+F13+F19+F25+F31 -> 1290902.9 | G37: =G7+G13+G19+G25+G31 -> 1118109.7 | H37: =H7+H13+H19+H25+H31 -> 968604.75 | I37: =I7+I13+I19+I25+I31 -> 839226.67 | J37: =J7+J13+J19+J25+J31 -> 727246.5 | K37: =K7+K13+K19+K25+K31 -> 630308.03 | L37: =L7+L13+L19+L25+L31 -> 546376.55 | ... AB37: =AB7+AB13+AB19+AB25+AB31 -> 56635.221
B38: PORTFOLIO | C38: Portfolio viewing hours | D38: =$D$9+$D$15+$D$21+$D$27+$D$33 -> 14529862 | E38: =E9+E15+E21+E27+E33 -> 1978778.9 | F38: =F9+F15+F21+F27+F33 -> 1717299.9 | G38: =G9+G15+G21+G27+G33 -> 1490580.8 | H38: =H9+H15+H21+H27+H33 -> 1293971.1 | I38: =I9+I15+I21+I27+I33 -> 1123447 | J38: =J9+J15+J21+J27+J33 -> 975525.64 | K38: =K9+K15+K21+K27+K33 -> 847192.58 | L38: =L9+L15+L21+L27+L33 -> 735837.93 | ... AB38: =AB9+AB15+AB21+AB27+AB33 -> 78461.596
B39: PORTFOLIO | C39: Portfolio monetised impressions | D39: =$D$10+$D$16+$D$22+$D$28+$D$34 -> 1.8028977e+08 | E39: =E10+E16+E22+E28+E34 -> 24477565 | F39: =F10+F16+F22+F28+F34 -> 21255184 | G39: =G10+G16+G22+G28+G34 -> 18459447 | H39: =H10+H16+H22+H28+H34 -> 16033521 | I39: =I10+I16+I22+I28+I34 -> 13928191 | J39: =J10+J16+J22+J28+J34 -> 12100836 | K39: =K10+K16+K22+K28+K34 -> 10514535 | L39: =L10+L16+L22+L28+L34 -> 9137304.7 | ... AB39: =AB10+AB16+AB22+AB28+AB34 -> 981552.46
B40: PORTFOLIO | C40: Portfolio gross advertising revenue ($) | D40: =$D$11+$D$17+$D$23+$D$29+$D$35 -> 4131414.2 | E40: =E11+E17+E23+E29+E35 -> 558404.24 | F40: =F11+F17+F23+F29+F35 -> 485293.21 | G40: =G11+G17+G23+G29+G35 -> 421805.38 | H40: =H11+H17+H23+H29+H35 -> 366666.84 | I40: =I11+I17+I23+I29+I35 -> 318773.38 | J40: =J11+J17+J23+J29+J35 -> 277167.68 | K40: =K11+K17+K23+K29+K35 -> 241019.7 | L40: =L11+L17+L23+L29+L35 -> 209609.59 | ... AB40: =AB11+AB17+AB23+AB29+AB35 -> 22761.454
C41: Cumulative viewing hours | D41: =AB41 -> 14529862 | E41: =SUM(E38:E38) -> 1978778.9 | F41: =SUM(E38:F38) -> 3696078.8 | G41: =SUM(E38:G38) -> 5186659.5 | H41: =SUM(E38:H38) -> 6480630.7 | I41: =SUM(E38:I38) -> 7604077.6 | J41: =SUM(E38:J38) -> 8579603.3 | K41: =SUM(E38:K38) -> 9426795.9 | L41: =SUM(E38:L38) -> 10162634 | M41: =SUM(E38:M38) -> 10801836 | N41: =SUM(E38:N38) -> 11357163 | O41: =SUM(E38:O38) -> 11839681 | P41: =SUM(E38:P38) -> 12258988 | Q41: =SUM(E38:Q38) -> 12623410 | R41: =SUM(E38:R38) -> 12940167 | S41: =SUM(E38:S38) -> 13215528 | T41: =SUM(E38:T38) -> 13454929 | U41: =SUM(E38:U38) -> 13663091 | V41: =SUM(E38:V38) -> 13844110 | W41: =SUM(E38:W38) -> 14001544 | X41: =SUM(E38:X38) -> 14138480 | Y41: =SUM(E38:Y38) -> 14257599 | Z41: =SUM(E38:Z38) -> 14361232 | AA41: =SUM(E38:AA38) -> 14451400 | AB41: =SUM(E38:AB38) -> 14529862
C42: Cumulative gross advertising revenue ($) | D42: =AB42 -> 4131414.2 | E42: =SUM(E40:E40) -> 558404.24 | F42: =SUM(E40:F40) -> 1043697.4 | G42: =SUM(E40:G40) -> 1465502.8 | H42: =SUM(E40:H40) -> 1832169.7 | I42: =SUM(E40:I40) -> 2150943 | J42: =SUM(E40:J40) -> 2428110.7 | K42: =SUM(E40:K40) -> 2669130.4 | L42: =SUM(E40:L40) -> 2878740 | M42: =SUM(E40:M40) -> 3061053 | N42: =SUM(E40:N40) -> 3219641.5 | O42: =SUM(E40:O40) -> 3357607.4 | P42: =SUM(E40:P40) -> 3477645.2 | Q42: =SUM(E40:Q40) -> 3582095.4 | R42: =SUM(E40:R40) -> 3672991.4 | S42: =SUM(E40:S40) -> 3752100.1 | T42: =SUM(E40:T40) -> 3820956.9 | U42: =SUM(E40:U40) -> 3880896.2 | V42: =SUM(E40:V40) -> 3933078 | W42: =SUM(E40:W40) -> 3978510.4 | X42: =SUM(E40:X40) -> 4018070.3 | Y42: =SUM(E40:Y40) -> 4052519.8 | Z42: =SUM(E40:Z40) -> 4082521.8 | AA42: =SUM(E40:AA40) -> 4108652.8 | AB42: =SUM(E40:AB40) -> 4131414.2
A45: BASE SCENARIO
A46: Base | B46: Nightfall Protocol | C46: Monthly unique viewers | D46: =SUM(E46:AB46) -> 3600000 | E46: =Scenarios!$C$32*(1-Scenarios!$C$31)^(E$4-1) -> 437303.52 | F46: =Scenarios!$C$32*(1-Scenarios!$C$31)^(F$4-1) -> 387013.61 | G46: =Scenarios!$C$32*(1-Scenarios!$C$31)^(G$4-1) -> 342507.05 | H46: =Scenarios!$C$32*(1-Scenarios!$C$31)^(H$4-1) -> 303118.74 | I46: =Scenarios!$C$32*(1-Scenarios!$C$31)^(I$4-1) -> 268260.08 | J46: =Scenarios!$C$32*(1-Scenarios!$C$31)^(J$4-1) -> 237410.17 | K46: =Scenarios!$C$32*(1-Scenarios!$C$31)^(K$4-1) -> 210108 | L46: =Scenarios!$C$32*(1-Scenarios!$C$31)^(L$4-1) -> 185945.58 | ... AB46: =Scenarios!$C$32*(1-Scenarios!$C$31)^(AB$4-1) -> 26331.657
C47: Share of modelled lifetime viewers | D47: =SUM(E47:AB47) -> 1 | E47: =E46/$D$46 -> 0.1214732 | F47: =F46/$D$46 -> 0.10750378 | G47: =G46/$D$46 -> 0.095140846 | H47: =H46/$D$46 -> 0.084199649 | I47: =I46/$D$46 -> 0.074516689 | J47: =J46/$D$46 -> 0.06594727 | K47: =K46/$D$46 -> 0.058363334 | L47: =L46/$D$46 -> 0.051651551 | ... AB47: =AB46/$D$46 -> 0.0073143493
C48: Viewing hours | D48: =SUM(E48:AB48) -> 5890560 | E48: =E46*'Title Inputs'!$C$16*'Title Inputs'!$C$11*Scenarios!$C$33/60 -> 715545.17 | F48: =F46*'Title Inputs'!$C$16*'Title Inputs'!$C$11*Scenarios!$C$33/60 -> 633257.47 | G48: =G46*'Title Inputs'!$C$16*'Title Inputs'!$C$11*Scenarios!$C$33/60 -> 560432.86 | H48: =H46*'Title Inputs'!$C$16*'Title Inputs'!$C$11*Scenarios!$C$33/60 -> 495983.08 | I48: =I46*'Title Inputs'!$C$16*'Title Inputs'!$C$11*Scenarios!$C$33/60 -> 438945.03 | J48: =J46*'Title Inputs'!$C$16*'Title Inputs'!$C$11*Scenarios!$C$33/60 -> 388466.35 | K48: =K46*'Title Inputs'!$C$16*'Title Inputs'!$C$11*Scenarios!$C$33/60 -> 343792.72 | L48: =L46*'Title Inputs'!$C$16*'Title Inputs'!$C$11*Scenarios!$C$33/60 -> 304256.56 | ... AB48: =AB46*'Title Inputs'!$C$16*'Title Inputs'!$C$11*Scenarios!$C$33/60 -> 43085.613
C49: Monetised ad impressions | D49: =SUM(E49:AB49) -> 77284147 | E49: =E48*'Title Inputs'!$C$24*Scenarios!$C$34 -> 9387952.6 | F49: =F48*'Title Inputs'!$C$24*Scenarios!$C$34 -> 8308338.1 | G49: =G48*'Title Inputs'!$C$24*Scenarios!$C$34 -> 7352879.2 | H49: =H48*'Title Inputs'!$C$24*Scenarios!$C$34 -> 6507298.1 | I49: =I48*'Title Inputs'!$C$24*Scenarios!$C$34 -> 5758958.8 | J49: =J48*'Title Inputs'!$C$24*Scenarios!$C$34 -> 5096678.5 | K49: =K48*'Title Inputs'!$C$24*Scenarios!$C$34 -> 4510560.5 | L49: =L48*'Title Inputs'!$C$24*Scenarios!$C$34 -> 3991846 | ... AB49: =AB48*'Title Inputs'!$C$24*Scenarios!$C$34 -> 565283.25
C50: Gross advertising revenue ($) | D50: =SUM(E50:AB50) -> 1970745.8 | E50: =E49/1000*Scenarios!$C$35 -> 239392.79 | F50: =F49/1000*Scenarios!$C$35 -> 211862.62 | G50: =G49/1000*Scenarios!$C$35 -> 187498.42 | H50: =H49/1000*Scenarios!$C$35 -> 165936.1 | I50: =I49/1000*Scenarios!$C$35 -> 146853.45 | J50: =J49/1000*Scenarios!$C$35 -> 129965.3 | K50: =K49/1000*Scenarios!$C$35 -> 115019.29 | L50: =L49/1000*Scenarios!$C$35 -> 101792.07 | ... AB50: =AB49/1000*Scenarios!$C$35 -> 14414.723
A52: Base | B52: Ash Ridge | C52: Monthly unique viewers | D52: =SUM(E52:AB52) -> 3050000 | E52: =Scenarios!$D$32*(1-Scenarios!$D$31)^(E$4-1) -> 383854.63 | F52: =Scenarios!$D$32*(1-Scenarios!$D$31)^(F$4-1) -> 337792.08 | G52: =Scenarios!$D$32*(1-Scenarios!$D$31)^(G$4-1) -> 297257.03 | H52: =Scenarios!$D$32*(1-Scenarios!$D$31)^(H$4-1) -> 261586.18 | I52: =Scenarios!$D$32*(1-Scenarios!$D$31)^(I$4-1) -> 230195.84 | J52: =Scenarios!$D$32*(1-Scenarios!$D$31)^(J$4-1) -> 202572.34 | K52: =Scenarios!$D$32*(1-Scenarios!$D$31)^(K$4-1) -> 178263.66 | L52: =Scenarios!$D$32*(1-Scenarios!$D$31)^(L$4-1) -> 156872.02 | ... AB52: =Scenarios!$D$32*(1-Scenarios!$D$31)^(AB$4-1) -> 20289.355
C53: Share of modelled lifetime viewers | D53: =SUM(E53:AB53) -> 1 | E53: =E52/$D$52 -> 0.12585398 | F53: =F52/$D$52 -> 0.1107515 | G53: =G52/$D$52 -> 0.09746132 | H53: =H52/$D$52 -> 0.085765962 | I53: =I52/$D$52 -> 0.075474047 | J53: =J52/$D$52 -> 0.066417161 | K53: =K52/$D$52 -> 0.058447102 | L53: =L52/$D$52 -> 0.051433449 | ... AB53: =AB52/$D$52 -> 0.0066522476
C54: Viewing hours | D54: =SUM(E54:AB54) -> 4306437.3 | E54: =E52*'Title Inputs'!$D$16*'Title Inputs'!$D$11*Scenarios!$D$33/60 -> 541982.27 | F54: =F52*'Title Inputs'!$D$16*'Title Inputs'!$D$11*Scenarios!$D$33/60 -> 476944.4 | G54: =G52*'Title Inputs'!$D$16*'Title Inputs'!$D$11*Scenarios!$D$33/60 -> 419711.07 | H54: =H52*'Title Inputs'!$D$16*'Title Inputs'!$D$11*Scenarios!$D$33/60 -> 369345.74 | I54: =I52*'Title Inputs'!$D$16*'Title Inputs'!$D$11*Scenarios!$D$33/60 -> 325024.25 | J54: =J52*'Title Inputs'!$D$16*'Title Inputs'!$D$11*Scenarios!$D$33/60 -> 286021.34 | K54: =K52*'Title Inputs'!$D$16*'Title Inputs'!$D$11*Scenarios!$D$33/60 -> 251698.78 | L54: =L52*'Title Inputs'!$D$16*'Title Inputs'!$D$11*Scenarios!$D$33/60 -> 221494.93 | ... AB54: =AB52*'Title Inputs'!$D$16*'Title Inputs'!$D$11*Scenarios!$D$33/60 -> 28647.487
C55: Monetised ad impressions | D55: =SUM(E55:AB55) -> 55811428 | E55: =E54*'Title Inputs'!$D$24*Scenarios!$D$34 -> 7024090.2 | F55: =F54*'Title Inputs'!$D$24*Scenarios!$D$34 -> 6181199.4 | G55: =G54*'Title Inputs'!$D$24*Scenarios!$D$34 -> 5439455.5 | H55: =H54*'Title Inputs'!$D$24*Scenarios!$D$34 -> 4786720.8 | I55: =I54*'Title Inputs'!$D$24*Scenarios!$D$34 -> 4212314.3 | J55: =J54*'Title Inputs'!$D$24*Scenarios!$D$34 -> 3706836.6 | K55: =K54*'Title Inputs'!$D$24*Scenarios!$D$34 -> 3262016.2 | L55: =L54*'Title Inputs'!$D$24*Scenarios!$D$34 -> 2870574.3 | ... AB55: =AB54*'Title Inputs'!$D$24*Scenarios!$D$34 -> 371271.44
C56: Gross advertising revenue ($) | D56: =SUM(E56:AB56) -> 1339474.3 | E56: =E55/1000*Scenarios!$D$35 -> 168578.16 | F56: =F55/1000*Scenarios!$D$35 -> 148348.79 | G56: =G55/1000*Scenarios!$D$35 -> 130546.93 | H56: =H55/1000*Scenarios!$D$35 -> 114881.3 | I56: =I55/1000*Scenarios!$D$35 -> 101095.54 | J56: =J55/1000*Scenarios!$D$35 -> 88964.078 | K56: =K55/1000*Scenarios!$D$35 -> 78288.389 | L56: =L55/1000*Scenarios!$D$35 -> 68893.782 | ... AB56: =AB55/1000*Scenarios!$D$35 -> 8910.5145
A58: Base | B58: Cold Harbor | C58: Monthly unique viewers | D58: =SUM(E58:AB58) -> 2500000 | E58: =Scenarios!$E$32*(1-Scenarios!$E$31)^(E$4-1) -> 332418.85 | F58: =Scenarios!$E$32*(1-Scenarios!$E$31)^(F$4-1) -> 289869.23 | G58: =Scenarios!$E$32*(1-Scenarios!$E$31)^(G$4-1) -> 252765.97 | H58: =Scenarios!$E$32*(1-Scenarios!$E$31)^(H$4-1) -> 220411.93 | I58: =Scenarios!$E$32*(1-Scenarios!$E$31)^(I$4-1) -> 192199.2 | J58: =Scenarios!$E$32*(1-Scenarios!$E$31)^(J$4-1) -> 167597.7 | K58: =Scenarios!$E$32*(1-Scenarios!$E$31)^(K$4-1) -> 146145.2 | L58: =Scenarios!$E$32*(1-Scenarios!$E$31)^(L$4-1) -> 127438.61 | ... AB58: =Scenarios!$E$32*(1-Scenarios!$E$31)^(AB$4-1) -> 14241.797
C59: Share of modelled lifetime viewers | D59: =SUM(E59:AB59) -> 1 | E59: =E58/$D$58 -> 0.13296754 | F59: =F58/$D$58 -> 0.11594769 | G59: =G58/$D$58 -> 0.10110639 | H59: =H58/$D$58 -> 0.088164771 | I59: =I58/$D$58 -> 0.076879681 | J59: =J58/$D$58 -> 0.067039081 | K59: =K58/$D$58 -> 0.058458079 | L59: =L58/$D$58 -> 0.050975445 | ... AB59: =AB58/$D$58 -> 0.0056967188
C60: Viewing hours | D60: =SUM(E60:AB60) -> 3127000 | E60: =E58*'Title Inputs'!$E$16*'Title Inputs'!$E$11*Scenarios!$E$33/60 -> 415789.49 | F60: =F58*'Title Inputs'!$E$16*'Title Inputs'!$E$11*Scenarios!$E$33/60 -> 362568.44 | G60: =G58*'Title Inputs'!$E$16*'Title Inputs'!$E$11*Scenarios!$E$33/60 -> 316159.68 | H60: =H58*'Title Inputs'!$E$16*'Title Inputs'!$E$11*Scenarios!$E$33/60 -> 275691.24 | I60: =I58*'Title Inputs'!$E$16*'Title Inputs'!$E$11*Scenarios!$E$33/60 -> 240402.76 | J60: =J58*'Title Inputs'!$E$16*'Title Inputs'!$E$11*Scenarios!$E$33/60 -> 209631.21 | K60: =K58*'Title Inputs'!$E$16*'Title Inputs'!$E$11*Scenarios!$E$33/60 -> 182798.41 | L60: =L58*'Title Inputs'!$E$16*'Title Inputs'!$E$11*Scenarios!$E$33/60 -> 159400.22 | ... AB60: =AB58*'Title Inputs'!$E$16*'Title Inputs'!$E$11*Scenarios!$E$33/60 -> 17813.64
C61: Monetised ad impressions | D61: =SUM(E61:AB61) -> 38774800 | E61: =E60*'Title Inputs'!$E$24*Scenarios!$E$34 -> 5155789.7 | F61: =F60*'Title Inputs'!$E$24*Scenarios!$E$34 -> 4495848.6 | G61: =G60*'Title Inputs'!$E$24*Scenarios!$E$34 -> 3920380 | H61: =H60*'Title Inputs'!$E$24*Scenarios!$E$34 -> 3418571.4 | I61: =I60*'Title Inputs'!$E$24*Scenarios!$E$34 -> 2980994.2 | J61: =J60*'Title Inputs'!$E$24*Scenarios!$E$34 -> 2599427 | K61: =K60*'Title Inputs'!$E$24*Scenarios!$E$34 -> 2266700.3 | L61: =L60*'Title Inputs'!$E$24*Scenarios!$E$34 -> 1976562.7 | ... AB61: =AB60*'Title Inputs'!$E$24*Scenarios!$E$34 -> 220889.13
C62: Gross advertising revenue ($) | D62: =SUM(E62:AB62) -> 891820.4 | E62: =E61/1000*Scenarios!$E$35 -> 118583.16 | F62: =F61/1000*Scenarios!$E$35 -> 103404.52 | G62: =G61/1000*Scenarios!$E$35 -> 90168.74 | H62: =H61/1000*Scenarios!$E$35 -> 78627.142 | I62: =I61/1000*Scenarios!$E$35 -> 68562.867 | J62: =J61/1000*Scenarios!$E$35 -> 59786.82 | K62: =K61/1000*Scenarios!$E$35 -> 52134.107 | L62: =L61/1000*Scenarios!$E$35 -> 45460.942 | ... AB62: =AB61/1000*Scenarios!$E$35 -> 5080.4501
A64: Base | B64: The Quiet Depth | C64: Monthly unique viewers | D64: =SUM(E64:AB64) -> 1650000 | E64: =Scenarios!$F$32*(1-Scenarios!$F$31)^(E$4-1) -> 237358.69 | F64: =Scenarios!$F$32*(1-Scenarios!$F$31)^(F$4-1) -> 204128.48 | G64: =Scenarios!$F$32*(1-Scenarios!$F$31)^(G$4-1) -> 175550.49 | H64: =Scenarios!$F$32*(1-Scenarios!$F$31)^(H$4-1) -> 150973.42 | I64: =Scenarios!$F$32*(1-Scenarios!$F$31)^(I$4-1) -> 129837.14 | J64: =Scenarios!$F$32*(1-Scenarios!$F$31)^(J$4-1) -> 111659.94 | K64: =Scenarios!$F$32*(1-Scenarios!$F$31)^(K$4-1) -> 96027.551 | L64: =Scenarios!$F$32*(1-Scenarios!$F$31)^(L$4-1) -> 82583.694 | ... AB64: =Scenarios!$F$32*(1-Scenarios!$F$31)^(AB$4-1) -> 7393.8311
C65: Share of modelled lifetime viewers | D65: =SUM(E65:AB65) -> 1 | E65: =E64/$D$64 -> 0.14385375 | F65: =F64/$D$64 -> 0.12371423 | G65: =G64/$D$64 -> 0.10639424 | H65: =H64/$D$64 -> 0.091499044 | I65: =I64/$D$64 -> 0.078689177 | J65: =J64/$D$64 -> 0.067672693 | K65: =K64/$D$64 -> 0.058198516 | L65: =L64/$D$64 -> 0.050050723 | ... AB65: =AB64/$D$64 -> 0.0044811097
C66: Viewing hours | D66: =SUM(E66:AB66) -> 1965183 | E66: =E64*'Title Inputs'!$F$16*'Title Inputs'!$F$11*Scenarios!$F$33/60 -> 282698.95 | F66: =F64*'Title Inputs'!$F$16*'Title Inputs'!$F$11*Scenarios!$F$33/60 -> 243121.1 | G66: =G64*'Title Inputs'!$F$16*'Title Inputs'!$F$11*Scenarios!$F$33/60 -> 209084.15 | H66: =H64*'Title Inputs'!$F$16*'Title Inputs'!$F$11*Scenarios!$F$33/60 -> 179812.36 | I66: =I64*'Title Inputs'!$F$16*'Title Inputs'!$F$11*Scenarios!$F$33/60 -> 154638.63 | J66: =J64*'Title Inputs'!$F$16*'Title Inputs'!$F$11*Scenarios!$F$33/60 -> 132989.23 | K66: =K64*'Title Inputs'!$F$16*'Title Inputs'!$F$11*Scenarios!$F$33/60 -> 114370.73 | L66: =L64*'Title Inputs'!$F$16*'Title Inputs'!$F$11*Scenarios!$F$33/60 -> 98358.831 | ... AB66: =AB64*'Title Inputs'!$F$16*'Title Inputs'!$F$11*Scenarios!$F$33/60 -> 8806.2007
C67: Monetised ad impressions | D67: =SUM(E67:AB67) -> 22697864 | E67: =E66*'Title Inputs'!$F$24*Scenarios!$F$34 -> 3265172.9 | F67: =F66*'Title Inputs'!$F$24*Scenarios!$F$34 -> 2808048.7 | G67: =G66*'Title Inputs'!$F$24*Scenarios!$F$34 -> 2414921.9 | H67: =H66*'Title Inputs'!$F$24*Scenarios!$F$34 -> 2076832.8 | I67: =I66*'Title Inputs'!$F$24*Scenarios!$F$34 -> 1786076.2 | J67: =J66*'Title Inputs'!$F$24*Scenarios!$F$34 -> 1536025.6 | K67: =K66*'Title Inputs'!$F$24*Scenarios!$F$34 -> 1320982 | L67: =L66*'Title Inputs'!$F$24*Scenarios!$F$34 -> 1136044.5 | ... AB67: =AB66*'Title Inputs'!$F$24*Scenarios!$F$34 -> 101711.62
C68: Gross advertising revenue ($) | D68: =SUM(E68:AB68) -> 476655.14 | E68: =E67/1000*Scenarios!$F$35 -> 68568.631 | F68: =F67/1000*Scenarios!$F$35 -> 58969.023 | G68: =G67/1000*Scenarios!$F$35 -> 50713.359 | H68: =H67/1000*Scenarios!$F$35 -> 43613.489 | I68: =I67/1000*Scenarios!$F$35 -> 37507.601 | J68: =J67/1000*Scenarios!$F$35 -> 32256.537 | K68: =K67/1000*Scenarios!$F$35 -> 27740.621 | L68: =L67/1000*Scenarios!$F$35 -> 23856.934 | ... AB68: =AB67/1000*Scenarios!$F$35 -> 2135.944
A70: Base | B70: Vector Nine | C70: Monthly unique viewers | D70: =SUM(E70:AB70) -> 850000 | E70: =Scenarios!$G$32*(1-Scenarios!$G$31)^(E$4-1) -> 130132.94 | F70: =Scenarios!$G$32*(1-Scenarios!$G$31)^(F$4-1) -> 110613 | G70: =Scenarios!$G$32*(1-Scenarios!$G$31)^(G$4-1) -> 94021.051 | H70: =Scenarios!$G$32*(1-Scenarios!$G$31)^(H$4-1) -> 79917.894 | I70: =Scenarios!$G$32*(1-Scenarios!$G$31)^(I$4-1) -> 67930.21 | J70: =Scenarios!$G$32*(1-Scenarios!$G$31)^(J$4-1) -> 57740.678 | K70: =Scenarios!$G$32*(1-Scenarios!$G$31)^(K$4-1) -> 49079.576 | L70: =Scenarios!$G$32*(1-Scenarios!$G$31)^(L$4-1) -> 41717.64 | ... AB70: =Scenarios!$G$32*(1-Scenarios!$G$31)^(AB$4-1) -> 3097.5801
C71: Share of modelled lifetime viewers | D71: =SUM(E71:AB71) -> 1 | E71: =E70/$D$70 -> 0.15309758 | F71: =F70/$D$70 -> 0.13013294 | G71: =G70/$D$70 -> 0.110613 | H71: =H70/$D$70 -> 0.094021051 | I71: =I70/$D$70 -> 0.079917894 | J71: =J70/$D$70 -> 0.06793021 | K71: =K70/$D$70 -> 0.057740678 | L71: =L70/$D$70 -> 0.049079576 | ... AB71: =AB70/$D$70 -> 0.0036442119
C72: Viewing hours | D72: =SUM(E72:AB72) -> 681615 | E72: =E70*'Title Inputs'!$G$16*'Title Inputs'!$G$11*Scenarios!$G$33/60 -> 104353.61 | F72: =F70*'Title Inputs'!$G$16*'Title Inputs'!$G$11*Scenarios!$G$33/60 -> 88700.566 | G72: =G70*'Title Inputs'!$G$16*'Title Inputs'!$G$11*Scenarios!$G$33/60 -> 75395.481 | H72: =H70*'Title Inputs'!$G$16*'Title Inputs'!$G$11*Scenarios!$G$33/60 -> 64086.159 | I72: =I70*'Title Inputs'!$G$16*'Title Inputs'!$G$11*Scenarios!$G$33/60 -> 54473.235 | J72: =J70*'Title Inputs'!$G$16*'Title Inputs'!$G$11*Scenarios!$G$33/60 -> 46302.25 | K72: =K70*'Title Inputs'!$G$16*'Title Inputs'!$G$11*Scenarios!$G$33/60 -> 39356.912 | L72: =L70*'Title Inputs'!$G$16*'Title Inputs'!$G$11*Scenarios!$G$33/60 -> 33453.375 | ... AB72: =AB70*'Title Inputs'!$G$16*'Title Inputs'!$G$11*Scenarios!$G$33/60 -> 2483.9495
C73: Monetised ad impressions | D73: =SUM(E73:AB73) -> 7668168.8 | E73: =E72*'Title Inputs'!$G$24*Scenarios!$G$34 -> 1173978.1 | F73: =F72*'Title Inputs'!$G$24*Scenarios!$G$34 -> 997881.37 | G73: =G72*'Title Inputs'!$G$24*Scenarios!$G$34 -> 848199.16 | H73: =H72*'Title Inputs'!$G$24*Scenarios!$G$34 -> 720969.29 | I73: =I72*'Title Inputs'!$G$24*Scenarios!$G$34 -> 612823.89 | J73: =J72*'Title Inputs'!$G$24*Scenarios!$G$34 -> 520900.31 | K73: =K72*'Title Inputs'!$G$24*Scenarios!$G$34 -> 442765.26 | L73: =L72*'Title Inputs'!$G$24*Scenarios!$G$34 -> 376350.47 | ... AB73: =AB72*'Title Inputs'!$G$24*Scenarios!$G$34 -> 27944.432
C74: Gross advertising revenue ($) | D74: =SUM(E74:AB74) -> 149529.29 | E74: =E73/1000*Scenarios!$G$35 -> 22892.573 | F74: =F73/1000*Scenarios!$G$35 -> 19458.687 | G74: =G73/1000*Scenarios!$G$35 -> 16539.884 | H74: =H73/1000*Scenarios!$G$35 -> 14058.901 | I74: =I73/1000*Scenarios!$G$35 -> 11950.066 | J74: =J73/1000*Scenarios!$G$35 -> 10157.556 | K74: =K73/1000*Scenarios!$G$35 -> 8633.9226 | L74: =L73/1000*Scenarios!$G$35 -> 7338.8343 | ... AB74: =AB73/1000*Scenarios!$G$35 -> 544.91641
B76: PORTFOLIO | C76: Portfolio unique viewers | D76: =$D$46+$D$52+$D$58+$D$64+$D$70 -> 11650000 | E76: =E46+E52+E58+E64+E70 -> 1521068.6 | F76: =F46+F52+F58+F64+F70 -> 1329416.4 | G76: =G46+G52+G58+G64+G70 -> 1162101.6 | H76: =H46+H52+H58+H64+H70 -> 1016008.2 | I76: =I46+I52+I58+I64+I70 -> 888422.48 | J76: =J46+J52+J58+J64+J70 -> 776980.84 | K76: =K46+K52+K58+K64+K70 -> 679623.99 | L76: =L46+L52+L58+L64+L70 -> 594557.55 | ... AB76: =AB46+AB52+AB58+AB64+AB70 -> 71354.221
B77: PORTFOLIO | C77: Portfolio viewing hours | D77: =$D$48+$D$54+$D$60+$D$66+$D$72 -> 15970795 | E77: =E48+E54+E60+E66+E72 -> 2060369.5 | F77: =F48+F54+F60+F66+F72 -> 1804592 | G77: =G48+G54+G60+G66+G72 -> 1580783.2 | H77: =H48+H54+H60+H66+H72 -> 1384918.6 | I77: =I48+I54+I60+I66+I72 -> 1213483.9 | J77: =J48+J54+J60+J66+J72 -> 1063410.4 | K77: =K48+K54+K60+K66+K72 -> 932017.56 | L77: =L48+L54+L60+L66+L72 -> 816963.91 | ... AB77: =AB48+AB54+AB60+AB66+AB72 -> 100836.89
B78: PORTFOLIO | C78: Portfolio monetised impressions | D78: =$D$49+$D$55+$D$61+$D$67+$D$73 -> 2.0223641e+08 | E78: =E49+E55+E61+E67+E73 -> 26006984 | F78: =F49+F55+F61+F67+F73 -> 22791316 | G78: =G49+G55+G61+G67+G73 -> 19975836 | H78: =H49+H55+H61+H67+H73 -> 17510392 | I78: =I49+I55+I61+I67+I73 -> 15351167 | J78: =J49+J55+J61+J67+J73 -> 13459868 | K78: =K49+K55+K61+K67+K73 -> 11803024 | L78: =L49+L55+L61+L67+L73 -> 10351378 | ... AB78: =AB49+AB55+AB61+AB67+AB73 -> 1287099.9
B79: PORTFOLIO | C79: Portfolio gross advertising revenue ($) | D79: =$D$50+$D$56+$D$62+$D$68+$D$74 -> 4828224.8 | E79: =E50+E56+E62+E68+E74 -> 618015.32 | F79: =F50+F56+F62+F68+F74 -> 542043.63 | G79: =G50+G56+G62+G68+G74 -> 475467.33 | H79: =H50+H56+H62+H68+H74 -> 417116.93 | I79: =I50+I56+I62+I68+I74 -> 365969.53 | J79: =J50+J56+J62+J68+J74 -> 321130.29 | K79: =K50+K56+K62+K68+K74 -> 281816.33 | L79: =L50+L56+L62+L68+L74 -> 247342.57 | ... AB79: =AB50+AB56+AB62+AB68+AB74 -> 31086.548
C80: Cumulative viewing hours | D80: =AB80 -> 15970795 | E80: =SUM(E77:E77) -> 2060369.5 | F80: =SUM(E77:F77) -> 3864961.5 | G80: =SUM(E77:G77) -> 5445744.7 | H80: =SUM(E77:H77) -> 6830663.3 | I80: =SUM(E77:I77) -> 8044147.2 | J80: =SUM(E77:J77) -> 9107557.6 | K80: =SUM(E77:K77) -> 10039575 | L80: =SUM(E77:L77) -> 10856539 | M80: =SUM(E77:M77) -> 11572743 | N80: =SUM(E77:N77) -> 12200691 | O80: =SUM(E77:O77) -> 12751328 | P80: =SUM(E77:P77) -> 13234230 | Q80: =SUM(E77:Q77) -> 13657779 | R80: =SUM(E77:R77) -> 14029315 | S80: =SUM(E77:S77) -> 14355262 | T80: =SUM(E77:T77) -> 14641248 | U80: =SUM(E77:U77) -> 14892199 | V80: =SUM(E77:V77) -> 15112432 | W80: =SUM(E77:W77) -> 15305729 | X80: =SUM(E77:X77) -> 15475402 | Y80: =SUM(E77:Y77) -> 15624354 | Z80: =SUM(E77:Z77) -> 15755130 | AA80: =SUM(E77:AA77) -> 15869958 | AB80: =SUM(E77:AB77) -> 15970795
C81: Cumulative gross advertising revenue ($) | D81: =AB81 -> 4828224.8 | E81: =SUM(E79:E79) -> 618015.32 | F81: =SUM(E79:F79) -> 1160059 | G81: =SUM(E79:G79) -> 1635526.3 | H81: =SUM(E79:H79) -> 2052643.2 | I81: =SUM(E79:I79) -> 2418612.7 | J81: =SUM(E79:J79) -> 2739743 | K81: =SUM(E79:K79) -> 3021559.4 | L81: =SUM(E79:L79) -> 3268901.9 | M81: =SUM(E79:M79) -> 3486011.4 | N81: =SUM(E79:N79) -> 3676603.5 | O81: =SUM(E79:O79) -> 3843934.7 | P81: =SUM(E79:P79) -> 3990859.1 | Q81: =SUM(E79:Q79) -> 4119878.5 | R81: =SUM(E79:R79) -> 4233186.5 | S81: =SUM(E79:S79) -> 4332706 | T81: =SUM(E79:T79) -> 4420123.7 | U81: =SUM(E79:U79) -> 4496918.3 | V81: =SUM(E79:V79) -> 4564387.4 | W81: =SUM(E79:W79) -> 4623668.7 | X81: =SUM(E79:X79) -> 4675760.8 | Y81: =SUM(E79:Y79) -> 4721539.7 | Z81: =SUM(E79:Z79) -> 4761774 | AA81: =SUM(E79:AA79) -> 4797138.3 | AB81: =SUM(E79:AB79) -> 4828224.8
A84: UPSIDE SCENARIO
A85: Upside | B85: Nightfall Protocol | C85: Monthly unique viewers | D85: =SUM(E85:AB85) -> 3969322.4 | E85: =Scenarios!$C$41*(1-Scenarios!$C$40)^(E$4-1) -> 454795.66 | F85: =Scenarios!$C$41*(1-Scenarios!$C$40)^(F$4-1) -> 406132.52 | G85: =Scenarios!$C$41*(1-Scenarios!$C$40)^(G$4-1) -> 362676.34 | H85: =Scenarios!$C$41*(1-Scenarios!$C$40)^(H$4-1) -> 323869.97 | I85: =Scenarios!$C$41*(1-Scenarios!$C$40)^(I$4-1) -> 289215.89 | J85: =Scenarios!$C$41*(1-Scenarios!$C$40)^(J$4-1) -> 258269.79 | K85: =Scenarios!$C$41*(1-Scenarios!$C$40)^(K$4-1) -> 230634.92 | L85: =Scenarios!$C$41*(1-Scenarios!$C$40)^(L$4-1) -> 205956.98 | ... AB85: =Scenarios!$C$41*(1-Scenarios!$C$40)^(AB$4-1) -> 33682.155
C86: Share of modelled lifetime viewers | D86: =SUM(E86:AB86) -> 1 | E86: =E85/$D$85 -> 0.11457766 | F86: =F85/$D$85 -> 0.10231785 | G86: =G85/$D$85 -> 0.091369838 | H86: =H85/$D$85 -> 0.081593265 | I86: =I85/$D$85 -> 0.072862786 | J86: =J85/$D$85 -> 0.065066468 | K86: =K85/$D$85 -> 0.058104356 | L86: =L85/$D$85 -> 0.05188719 | ... AB86: =AB85/$D$85 -> 0.0084856183
C87: Viewing hours | D87: =SUM(E87:AB87) -> 6624767.3 | E87: =E85*'Title Inputs'!$C$16*'Title Inputs'!$C$11*Scenarios!$C$42/60 -> 759050.31 | F87: =F85*'Title Inputs'!$C$16*'Title Inputs'!$C$11*Scenarios!$C$42/60 -> 677831.93 | G87: =G85*'Title Inputs'!$C$16*'Title Inputs'!$C$11*Scenarios!$C$42/60 -> 605303.91 | H87: =H85*'Title Inputs'!$C$16*'Title Inputs'!$C$11*Scenarios!$C$42/60 -> 540536.4 | I87: =I85*'Title Inputs'!$C$16*'Title Inputs'!$C$11*Scenarios!$C$42/60 -> 482699 | J87: =J85*'Title Inputs'!$C$16*'Title Inputs'!$C$11*Scenarios!$C$42/60 -> 431050.21 | K87: =K85*'Title Inputs'!$C$16*'Title Inputs'!$C$11*Scenarios!$C$42/60 -> 384927.84 | L87: =L85*'Title Inputs'!$C$16*'Title Inputs'!$C$11*Scenarios!$C$42/60 -> 343740.56 | ... AB87: =AB85*'Title Inputs'!$C$16*'Title Inputs'!$C$11*Scenarios!$C$42/60 -> 56215.246
C88: Monetised ad impressions | D88: =SUM(E88:AB88) -> 88655286 | E88: =E87*'Title Inputs'!$C$24*Scenarios!$C$43 -> 10157915 | F88: =F87*'Title Inputs'!$C$24*Scenarios!$C$43 -> 9071018 | G88: =G87*'Title Inputs'!$C$24*Scenarios!$C$43 -> 8100419.1 | H88: =H87*'Title Inputs'!$C$24*Scenarios!$C$43 -> 7233674.3 | I88: =I87*'Title Inputs'!$C$24*Scenarios!$C$43 -> 6459671.1 | J88: =J87*'Title Inputs'!$C$24*Scenarios!$C$43 -> 5768486.3 | K88: =K87*'Title Inputs'!$C$24*Scenarios!$C$43 -> 5151258.3 | L88: =L87*'Title Inputs'!$C$24*Scenarios!$C$43 -> 4600073.6 | ... AB88: =AB87*'Title Inputs'!$C$24*Scenarios!$C$43 -> 752294.91
C89: Gross advertising revenue ($) | D89: =SUM(E89:AB89) -> 2339834.6 | E89: =E88/1000*Scenarios!$C$44 -> 268092.77 | F89: =F88/1000*Scenarios!$C$44 -> 239406.84 | G89: =G88/1000*Scenarios!$C$44 -> 213790.31 | H89: =H88/1000*Scenarios!$C$44 -> 190914.75 | I89: =I88/1000*Scenarios!$C$44 -> 170486.87 | J89: =J88/1000*Scenarios!$C$44 -> 152244.77 | K89: =K88/1000*Scenarios!$C$44 -> 135954.58 | L89: =L88/1000*Scenarios!$C$44 -> 121407.44 | ... AB89: =AB88/1000*Scenarios!$C$44 -> 19854.944
A91: Upside | B91: Ash Ridge | C91: Monthly unique viewers | D91: =SUM(E91:AB91) -> 3358352.1 | E91: =Scenarios!$D$41*(1-Scenarios!$D$40)^(E$4-1) -> 399208.82 | F91: =Scenarios!$D$41*(1-Scenarios!$D$40)^(F$4-1) -> 354497.43 | G91: =Scenarios!$D$41*(1-Scenarios!$D$40)^(G$4-1) -> 314793.72 | H91: =Scenarios!$D$41*(1-Scenarios!$D$40)^(H$4-1) -> 279536.82 | I91: =Scenarios!$D$41*(1-Scenarios!$D$40)^(I$4-1) -> 248228.7 | J91: =Scenarios!$D$41*(1-Scenarios!$D$40)^(J$4-1) -> 220427.08 | K91: =Scenarios!$D$41*(1-Scenarios!$D$40)^(K$4-1) -> 195739.25 | L91: =Scenarios!$D$41*(1-Scenarios!$D$40)^(L$4-1) -> 173816.45 | ... AB91: =Scenarios!$D$41*(1-Scenarios!$D$40)^(AB$4-1) -> 25983.541
C92: Share of modelled lifetime viewers | D92: =SUM(E92:AB92) -> 1 | E92: =E91/$D$91 -> 0.11887045 | F92: =F91/$D$91 -> 0.10555696 | G92: =G91/$D$91 -> 0.093734579 | H92: =H91/$D$91 -> 0.083236306 | I92: =I91/$D$91 -> 0.07391384 | J92: =J91/$D$91 -> 0.06563549 | K92: =K91/$D$91 -> 0.058284315 | L92: =L91/$D$91 -> 0.051756472 | ... AB92: =AB91/$D$91 -> 0.0077369914
C93: Viewing hours | D93: =SUM(E93:AB93) -> 4836650.3 | E93: =E91*'Title Inputs'!$D$16*'Title Inputs'!$D$11*Scenarios!$D$42/60 -> 574934.79 | F93: =F91*'Title Inputs'!$D$16*'Title Inputs'!$D$11*Scenarios!$D$42/60 -> 510542.09 | G93: =G91*'Title Inputs'!$D$16*'Title Inputs'!$D$11*Scenarios!$D$42/60 -> 453361.38 | H93: =H91*'Title Inputs'!$D$16*'Title Inputs'!$D$11*Scenarios!$D$42/60 -> 402584.91 | I93: =I91*'Title Inputs'!$D$16*'Title Inputs'!$D$11*Scenarios!$D$42/60 -> 357495.4 | J93: =J91*'Title Inputs'!$D$16*'Title Inputs'!$D$11*Scenarios!$D$42/60 -> 317455.91 | K93: =K91*'Title Inputs'!$D$16*'Title Inputs'!$D$11*Scenarios!$D$42/60 -> 281900.85 | L93: =L91*'Title Inputs'!$D$16*'Title Inputs'!$D$11*Scenarios!$D$42/60 -> 250327.95 | ... AB93: =AB91*'Title Inputs'!$D$16*'Title Inputs'!$D$11*Scenarios!$D$42/60 -> 37421.122
C94: Monetised ad impressions | D94: =SUM(E94:AB94) -> 63936648 | E94: =E93*'Title Inputs'!$D$24*Scenarios!$D$43 -> 7600178 | F94: =F93*'Title Inputs'!$D$24*Scenarios!$D$43 -> 6748958.1 | G94: =G93*'Title Inputs'!$D$24*Scenarios!$D$43 -> 5993074.8 | H94: =H93*'Title Inputs'!$D$24*Scenarios!$D$43 -> 5321850.4 | I94: =I93*'Title Inputs'!$D$24*Scenarios!$D$43 -> 4725803.1 | J94: =J93*'Title Inputs'!$D$24*Scenarios!$D$43 -> 4196513.2 | K94: =K93*'Title Inputs'!$D$24*Scenarios!$D$43 -> 3726503.7 | L94: =L93*'Title Inputs'!$D$24*Scenarios!$D$43 -> 3309135.3 | ... AB94: =AB93*'Title Inputs'!$D$24*Scenarios!$D$43 -> 494677.29
C95: Gross advertising revenue ($) | D95: =SUM(E95:AB95) -> 1588186.3 | E95: =E94/1000*Scenarios!$D$44 -> 188788.42 | F95: =F94/1000*Scenarios!$D$44 -> 167644.12 | G95: =G94/1000*Scenarios!$D$44 -> 148867.98 | H95: =H94/1000*Scenarios!$D$44 -> 132194.76 | I95: =I94/1000*Scenarios!$D$44 -> 117388.95 | J95: =J94/1000*Scenarios!$D$44 -> 104241.39 | K95: =K94/1000*Scenarios!$D$44 -> 92566.352 | L95: =L94/1000*Scenarios!$D$44 -> 82198.921 | ... AB95: =AB94/1000*Scenarios!$D$44 -> 12287.784
A97: Upside | B97: Cold Harbor | C97: Monthly unique viewers | D97: =SUM(E97:AB97) -> 2746958.1 | E97: =Scenarios!$E$41*(1-Scenarios!$E$40)^(E$4-1) -> 345715.6 | F97: =Scenarios!$E$41*(1-Scenarios!$E$40)^(F$4-1) -> 304229.73 | G97: =Scenarios!$E$41*(1-Scenarios!$E$40)^(G$4-1) -> 267722.16 | H97: =Scenarios!$E$41*(1-Scenarios!$E$40)^(H$4-1) -> 235595.5 | I97: =Scenarios!$E$41*(1-Scenarios!$E$40)^(I$4-1) -> 207324.04 | J97: =Scenarios!$E$41*(1-Scenarios!$E$40)^(J$4-1) -> 182445.16 | K97: =Scenarios!$E$41*(1-Scenarios!$E$40)^(K$4-1) -> 160551.74 | L97: =Scenarios!$E$41*(1-Scenarios!$E$40)^(L$4-1) -> 141285.53 | ... AB97: =Scenarios!$E$41*(1-Scenarios!$E$40)^(AB$4-1) -> 18273.445
C98: Share of modelled lifetime viewers | D98: =SUM(E98:AB98) -> 1 | E98: =E97/$D$97 -> 0.12585398 | F98: =F97/$D$97 -> 0.1107515 | G98: =G97/$D$97 -> 0.09746132 | H98: =H97/$D$97 -> 0.085765962 | I98: =I97/$D$97 -> 0.075474047 | J98: =J97/$D$97 -> 0.066417161 | K98: =K97/$D$97 -> 0.058447102 | L98: =L97/$D$97 -> 0.051433449 | ... AB98: =AB97/$D$97 -> 0.0066522476
C99: Viewing hours | D99: =SUM(E99:AB99) -> 3504613.1 | E99: =E97*'Title Inputs'!$E$16*'Title Inputs'!$E$11*Scenarios!$E$42/60 -> 441069.5 | F99: =F97*'Title Inputs'!$E$16*'Title Inputs'!$E$11*Scenarios!$E$42/60 -> 388141.16 | G99: =G97*'Title Inputs'!$E$16*'Title Inputs'!$E$11*Scenarios!$E$42/60 -> 341564.22 | H99: =H97*'Title Inputs'!$E$16*'Title Inputs'!$E$11*Scenarios!$E$42/60 -> 300576.51 | I99: =I97*'Title Inputs'!$E$16*'Title Inputs'!$E$11*Scenarios!$E$42/60 -> 264507.33 | J99: =J97*'Title Inputs'!$E$16*'Title Inputs'!$E$11*Scenarios!$E$42/60 -> 232766.45 | K99: =K97*'Title Inputs'!$E$16*'Title Inputs'!$E$11*Scenarios!$E$42/60 -> 204834.48 | L99: =L97*'Title Inputs'!$E$16*'Title Inputs'!$E$11*Scenarios!$E$42/60 -> 180254.34 | ... AB99: =AB97*'Title Inputs'!$E$16*'Title Inputs'!$E$11*Scenarios!$E$42/60 -> 23313.554
C100: Monetised ad impressions | D100: =SUM(E100:AB100) -> 44326346 | E100: =E99*'Title Inputs'!$E$24*Scenarios!$E$43 -> 5578647 | F100: =F99*'Title Inputs'!$E$24*Scenarios!$E$43 -> 4909209.3 | G100: =G99*'Title Inputs'!$E$24*Scenarios!$E$43 -> 4320104.2 | H100: =H99*'Title Inputs'!$E$24*Scenarios!$E$43 -> 3801691.7 | I100: =I99*'Title Inputs'!$E$24*Scenarios!$E$43 -> 3345488.7 | J100: =J99*'Title Inputs'!$E$24*Scenarios!$E$43 -> 2944030.1 | K100: =K99*'Title Inputs'!$E$24*Scenarios!$E$43 -> 2590746.5 | L100: =L99*'Title Inputs'!$E$24*Scenarios!$E$43 -> 2279856.9 | ... AB100: =AB99*'Title Inputs'!$E$24*Scenarios!$E$43 -> 294869.83
C101: Gross advertising revenue ($) | D101: =SUM(E101:AB101) -> 1055188.7 | E101: =E100/1000*Scenarios!$E$44 -> 132799.69 | F101: =F100/1000*Scenarios!$E$44 -> 116863.73 | G101: =G100/1000*Scenarios!$E$44 -> 102840.08 | H101: =H100/1000*Scenarios!$E$44 -> 90499.271 | I101: =I100/1000*Scenarios!$E$44 -> 79639.359 | J101: =J100/1000*Scenarios!$E$44 -> 70082.636 | K101: =K100/1000*Scenarios!$E$44 -> 61672.719 | L101: =L100/1000*Scenarios!$E$44 -> 54271.993 | ... AB101: =AB100/1000*Scenarios!$E$44 -> 7019.3763
A103: Upside | B103: The Quiet Depth | C103: Monthly unique viewers | D103: =SUM(E103:AB103) -> 1807532.9 | E103: =Scenarios!$F$41*(1-Scenarios!$F$40)^(E$4-1) -> 246853.04 | F103: =Scenarios!$F$41*(1-Scenarios!$F$40)^(F$4-1) -> 214268.44 | G103: =Scenarios!$F$41*(1-Scenarios!$F$40)^(G$4-1) -> 185985.01 | H103: =Scenarios!$F$41*(1-Scenarios!$F$40)^(H$4-1) -> 161434.99 | I103: =Scenarios!$F$41*(1-Scenarios!$F$40)^(I$4-1) -> 140125.57 | J103: =Scenarios!$F$41*(1-Scenarios!$F$40)^(J$4-1) -> 121628.99 | K103: =Scenarios!$F$41*(1-Scenarios!$F$40)^(K$4-1) -> 105573.97 | L103: =Scenarios!$F$41*(1-Scenarios!$F$40)^(L$4-1) -> 91638.202 | ... AB103: =Scenarios!$F$41*(1-Scenarios!$F$40)^(AB$4-1) -> 9514.6357
C104: Share of modelled lifetime viewers | D104: =SUM(E104:AB104) -> 1 | E104: =E103/$D$103 -> 0.13656905 | F104: =F103/$D$103 -> 0.11854193 | G104: =G103/$D$103 -> 0.1028944 | H104: =H103/$D$103 -> 0.089312338 | I104: =I103/$D$103 -> 0.077523109 | J104: =J103/$D$103 -> 0.067290059 | K104: =K103/$D$103 -> 0.058407771 | L104: =L103/$D$103 -> 0.050697945 | ... AB104: =AB103/$D$103 -> 0.0052638798
C105: Viewing hours | D105: =SUM(E105:AB105) -> 2195864 | E105: =E103*'Title Inputs'!$F$16*'Title Inputs'!$F$11*Scenarios!$F$42/60 -> 299887.05 | F105: =F103*'Title Inputs'!$F$16*'Title Inputs'!$F$11*Scenarios!$F$42/60 -> 260301.96 | G105: =G103*'Title Inputs'!$F$16*'Title Inputs'!$F$11*Scenarios!$F$42/60 -> 225942.1 | H105: =H103*'Title Inputs'!$F$16*'Title Inputs'!$F$11*Scenarios!$F$42/60 -> 196117.74 | I105: =I103*'Title Inputs'!$F$16*'Title Inputs'!$F$11*Scenarios!$F$42/60 -> 170230.2 | J105: =J103*'Title Inputs'!$F$16*'Title Inputs'!$F$11*Scenarios!$F$42/60 -> 147759.81 | K105: =K103*'Title Inputs'!$F$16*'Title Inputs'!$F$11*Scenarios!$F$42/60 -> 128255.52 | L105: =L103*'Title Inputs'!$F$16*'Title Inputs'!$F$11*Scenarios!$F$42/60 -> 111325.79 | ... AB105: =AB103*'Title Inputs'!$F$16*'Title Inputs'!$F$11*Scenarios!$F$42/60 -> 11558.764
C106: Monetised ad impressions | D106: =SUM(E106:AB106) -> 25869473 | E106: =E105*'Title Inputs'!$F$24*Scenarios!$F$43 -> 3532969.3 | F106: =F105*'Title Inputs'!$F$24*Scenarios!$F$43 -> 3066617.4 | G106: =G105*'Title Inputs'!$F$24*Scenarios!$F$43 -> 2661823.9 | H106: =H105*'Title Inputs'!$F$24*Scenarios!$F$43 -> 2310463.1 | I106: =I105*'Title Inputs'!$F$24*Scenarios!$F$43 -> 2005482 | J106: =J105*'Title Inputs'!$F$24*Scenarios!$F$43 -> 1740758.4 | K106: =K105*'Title Inputs'!$F$24*Scenarios!$F$43 -> 1510978.3 | L106: =L105*'Title Inputs'!$F$24*Scenarios!$F$43 -> 1311529.1 | ... AB106: =AB105*'Title Inputs'!$F$24*Scenarios!$F$43 -> 136173.8
C107: Gross advertising revenue ($) | D107: =SUM(E107:AB107) -> 562273 | E107: =E106/1000*Scenarios!$F$44 -> 76789.088 | F107: =F106/1000*Scenarios!$F$44 -> 66652.929 | G107: =G106/1000*Scenarios!$F$44 -> 57854.742 | H107: =H106/1000*Scenarios!$F$44 -> 50217.916 | I107: =I106/1000*Scenarios!$F$44 -> 43589.151 | J107: =J106/1000*Scenarios!$F$44 -> 37835.383 | K107: =K106/1000*Scenarios!$F$44 -> 32841.113 | L107: =L106/1000*Scenarios!$F$44 -> 28506.086 | ... AB107: =AB106/1000*Scenarios!$F$44 -> 2959.7375
A109: Upside | B109: Vector Nine | C109: Monthly unique viewers | D109: =SUM(E109:AB109) -> 928941.35 | E109: =Scenarios!$G$41*(1-Scenarios!$G$40)^(E$4-1) -> 135338.26 | F109: =Scenarios!$G$41*(1-Scenarios!$G$40)^(F$4-1) -> 116120.23 | G109: =Scenarios!$G$41*(1-Scenarios!$G$40)^(G$4-1) -> 99631.155 | H109: =Scenarios!$G$41*(1-Scenarios!$G$40)^(H$4-1) -> 85483.531 | I109: =Scenarios!$G$41*(1-Scenarios!$G$40)^(I$4-1) -> 73344.87 | J109: =Scenarios!$G$41*(1-Scenarios!$G$40)^(J$4-1) -> 62929.898 | K109: =Scenarios!$G$41*(1-Scenarios!$G$40)^(K$4-1) -> 53993.853 | L109: =Scenarios!$G$41*(1-Scenarios!$G$40)^(L$4-1) -> 46326.726 | ... AB109: =Scenarios!$G$41*(1-Scenarios!$G$40)^(AB$4-1) -> 3996.0251
C110: Share of modelled lifetime viewers | D110: =SUM(E110:AB110) -> 1 | E110: =E109/$D$109 -> 0.14569086 | F110: =F109/$D$109 -> 0.12500276 | G110: =G109/$D$109 -> 0.10725236 | H110: =H109/$D$109 -> 0.092022528 | I110: =I109/$D$109 -> 0.078955329 | J110: =J109/$D$109 -> 0.067743673 | K110: =K109/$D$109 -> 0.058124071 | L110: =L109/$D$109 -> 0.049870453 | ... AB110: =AB109/$D$109 -> 0.004301698
C111: Viewing hours | D111: =SUM(E111:AB111) -> 759816.43 | E111: =E109*'Title Inputs'!$G$16*'Title Inputs'!$G$11*Scenarios!$G$42/60 -> 110698.31 | F111: =F109*'Title Inputs'!$G$16*'Title Inputs'!$G$11*Scenarios!$G$42/60 -> 94979.147 | G111: =G109*'Title Inputs'!$G$16*'Title Inputs'!$G$11*Scenarios!$G$42/60 -> 81492.108 | H111: =H109*'Title Inputs'!$G$16*'Title Inputs'!$G$11*Scenarios!$G$42/60 -> 69920.229 | I111: =I109*'Title Inputs'!$G$16*'Title Inputs'!$G$11*Scenarios!$G$42/60 -> 59991.556 | J111: =J109*'Title Inputs'!$G$16*'Title Inputs'!$G$11*Scenarios!$G$42/60 -> 51472.755 | K111: =K109*'Title Inputs'!$G$16*'Title Inputs'!$G$11*Scenarios!$G$42/60 -> 44163.624 | L111: =L109*'Title Inputs'!$G$16*'Title Inputs'!$G$11*Scenarios!$G$42/60 -> 37892.389 | ... AB111: =AB109*'Title Inputs'!$G$16*'Title Inputs'!$G$11*Scenarios!$G$42/60 -> 3268.5008
C112: Monetised ad impressions | D112: =SUM(E112:AB112) -> 8718893.5 | E112: =E111*'Title Inputs'!$G$24*Scenarios!$G$43 -> 1270263.1 | F112: =F111*'Title Inputs'!$G$24*Scenarios!$G$43 -> 1089885.7 | G112: =G111*'Title Inputs'!$G$24*Scenarios!$G$43 -> 935121.94 | H112: =H111*'Title Inputs'!$G$24*Scenarios!$G$43 -> 802334.62 | I112: =I111*'Title Inputs'!$G$24*Scenarios!$G$43 -> 688403.11 | J112: =J111*'Title Inputs'!$G$24*Scenarios!$G$43 -> 590649.87 | K112: =K111*'Title Inputs'!$G$24*Scenarios!$G$43 -> 506777.59 | L112: =L111*'Title Inputs'!$G$24*Scenarios!$G$43 -> 434815.17 | ... AB112: =AB111*'Title Inputs'!$G$24*Scenarios!$G$43 -> 37506.047
C113: Gross advertising revenue ($) | D113: =SUM(E113:AB113) -> 175969.07 | E113: =E112/1000*Scenarios!$G$44 -> 25637.084 | F113: =F112/1000*Scenarios!$G$44 -> 21996.618 | G113: =G112/1000*Scenarios!$G$44 -> 18873.099 | H113: =H112/1000*Scenarios!$G$44 -> 16193.119 | I113: =I112/1000*Scenarios!$G$44 -> 13893.696 | J113: =J112/1000*Scenarios!$G$44 -> 11920.791 | K113: =K112/1000*Scenarios!$G$44 -> 10228.039 | L113: =L112/1000*Scenarios!$G$44 -> 8775.6571 | ... AB113: =AB112/1000*Scenarios!$G$44 -> 756.96579
B115: PORTFOLIO | C115: Portfolio unique viewers | D115: =$D$85+$D$91+$D$97+$D$103+$D$109 -> 12811107 | E115: =E85+E91+E97+E103+E109 -> 1581911.4 | F115: =F85+F91+F97+F103+F109 -> 1395248.3 | G115: =G85+G91+G97+G103+G109 -> 1230808.4 | H115: =H85+H91+H97+H103+H109 -> 1085920.8 | I115: =I85+I91+I97+I103+I109 -> 958239.06 | J115: =J85+J91+J97+J103+J109 -> 845700.92 | K115: =K85+K91+K97+K103+K109 -> 746493.73 | L115: =L85+L91+L97+L103+L109 -> 659023.89 | ... AB115: =AB85+AB91+AB97+AB103+AB109 -> 91449.802
B116: PORTFOLIO | C116: Portfolio viewing hours | D116: =$D$87+$D$93+$D$99+$D$105+$D$111 -> 17921711 | E116: =E87+E93+E99+E105+E111 -> 2185640 | F116: =F87+F93+F99+F105+F111 -> 1931796.3 | G116: =G87+G93+G99+G105+G111 -> 1707663.7 | H116: =H87+H93+H99+H105+H111 -> 1509735.8 | I116: =I87+I93+I99+I105+I111 -> 1334923.5 | J116: =J87+J93+J99+J105+J111 -> 1180505.1 | K116: =K87+K93+K99+K105+K111 -> 1044082.3 | L116: =L87+L93+L99+L105+L111 -> 923541.03 | ... AB116: =AB87+AB93+AB99+AB105+AB111 -> 131777.19
B117: PORTFOLIO | C117: Portfolio monetised impressions | D117: =$D$88+$D$94+$D$100+$D$106+$D$112 -> 2.3150665e+08 | E117: =E88+E94+E100+E106+E112 -> 28139972 | F117: =F88+F94+F100+F106+F112 -> 24885688 | G117: =G88+G94+G100+G106+G112 -> 22010544 | H117: =H88+H94+H100+H106+H112 -> 19470014 | I117: =I88+I94+I100+I106+I112 -> 17224848 | J117: =J88+J94+J100+J106+J112 -> 15240438 | K117: =K88+K94+K100+K106+K112 -> 13486264 | L117: =L88+L94+L100+L106+L112 -> 11935410 | ... AB117: =AB88+AB94+AB100+AB106+AB112 -> 1715521.9
B118: PORTFOLIO | C118: Portfolio gross advertising revenue ($) | D118: =$D$89+$D$95+$D$101+$D$107+$D$113 -> 5721451.7 | E118: =E89+E95+E101+E107+E113 -> 692107.05 | F118: =F89+F95+F101+F107+F113 -> 612564.24 | G118: =G89+G95+G101+G107+G113 -> 542226.21 | H118: =H89+H95+H101+H107+H113 -> 480019.82 | I118: =I89+I95+I101+I107+I113 -> 424998.03 | J118: =J89+J95+J101+J107+J113 -> 376324.97 | K118: =K89+K95+K101+K107+K113 -> 333262.81 | L118: =L89+L95+L101+L107+L113 -> 295160.1 | ... AB118: =AB89+AB95+AB101+AB107+AB113 -> 42878.807
C119: Cumulative viewing hours | D119: =AB119 -> 17921711 | E119: =SUM(E116:E116) -> 2185640 | F119: =SUM(E116:F116) -> 4117436.2 | G119: =SUM(E116:G116) -> 5825100 | H119: =SUM(E116:H116) -> 7334835.7 | I119: =SUM(E116:I116) -> 8669759.2 | J119: =SUM(E116:J116) -> 9850264.4 | K119: =SUM(E116:K116) -> 10894347 | L119: =SUM(E116:L116) -> 11817888 | M119: =SUM(E116:M116) -> 12634906 | N119: =SUM(E116:N116) -> 13357775 | O119: =SUM(E116:O116) -> 13997423 | P119: =SUM(E116:P116) -> 14563497 | Q119: =SUM(E116:Q116) -> 15064520 | R119: =SUM(E116:R116) -> 15508017 | S119: =SUM(E116:S116) -> 15900638 | T119: =SUM(E116:T116) -> 16248260 | U119: =SUM(E116:U116) -> 16556073 | V119: =SUM(E116:V116) -> 16828665 | W119: =SUM(E116:W116) -> 17070094 | X119: =SUM(E116:X116) -> 17283945 | Y119: =SUM(E116:Y116) -> 17473387 | Z119: =SUM(E116:Z116) -> 17641223 | AA119: =SUM(E116:AA116) -> 17789934 | AB119: =SUM(E116:AB116) -> 17921711
C120: Cumulative gross advertising revenue ($) | D120: =AB120 -> 5721451.7 | E120: =SUM(E118:E118) -> 692107.05 | F120: =SUM(E118:F118) -> 1304671.3 | G120: =SUM(E118:G118) -> 1846897.5 | H120: =SUM(E118:H118) -> 2326917.3 | I120: =SUM(E118:I118) -> 2751915.3 | J120: =SUM(E118:J118) -> 3128240.3 | K120: =SUM(E118:K118) -> 3461503.1 | L120: =SUM(E118:L118) -> 3756663.2 | M120: =SUM(E118:M118) -> 4018104.9 | N120: =SUM(E118:N118) -> 4249704.3 | O120: =SUM(E118:O118) -> 4454889.1 | P120: =SUM(E118:P118) -> 4636690.5 | Q120: =SUM(E118:Q118) -> 4797789.4 | R120: =SUM(E118:R118) -> 4940557.6 | S120: =SUM(E118:S118) -> 5067093.1 | T120: =SUM(E118:T118) -> 5179252.3 | U120: =SUM(E118:U118) -> 5278678 | V120: =SUM(E118:V118) -> 5366824 | W120: =SUM(E118:W118) -> 5444977.1 | X120: =SUM(E118:X118) -> 5514276.6 | Y120: =SUM(E118:Y118) -> 5575730.8 | Z120: =SUM(E118:Z118) -> 5630232.7 | AA120: =SUM(E118:AA118) -> 5678572.9 | AB120: =SUM(E118:AB118) -> 5721451.7

Sheet Title Economics
A1: PROJECT NIGHTFALL
A2: Monthly contribution by title and scenario
A3: Independent analytical case study using synthetic assumptions. Not based on proprietary company information.
A4: Scenario | B4: Title | C4: Month | D4: Total | E4: 1 | F4: 2 | G4: 3 | H4: 4 | I4: 5 | J4: 6 | K4: 7 | L4: 8 | M4: 9 | N4: 10 | O4: 11 | P4: 12 | Q4: 13 | R4: 14 | S4: 15 | T4: 16 | U4: 17 | V4: 18 | W4: 19 | X4: 20 | Y4: 21 | Z4: 22 | AA4: 23 | AB4: 24
C6: Discount factor (end of month) | E6: =1/(1+Assumptions!$C$14)^E$4 -> 0.9906004 | F6: =1/(1+Assumptions!$C$14)^F$4 -> 0.98128915 | G6: =1/(1+Assumptions!$C$14)^G$4 -> 0.97206542 | H6: =1/(1+Assumptions!$C$14)^H$4 -> 0.96292839 | I6: =1/(1+Assumptions!$C$14)^I$4 -> 0.95387725 | J6: =1/(1+Assumptions!$C$14)^J$4 -> 0.94491118 | K6: =1/(1+Assumptions!$C$14)^K$4 -> 0.93602939 | L6: =1/(1+Assumptions!$C$14)^L$4 -> 0.92723109 | ... AB6: =1/(1+Assumptions!$C$14)^AB$4 -> 0.79719388
A8: DOWNSIDE SCENARIO
A9: Downside | B9: Nightfall Protocol | C9: Incremental advertising revenue ($) | D9: =SUM(E9:AB9) -> 1012271.7 | E9: ='Monthly Viewing Forecast'!E11*Scenarios!$C$27 -> 130084.02 | F9: ='Monthly Viewing Forecast'!F11*Scenarios!$C$27 -> 114083.69 | G9: ='Monthly Viewing Forecast'!G11*Scenarios!$C$27 -> 100051.39 | H9: ='Monthly Viewing Forecast'!H11*Scenarios!$C$27 -> 87745.072 | I9: ='Monthly Viewing Forecast'!I11*Scenarios!$C$27 -> 76952.428 | J9: ='Monthly Viewing Forecast'!J11*Scenarios!$C$27 -> 67487.279 | K9: ='Monthly Viewing Forecast'!K11*Scenarios!$C$27 -> 59186.344 | L9: ='Monthly Viewing Forecast'!L11*Scenarios!$C$27 -> 51906.424 | ... AB9: ='Monthly Viewing Forecast'!AB11*Scenarios!$C$27 -> 6356.4495
C10: Follow-on engagement value ($) | D10: =SUM(E10:AB10) -> 144723.24 | E10: ='Monthly Viewing Forecast'!E9*Scenarios!$C$27*'Title Inputs'!$C$34 -> 18597.953 | F10: ='Monthly Viewing Forecast'!F9*Scenarios!$C$27*'Title Inputs'!$C$34 -> 16310.405 | G10: ='Monthly Viewing Forecast'!G9*Scenarios!$C$27*'Title Inputs'!$C$34 -> 14304.225 | H10: ='Monthly Viewing Forecast'!H9*Scenarios!$C$27*'Title Inputs'!$C$34 -> 12544.805 | I10: ='Monthly Viewing Forecast'!I9*Scenarios!$C$27*'Title Inputs'!$C$34 -> 11001.794 | J10: ='Monthly Viewing Forecast'!J9*Scenarios!$C$27*'Title Inputs'!$C$34 -> 9648.5735 | K10: ='Monthly Viewing Forecast'!K9*Scenarios!$C$27*'Title Inputs'!$C$34 -> 8461.7989 | L10: ='Monthly Viewing Forecast'!L9*Scenarios!$C$27*'Title Inputs'!$C$34 -> 7420.9977 | ... AB10: ='Monthly Viewing Forecast'!AB9*Scenarios!$C$27*'Title Inputs'!$C$34 -> 908.77378
C11: Marketing support ($) | D11: =SUM(E11:AB11) -> 173250 | E11: =Scenarios!$C$28*INDEX(Assumptions!$C$23:$C$26,E$4) -> 95287.5 | F11: =Scenarios!$C$28*INDEX(Assumptions!$C$23:$C$26,F$4) -> 43312.5 | G11: =Scenarios!$C$28*INDEX(Assumptions!$C$23:$C$26,G$4) -> 20790 | H11: =Scenarios!$C$28*INDEX(Assumptions!$C$23:$C$26,H$4) -> 13860 | I11: =0 -> 0 | J11: =0 -> 0 | K11: =0 -> 0 | L11: =0 -> 0 | M11: =0 -> 0 | N11: =0 -> 0 | O11: =0 -> 0 | P11: =0 -> 0 | ... AB11: =0 -> 0
C12: Delivery, localisation and QC ($) | D12: =SUM(E12:AB12) -> 58000 | E12: ='Title Inputs'!$C$32 -> 58000 | F12: =0 -> 0 | G12: =0 -> 0 | H12: =0 -> 0 | I12: =0 -> 0 | J12: =0 -> 0 | K12: =0 -> 0 | L12: =0 -> 0 | M12: =0 -> 0 | ... AB12: =0 -> 0
C13: Variable serving costs ($) | D13: =SUM(E13:AB13) -> 101605.2 | E13: ='Monthly Viewing Forecast'!E9*'Title Inputs'!$C$33 -> 13056.982 | F13: ='Monthly Viewing Forecast'!F9*'Title Inputs'!$C$33 -> 11450.973 | G13: ='Monthly Viewing Forecast'!G9*'Title Inputs'!$C$33 -> 10042.504 | H13: ='Monthly Viewing Forecast'!H9*'Title Inputs'!$C$33 -> 8807.2756 | I13: ='Monthly Viewing Forecast'!I9*'Title Inputs'!$C$33 -> 7723.9807 | J13: ='Monthly Viewing Forecast'!J9*'Title Inputs'!$C$33 -> 6773.9311 | K13: ='Monthly Viewing Forecast'!K9*'Title Inputs'!$C$33 -> 5940.7375 | L13: ='Monthly Viewing Forecast'!L9*'Title Inputs'!$C$33 -> 5210.0268 | ... AB13: ='Monthly Viewing Forecast'!AB9*'Title Inputs'!$C$33 -> 638.01877
C14: Contribution before licence fee ($) | D14: =SUM(E14:AB14) -> 824139.7 | E14: =E9+E10-E11-E12-E13 -> -17662.508 | F14: =F9+F10-F11-F12-F13 -> 75630.618 | G14: =G9+G10-G11-G12-G13 -> 83523.114 | H14: =H9+H10-H11-H12-H13 -> 77622.601 | I14: =I9+I10-I11-I12-I13 -> 80230.241 | J14: =J9+J10-J11-J12-J13 -> 70361.922 | K14: =K9+K10-K11-K12-K13 -> 61707.405 | L14: =L9+L10-L11-L12-L13 -> 54117.394 | ... AB14: =AB9+AB10-AB11-AB12-AB13 -> 6627.2045
A16: Downside | B16: Ash Ridge | C16: Incremental advertising revenue ($) | D16: =SUM(E16:AB16) -> 644473.23 | E16: ='Monthly Viewing Forecast'!E17*Scenarios!$D$27 -> 85694.019 | F16: ='Monthly Viewing Forecast'!F17*Scenarios!$D$27 -> 74725.184 | G16: ='Monthly Viewing Forecast'!G17*Scenarios!$D$27 -> 65160.361 | H16: ='Monthly Viewing Forecast'!H17*Scenarios!$D$27 -> 56819.835 | I16: ='Monthly Viewing Forecast'!I17*Scenarios!$D$27 -> 49546.896 | J16: ='Monthly Viewing Forecast'!J17*Scenarios!$D$27 -> 43204.893 | K16: ='Monthly Viewing Forecast'!K17*Scenarios!$D$27 -> 37674.667 | L16: ='Monthly Viewing Forecast'!L17*Scenarios!$D$27 -> 32852.309 | ... AB16: ='Monthly Viewing Forecast'!AB17*Scenarios!$D$27 -> 3671.3828
C17: Follow-on engagement value ($) | D17: =SUM(E17:AB17) -> 99106.889 | E17: ='Monthly Viewing Forecast'!E15*Scenarios!$D$27*'Title Inputs'!$D$34 -> 13177.999 | F17: ='Monthly Viewing Forecast'!F15*Scenarios!$D$27*'Title Inputs'!$D$34 -> 11491.215 | G17: ='Monthly Viewing Forecast'!G15*Scenarios!$D$27*'Title Inputs'!$D$34 -> 10020.34 | H17: ='Monthly Viewing Forecast'!H15*Scenarios!$D$27*'Title Inputs'!$D$34 -> 8737.7362 | I17: ='Monthly Viewing Forecast'!I15*Scenarios!$D$27*'Title Inputs'!$D$34 -> 7619.3059 | J17: ='Monthly Viewing Forecast'!J15*Scenarios!$D$27*'Title Inputs'!$D$34 -> 6644.0348 | K17: ='Monthly Viewing Forecast'!K15*Scenarios!$D$27*'Title Inputs'!$D$34 -> 5793.5983 | L17: ='Monthly Viewing Forecast'!L15*Scenarios!$D$27*'Title Inputs'!$D$34 -> 5052.0177 | ... AB17: ='Monthly Viewing Forecast'!AB15*Scenarios!$D$27*'Title Inputs'!$D$34 -> 564.58408
C18: Marketing support ($) | D18: =SUM(E18:AB18) -> 136500 | E18: =Scenarios!$D$28*INDEX(Assumptions!$C$23:$C$26,E$4) -> 75075 | F18: =Scenarios!$D$28*INDEX(Assumptions!$C$23:$C$26,F$4) -> 34125 | G18: =Scenarios!$D$28*INDEX(Assumptions!$C$23:$C$26,G$4) -> 16380 | H18: =Scenarios!$D$28*INDEX(Assumptions!$C$23:$C$26,H$4) -> 10920 | I18: =0 -> 0 | J18: =0 -> 0 | K18: =0 -> 0 | L18: =0 -> 0 | M18: =0 -> 0 | N18: =0 -> 0 | O18: =0 -> 0 | P18: =0 -> 0 | ... AB18: =0 -> 0
C19: Delivery, localisation and QC ($) | D19: =SUM(E19:AB19) -> 52000 | E19: ='Title Inputs'!$D$32 -> 52000 | F19: =0 -> 0 | G19: =0 -> 0 | H19: =0 -> 0 | I19: =0 -> 0 | J19: =0 -> 0 | K19: =0 -> 0 | L19: =0 -> 0 | M19: =0 -> 0 | ... AB19: =0 -> 0
C20: Variable serving costs ($) | D20: =SUM(E20:AB20) -> 74378.121 | E20: ='Monthly Viewing Forecast'!E15*'Title Inputs'!$D$33 -> 9889.8757 | F20: ='Monthly Viewing Forecast'!F15*'Title Inputs'!$D$33 -> 8623.9716 | G20: ='Monthly Viewing Forecast'!G15*'Title Inputs'!$D$33 -> 7520.1032 | H20: ='Monthly Viewing Forecast'!H15*'Title Inputs'!$D$33 -> 6557.53 | I20: ='Monthly Viewing Forecast'!I15*'Title Inputs'!$D$33 -> 5718.1662 | J20: ='Monthly Viewing Forecast'!J15*'Title Inputs'!$D$33 -> 4986.2409 | K20: ='Monthly Viewing Forecast'!K15*'Title Inputs'!$D$33 -> 4348.0021 | L20: ='Monthly Viewing Forecast'!L15*'Title Inputs'!$D$33 -> 3791.4578 | ... AB20: ='Monthly Viewing Forecast'!AB15*'Title Inputs'!$D$33 -> 423.71124
C21: Contribution before licence fee ($) | D21: =SUM(E21:AB21) -> 480701.99 | E21: =E16+E17-E18-E19-E20 -> -38092.858 | F21: =F16+F17-F18-F19-F20 -> 43467.428 | G21: =G16+G17-G18-G19-G20 -> 51280.597 | H21: =H16+H17-H18-H19-H20 -> 48080.041 | I21: =I16+I17-I18-I19-I20 -> 51448.035 | J21: =J16+J17-J18-J19-J20 -> 44862.687 | K21: =K16+K17-K18-K19-K20 -> 39120.263 | L21: =L16+L17-L18-L19-L20 -> 34112.869 | ... AB21: =AB16+AB17-AB18-AB19-AB20 -> 3812.2556
A23: Downside | B23: Cold Harbor | C23: Incremental advertising revenue ($) | D23: =SUM(E23:AB23) -> 407722.05 | E23: ='Monthly Viewing Forecast'!E23*Scenarios!$E$27 -> 57161.934 | F23: ='Monthly Viewing Forecast'!F23*Scenarios!$E$27 -> 49387.911 | G23: ='Monthly Viewing Forecast'!G23*Scenarios!$E$27 -> 42671.155 | H23: ='Monthly Viewing Forecast'!H23*Scenarios!$E$27 -> 36867.878 | I23: ='Monthly Viewing Forecast'!I23*Scenarios!$E$27 -> 31853.847 | J23: ='Monthly Viewing Forecast'!J23*Scenarios!$E$27 -> 27521.724 | K23: ='Monthly Viewing Forecast'!K23*Scenarios!$E$27 -> 23778.769 | L23: ='Monthly Viewing Forecast'!L23*Scenarios!$E$27 -> 20544.857 | ... AB23: ='Monthly Viewing Forecast'!AB23*Scenarios!$E$27 -> 1981.1757
C24: Follow-on engagement value ($) | D24: =SUM(E24:AB24) -> 68380.123 | E24: ='Monthly Viewing Forecast'!E21*Scenarios!$E$27*'Title Inputs'!$E$34 -> 9586.7764 | F24: ='Monthly Viewing Forecast'!F21*Scenarios!$E$27*'Title Inputs'!$E$34 -> 8282.9749 | G24: ='Monthly Viewing Forecast'!G21*Scenarios!$E$27*'Title Inputs'!$E$34 -> 7156.4903 | H24: ='Monthly Viewing Forecast'!H21*Scenarios!$E$27*'Title Inputs'!$E$34 -> 6183.2076 | I24: ='Monthly Viewing Forecast'!I21*Scenarios!$E$27*'Title Inputs'!$E$34 -> 5342.2914 | J24: ='Monthly Viewing Forecast'!J21*Scenarios!$E$27*'Title Inputs'!$E$34 -> 4615.7397 | K24: ='Monthly Viewing Forecast'!K21*Scenarios!$E$27*'Title Inputs'!$E$34 -> 3987.9991 | L24: ='Monthly Viewing Forecast'!L21*Scenarios!$E$27*'Title Inputs'!$E$34 -> 3445.6313 | ... AB24: ='Monthly Viewing Forecast'!AB21*Scenarios!$E$27*'Title Inputs'!$E$34 -> 332.26812
C25: Marketing support ($) | D25: =SUM(E25:AB25) -> 105000 | E25: =Scenarios!$E$28*INDEX(Assumptions!$C$23:$C$26,E$4) -> 57750 | F25: =Scenarios!$E$28*INDEX(Assumptions!$C$23:$C$26,F$4) -> 26250 | G25: =Scenarios!$E$28*INDEX(Assumptions!$C$23:$C$26,G$4) -> 12600 | H25: =Scenarios!$E$28*INDEX(Assumptions!$C$23:$C$26,H$4) -> 8400 | I25: =0 -> 0 | J25: =0 -> 0 | K25: =0 -> 0 | L25: =0 -> 0 | M25: =0 -> 0 | N25: =0 -> 0 | O25: =0 -> 0 | P25: =0 -> 0 | ... AB25: =0 -> 0
C26: Delivery, localisation and QC ($) | D26: =SUM(E26:AB26) -> 46000 | E26: ='Title Inputs'!$E$32 -> 46000 | F26: =0 -> 0 | G26: =0 -> 0 | H26: =0 -> 0 | I26: =0 -> 0 | J26: =0 -> 0 | K26: =0 -> 0 | L26: =0 -> 0 | M26: =0 -> 0 | ... AB26: =0 -> 0
C27: Variable serving costs ($) | D27: =SUM(E27:AB27) -> 54117.353 | E27: ='Monthly Viewing Forecast'!E21*'Title Inputs'!$E$33 -> 7587.1604 | F27: ='Monthly Viewing Forecast'!F21*'Title Inputs'!$E$33 -> 6555.3066 | G27: ='Monthly Viewing Forecast'!G21*'Title Inputs'!$E$33 -> 5663.7849 | H27: ='Monthly Viewing Forecast'!H21*'Title Inputs'!$E$33 -> 4893.5101 | I27: ='Monthly Viewing Forecast'!I21*'Title Inputs'!$E$33 -> 4227.9927 | J27: ='Monthly Viewing Forecast'!J21*'Title Inputs'!$E$33 -> 3652.9857 | K27: ='Monthly Viewing Forecast'!K21*'Title Inputs'!$E$33 -> 3156.1797 | L27: ='Monthly Viewing Forecast'!L21*'Title Inputs'!$E$33 -> 2726.9392 | ... AB27: ='Monthly Viewing Forecast'!AB21*'Title Inputs'!$E$33 -> 262.96342
C28: Contribution before licence fee ($) | D28: =SUM(E28:AB28) -> 270984.82 | E28: =E23+E24-E25-E26-E27 -> -44588.45 | F28: =F23+F24-F25-F26-F27 -> 24865.58 | G28: =G23+G24-G25-G26-G27 -> 31563.861 | H28: =H23+H24-H25-H26-H27 -> 29757.576 | I28: =I23+I24-I25-I26-I27 -> 32968.145 | J28: =J23+J24-J25-J26-J27 -> 28484.478 | K28: =K23+K24-K25-K26-K27 -> 24610.589 | L28: =L23+L24-L25-L26-L27 -> 21263.549 | ... AB28: =AB23+AB24-AB25-AB26-AB27 -> 2050.4804
A30: Downside | B30: The Quiet Depth | C30: Incremental advertising revenue ($) | D30: =SUM(E30:AB30) -> 186760.51 | E30: ='Monthly Viewing Forecast'!E29*Scenarios!$F$27 -> 28245.192 | F30: ='Monthly Viewing Forecast'!F29*Scenarios!$F$27 -> 24064.904 | G30: ='Monthly Viewing Forecast'!G29*Scenarios!$F$27 -> 20503.298 | H30: ='Monthly Viewing Forecast'!H29*Scenarios!$F$27 -> 17468.81 | I30: ='Monthly Viewing Forecast'!I29*Scenarios!$F$27 -> 14883.426 | J30: ='Monthly Viewing Forecast'!J29*Scenarios!$F$27 -> 12680.679 | K30: ='Monthly Viewing Forecast'!K29*Scenarios!$F$27 -> 10803.938 | L30: ='Monthly Viewing Forecast'!L29*Scenarios!$F$27 -> 9204.9555 | ... AB30: ='Monthly Viewing Forecast'!AB29*Scenarios!$F$27 -> 709.66798
C31: Follow-on engagement value ($) | D31: =SUM(E31:AB31) -> 36829.767 | E31: ='Monthly Viewing Forecast'!E27*Scenarios!$F$27*'Title Inputs'!$F$34 -> 5570.0418 | F31: ='Monthly Viewing Forecast'!F27*Scenarios!$F$27*'Title Inputs'!$F$34 -> 4745.6756 | G31: ='Monthly Viewing Forecast'!G27*Scenarios!$F$27*'Title Inputs'!$F$34 -> 4043.3156 | H31: ='Monthly Viewing Forecast'!H27*Scenarios!$F$27*'Title Inputs'!$F$34 -> 3444.9049 | I31: ='Monthly Viewing Forecast'!I27*Scenarios!$F$27*'Title Inputs'!$F$34 -> 2935.059 | J31: ='Monthly Viewing Forecast'!J27*Scenarios!$F$27*'Title Inputs'!$F$34 -> 2500.6703 | K31: ='Monthly Viewing Forecast'!K27*Scenarios!$F$27*'Title Inputs'!$F$34 -> 2130.5711 | L31: ='Monthly Viewing Forecast'!L27*Scenarios!$F$27*'Title Inputs'!$F$34 -> 1815.2466 | ... AB31: ='Monthly Viewing Forecast'!AB27*Scenarios!$F$27*'Title Inputs'!$F$34 -> 139.94879
C32: Marketing support ($) | D32: =SUM(E32:AB32) -> 75600 | E32: =Scenarios!$F$28*INDEX(Assumptions!$C$23:$C$26,E$4) -> 41580 | F32: =Scenarios!$F$28*INDEX(Assumptions!$C$23:$C$26,F$4) -> 18900 | G32: =Scenarios!$F$28*INDEX(Assumptions!$C$23:$C$26,G$4) -> 9072 | H32: =Scenarios!$F$28*INDEX(Assumptions!$C$23:$C$26,H$4) -> 6048 | I32: =0 -> 0 | J32: =0 -> 0 | K32: =0 -> 0 | L32: =0 -> 0 | M32: =0 -> 0 | N32: =0 -> 0 | O32: =0 -> 0 | P32: =0 -> 0 | ... AB32: =0 -> 0
C33: Delivery, localisation and QC ($) | D33: =SUM(E33:AB33) -> 44000 | E33: ='Title Inputs'!$F$32 -> 44000 | F33: =0 -> 0 | G33: =0 -> 0 | H33: =0 -> 0 | I33: =0 -> 0 | J33: =0 -> 0 | K33: =0 -> 0 | L33: =0 -> 0 | M33: =0 -> 0 | ... AB33: =0 -> 0
C34: Variable serving costs ($) | D34: =SUM(E34:AB34) -> 34109.116 | E34: ='Monthly Viewing Forecast'!E27*'Title Inputs'!$F$33 -> 5158.5774 | F34: ='Monthly Viewing Forecast'!F27*'Title Inputs'!$F$33 -> 4395.108 | G34: ='Monthly Viewing Forecast'!G27*'Title Inputs'!$F$33 -> 3744.632 | H34: ='Monthly Viewing Forecast'!H27*'Title Inputs'!$F$33 -> 3190.4264 | I34: ='Monthly Viewing Forecast'!I27*'Title Inputs'!$F$33 -> 2718.2433 | J34: ='Monthly Viewing Forecast'!J27*'Title Inputs'!$F$33 -> 2315.9433 | K34: ='Monthly Viewing Forecast'!K27*'Title Inputs'!$F$33 -> 1973.1837 | L34: ='Monthly Viewing Forecast'!L27*'Title Inputs'!$F$33 -> 1681.1525 | ... AB34: ='Monthly Viewing Forecast'!AB27*'Title Inputs'!$F$33 -> 129.61063
C35: Contribution before licence fee ($) | D35: =SUM(E35:AB35) -> 69881.157 | E35: =E30+E31-E32-E33-E34 -> -56923.344 | F35: =F30+F31-F32-F33-F34 -> 5515.4712 | G35: =G30+G31-G32-G33-G34 -> 11729.981 | H35: =H30+H31-H32-H33-H34 -> 11675.288 | I35: =I30+I31-I32-I33-I34 -> 15100.242 | J35: =J30+J31-J32-J33-J34 -> 12865.406 | K35: =K30+K31-K32-K33-K34 -> 10961.326 | L35: =L30+L31-L32-L33-L34 -> 9339.0495 | ... AB35: =AB30+AB31-AB32-AB33-AB34 -> 720.00613
A37: Downside | B37: Vector Nine | C37: Incremental advertising revenue ($) | D37: =SUM(E37:AB37) -> 49975.688 | E37: ='Monthly Viewing Forecast'!E35*Scenarios!$G$27 -> 8025.5681 | F37: ='Monthly Viewing Forecast'!F35*Scenarios!$G$27 -> 6757.5283 | G37: ='Monthly Viewing Forecast'!G35*Scenarios!$G$27 -> 5689.8389 | H37: ='Monthly Viewing Forecast'!H35*Scenarios!$G$27 -> 4790.8443 | I37: ='Monthly Viewing Forecast'!I35*Scenarios!$G$27 -> 4033.8909 | J37: ='Monthly Viewing Forecast'!J35*Scenarios!$G$27 -> 3396.5362 | K37: ='Monthly Viewing Forecast'!K35*Scenarios!$G$27 -> 2859.8834 | L37: ='Monthly Viewing Forecast'!L35*Scenarios!$G$27 -> 2408.0219 | ... AB37: ='Monthly Viewing Forecast'!AB35*Scenarios!$G$27 -> 153.69293
C38: Follow-on engagement value ($) | D38: =SUM(E38:AB38) -> 10896.496 | E38: ='Monthly Viewing Forecast'!E33*Scenarios!$G$27*'Title Inputs'!$G$34 -> 1749.8622 | F38: ='Monthly Viewing Forecast'!F33*Scenarios!$G$27*'Title Inputs'!$G$34 -> 1473.384 | G38: ='Monthly Viewing Forecast'!G33*Scenarios!$G$27*'Title Inputs'!$G$34 -> 1240.5893 | H38: ='Monthly Viewing Forecast'!H33*Scenarios!$G$27*'Title Inputs'!$G$34 -> 1044.5762 | I38: ='Monthly Viewing Forecast'!I33*Scenarios!$G$27*'Title Inputs'!$G$34 -> 879.53317 | J38: ='Monthly Viewing Forecast'!J33*Scenarios!$G$27*'Title Inputs'!$G$34 -> 740.56693 | K38: ='Monthly Viewing Forecast'!K33*Scenarios!$G$27*'Title Inputs'!$G$34 -> 623.55735 | L38: ='Monthly Viewing Forecast'!L33*Scenarios!$G$27*'Title Inputs'!$G$34 -> 525.03529 | ... AB38: ='Monthly Viewing Forecast'!AB33*Scenarios!$G$27*'Title Inputs'!$G$34 -> 33.510581
C39: Marketing support ($) | D39: =SUM(E39:AB39) -> 60900 | E39: =Scenarios!$G$28*INDEX(Assumptions!$C$23:$C$26,E$4) -> 33495 | F39: =Scenarios!$G$28*INDEX(Assumptions!$C$23:$C$26,F$4) -> 15225 | G39: =Scenarios!$G$28*INDEX(Assumptions!$C$23:$C$26,G$4) -> 7308 | H39: =Scenarios!$G$28*INDEX(Assumptions!$C$23:$C$26,H$4) -> 4872 | I39: =0 -> 0 | J39: =0 -> 0 | K39: =0 -> 0 | L39: =0 -> 0 | M39: =0 -> 0 | N39: =0 -> 0 | O39: =0 -> 0 | P39: =0 -> 0 | ... AB39: =0 -> 0
C40: Delivery, localisation and QC ($) | D40: =SUM(E40:AB40) -> 40000 | E40: ='Title Inputs'!$G$32 -> 40000 | F40: =0 -> 0 | G40: =0 -> 0 | H40: =0 -> 0 | I40: =0 -> 0 | J40: =0 -> 0 | K40: =0 -> 0 | L40: =0 -> 0 | M40: =0 -> 0 | ... AB40: =0 -> 0
C41: Variable serving costs ($) | D41: =SUM(E41:AB41) -> 11857.584 | E41: ='Monthly Viewing Forecast'!E33*'Title Inputs'!$G$33 -> 1904.2029 | F41: ='Monthly Viewing Forecast'!F33*'Title Inputs'!$G$33 -> 1603.3388 | G41: ='Monthly Viewing Forecast'!G33*'Title Inputs'!$G$33 -> 1350.0113 | H41: ='Monthly Viewing Forecast'!H33*'Title Inputs'!$G$33 -> 1136.7095 | I41: ='Monthly Viewing Forecast'!I33*'Title Inputs'!$G$33 -> 957.1094 | J41: ='Monthly Viewing Forecast'!J33*'Title Inputs'!$G$33 -> 805.88612 | K41: ='Monthly Viewing Forecast'!K33*'Title Inputs'!$G$33 -> 678.55611 | L41: ='Monthly Viewing Forecast'!L33*'Title Inputs'!$G$33 -> 571.34425 | ... AB41: ='Monthly Viewing Forecast'!AB33*'Title Inputs'!$G$33 -> 36.466268
C42: Contribution before licence fee ($) | D42: =SUM(E42:AB42) -> -51885.401 | E42: =E37+E38-E39-E40-E41 -> -65623.773 | F42: =F37+F38-F39-F40-F41 -> -8597.4265 | G42: =G37+G38-G39-G40-G41 -> -1727.5831 | H42: =H37+H38-H39-H40-H41 -> -173.28897 | I42: =I37+I38-I39-I40-I41 -> 3956.3147 | J42: =J37+J38-J39-J40-J41 -> 3331.217 | K42: =K37+K38-K39-K40-K41 -> 2804.8847 | L42: =L37+L38-L39-L40-L41 -> 2361.7129 | ... AB42: =AB37+AB38-AB39-AB40-AB41 -> 150.73724
B44: PORTFOLIO | C44: Portfolio incremental advertising revenue ($) | D44: =$D$9+$D$16+$D$23+$D$30+$D$37 -> 2301203.1 | E44: =E9+E16+E23+E30+E37 -> 309210.73 | F44: =F9+F16+F23+F30+F37 -> 269019.21 | G44: =G9+G16+G23+G30+G37 -> 234076.05 | H44: =H9+H16+H23+H30+H37 -> 203692.44 | I44: =I9+I16+I23+I30+I37 -> 177270.49 | J44: =J9+J16+J23+J30+J37 -> 154291.11 | K44: =K9+K16+K23+K30+K37 -> 134303.6 | L44: =L9+L16+L23+L30+L37 -> 116916.57 | ... AB44: =AB9+AB16+AB23+AB30+AB37 -> 12872.369
B45: PORTFOLIO | C45: Portfolio follow-on engagement value ($) | D45: =$D$10+$D$17+$D$24+$D$31+$D$38 -> 359936.51 | E45: =E10+E17+E24+E31+E38 -> 48682.632 | F45: =F10+F17+F24+F31+F38 -> 42303.654 | G45: =G10+G17+G24+G31+G38 -> 36764.96 | H45: =H10+H17+H24+H31+H38 -> 31955.23 | I45: =I10+I17+I24+I31+I38 -> 27777.984 | J45: =J10+J17+J24+J31+J38 -> 24149.585 | K45: =K10+K17+K24+K31+K38 -> 20997.525 | L45: =L10+L17+L24+L31+L38 -> 18258.929 | ... AB45: =AB10+AB17+AB24+AB31+AB38 -> 1979.0853
B46: PORTFOLIO | C46: Portfolio marketing support ($) | D46: =$D$11+$D$18+$D$25+$D$32+$D$39 -> 551250 | E46: =E11+E18+E25+E32+E39 -> 303187.5 | F46: =F11+F18+F25+F32+F39 -> 137812.5 | G46: =G11+G18+G25+G32+G39 -> 66150 | H46: =H11+H18+H25+H32+H39 -> 44100 | I46: =I11+I18+I25+I32+I39 -> 0 | J46: =J11+J18+J25+J32+J39 -> 0 | K46: =K11+K18+K25+K32+K39 -> 0 | L46: =L11+L18+L25+L32+L39 -> 0 | ... AB46: =AB11+AB18+AB25+AB32+AB39 -> 0
B47: PORTFOLIO | C47: Portfolio delivery, localisation and QC ($) | D47: =$D$12+$D$19+$D$26+$D$33+$D$40 -> 240000 | E47: =E12+E19+E26+E33+E40 -> 240000 | F47: =F12+F19+F26+F33+F40 -> 0 | G47: =G12+G19+G26+G33+G40 -> 0 | H47: =H12+H19+H26+H33+H40 -> 0 | I47: =I12+I19+I26+I33+I40 -> 0 | J47: =J12+J19+J26+J33+J40 -> 0 | K47: =K12+K19+K26+K33+K40 -> 0 | L47: =L12+L19+L26+L33+L40 -> 0 | ... AB47: =AB12+AB19+AB26+AB33+AB40 -> 0
B48: PORTFOLIO | C48: Portfolio variable serving costs ($) | D48: =$D$13+$D$20+$D$27+$D$34+$D$41 -> 276067.37 | E48: =E13+E20+E27+E34+E41 -> 37596.798 | F48: =F13+F20+F27+F34+F41 -> 32628.698 | G48: =G13+G20+G27+G34+G41 -> 28321.035 | H48: =H13+H20+H27+H34+H41 -> 24585.452 | I48: =I13+I20+I27+I34+I41 -> 21345.492 | J48: =J13+J20+J27+J34+J41 -> 18534.987 | K48: =K13+K20+K27+K34+K41 -> 16096.659 | L48: =L13+L20+L27+L34+L41 -> 13980.921 | ... AB48: =AB13+AB20+AB27+AB34+AB41 -> 1490.7703
B49: PORTFOLIO | C49: Total modelled benefits ($) | D49: =SUM(E49:AB49) -> 2661139.6 | E49: =E44+E45 -> 357893.37 | F49: =F44+F45 -> 311322.87 | G49: =G44+G45 -> 270841.01 | H49: =H44+H45 -> 235647.67 | I49: =I44+I45 -> 205048.47 | J49: =J44+J45 -> 178440.7 | K49: =K44+K45 -> 155301.13 | L49: =L44+L45 -> 135175.5 | ... AB49: =AB44+AB45 -> 14851.454
B50: PORTFOLIO | C50: Total support costs ($) | D50: =SUM(E50:AB50) -> 1067317.4 | E50: =E46+E47+E48 -> 580784.3 | F50: =F46+F47+F48 -> 170441.2 | G50: =G46+G47+G48 -> 94471.035 | H50: =H46+H47+H48 -> 68685.452 | I50: =I46+I47+I48 -> 21345.492 | J50: =J46+J47+J48 -> 18534.987 | K50: =K46+K47+K48 -> 16096.659 | L50: =L46+L47+L48 -> 13980.921 | ... AB50: =AB46+AB47+AB48 -> 1490.7703
B51: PORTFOLIO | C51: Contribution before licence fee ($) | D51: =SUM(E51:AB51) -> 1593822.3 | E51: =E49-E50 -> -222890.93 | F51: =F49-F50 -> 140881.67 | G51: =G49-G50 -> 176369.97 | H51: =H49-H50 -> 166962.22 | I51: =I49-I50 -> 183702.98 | J51: =J49-J50 -> 159905.71 | K51: =K49-K50 -> 139204.47 | L51: =L49-L50 -> 121194.57 | ... AB51: =AB49-AB50 -> 13360.684
C52: PV of modelled benefits ($) | D52: =SUMPRODUCT(E49:AB49,'Title Economics'!$E$6:$AB$6) -> 2498097.6
C53: PV of support costs ($) | D53: =SUMPRODUCT(E50:AB50,'Title Economics'!$E$6:$AB$6) -> 1039381.4
C54: PV of contribution before licence fee ($) | D54: =SUMPRODUCT(E51:AB51,'Title Economics'!$E$6:$AB$6) -> 1458716.2
C55: PV of incremental advertising revenue ($) | D55: =SUMPRODUCT(E44:AB44,'Title Economics'!$E$6:$AB$6) -> 2160128
C56: PV of follow-on engagement value ($) | D56: =SUMPRODUCT(E45:AB45,'Title Economics'!$E$6:$AB$6) -> 337969.62
C57: PV of variable serving costs ($) | D57: =SUMPRODUCT(E48:AB48,'Title Economics'!$E$6:$AB$6) -> 259298.45
C58: PV of fixed support costs (marketing, delivery and QC) ($) | D58: =SUMPRODUCT(E46:AB46,'Title Economics'!$E$6:$AB$6)+SUMPRODUCT(E47:AB47,'Title Economics'!$E$6:$AB$6) -> 780082.93
A61: BASE SCENARIO
A62: Base | B62: Nightfall Protocol | C62: Incremental advertising revenue ($) | D62: =SUM(E62:AB62) -> 1221862.4 | E62: ='Monthly Viewing Forecast'!E50*Scenarios!$C$36 -> 148423.53 | F62: ='Monthly Viewing Forecast'!F50*Scenarios!$C$36 -> 131354.82 | G62: ='Monthly Viewing Forecast'!G50*Scenarios!$C$36 -> 116249.02 | H62: ='Monthly Viewing Forecast'!H50*Scenarios!$C$36 -> 102880.38 | I62: ='Monthly Viewing Forecast'!I50*Scenarios!$C$36 -> 91049.139 | J62: ='Monthly Viewing Forecast'!J50*Scenarios!$C$36 -> 80578.488 | K62: ='Monthly Viewing Forecast'!K50*Scenarios!$C$36 -> 71311.962 | L62: ='Monthly Viewing Forecast'!L50*Scenarios!$C$36 -> 63111.086 | ... AB62: ='Monthly Viewing Forecast'!AB50*Scenarios!$C$36 -> 8937.1281
C63: Follow-on engagement value ($) | D63: =SUM(E63:AB63) -> 164346.62 | E63: ='Monthly Viewing Forecast'!E48*Scenarios!$C$36*'Title Inputs'!$C$34 -> 19963.71 | F63: ='Monthly Viewing Forecast'!F48*Scenarios!$C$36*'Title Inputs'!$C$34 -> 17667.884 | G63: ='Monthly Viewing Forecast'!G48*Scenarios!$C$36*'Title Inputs'!$C$34 -> 15636.077 | H63: ='Monthly Viewing Forecast'!H48*Scenarios!$C$36*'Title Inputs'!$C$34 -> 13837.928 | I63: ='Monthly Viewing Forecast'!I48*Scenarios!$C$36*'Title Inputs'!$C$34 -> 12246.566 | J63: ='Monthly Viewing Forecast'!J48*Scenarios!$C$36*'Title Inputs'!$C$34 -> 10838.211 | K63: ='Monthly Viewing Forecast'!K48*Scenarios!$C$36*'Title Inputs'!$C$34 -> 9591.8169 | L63: ='Monthly Viewing Forecast'!L48*Scenarios!$C$36*'Title Inputs'!$C$34 -> 8488.758 | ... AB63: ='Monthly Viewing Forecast'!AB48*Scenarios!$C$36*'Title Inputs'!$C$34 -> 1202.0886
C64: Marketing support ($) | D64: =SUM(E64:AB64) -> 165000 | E64: =Scenarios!$C$37*INDEX(Assumptions!$C$23:$C$26,E$4) -> 90750 | F64: =Scenarios!$C$37*INDEX(Assumptions!$C$23:$C$26,F$4) -> 41250 | G64: =Scenarios!$C$37*INDEX(Assumptions!$C$23:$C$26,G$4) -> 19800 | H64: =Scenarios!$C$37*INDEX(Assumptions!$C$23:$C$26,H$4) -> 13200 | I64: =0 -> 0 | J64: =0 -> 0 | K64: =0 -> 0 | L64: =0 -> 0 | M64: =0 -> 0 | N64: =0 -> 0 | O64: =0 -> 0 | P64: =0 -> 0 | ... AB64: =0 -> 0
C65: Delivery, localisation and QC ($) | D65: =SUM(E65:AB65) -> 58000 | E65: ='Title Inputs'!$C$32 -> 58000 | F65: =0 -> 0 | G65: =0 -> 0 | H65: =0 -> 0 | I65: =0 -> 0 | J65: =0 -> 0 | K65: =0 -> 0 | L65: =0 -> 0 | M65: =0 -> 0 | ... AB65: =0 -> 0
C66: Variable serving costs ($) | D66: =SUM(E66:AB66) -> 111920.64 | E66: ='Monthly Viewing Forecast'!E48*'Title Inputs'!$C$33 -> 13595.358 | F66: ='Monthly Viewing Forecast'!F48*'Title Inputs'!$C$33 -> 12031.892 | G66: ='Monthly Viewing Forecast'!G48*'Title Inputs'!$C$33 -> 10648.224 | H66: ='Monthly Viewing Forecast'!H48*'Title Inputs'!$C$33 -> 9423.6786 | I66: ='Monthly Viewing Forecast'!I48*'Title Inputs'!$C$33 -> 8339.9556 | J66: ='Monthly Viewing Forecast'!J48*'Title Inputs'!$C$33 -> 7380.8607 | K66: ='Monthly Viewing Forecast'!K48*'Title Inputs'!$C$33 -> 6532.0617 | L66: ='Monthly Viewing Forecast'!L48*'Title Inputs'!$C$33 -> 5780.8746 | ... AB66: ='Monthly Viewing Forecast'!AB48*'Title Inputs'!$C$33 -> 818.62665
C67: Contribution before licence fee ($) | D67: =SUM(E67:AB67) -> 1051288.4 | E67: =E62+E63-E64-E65-E66 -> 6041.8826 | F67: =F62+F63-F64-F65-F66 -> 95740.816 | G67: =G62+G63-G64-G65-G66 -> 101436.87 | H67: =H62+H63-H64-H65-H66 -> 94094.632 | I67: =I62+I63-I64-I65-I66 -> 94955.749 | J67: =J62+J63-J64-J65-J66 -> 84035.838 | K67: =K62+K63-K64-K65-K66 -> 74371.717 | L67: =L62+L63-L64-L65-L66 -> 65818.969 | ... AB67: =AB62+AB63-AB64-AB65-AB66 -> 9320.5901
A69: Base | B69: Ash Ridge | C69: Incremental advertising revenue ($) | D69: =SUM(E69:AB69) -> 776895.08 | E69: ='Monthly Viewing Forecast'!E56*Scenarios!$D$36 -> 97775.336 | F69: ='Monthly Viewing Forecast'!F56*Scenarios!$D$36 -> 86042.295 | G69: ='Monthly Viewing Forecast'!G56*Scenarios!$D$36 -> 75717.22 | H69: ='Monthly Viewing Forecast'!H56*Scenarios!$D$36 -> 66631.154 | I69: ='Monthly Viewing Forecast'!I56*Scenarios!$D$36 -> 58635.415 | J69: ='Monthly Viewing Forecast'!J56*Scenarios!$D$36 -> 51599.165 | K69: ='Monthly Viewing Forecast'!K56*Scenarios!$D$36 -> 45407.265 | L69: ='Monthly Viewing Forecast'!L56*Scenarios!$D$36 -> 39958.394 | ... AB69: ='Monthly Viewing Forecast'!AB56*Scenarios!$D$36 -> 5168.0984
C70: Follow-on engagement value ($) | D70: =SUM(E70:AB70) -> 112398.01 | E70: ='Monthly Viewing Forecast'!E54*Scenarios!$D$36*'Title Inputs'!$D$34 -> 14145.737 | F70: ='Monthly Viewing Forecast'!F54*Scenarios!$D$36*'Title Inputs'!$D$34 -> 12448.249 | G70: ='Monthly Viewing Forecast'!G54*Scenarios!$D$36*'Title Inputs'!$D$34 -> 10954.459 | H70: ='Monthly Viewing Forecast'!H54*Scenarios!$D$36*'Title Inputs'!$D$34 -> 9639.9238 | I70: ='Monthly Viewing Forecast'!I54*Scenarios!$D$36*'Title Inputs'!$D$34 -> 8483.133 | J70: ='Monthly Viewing Forecast'!J54*Scenarios!$D$36*'Title Inputs'!$D$34 -> 7465.157 | K70: ='Monthly Viewing Forecast'!K54*Scenarios!$D$36*'Title Inputs'!$D$34 -> 6569.3382 | L70: ='Monthly Viewing Forecast'!L54*Scenarios!$D$36*'Title Inputs'!$D$34 -> 5781.0176 | ... AB70: ='Monthly Viewing Forecast'!AB54*Scenarios!$D$36*'Title Inputs'!$D$34 -> 747.69942
C71: Marketing support ($) | D71: =SUM(E71:AB71) -> 130000 | E71: =Scenarios!$D$37*INDEX(Assumptions!$C$23:$C$26,E$4) -> 71500 | F71: =Scenarios!$D$37*INDEX(Assumptions!$C$23:$C$26,F$4) -> 32500 | G71: =Scenarios!$D$37*INDEX(Assumptions!$C$23:$C$26,G$4) -> 15600 | H71: =Scenarios!$D$37*INDEX(Assumptions!$C$23:$C$26,H$4) -> 10400 | I71: =0 -> 0 | J71: =0 -> 0 | K71: =0 -> 0 | L71: =0 -> 0 | M71: =0 -> 0 | N71: =0 -> 0 | O71: =0 -> 0 | P71: =0 -> 0 | ... AB71: =0 -> 0
C72: Delivery, localisation and QC ($) | D72: =SUM(E72:AB72) -> 52000 | E72: ='Title Inputs'!$D$32 -> 52000 | F72: =0 -> 0 | G72: =0 -> 0 | H72: =0 -> 0 | I72: =0 -> 0 | J72: =0 -> 0 | K72: =0 -> 0 | L72: =0 -> 0 | M72: =0 -> 0 | ... AB72: =0 -> 0
C73: Variable serving costs ($) | D73: =SUM(E73:AB73) -> 81822.309 | E73: ='Monthly Viewing Forecast'!E54*'Title Inputs'!$D$33 -> 10297.663 | F73: ='Monthly Viewing Forecast'!F54*'Title Inputs'!$D$33 -> 9061.9435 | G73: ='Monthly Viewing Forecast'!G54*'Title Inputs'!$D$33 -> 7974.5103 | H73: ='Monthly Viewing Forecast'!H54*'Title Inputs'!$D$33 -> 7017.5691 | I73: ='Monthly Viewing Forecast'!I54*'Title Inputs'!$D$33 -> 6175.4608 | J73: ='Monthly Viewing Forecast'!J54*'Title Inputs'!$D$33 -> 5434.4055 | K73: ='Monthly Viewing Forecast'!K54*'Title Inputs'!$D$33 -> 4782.2768 | L73: ='Monthly Viewing Forecast'!L54*'Title Inputs'!$D$33 -> 4208.4036 | ... AB73: ='Monthly Viewing Forecast'!AB54*'Title Inputs'!$D$33 -> 544.30226
C74: Contribution before licence fee ($) | D74: =SUM(E74:AB74) -> 625470.78 | E74: =E69+E70-E71-E72-E73 -> -21876.59 | F74: =F69+F70-F71-F72-F73 -> 56928.601 | G74: =G69+G70-G71-G72-G73 -> 63097.169 | H74: =H69+H70-H71-H72-H73 -> 58853.508 | I74: =I69+I70-I71-I72-I73 -> 60943.087 | J74: =J69+J70-J71-J72-J73 -> 53629.917 | K74: =K69+K70-K71-K72-K73 -> 47194.327 | L74: =L69+L70-L71-L72-L73 -> 41531.008 | ... AB74: =AB69+AB70-AB71-AB72-AB73 -> 5371.4956
A76: Base | B76: Cold Harbor | C76: Incremental advertising revenue ($) | D76: =SUM(E76:AB76) -> 490501.22 | E76: ='Monthly Viewing Forecast'!E62*Scenarios!$E$36 -> 65220.74 | F76: ='Monthly Viewing Forecast'!F62*Scenarios!$E$36 -> 56872.485 | G76: ='Monthly Viewing Forecast'!G62*Scenarios!$E$36 -> 49592.807 | H76: ='Monthly Viewing Forecast'!H62*Scenarios!$E$36 -> 43244.928 | I76: ='Monthly Viewing Forecast'!I62*Scenarios!$E$36 -> 37709.577 | J76: ='Monthly Viewing Forecast'!J62*Scenarios!$E$36 -> 32882.751 | K76: ='Monthly Viewing Forecast'!K62*Scenarios!$E$36 -> 28673.759 | L76: ='Monthly Viewing Forecast'!L62*Scenarios!$E$36 -> 25003.518 | ... AB76: ='Monthly Viewing Forecast'!AB62*Scenarios!$E$36 -> 2794.2475
C77: Follow-on engagement value ($) | D77: =SUM(E77:AB77) -> 77393.25 | E77: ='Monthly Viewing Forecast'!E60*Scenarios!$E$36*'Title Inputs'!$E$34 -> 10290.79 | F77: ='Monthly Viewing Forecast'!F60*Scenarios!$E$36*'Title Inputs'!$E$34 -> 8973.5689 | G77: ='Monthly Viewing Forecast'!G60*Scenarios!$E$36*'Title Inputs'!$E$34 -> 7824.952 | H77: ='Monthly Viewing Forecast'!H60*Scenarios!$E$36*'Title Inputs'!$E$34 -> 6823.3582 | I77: ='Monthly Viewing Forecast'!I60*Scenarios!$E$36*'Title Inputs'!$E$34 -> 5949.9683 | J77: ='Monthly Viewing Forecast'!J60*Scenarios!$E$36*'Title Inputs'!$E$34 -> 5188.3724 | K77: ='Monthly Viewing Forecast'!K60*Scenarios!$E$36*'Title Inputs'!$E$34 -> 4524.2607 | L77: ='Monthly Viewing Forecast'!L60*Scenarios!$E$36*'Title Inputs'!$E$34 -> 3945.1553 | ... AB77: ='Monthly Viewing Forecast'!AB60*Scenarios!$E$36*'Title Inputs'!$E$34 -> 440.88758
C78: Marketing support ($) | D78: =SUM(E78:AB78) -> 100000 | E78: =Scenarios!$E$37*INDEX(Assumptions!$C$23:$C$26,E$4) -> 55000 | F78: =Scenarios!$E$37*INDEX(Assumptions!$C$23:$C$26,F$4) -> 25000 | G78: =Scenarios!$E$37*INDEX(Assumptions!$C$23:$C$26,G$4) -> 12000 | H78: =Scenarios!$E$37*INDEX(Assumptions!$C$23:$C$26,H$4) -> 8000 | I78: =0 -> 0 | J78: =0 -> 0 | K78: =0 -> 0 | L78: =0 -> 0 | M78: =0 -> 0 | N78: =0 -> 0 | O78: =0 -> 0 | P78: =0 -> 0 | ... AB78: =0 -> 0
C79: Delivery, localisation and QC ($) | D79: =SUM(E79:AB79) -> 46000 | E79: ='Title Inputs'!$E$32 -> 46000 | F79: =0 -> 0 | G79: =0 -> 0 | H79: =0 -> 0 | I79: =0 -> 0 | J79: =0 -> 0 | K79: =0 -> 0 | L79: =0 -> 0 | M79: =0 -> 0 | ... AB79: =0 -> 0
C80: Variable serving costs ($) | D80: =SUM(E80:AB80) -> 59413 | E80: ='Monthly Viewing Forecast'!E60*'Title Inputs'!$E$33 -> 7900.0004 | F80: ='Monthly Viewing Forecast'!F60*'Title Inputs'!$E$33 -> 6888.8003 | G80: ='Monthly Viewing Forecast'!G60*'Title Inputs'!$E$33 -> 6007.0339 | H80: ='Monthly Viewing Forecast'!H60*'Title Inputs'!$E$33 -> 5238.1336 | I80: ='Monthly Viewing Forecast'!I60*'Title Inputs'!$E$33 -> 4567.6525 | J80: ='Monthly Viewing Forecast'!J60*'Title Inputs'!$E$33 -> 3982.9929 | K80: ='Monthly Viewing Forecast'!K60*'Title Inputs'!$E$33 -> 3473.1698 | L80: ='Monthly Viewing Forecast'!L60*'Title Inputs'!$E$33 -> 3028.6041 | ... AB80: ='Monthly Viewing Forecast'!AB60*'Title Inputs'!$E$33 -> 338.45915
C81: Contribution before licence fee ($) | D81: =SUM(E81:AB81) -> 362481.47 | E81: =E76+E77-E78-E79-E80 -> -33388.47 | F81: =F76+F77-F78-F79-F80 -> 33957.254 | G81: =G76+G77-G78-G79-G80 -> 39410.725 | H81: =H76+H77-H78-H79-H80 -> 36830.152 | I81: =I76+I77-I78-I79-I80 -> 39091.893 | J81: =J76+J77-J78-J79-J80 -> 34088.131 | K81: =K76+K77-K78-K79-K80 -> 29724.85 | L81: =L76+L77-L78-L79-L80 -> 25920.069 | ... AB81: =AB76+AB77-AB78-AB79-AB80 -> 2896.676
A83: Base | B83: The Quiet Depth | C83: Incremental advertising revenue ($) | D83: =SUM(E83:AB83) -> 224027.91 | E83: ='Monthly Viewing Forecast'!E68*Scenarios!$F$36 -> 32227.257 | F83: ='Monthly Viewing Forecast'!F68*Scenarios!$F$36 -> 27715.441 | G83: ='Monthly Viewing Forecast'!G68*Scenarios!$F$36 -> 23835.279 | H83: ='Monthly Viewing Forecast'!H68*Scenarios!$F$36 -> 20498.34 | I83: ='Monthly Viewing Forecast'!I68*Scenarios!$F$36 -> 17628.572 | J83: ='Monthly Viewing Forecast'!J68*Scenarios!$F$36 -> 15160.572 | K83: ='Monthly Viewing Forecast'!K68*Scenarios!$F$36 -> 13038.092 | L83: ='Monthly Viewing Forecast'!L68*Scenarios!$F$36 -> 11212.759 | ... AB83: ='Monthly Viewing Forecast'!AB68*Scenarios!$F$36 -> 1003.8937
C84: Follow-on engagement value ($) | D84: =SUM(E84:AB84) -> 41563.62 | E84: ='Monthly Viewing Forecast'!E66*Scenarios!$F$36*'Title Inputs'!$F$34 -> 5979.0828 | F84: ='Monthly Viewing Forecast'!F66*Scenarios!$F$36*'Title Inputs'!$F$34 -> 5142.0112 | G84: ='Monthly Viewing Forecast'!G66*Scenarios!$F$36*'Title Inputs'!$F$34 -> 4422.1297 | H84: ='Monthly Viewing Forecast'!H66*Scenarios!$F$36*'Title Inputs'!$F$34 -> 3803.0315 | I84: ='Monthly Viewing Forecast'!I66*Scenarios!$F$36*'Title Inputs'!$F$34 -> 3270.6071 | J84: ='Monthly Viewing Forecast'!J66*Scenarios!$F$36*'Title Inputs'!$F$34 -> 2812.7221 | K84: ='Monthly Viewing Forecast'!K66*Scenarios!$F$36*'Title Inputs'!$F$34 -> 2418.941 | L84: ='Monthly Viewing Forecast'!L66*Scenarios!$F$36*'Title Inputs'!$F$34 -> 2080.2893 | ... AB84: ='Monthly Viewing Forecast'!AB66*Scenarios!$F$36*'Title Inputs'!$F$34 -> 186.25114
C85: Marketing support ($) | D85: =SUM(E85:AB85) -> 72000 | E85: =Scenarios!$F$37*INDEX(Assumptions!$C$23:$C$26,E$4) -> 39600 | F85: =Scenarios!$F$37*INDEX(Assumptions!$C$23:$C$26,F$4) -> 18000 | G85: =Scenarios!$F$37*INDEX(Assumptions!$C$23:$C$26,G$4) -> 8640 | H85: =Scenarios!$F$37*INDEX(Assumptions!$C$23:$C$26,H$4) -> 5760 | I85: =0 -> 0 | J85: =0 -> 0 | K85: =0 -> 0 | L85: =0 -> 0 | M85: =0 -> 0 | N85: =0 -> 0 | O85: =0 -> 0 | P85: =0 -> 0 | ... AB85: =0 -> 0
C86: Delivery, localisation and QC ($) | D86: =SUM(E86:AB86) -> 44000 | E86: ='Title Inputs'!$F$32 -> 44000 | F86: =0 -> 0 | G86: =0 -> 0 | H86: =0 -> 0 | I86: =0 -> 0 | J86: =0 -> 0 | K86: =0 -> 0 | L86: =0 -> 0 | M86: =0 -> 0 | ... AB86: =0 -> 0
C87: Variable serving costs ($) | D87: =SUM(E87:AB87) -> 37338.477 | E87: ='Monthly Viewing Forecast'!E66*'Title Inputs'!$F$33 -> 5371.2801 | F87: ='Monthly Viewing Forecast'!F66*'Title Inputs'!$F$33 -> 4619.3009 | G87: ='Monthly Viewing Forecast'!G66*'Title Inputs'!$F$33 -> 3972.5988 | H87: ='Monthly Viewing Forecast'!H66*'Title Inputs'!$F$33 -> 3416.4349 | I87: ='Monthly Viewing Forecast'!I66*'Title Inputs'!$F$33 -> 2938.134 | J87: ='Monthly Viewing Forecast'!J66*'Title Inputs'!$F$33 -> 2526.7953 | K87: ='Monthly Viewing Forecast'!K66*'Title Inputs'!$F$33 -> 2173.0439 | L87: ='Monthly Viewing Forecast'!L66*'Title Inputs'!$F$33 -> 1868.8178 | ... AB87: ='Monthly Viewing Forecast'!AB66*'Title Inputs'!$F$33 -> 167.31781
C88: Contribution before licence fee ($) | D88: =SUM(E88:AB88) -> 112253.06 | E88: =E83+E84-E85-E86-E87 -> -50764.941 | F88: =F83+F84-F85-F86-F87 -> 10238.151 | G88: =G83+G84-G85-G86-G87 -> 15644.81 | H88: =H83+H84-H85-H86-H87 -> 15124.936 | I88: =I83+I84-I85-I86-I87 -> 17961.045 | J88: =J83+J84-J85-J86-J87 -> 15446.499 | K88: =K83+K84-K85-K86-K87 -> 13283.989 | L88: =L83+L84-L85-L86-L87 -> 11424.231 | ... AB88: =AB83+AB84-AB85-AB86-AB87 -> 1022.827
A90: Base | B90: Vector Nine | C90: Incremental advertising revenue ($) | D90: =SUM(E90:AB90) -> 59811.716 | E90: ='Monthly Viewing Forecast'!E74*Scenarios!$G$36 -> 9157.029 | F90: ='Monthly Viewing Forecast'!F74*Scenarios!$G$36 -> 7783.4747 | G90: ='Monthly Viewing Forecast'!G74*Scenarios!$G$36 -> 6615.9535 | H90: ='Monthly Viewing Forecast'!H74*Scenarios!$G$36 -> 5623.5604 | I90: ='Monthly Viewing Forecast'!I74*Scenarios!$G$36 -> 4780.0264 | J90: ='Monthly Viewing Forecast'!J74*Scenarios!$G$36 -> 4063.0224 | K90: ='Monthly Viewing Forecast'!K74*Scenarios!$G$36 -> 3453.5691 | L90: ='Monthly Viewing Forecast'!L74*Scenarios!$G$36 -> 2935.5337 | ... AB90: ='Monthly Viewing Forecast'!AB74*Scenarios!$G$36 -> 217.96657
C91: Follow-on engagement value ($) | D91: =SUM(E91:AB91) -> 12269.07 | E91: ='Monthly Viewing Forecast'!E72*Scenarios!$G$36*'Title Inputs'!$G$34 -> 1878.3649 | F91: ='Monthly Viewing Forecast'!F72*Scenarios!$G$36*'Title Inputs'!$G$34 -> 1596.6102 | G91: ='Monthly Viewing Forecast'!G72*Scenarios!$G$36*'Title Inputs'!$G$34 -> 1357.1187 | H91: ='Monthly Viewing Forecast'!H72*Scenarios!$G$36*'Title Inputs'!$G$34 -> 1153.5509 | I91: ='Monthly Viewing Forecast'!I72*Scenarios!$G$36*'Title Inputs'!$G$34 -> 980.51823 | J91: ='Monthly Viewing Forecast'!J72*Scenarios!$G$36*'Title Inputs'!$G$34 -> 833.4405 | K91: ='Monthly Viewing Forecast'!K72*Scenarios!$G$36*'Title Inputs'!$G$34 -> 708.42442 | L91: ='Monthly Viewing Forecast'!L72*Scenarios!$G$36*'Title Inputs'!$G$34 -> 602.16076 | ... AB91: ='Monthly Viewing Forecast'!AB72*Scenarios!$G$36*'Title Inputs'!$G$34 -> 44.71109
C92: Marketing support ($) | D92: =SUM(E92:AB92) -> 58000 | E92: =Scenarios!$G$37*INDEX(Assumptions!$C$23:$C$26,E$4) -> 31900 | F92: =Scenarios!$G$37*INDEX(Assumptions!$C$23:$C$26,F$4) -> 14500 | G92: =Scenarios!$G$37*INDEX(Assumptions!$C$23:$C$26,G$4) -> 6960 | H92: =Scenarios!$G$37*INDEX(Assumptions!$C$23:$C$26,H$4) -> 4640 | I92: =0 -> 0 | J92: =0 -> 0 | K92: =0 -> 0 | L92: =0 -> 0 | M92: =0 -> 0 | N92: =0 -> 0 | O92: =0 -> 0 | P92: =0 -> 0 | ... AB92: =0 -> 0
C93: Delivery, localisation and QC ($) | D93: =SUM(E93:AB93) -> 40000 | E93: ='Title Inputs'!$G$32 -> 40000 | F93: =0 -> 0 | G93: =0 -> 0 | H93: =0 -> 0 | I93: =0 -> 0 | J93: =0 -> 0 | K93: =0 -> 0 | L93: =0 -> 0 | M93: =0 -> 0 | ... AB93: =0 -> 0
C94: Variable serving costs ($) | D94: =SUM(E94:AB94) -> 12950.685 | E94: ='Monthly Viewing Forecast'!E72*'Title Inputs'!$G$33 -> 1982.7185 | F94: ='Monthly Viewing Forecast'!F72*'Title Inputs'!$G$33 -> 1685.3108 | G94: ='Monthly Viewing Forecast'!G72*'Title Inputs'!$G$33 -> 1432.5141 | H94: ='Monthly Viewing Forecast'!H72*'Title Inputs'!$G$33 -> 1217.637 | I94: ='Monthly Viewing Forecast'!I72*'Title Inputs'!$G$33 -> 1034.9915 | J94: ='Monthly Viewing Forecast'!J72*'Title Inputs'!$G$33 -> 879.74275 | K94: ='Monthly Viewing Forecast'!K72*'Title Inputs'!$G$33 -> 747.78133 | L94: ='Monthly Viewing Forecast'!L72*'Title Inputs'!$G$33 -> 635.61413 | ... AB94: ='Monthly Viewing Forecast'!AB72*'Title Inputs'!$G$33 -> 47.19504
C95: Contribution before licence fee ($) | D95: =SUM(E95:AB95) -> -38869.899 | E95: =E90+E91-E92-E93-E94 -> -62847.325 | F95: =F90+F91-F92-F93-F94 -> -6805.2259 | G95: =G90+G91-G92-G93-G94 -> -419.44202 | H95: =H90+H91-H92-H93-H94 -> 919.47429 | I95: =I90+I91-I92-I93-I94 -> 4725.5531 | J95: =J90+J91-J92-J93-J94 -> 4016.7202 | K95: =K90+K91-K92-K93-K94 -> 3414.2121 | L95: =L90+L91-L92-L93-L94 -> 2902.0803 | ... AB95: =AB90+AB91-AB92-AB93-AB94 -> 215.48262
B97: PORTFOLIO | C97: Portfolio incremental advertising revenue ($) | D97: =$D$62+$D$69+$D$76+$D$83+$D$90 -> 2773098.3 | E97: =E62+E69+E76+E83+E90 -> 352803.89 | F97: =F62+F69+F76+F83+F90 -> 309768.52 | G97: =G62+G69+G76+G83+G90 -> 272010.28 | H97: =H62+H69+H76+H83+H90 -> 238878.36 | I97: =I62+I69+I76+I83+I90 -> 209802.73 | J97: =J62+J69+J76+J83+J90 -> 184284 | K97: =K62+K69+K76+K83+K90 -> 161884.65 | L97: =L62+L69+L76+L83+L90 -> 142221.29 | ... AB97: =AB62+AB69+AB76+AB83+AB90 -> 18121.334
B98: PORTFOLIO | C98: Portfolio follow-on engagement value ($) | D98: =$D$63+$D$70+$D$77+$D$84+$D$91 -> 407970.58 | E98: =E63+E70+E77+E84+E91 -> 52257.685 | F98: =F63+F70+F77+F84+F91 -> 45828.323 | G98: =G63+G70+G77+G84+G91 -> 40194.736 | H98: =H63+H70+H77+H84+H91 -> 35257.792 | I98: =I63+I70+I77+I84+I91 -> 30930.793 | J98: =J63+J70+J77+J84+J91 -> 27137.903 | K98: =K63+K70+K77+K84+K91 -> 23812.781 | L98: =L63+L70+L77+L84+L91 -> 20897.381 | ... AB98: =AB63+AB70+AB77+AB84+AB91 -> 2621.6379
B99: PORTFOLIO | C99: Portfolio marketing support ($) | D99: =$D$64+$D$71+$D$78+$D$85+$D$92 -> 525000 | E99: =E64+E71+E78+E85+E92 -> 288750 | F99: =F64+F71+F78+F85+F92 -> 131250 | G99: =G64+G71+G78+G85+G92 -> 63000 | H99: =H64+H71+H78+H85+H92 -> 42000 | I99: =I64+I71+I78+I85+I92 -> 0 | J99: =J64+J71+J78+J85+J92 -> 0 | K99: =K64+K71+K78+K85+K92 -> 0 | L99: =L64+L71+L78+L85+L92 -> 0 | ... AB99: =AB64+AB71+AB78+AB85+AB92 -> 0
B100: PORTFOLIO | C100: Portfolio delivery, localisation and QC ($) | D100: =$D$65+$D$72+$D$79+$D$86+$D$93 -> 240000 | E100: =E65+E72+E79+E86+E93 -> 240000 | F100: =F65+F72+F79+F86+F93 -> 0 | G100: =G65+G72+G79+G86+G93 -> 0 | H100: =H65+H72+H79+H86+H93 -> 0 | I100: =I65+I72+I79+I86+I93 -> 0 | J100: =J65+J72+J79+J86+J93 -> 0 | K100: =K65+K72+K79+K86+K93 -> 0 | L100: =L65+L72+L79+L86+L93 -> 0 | ... AB100: =AB65+AB72+AB79+AB86+AB93 -> 0
B101: PORTFOLIO | C101: Portfolio variable serving costs ($) | D101: =$D$66+$D$73+$D$80+$D$87+$D$94 -> 303445.11 | E101: =E66+E73+E80+E87+E94 -> 39147.02 | F101: =F66+F73+F80+F87+F94 -> 34287.248 | G101: =G66+G73+G80+G87+G94 -> 30034.882 | H101: =H66+H73+H80+H87+H94 -> 26313.453 | I101: =I66+I73+I80+I87+I94 -> 23056.194 | J101: =J66+J73+J80+J87+J94 -> 20204.797 | K101: =K66+K73+K80+K87+K94 -> 17708.334 | L101: =L66+L73+L80+L87+L94 -> 15522.314 | ... AB101: =AB66+AB73+AB80+AB87+AB94 -> 1915.9009
B102: PORTFOLIO | C102: Total modelled benefits ($) | D102: =SUM(E102:AB102) -> 3181068.9 | E102: =E97+E98 -> 405061.58 | F102: =F97+F98 -> 355596.84 | G102: =G97+G98 -> 312205.02 | H102: =H97+H98 -> 274136.16 | I102: =I97+I98 -> 240733.52 | J102: =J97+J98 -> 211421.9 | K102: =K97+K98 -> 185697.43 | L102: =L97+L98 -> 163118.67 | ... AB102: =AB97+AB98 -> 20742.972
B103: PORTFOLIO | C103: Total support costs ($) | D103: =SUM(E103:AB103) -> 1068445.1 | E103: =E99+E100+E101 -> 567897.02 | F103: =F99+F100+F101 -> 165537.25 | G103: =G99+G100+G101 -> 93034.882 | H103: =H99+H100+H101 -> 68313.453 | I103: =I99+I100+I101 -> 23056.194 | J103: =J99+J100+J101 -> 20204.797 | K103: =K99+K100+K101 -> 17708.334 | L103: =L99+L100+L101 -> 15522.314 | ... AB103: =AB99+AB100+AB101 -> 1915.9009
B104: PORTFOLIO | C104: Contribution before licence fee ($) | D104: =SUM(E104:AB104) -> 2112623.8 | E104: =E102-E103 -> -162835.44 | F104: =F102-F103 -> 190059.6 | G104: =G102-G103 -> 219170.13 | H104: =H102-H103 -> 205822.7 | I104: =I102-I103 -> 217677.33 | J104: =J102-J103 -> 191217.1 | K104: =K102-K103 -> 167989.09 | L104: =L102-L103 -> 147596.36 | ... AB104: =AB102-AB103 -> 18827.071
C105: PV of modelled benefits ($) | D105: =SUMPRODUCT(E102:AB102,'Title Economics'!$E$6:$AB$6) -> 2978508.3
C106: PV of support costs ($) | D106: =SUMPRODUCT(E103:AB103,'Title Economics'!$E$6:$AB$6) -> 1038546.8
C107: PV of contribution before licence fee ($) | D107: =SUMPRODUCT(E104:AB104,'Title Economics'!$E$6:$AB$6) -> 1939961.5
C108: PV of incremental advertising revenue ($) | D108: =SUMPRODUCT(E97:AB97,'Title Economics'!$E$6:$AB$6) -> 2596414
C109: PV of follow-on engagement value ($) | D109: =SUMPRODUCT(E98:AB98,'Title Economics'!$E$6:$AB$6) -> 382094.23
C110: PV of variable serving costs ($) | D110: =SUMPRODUCT(E101:AB101,'Title Economics'!$E$6:$AB$6) -> 284289.52
C111: PV of fixed support costs (marketing, delivery and QC) ($) | D111: =SUMPRODUCT(E99:AB99,'Title Economics'!$E$6:$AB$6)+SUMPRODUCT(E100:AB100,'Title Economics'!$E$6:$AB$6) -> 754257.28
A114: UPSIDE SCENARIO
A115: Upside | B115: Nightfall Protocol | C115: Incremental advertising revenue ($) | D115: =SUM(E115:AB115) -> 1494218.4 | E115: ='Monthly Viewing Forecast'!E89*Scenarios!$C$45 -> 171204.04 | F115: ='Monthly Viewing Forecast'!F89*Scenarios!$C$45 -> 152885.21 | G115: ='Monthly Viewing Forecast'!G89*Scenarios!$C$45 -> 136526.49 | H115: ='Monthly Viewing Forecast'!H89*Scenarios!$C$45 -> 121918.16 | I115: ='Monthly Viewing Forecast'!I89*Scenarios!$C$45 -> 108872.92 | J115: ='Monthly Viewing Forecast'!J89*Scenarios!$C$45 -> 97223.513 | K115: ='Monthly Viewing Forecast'!K89*Scenarios!$C$45 -> 86820.597 | L115: ='Monthly Viewing Forecast'!L89*Scenarios!$C$45 -> 77530.793 | ... AB115: ='Monthly Viewing Forecast'!AB89*Scenarios!$C$45 -> 12679.367
C116: Follow-on engagement value ($) | D116: =SUM(E116:AB116) -> 190375.94 | E116: ='Monthly Viewing Forecast'!E87*Scenarios!$C$45*'Title Inputs'!$C$34 -> 21812.829 | F116: ='Monthly Viewing Forecast'!F87*Scenarios!$C$45*'Title Inputs'!$C$34 -> 19478.856 | G116: ='Monthly Viewing Forecast'!G87*Scenarios!$C$45*'Title Inputs'!$C$34 -> 17394.619 | H116: ='Monthly Viewing Forecast'!H87*Scenarios!$C$45*'Title Inputs'!$C$34 -> 15533.394 | I116: ='Monthly Viewing Forecast'!I87*Scenarios!$C$45*'Title Inputs'!$C$34 -> 13871.321 | J116: ='Monthly Viewing Forecast'!J87*Scenarios!$C$45*'Title Inputs'!$C$34 -> 12387.09 | K116: ='Monthly Viewing Forecast'!K87*Scenarios!$C$45*'Title Inputs'!$C$34 -> 11061.671 | L116: ='Monthly Viewing Forecast'!L87*Scenarios!$C$45*'Title Inputs'!$C$34 -> 9878.0724 | ... AB116: ='Monthly Viewing Forecast'!AB87*Scenarios!$C$45*'Title Inputs'!$C$34 -> 1615.4575
...

Sheet Deal Structures
A1: PROJECT NIGHTFALL
A2: Payment mechanics and comparison of three deal structures
A3: Independent analytical case study using synthetic assumptions. Not based on proprietary company information.
A4: Scenario | B4: Structure | C4: Month | D4: Total | E4: 1 | F4: 2 | G4: 3 | H4: 4 | I4: 5 | J4: 6 | K4: 7 | L4: 8 | M4: 9 | N4: 10 | O4: 11 | P4: 12 | Q4: 13 | R4: 14 | S4: 15 | T4: 16 | U4: 17 | V4: 18 | W4: 19 | X4: 20 | Y4: 21 | Z4: 22 | AA4: 23 | AB4: 24
C6: Structure A licence fee - recommended target price ($) | D6: =Scenarios!$C$66 -> 1498516.7 | F6: All three structures are priced from the same recommended target price so that they are comparable.
A8: DOWNSIDE SCENARIO
A9: Downside | B9: A - Fixed licence fee | C9: Licence payment ($) | D9: =SUM(E9:AB9) -> 1498516.7 | E9: =IF(E$4=Assumptions!$C$31,'Deal Structures'!$D$6*Assumptions!$C$30,0)+IF(E$4=Assumptions!$C$33,'Deal Structures'!$D$6*Assumptions!$C$32,0) -> 749258.33 | F9: =IF(F$4=Assumptions!$C$31,'Deal Structures'!$D$6*Assumptions!$C$30,0)+IF(F$4=Assumptions!$C$33,'Deal Structures'!$D$6*Assumptions!$C$32,0) -> 0 | G9: =IF(G$4=Assumptions!$C$31,'Deal Structures'!$D$6*Assumptions!$C$30,0)+IF(G$4=Assumptions!$C$33,'Deal Structures'!$D$6*Assumptions!$C$32,0) -> 0 | H9: =IF(H$4=Assumptions!$C$31,'Deal Structures'!$D$6*Assumptions!$C$30,0)+IF(H$4=Assumptions!$C$33,'Deal Structures'!$D$6*Assumptions!$C$32,0) -> 0 | I9: =IF(I$4=Assumptions!$C$31,'Deal Structures'!$D$6*Assumptions!$C$30,0)+IF(I$4=Assumptions!$C$33,'Deal Structures'!$D$6*Assumptions!$C$32,0) -> 0 | J9: =IF(J$4=Assumptions!$C$31,'Deal Structures'!$D$6*Assumptions!$C$30,0)+IF(J$4=Assumptions!$C$33,'Deal Structures'!$D$6*Assumptions!$C$32,0) -> 0 | K9: =IF(K$4=Assumptions!$C$31,'Deal Structures'!$D$6*Assumptions!$C$30,0)+IF(K$4=Assumptions!$C$33,'Deal Structures'!$D$6*Assumptions!$C$32,0) -> 749258.33 | L9: =IF(L$4=Assumptions!$C$31,'Deal Structures'!$D$6*Assumptions!$C$30,0)+IF(L$4=Assumptions!$C$33,'Deal Structures'!$D$6*Assumptions!$C$32,0) -> 0 | ... AB9: =IF(AB$4=Assumptions!$C$31,'Deal Structures'!$D$6*Assumptions!$C$30,0)+IF(AB$4=Assumptions!$C$33,'Deal Structures'!$D$6*Assumptions!$C$32,0) -> 0
C10: Net cash flow ($) | D10: =SUM(E10:AB10) -> 95305.615 | E10: ='Title Economics'!E51-E9 -> -972149.26 | F10: ='Title Economics'!F51-F9 -> 140881.67 | G10: ='Title Economics'!G51-G9 -> 176369.97 | H10: ='Title Economics'!H51-H9 -> 166962.22 | I10: ='Title Economics'!I51-I9 -> 183702.98 | J10: ='Title Economics'!J51-J9 -> 159905.71 | K10: ='Title Economics'!K51-K9 -> -610053.86 | L10: ='Title Economics'!L51-L9 -> 121194.57 | ... AB10: ='Title Economics'!AB51-AB9 -> 13360.684
C11: Cumulative net cash flow ($) | D11: =SUM(E11:AB11) -> -6742743.2 | E11: =SUM($E$10:E10) -> -972149.26 | F11: =SUM($E$10:F10) -> -831267.59 | G11: =SUM($E$10:G10) -> -654897.62 | H11: =SUM($E$10:H10) -> -487935.4 | I11: =SUM($E$10:I10) -> -304232.42 | J11: =SUM($E$10:J10) -> -144326.72 | K11: =SUM($E$10:K10) -> -754380.58 | L11: =SUM($E$10:L10) -> -633186 | ... AB11: =SUM($E$10:AB10) -> 95305.615
C12: Payback flag | D12: =IFERROR(MATCH(1,E12:AB12,0),"n/a") -> 19 | E12: =IF(MIN(E11:$AB$11)>0,1,0) -> 0 | F12: =IF(MIN(F11:$AB$11)>0,1,0) -> 0 | G12: =IF(MIN(G11:$AB$11)>0,1,0) -> 0 | H12: =IF(MIN(H11:$AB$11)>0,1,0) -> 0 | I12: =IF(MIN(I11:$AB$11)>0,1,0) -> 0 | J12: =IF(MIN(J11:$AB$11)>0,1,0) -> 0 | K12: =IF(MIN(K11:$AB$11)>0,1,0) -> 0 | L12: =IF(MIN(L11:$AB$11)>0,1,0) -> 0 | ... AB12: =IF(MIN(AB11:$AB$11)>0,1,0) -> 1
A14: Downside | B14: B - Minimum guarantee plus revenue share | C14: Revenue share accrued ($) | D14: =SUM(E14:AB14) -> 1156796 | E14: ='Monthly Viewing Forecast'!E40*Assumptions!$C$38 -> 156353.19 | F14: ='Monthly Viewing Forecast'!F40*Assumptions!$C$38 -> 135882.1 | G14: ='Monthly Viewing Forecast'!G40*Assumptions!$C$38 -> 118105.51 | H14: ='Monthly Viewing Forecast'!H40*Assumptions!$C$38 -> 102666.72 | I14: ='Monthly Viewing Forecast'!I40*Assumptions!$C$38 -> 89256.546 | J14: ='Monthly Viewing Forecast'!J40*Assumptions!$C$38 -> 77606.951 | K14: ='Monthly Viewing Forecast'!K40*Assumptions!$C$38 -> 67485.515 | L14: ='Monthly Viewing Forecast'!L40*Assumptions!$C$38 -> 58690.685 | ... AB14: ='Monthly Viewing Forecast'!AB40*Assumptions!$C$38 -> 6373.207
C15: Cumulative revenue share accrued ($) | D15: =AB15 -> 1156796 | E15: =SUM($E$14:E14) -> 156353.19 | F15: =SUM($E$14:F14) -> 292235.29 | G15: =SUM($E$14:G14) -> 410340.79 | H15: =SUM($E$14:H14) -> 513007.51 | I15: =SUM($E$14:I14) -> 602264.05 | J15: =SUM($E$14:J14) -> 679871 | K15: =SUM($E$14:K14) -> 747356.52 | L15: =SUM($E$14:L14) -> 806047.2 | ... AB15: =SUM($E$14:AB14) -> 1156796
C16: Cumulative obligation ($) | D16: =AB16 -> 1156796 | E16: =MAX(Assumptions!$C$37,E15) -> 950000 | F16: =MAX(Assumptions!$C$37,F15) -> 950000 | G16: =MAX(Assumptions!$C$37,G15) -> 950000 | H16: =MAX(Assumptions!$C$37,H15) -> 950000 | I16: =MAX(Assumptions!$C$37,I15) -> 950000 | J16: =MAX(Assumptions!$C$37,J15) -> 950000 | K16: =MAX(Assumptions!$C$37,K15) -> 950000 | L16: =MAX(Assumptions!$C$37,L15) -> 950000 | ... AB16: =MAX(Assumptions!$C$37,AB15) -> 1156796
C17: Licence payment ($) | D17: =SUM(E17:AB17) -> 1156796 | E17: =E16 -> 950000 | F17: =F16-E16 -> 0 | G17: =G16-F16 -> 0 | H17: =H16-G16 -> 0 | I17: =I16-H16 -> 0 | J17: =J16-I16 -> 0 | K17: =K16-J16 -> 0 | L17: =L16-K16 -> 0 | M17: =M16-L16 -> 0 | ... AB17: =AB16-AA16 -> 6373.207
C18: Net cash flow ($) | D18: =SUM(E18:AB18) -> 437026.29 | E18: ='Title Economics'!E51-E17 -> -1172890.9 | F18: ='Title Economics'!F51-F17 -> 140881.67 | G18: ='Title Economics'!G51-G17 -> 176369.97 | H18: ='Title Economics'!H51-H17 -> 166962.22 | I18: ='Title Economics'!I51-I17 -> 183702.98 | J18: ='Title Economics'!J51-J17 -> 159905.71 | K18: ='Title Economics'!K51-K17 -> 139204.47 | L18: ='Title Economics'!L51-L17 -> 121194.57 | ... AB18: ='Title Economics'!AB51-AB17 -> 6987.4769
C19: Cumulative net cash flow ($) | D19: =SUM(E19:AB19) -> 138499.98 | E19: =SUM($E$18:E18) -> -1172890.9 | F19: =SUM($E$18:F18) -> -1032009.3 | G19: =SUM($E$18:G18) -> -855639.29 | H19: =SUM($E$18:H18) -> -688677.07 | I19: =SUM($E$18:I18) -> -504974.1 | J19: =SUM($E$18:J18) -> -345068.39 | K19: =SUM($E$18:K18) -> -205863.92 | L19: =SUM($E$18:L18) -> -84669.345 | ... AB19: =SUM($E$18:AB18) -> 437026.29
C20: Payback flag | D20: =IFERROR(MATCH(1,E20:AB20,0),"n/a") -> 9 | E20: =IF(MIN(E19:$AB$19)>0,1,0) -> 0 | F20: =IF(MIN(F19:$AB$19)>0,1,0) -> 0 | G20: =IF(MIN(G19:$AB$19)>0,1,0) -> 0 | H20: =IF(MIN(H19:$AB$19)>0,1,0) -> 0 | I20: =IF(MIN(I19:$AB$19)>0,1,0) -> 0 | J20: =IF(MIN(J19:$AB$19)>0,1,0) -> 0 | K20: =IF(MIN(K19:$AB$19)>0,1,0) -> 0 | L20: =IF(MIN(L19:$AB$19)>0,1,0) -> 0 | ... AB20: =IF(MIN(AB19:$AB$19)>0,1,0) -> 1
A22: Downside | B22: C - Performance fee with earn-outs | C22: Cumulative viewing hours | D22: =AB22 -> 14529862 | E22: ='Monthly Viewing Forecast'!E41 -> 1978778.9 | F22: ='Monthly Viewing Forecast'!F41 -> 3696078.8 | G22: ='Monthly Viewing Forecast'!G41 -> 5186659.5 | H22: ='Monthly Viewing Forecast'!H41 -> 6480630.7 | I22: ='Monthly Viewing Forecast'!I41 -> 7604077.6 | J22: ='Monthly Viewing Forecast'!J41 -> 8579603.3 | K22: ='Monthly Viewing Forecast'!K41 -> 9426795.9 | L22: ='Monthly Viewing Forecast'!L41 -> 10162634 | ... AB22: ='Monthly Viewing Forecast'!AB41 -> 14529862
C23: Licence payment ($) | D23: =SUM(E23:AB23) -> 850000 | E23: =IF(E$4=1,Assumptions!$C$41,0)+IF(E$4=12,IF(E22>=Assumptions!$C$43,Assumptions!$C$42,0),0)+IF(E$4=18,IF(E22>=Assumptions!$C$45,Assumptions!$C$44,0),0)+IF(E$4=24,IF(E22>=Assumptions!$C$47,Assumptions!$C$46,0),0) -> 850000 | F23: =IF(F$4=1,Assumptions!$C$41,0)+IF(F$4=12,IF(F22>=Assumptions!$C$43,Assumptions!$C$42,0),0)+IF(F$4=18,IF(F22>=Assumptions!$C$45,Assumptions!$C$44,0),0)+IF(F$4=24,IF(F22>=Assumptions!$C$47,Assumptions!$C$46,0),0) -> 0 | G23: =IF(G$4=1,Assumptions!$C$41,0)+IF(G$4=12,IF(G22>=Assumptions!$C$43,Assumptions!$C$42,0),0)+IF(G$4=18,IF(G22>=Assumptions!$C$45,Assumptions!$C$44,0),0)+IF(G$4=24,IF(G22>=Assumptions!$C$47,Assumptions!$C$46,0),0) -> 0 | H23: =IF(H$4=1,Assumptions!$C$41,0)+IF(H$4=12,IF(H22>=Assumptions!$C$43,Assumptions!$C$42,0),0)+IF(H$4=18,IF(H22>=Assumptions!$C$45,Assumptions!$C$44,0),0)+IF(H$4=24,IF(H22>=Assumptions!$C$47,Assumptions!$C$46,0),0) -> 0 | I23: =IF(I$4=1,Assumptions!$C$41,0)+IF(I$4=12,IF(I22>=Assumptions!$C$43,Assumptions!$C$42,0),0)+IF(I$4=18,IF(I22>=Assumptions!$C$45,Assumptions!$C$44,0),0)+IF(I$4=24,IF(I22>=Assumptions!$C$47,Assumptions!$C$46,0),0) -> 0 | J23: =IF(J$4=1,Assumptions!$C$41,0)+IF(J$4=12,IF(J22>=Assumptions!$C$43,Assumptions!$C$42,0),0)+IF(J$4=18,IF(J22>=Assumptions!$C$45,Assumptions!$C$44,0),0)+IF(J$4=24,IF(J22>=Assumptions!$C$47,Assumptions!$C$46,0),0) -> 0 | K23: =IF(K$4=1,Assumptions!$C$41,0)+IF(K$4=12,IF(K22>=Assumptions!$C$43,Assumptions!$C$42,0),0)+IF(K$4=18,IF(K22>=Assumptions!$C$45,Assumptions!$C$44,0),0)+IF(K$4=24,IF(K22>=Assumptions!$C$47,Assumptions!$C$46,0),0) -> 0 | L23: =IF(L$4=1,Assumptions!$C$41,0)+IF(L$4=12,IF(L22>=Assumptions!$C$43,Assumptions!$C$42,0),0)+IF(L$4=18,IF(L22>=Assumptions!$C$45,Assumptions!$C$44,0),0)+IF(L$4=24,IF(L22>=Assumptions!$C$47,Assumptions!$C$46,0),0) -> 0 | ... AB23: =IF(AB$4=1,Assumptions!$C$41,0)+IF(AB$4=12,IF(AB22>=Assumptions!$C$43,Assumptions!$C$42,0),0)+IF(AB$4=18,IF(AB22>=Assumptions!$C$45,Assumptions!$C$44,0),0)+IF(AB$4=24,IF(AB22>=Assumptions!$C$47,Assumptions!$C$46,0),0) -> 0
C24: Net cash flow ($) | D24: =SUM(E24:AB24) -> 743822.27 | E24: ='Title Economics'!E51-E23 -> -1072890.9 | F24: ='Title Economics'!F51-F23 -> 140881.67 | G24: ='Title Economics'!G51-G23 -> 176369.97 | H24: ='Title Economics'!H51-H23 -> 166962.22 | I24: ='Title Economics'!I51-I23 -> 183702.98 | J24: ='Title Economics'!J51-J23 -> 159905.71 | K24: ='Title Economics'!K51-K23 -> 139204.47 | L24: ='Title Economics'!L51-L23 -> 121194.57 | ... AB24: ='Title Economics'!AB51-AB23 -> 13360.684
C25: Cumulative net cash flow ($) | D25: =SUM(E25:AB25) -> 4326106.6 | E25: =SUM($E$24:E24) -> -1072890.9 | F25: =SUM($E$24:F24) -> -932009.26 | G25: =SUM($E$24:G24) -> -755639.29 | H25: =SUM($E$24:H24) -> -588677.07 | I25: =SUM($E$24:I24) -> -404974.1 | J25: =SUM($E$24:J24) -> -245068.39 | K25: =SUM($E$24:K24) -> -105863.92 | L25: =SUM($E$24:L24) -> 15330.655 | ... AB25: =SUM($E$24:AB24) -> 743822.27
C26: Payback flag | D26: =IFERROR(MATCH(1,E26:AB26,0),"n/a") -> 8 | E26: =IF(MIN(E25:$AB$25)>0,1,0) -> 0 | F26: =IF(MIN(F25:$AB$25)>0,1,0) -> 0 | G26: =IF(MIN(G25:$AB$25)>0,1,0) -> 0 | H26: =IF(MIN(H25:$AB$25)>0,1,0) -> 0 | I26: =IF(MIN(I25:$AB$25)>0,1,0) -> 0 | J26: =IF(MIN(J25:$AB$25)>0,1,0) -> 0 | K26: =IF(MIN(K25:$AB$25)>0,1,0) -> 0 | L26: =IF(MIN(L25:$AB$25)>0,1,0) -> 1 | ... AB26: =IF(MIN(AB25:$AB$25)>0,1,0) -> 1
A29: BASE SCENARIO
A30: Base | B30: A - Fixed licence fee | C30: Licence payment ($) | D30: =SUM(E30:AB30) -> 1498516.7 | E30: =IF(E$4=Assumptions!$C$31,'Deal Structures'!$D$6*Assumptions!$C$30,0)+IF(E$4=Assumptions!$C$33,'Deal Structures'!$D$6*Assumptions!$C$32,0) -> 749258.33 | F30: =IF(F$4=Assumptions!$C$31,'Deal Structures'!$D$6*Assumptions!$C$30,0)+IF(F$4=Assumptions!$C$33,'Deal Structures'!$D$6*Assumptions!$C$32,0) -> 0 | G30: =IF(G$4=Assumptions!$C$31,'Deal Structures'!$D$6*Assumptions!$C$30,0)+IF(G$4=Assumptions!$C$33,'Deal Structures'!$D$6*Assumptions!$C$32,0) -> 0 | H30: =IF(H$4=Assumptions!$C$31,'Deal Structures'!$D$6*Assumptions!$C$30,0)+IF(H$4=Assumptions!$C$33,'Deal Structures'!$D$6*Assumptions!$C$32,0) -> 0 | I30: =IF(I$4=Assumptions!$C$31,'Deal Structures'!$D$6*Assumptions!$C$30,0)+IF(I$4=Assumptions!$C$33,'Deal Structures'!$D$6*Assumptions!$C$32,0) -> 0 | J30: =IF(J$4=Assumptions!$C$31,'Deal Structures'!$D$6*Assumptions!$C$30,0)+IF(J$4=Assumptions!$C$33,'Deal Structures'!$D$6*Assumptions!$C$32,0) -> 0 | K30: =IF(K$4=Assumptions!$C$31,'Deal Structures'!$D$6*Assumptions!$C$30,0)+IF(K$4=Assumptions!$C$33,'Deal Structures'!$D$6*Assumptions!$C$32,0) -> 749258.33 | L30: =IF(L$4=Assumptions!$C$31,'Deal Structures'!$D$6*Assumptions!$C$30,0)+IF(L$4=Assumptions!$C$33,'Deal Structures'!$D$6*Assumptions!$C$32,0) -> 0 | ... AB30: =IF(AB$4=Assumptions!$C$31,'Deal Structures'!$D$6*Assumptions!$C$30,0)+IF(AB$4=Assumptions!$C$33,'Deal Structures'!$D$6*Assumptions!$C$32,0) -> 0
C31: Net cash flow ($) | D31: =SUM(E31:AB31) -> 614107.1 | E31: ='Title Economics'!E104-E30 -> -912093.77 | F31: ='Title Economics'!F104-F30 -> 190059.6 | G31: ='Title Economics'!G104-G30 -> 219170.13 | H31: ='Title Economics'!H104-H30 -> 205822.7 | I31: ='Title Economics'!I104-I30 -> 217677.33 | J31: ='Title Economics'!J104-J30 -> 191217.1 | K31: ='Title Economics'!K104-K30 -> -581269.23 | L31: ='Title Economics'!L104-L30 -> 147596.36 | ... AB31: ='Title Economics'!AB104-AB30 -> 18827.071
C32: Cumulative net cash flow ($) | D32: =SUM(E32:AB32) -> 2008773.4 | E32: =SUM($E$31:E31) -> -912093.77 | F32: =SUM($E$31:F31) -> -722034.18 | G32: =SUM($E$31:G31) -> -502864.04 | H32: =SUM($E$31:H31) -> -297041.34 | I32: =SUM($E$31:I31) -> -79364.01 | J32: =SUM($E$31:J31) -> 111853.09 | K32: =SUM($E$31:K31) -> -469416.14 | L32: =SUM($E$31:L31) -> -321819.78 | ... AB32: =SUM($E$31:AB31) -> 614107.1
C33: Payback flag | D33: =IFERROR(MATCH(1,E33:AB33,0),"n/a") -> 11 | E33: =IF(MIN(E32:$AB$32)>0,1,0) -> 0 | F33: =IF(MIN(F32:$AB$32)>0,1,0) -> 0 | G33: =IF(MIN(G32:$AB$32)>0,1,0) -> 0 | H33: =IF(MIN(H32:$AB$32)>0,1,0) -> 0 | I33: =IF(MIN(I32:$AB$32)>0,1,0) -> 0 | J33: =IF(MIN(J32:$AB$32)>0,1,0) -> 0 | K33: =IF(MIN(K32:$AB$32)>0,1,0) -> 0 | L33: =IF(MIN(L32:$AB$32)>0,1,0) -> 0 | ... AB33: =IF(MIN(AB32:$AB$32)>0,1,0) -> 1
A35: Base | B35: B - Minimum guarantee plus revenue share | C35: Revenue share accrued ($) | D35: =SUM(E35:AB35) -> 1351903 | E35: ='Monthly Viewing Forecast'!E79*Assumptions!$C$38 -> 173044.29 | F35: ='Monthly Viewing Forecast'!F79*Assumptions!$C$38 -> 151772.22 | G35: ='Monthly Viewing Forecast'!G79*Assumptions!$C$38 -> 133130.85 | H35: ='Monthly Viewing Forecast'!H79*Assumptions!$C$38 -> 116792.74 | I35: ='Monthly Viewing Forecast'!I79*Assumptions!$C$38 -> 102471.47 | J35: ='Monthly Viewing Forecast'!J79*Assumptions!$C$38 -> 89916.482 | K35: ='Monthly Viewing Forecast'!K79*Assumptions!$C$38 -> 78908.573 | L35: ='Monthly Viewing Forecast'!L79*Assumptions!$C$38 -> 69255.919 | ... AB35: ='Monthly Viewing Forecast'!AB79*Assumptions!$C$38 -> 8704.2334
C36: Cumulative revenue share accrued ($) | D36: =AB36 -> 1351903 | E36: =SUM($E$35:E35) -> 173044.29 | F36: =SUM($E$35:F35) -> 324816.51 | G36: =SUM($E$35:G35) -> 457947.36 | H36: =SUM($E$35:H35) -> 574740.1 | I36: =SUM($E$35:I35) -> 677211.57 | J36: =SUM($E$35:J35) -> 767128.05 | K36: =SUM($E$35:K35) -> 846036.63 | L36: =SUM($E$35:L35) -> 915292.54 | ... AB36: =SUM($E$35:AB35) -> 1351903
C37: Cumulative obligation ($) | D37: =AB37 -> 1351903 | E37: =MAX(Assumptions!$C$37,E36) -> 950000 | F37: =MAX(Assumptions!$C$37,F36) -> 950000 | G37: =MAX(Assumptions!$C$37,G36) -> 950000 | H37: =MAX(Assumptions!$C$37,H36) -> 950000 | I37: =MAX(Assumptions!$C$37,I36) -> 950000 | J37: =MAX(Assumptions!$C$37,J36) -> 950000 | K37: =MAX(Assumptions!$C$37,K36) -> 950000 | L37: =MAX(Assumptions!$C$37,L36) -> 950000 | ... AB37: =MAX(Assumptions!$C$37,AB36) -> 1351903
C38: Licence payment ($) | D38: =SUM(E38:AB38) -> 1351903 | E38: =E37 -> 950000 | F38: =F37-E37 -> 0 | G38: =G37-F37 -> 0 | H38: =H37-G37 -> 0 | I38: =I37-H37 -> 0 | J38: =J37-I37 -> 0 | K38: =K37-J37 -> 0 | L38: =L37-K37 -> 0 | M38: =M37-L37 -> 26083.183 | ... AB38: =AB37-AA37 -> 8704.2334
C39: Net cash flow ($) | D39: =SUM(E39:AB39) -> 760720.8 | E39: ='Title Economics'!E104-E38 -> -1112835.4 | F39: ='Title Economics'!F104-F38 -> 190059.6 | G39: ='Title Economics'!G104-G38 -> 219170.13 | H39: ='Title Economics'!H104-H38 -> 205822.7 | I39: ='Title Economics'!I104-I38 -> 217677.33 | J39: ='Title Economics'!J104-J38 -> 191217.1 | K39: ='Title Economics'!K104-K38 -> 167989.09 | L39: ='Title Economics'!L104-L38 -> 147596.36 | ... AB39: ='Title Economics'!AB104-AB38 -> 10122.838
C40: Cumulative net cash flow ($) | D40: =SUM(E40:AB40) -> 6397262.9 | E40: =SUM($E$39:E39) -> -1112835.4 | F40: =SUM($E$39:F39) -> -922775.85 | G40: =SUM($E$39:G39) -> -703605.71 | H40: =SUM($E$39:H39) -> -497783.01 | I40: =SUM($E$39:I39) -> -280105.68 | J40: =SUM($E$39:J39) -> -88888.577 | K40: =SUM($E$39:K39) -> 79100.517 | L40: =SUM($E$39:L39) -> 226696.87 | ... AB40: =SUM($E$39:AB39) -> 760720.8
C41: Payback flag | D41: =IFERROR(MATCH(1,E41:AB41,0),"n/a") -> 7 | E41: =IF(MIN(E40:$AB$40)>0,1,0) -> 0 | F41: =IF(MIN(F40:$AB$40)>0,1,0) -> 0 | G41: =IF(MIN(G40:$AB$40)>0,1,0) -> 0 | H41: =IF(MIN(H40:$AB$40)>0,1,0) -> 0 | I41: =IF(MIN(I40:$AB$40)>0,1,0) -> 0 | J41: =IF(MIN(J40:$AB$40)>0,1,0) -> 0 | K41: =IF(MIN(K40:$AB$40)>0,1,0) -> 1 | L41: =IF(MIN(L40:$AB$40)>0,1,0) -> 1 | ... AB41: =IF(MIN(AB40:$AB$40)>0,1,0) -> 1
A43: Base | B43: C - Performance fee with earn-outs | C43: Cumulative viewing hours | D43: =AB43 -> 15970795 | E43: ='Monthly Viewing Forecast'!E80 -> 2060369.5 | F43: ='Monthly Viewing Forecast'!F80 -> 3864961.5 | G43: ='Monthly Viewing Forecast'!G80 -> 5445744.7 | H43: ='Monthly Viewing Forecast'!H80 -> 6830663.3 | I43: ='Monthly Viewing Forecast'!I80 -> 8044147.2 | J43: ='Monthly Viewing Forecast'!J80 -> 9107557.6 | K43: ='Monthly Viewing Forecast'!K80 -> 10039575 | L43: ='Monthly Viewing Forecast'!L80 -> 10856539 | ... AB43: ='Monthly Viewing Forecast'!AB80 -> 15970795
C44: Licence payment ($) | D44: =SUM(E44:AB44) -> 1350000 | E44: =IF(E$4=1,Assumptions!$C$41,0)+IF(E$4=12,IF(E43>=Assumptions!$C$43,Assumptions!$C$42,0),0)+IF(E$4=18,IF(E43>=Assumptions!$C$45,Assumptions!$C$44,0),0)+IF(E$4=24,IF(E43>=Assumptions!$C$47,Assumptions!$C$46,0),0) -> 850000 | F44: =IF(F$4=1,Assumptions!$C$41,0)+IF(F$4=12,IF(F43>=Assumptions!$C$43,Assumptions!$C$42,0),0)+IF(F$4=18,IF(F43>=Assumptions!$C$45,Assumptions!$C$44,0),0)+IF(F$4=24,IF(F43>=Assumptions!$C$47,Assumptions!$C$46,0),0) -> 0 | G44: =IF(G$4=1,Assumptions!$C$41,0)+IF(G$4=12,IF(G43>=Assumptions!$C$43,Assumptions!$C$42,0),0)+IF(G$4=18,IF(G43>=Assumptions!$C$45,Assumptions!$C$44,0),0)+IF(G$4=24,IF(G43>=Assumptions!$C$47,Assumptions!$C$46,0),0) -> 0 | H44: =IF(H$4=1,Assumptions!$C$41,0)+IF(H$4=12,IF(H43>=Assumptions!$C$43,Assumptions!$C$42,0),0)+IF(H$4=18,IF(H43>=Assumptions!$C$45,Assumptions!$C$44,0),0)+IF(H$4=24,IF(H43>=Assumptions!$C$47,Assumptions!$C$46,0),0) -> 0 | I44: =IF(I$4=1,Assumptions!$C$41,0)+IF(I$4=12,IF(I43>=Assumptions!$C$43,Assumptions!$C$42,0),0)+IF(I$4=18,IF(I43>=Assumptions!$C$45,Assumptions!$C$44,0),0)+IF(I$4=24,IF(I43>=Assumptions!$C$47,Assumptions!$C$46,0),0) -> 0 | J44: =IF(J$4=1,Assumptions!$C$41,0)+IF(J$4=12,IF(J43>=Assumptions!$C$43,Assumptions!$C$42,0),0)+IF(J$4=18,IF(J43>=Assumptions!$C$45,Assumptions!$C$44,0),0)+IF(J$4=24,IF(J43>=Assumptions!$C$47,Assumptions!$C$46,0),0) -> 0 | K44: =IF(K$4=1,Assumptions!$C$41,0)+IF(K$4=12,IF(K43>=Assumptions!$C$43,Assumptions!$C$42,0),0)+IF(K$4=18,IF(K43>=Assumptions!$C$45,Assumptions!$C$44,0),0)+IF(K$4=24,IF(K43>=Assumptions!$C$47,Assumptions!$C$46,0),0) -> 0 | L44: =IF(L$4=1,Assumptions!$C$41,0)+IF(L$4=12,IF(L43>=Assumptions!$C$43,Assumptions!$C$42,0),0)+IF(L$4=18,IF(L43>=Assumptions!$C$45,Assumptions!$C$44,0),0)+IF(L$4=24,IF(L43>=Assumptions!$C$47,Assumptions!$C$46,0),0) -> 0 | ... AB44: =IF(AB$4=1,Assumptions!$C$41,0)+IF(AB$4=12,IF(AB43>=Assumptions!$C$43,Assumptions!$C$42,0),0)+IF(AB$4=18,IF(AB43>=Assumptions!$C$45,Assumptions!$C$44,0),0)+IF(AB$4=24,IF(AB43>=Assumptions!$C$47,Assumptions!$C$46,0),0) -> 0
C45: Net cash flow ($) | D45: =SUM(E45:AB45) -> 762623.76 | E45: ='Title Economics'!E104-E44 -> -1012835.4 | F45: ='Title Economics'!F104-F44 -> 190059.6 | G45: ='Title Economics'!G104-G44 -> 219170.13 | H45: ='Title Economics'!H104-H44 -> 205822.7 | I45: ='Title Economics'!I104-I44 -> 217677.33 | J45: ='Title Economics'!J104-J44 -> 191217.1 | K45: ='Title Economics'!K104-K44 -> 167989.09 | L45: ='Title Economics'!L104-L44 -> 147596.36 | ... AB45: ='Title Economics'!AB104-AB44 -> 18827.071
C46: Cumulative net cash flow ($) | D46: =SUM(E46:AB46) -> 8077623.2 | E46: =SUM($E$45:E45) -> -1012835.4 | F46: =SUM($E$45:F45) -> -822775.85 | G46: =SUM($E$45:G45) -> -603605.71 | H46: =SUM($E$45:H45) -> -397783.01 | I46: =SUM($E$45:I45) -> -180105.68 | J46: =SUM($E$45:J45) -> 11111.423 | K46: =SUM($E$45:K45) -> 179100.52 | L46: =SUM($E$45:L45) -> 326696.87 | ... AB46: =SUM($E$45:AB45) -> 762623.76
C47: Payback flag | D47: =IFERROR(MATCH(1,E47:AB47,0),"n/a") -> 6 | E47: =IF(MIN(E46:$AB$46)>0,1,0) -> 0 | F47: =IF(MIN(F46:$AB$46)>0,1,0) -> 0 | G47: =IF(MIN(G46:$AB$46)>0,1,0) -> 0 | H47: =IF(MIN(H46:$AB$46)>0,1,0) -> 0 | I47: =IF(MIN(I46:$AB$46)>0,1,0) -> 0 | J47: =IF(MIN(J46:$AB$46)>0,1,0) -> 1 | K47: =IF(MIN(K46:$AB$46)>0,1,0) -> 1 | L47: =IF(MIN(L46:$AB$46)>0,1,0) -> 1 | ... AB47: =IF(MIN(AB46:$AB$46)>0,1,0) -> 1
A50: UPSIDE SCENARIO
A51: Upside | B51: A - Fixed licence fee | C51: Licence payment ($) | D51: =SUM(E51:AB51) -> 1498516.7 | E51: =IF(E$4=Assumptions!$C$31,'Deal Structures'!$D$6*Assumptions!$C$30,0)+IF(E$4=Assumptions!$C$33,'Deal Structures'!$D$6*Assumptions!$C$32,0) -> 749258.33 | F51: =IF(F$4=Assumptions!$C$31,'Deal Structures'!$D$6*Assumptions!$C$30,0)+IF(F$4=Assumptions!$C$33,'Deal Structures'!$D$6*Assumptions!$C$32,0) -> 0 | G51: =IF(G$4=Assumptions!$C$31,'Deal Structures'!$D$6*Assumptions!$C$30,0)+IF(G$4=Assumptions!$C$33,'Deal Structures'!$D$6*Assumptions!$C$32,0) -> 0 | H51: =IF(H$4=Assumptions!$C$31,'Deal Structures'!$D$6*Assumptions!$C$30,0)+IF(H$4=Assumptions!$C$33,'Deal Structures'!$D$6*Assumptions!$C$32,0) -> 0 | I51: =IF(I$4=Assumptions!$C$31,'Deal Structures'!$D$6*Assumptions!$C$30,0)+IF(I$4=Assumptions!$C$33,'Deal Structures'!$D$6*Assumptions!$C$32,0) -> 0 | J51: =IF(J$4=Assumptions!$C$31,'Deal Structures'!$D$6*Assumptions!$C$30,0)+IF(J$4=Assumptions!$C$33,'Deal Structures'!$D$6*Assumptions!$C$32,0) -> 0 | K51: =IF(K$4=Assumptions!$C$31,'Deal Structures'!$D$6*Assumptions!$C$30,0)+IF(K$4=Assumptions!$C$33,'Deal Structures'!$D$6*Assumptions!$C$32,0) -> 749258.33 | L51: =IF(L$4=Assumptions!$C$31,'Deal Structures'!$D$6*Assumptions!$C$30,0)+IF(L$4=Assumptions!$C$33,'Deal Structures'!$D$6*Assumptions!$C$32,0) -> 0 | ... AB51: =IF(AB$4=Assumptions!$C$31,'Deal Structures'!$D$6*Assumptions!$C$30,0)+IF(AB$4=Assumptions!$C$33,'Deal Structures'!$D$6*Assumptions!$C$32,0) -> 0
C52: Net cash flow ($) | D52: =SUM(E52:AB52) -> 1268845.5 | E52: ='Title Economics'!E157-E51 -> -846821.64 | F52: ='Title Economics'!F157-F51 -> 247081.68 | G52: ='Title Economics'!G157-G51 -> 270669.27 | H52: ='Title Economics'!H157-H51 -> 253303.4 | I52: ='Title Economics'!I157-I51 -> 260624.38 | J52: ='Title Economics'!J157-J51 -> 231025.24 | K52: ='Title Economics'!K157-K51 -> -544451.7 | L52: ='Title Economics'!L157-L51 -> 181580.07 | ... AB52: ='Title Economics'!AB157-AB51 -> 26765.648
C53: Cumulative net cash flow ($) | D53: =SUM(E53:AB53) -> 12774484 | E53: =SUM($E$52:E52) -> -846821.64 | F53: =SUM($E$52:F52) -> -599739.96 | G53: =SUM($E$52:G52) -> -329070.69 | H53: =SUM($E$52:H52) -> -75767.286 | I53: =SUM($E$52:I52) -> 184857.1 | J53: =SUM($E$52:J52) -> 415882.34 | K53: =SUM($E$52:K52) -> -128569.36 | L53: =SUM($E$52:L52) -> 53010.717 | ... AB53: =SUM($E$52:AB52) -> 1268845.5
C54: Payback flag | D54: =IFERROR(MATCH(1,E54:AB54,0),"n/a") -> 8 | E54: =IF(MIN(E53:$AB$53)>0,1,0) -> 0 | F54: =IF(MIN(F53:$AB$53)>0,1,0) -> 0 | G54: =IF(MIN(G53:$AB$53)>0,1,0) -> 0 | H54: =IF(MIN(H53:$AB$53)>0,1,0) -> 0 | I54: =IF(MIN(I53:$AB$53)>0,1,0) -> 0 | J54: =IF(MIN(J53:$AB$53)>0,1,0) -> 0 | K54: =IF(MIN(K53:$AB$53)>0,1,0) -> 0 | L54: =IF(MIN(L53:$AB$53)>0,1,0) -> 1 | ... AB54: =IF(MIN(AB53:$AB$53)>0,1,0) -> 1
A56: Upside | B56: B - Minimum guarantee plus revenue share | C56: Revenue share accrued ($) | D56: =SUM(E56:AB56) -> 1602006.5 | E56: ='Monthly Viewing Forecast'!E118*Assumptions!$C$38 -> 193789.98 | F56: ='Monthly Viewing Forecast'!F118*Assumptions!$C$38 -> 171517.99 | G56: ='Monthly Viewing Forecast'!G118*Assumptions!$C$38 -> 151823.34 | H56: ='Monthly Viewing Forecast'!H118*Assumptions!$C$38 -> 134405.55 | I56: ='Monthly Viewing Forecast'!I118*Assumptions!$C$38 -> 118999.45 | J56: ='Monthly Viewing Forecast'!J118*Assumptions!$C$38 -> 105370.99 | K56: ='Monthly Viewing Forecast'!K118*Assumptions!$C$38 -> 93313.586 | L56: ='Monthly Viewing Forecast'!L118*Assumptions!$C$38 -> 82644.828 | ... AB56: ='Monthly Viewing Forecast'!AB118*Assumptions!$C$38 -> 12006.066
C57: Cumulative revenue share accrued ($) | D57: =AB57 -> 1602006.5 | E57: =SUM($E$56:E56) -> 193789.98 | F57: =SUM($E$56:F56) -> 365307.96 | G57: =SUM($E$56:G56) -> 517131.3 | H57: =SUM($E$56:H56) -> 651536.85 | I57: =SUM($E$56:I56) -> 770536.3 | J57: =SUM($E$56:J56) -> 875907.29 | K57: =SUM($E$56:K56) -> 969220.87 | L57: =SUM($E$56:L56) -> 1051865.7 | ... AB57: =SUM($E$56:AB56) -> 1602006.5
C58: Cumulative obligation ($) | D58: =AB58 -> 1602006.5 | E58: =MAX(Assumptions!$C$37,E57) -> 950000 | F58: =MAX(Assumptions!$C$37,F57) -> 950000 | G58: =MAX(Assumptions!$C$37,G57) -> 950000 | H58: =MAX(Assumptions!$C$37,H57) -> 950000 | I58: =MAX(Assumptions!$C$37,I57) -> 950000 | J58: =MAX(Assumptions!$C$37,J57) -> 950000 | K58: =MAX(Assumptions!$C$37,K57) -> 969220.87 | L58: =MAX(Assumptions!$C$37,L57) -> 1051865.7 | ... AB58: =MAX(Assumptions!$C$37,AB57) -> 1602006.5
C59: Licence payment ($) | D59: =SUM(E59:AB59) -> 1602006.5 | E59: =E58 -> 950000 | F59: =F58-E58 -> 0 | G59: =G58-F58 -> 0 | H59: =H58-G58 -> 0 | I59: =I58-H58 -> 0 | J59: =J58-I58 -> 0 | K59: =K58-J58 -> 19220.874 | L59: =L58-K58 -> 82644.828 | M59: =M58-L58 -> 73203.659 | ... AB59: =AB58-AA58 -> 12006.066
C60: Net cash flow ($) | D60: =SUM(E60:AB60) -> 1165355.7 | E60: ='Title Economics'!E157-E59 -> -1047563.3 | F60: ='Title Economics'!F157-F59 -> 247081.68 | G60: ='Title Economics'!G157-G59 -> 270669.27 | H60: ='Title Economics'!H157-H59 -> 253303.4 | I60: ='Title Economics'!I157-I59 -> 260624.38 | J60: ='Title Economics'!J157-J59 -> 231025.24 | K60: ='Title Economics'!K157-K59 -> 185585.76 | L60: ='Title Economics'!L157-L59 -> 98935.246 | ... AB60: ='Title Economics'!AB157-AB59 -> 14759.582
C61: Cumulative net cash flow ($) | D61: =SUM(E61:AB61) -> 13686896 | E61: =SUM($E$60:E60) -> -1047563.3 | F61: =SUM($E$60:F60) -> -800481.63 | G61: =SUM($E$60:G60) -> -529812.36 | H61: =SUM($E$60:H60) -> -276508.96 | I61: =SUM($E$60:I60) -> -15884.577 | J61: =SUM($E$60:J60) -> 215140.67 | K61: =SUM($E$60:K60) -> 400726.42 | L61: =SUM($E$60:L60) -> 499661.67 | ... AB61: =SUM($E$60:AB60) -> 1165355.7
C62: Payback flag | D62: =IFERROR(MATCH(1,E62:AB62,0),"n/a") -> 6 | E62: =IF(MIN(E61:$AB$61)>0,1,0) -> 0 | F62: =IF(MIN(F61:$AB$61)>0,1,0) -> 0 | G62: =IF(MIN(G61:$AB$61)>0,1,0) -> 0 | H62: =IF(MIN(H61:$AB$61)>0,1,0) -> 0 | I62: =IF(MIN(I61:$AB$61)>0,1,0) -> 0 | J62: =IF(MIN(J61:$AB$61)>0,1,0) -> 1 | K62: =IF(MIN(K61:$AB$61)>0,1,0) -> 1 | L62: =IF(MIN(L61:$AB$61)>0,1,0) -> 1 | ... AB62: =IF(MIN(AB61:$AB$61)>0,1,0) -> 1
A64: Upside | B64: C - Performance fee with earn-outs | C64: Cumulative viewing hours | D64: =AB64 -> 17921711 | E64: ='Monthly Viewing Forecast'!E119 -> 2185640 | F64: ='Monthly Viewing Forecast'!F119 -> 4117436.2 | G64: ='Monthly Viewing Forecast'!G119 -> 5825100 | H64: ='Monthly Viewing Forecast'!H119 -> 7334835.7 | I64: ='Monthly Viewing Forecast'!I119 -> 8669759.2 | J64: ='Monthly Viewing Forecast'!J119 -> 9850264.4 | K64: ='Monthly Viewing Forecast'!K119 -> 10894347 | L64: ='Monthly Viewing Forecast'!L119 -> 11817888 | ... AB64: ='Monthly Viewing Forecast'!AB119 -> 17921711
C65: Licence payment ($) | D65: =SUM(E65:AB65) -> 1650000 | E65: =IF(E$4=1,Assumptions!$C$41,0)+IF(E$4=12,IF(E64>=Assumptions!$C$43,Assumptions!$C$42,0),0)+IF(E$4=18,IF(E64>=Assumptions!$C$45,Assumptions!$C$44,0),0)+IF(E$4=24,IF(E64>=Assumptions!$C$47,Assumptions!$C$46,0),0) -> 850000 | F65: =IF(F$4=1,Assumptions!$C$41,0)+IF(F$4=12,IF(F64>=Assumptions!$C$43,Assumptions!$C$42,0),0)+IF(F$4=18,IF(F64>=Assumptions!$C$45,Assumptions!$C$44,0),0)+IF(F$4=24,IF(F64>=Assumptions!$C$47,Assumptions!$C$46,0),0) -> 0 | G65: =IF(G$4=1,Assumptions!$C$41,0)+IF(G$4=12,IF(G64>=Assumptions!$C$43,Assumptions!$C$42,0),0)+IF(G$4=18,IF(G64>=Assumptions!$C$45,Assumptions!$C$44,0),0)+IF(G$4=24,IF(G64>=Assumptions!$C$47,Assumptions!$C$46,0),0) -> 0 | H65: =IF(H$4=1,Assumptions!$C$41,0)+IF(H$4=12,IF(H64>=Assumptions!$C$43,Assumptions!$C$42,0),0)+IF(H$4=18,IF(H64>=Assumptions!$C$45,Assumptions!$C$44,0),0)+IF(H$4=24,IF(H64>=Assumptions!$C$47,Assumptions!$C$46,0),0) -> 0 | I65: =IF(I$4=1,Assumptions!$C$41,0)+IF(I$4=12,IF(I64>=Assumptions!$C$43,Assumptions!$C$42,0),0)+IF(I$4=18,IF(I64>=Assumptions!$C$45,Assumptions!$C$44,0),0)+IF(I$4=24,IF(I64>=Assumptions!$C$47,Assumptions!$C$46,0),0) -> 0 | J65: =IF(J$4=1,Assumptions!$C$41,0)+IF(J$4=12,IF(J64>=Assumptions!$C$43,Assumptions!$C$42,0),0)+IF(J$4=18,IF(J64>=Assumptions!$C$45,Assumptions!$C$44,0),0)+IF(J$4=24,IF(J64>=Assumptions!$C$47,Assumptions!$C$46,0),0) -> 0 | K65: =IF(K$4=1,Assumptions!$C$41,0)+IF(K$4=12,IF(K64>=Assumptions!$C$43,Assumptions!$C$42,0),0)+IF(K$4=18,IF(K64>=Assumptions!$C$45,Assumptions!$C$44,0),0)+IF(K$4=24,IF(K64>=Assumptions!$C$47,Assumptions!$C$46,0),0) -> 0 | L65: =IF(L$4=1,Assumptions!$C$41,0)+IF(L$4=12,IF(L64>=Assumptions!$C$43,Assumptions!$C$42,0),0)+IF(L$4=18,IF(L64>=Assumptions!$C$45,Assumptions!$C$44,0),0)+IF(L$4=24,IF(L64>=Assumptions!$C$47,Assumptions!$C$46,0),0) -> 0 | ... AB65: =IF(AB$4=1,Assumptions!$C$41,0)+IF(AB$4=12,IF(AB64>=Assumptions!$C$43,Assumptions!$C$42,0),0)+IF(AB$4=18,IF(AB64>=Assumptions!$C$45,Assumptions!$C$44,0),0)+IF(AB$4=24,IF(AB64>=Assumptions!$C$47,Assumptions!$C$46,0),0) -> 300000
C66: Net cash flow ($) | D66: =SUM(E66:AB66) -> 1117362.1 | E66: ='Title Economics'!E157-E65 -> -947563.31 | F66: ='Title Economics'!F157-F65 -> 247081.68 | G66: ='Title Economics'!G157-G65 -> 270669.27 | H66: ='Title Economics'!H157-H65 -> 253303.4 | I66: ='Title Economics'!I157-I65 -> 260624.38 | J66: ='Title Economics'!J157-J65 -> 231025.24 | K66: ='Title Economics'!K157-K65 -> 204806.63 | L66: ='Title Economics'!L157-L65 -> 181580.07 | ... AB66: ='Title Economics'!AB157-AB65 -> -273234.35
C67: Cumulative net cash flow ($) | D67: =SUM(E67:AB67) -> 18543334 | E67: =SUM($E$66:E66) -> -947563.31 | F67: =SUM($E$66:F66) -> -700481.63 | G67: =SUM($E$66:G66) -> -429812.36 | H67: =SUM($E$66:H66) -> -176508.96 | I67: =SUM($E$66:I66) -> 84115.423 | J67: =SUM($E$66:J66) -> 315140.67 | K67: =SUM($E$66:K66) -> 519947.3 | L67: =SUM($E$66:L66) -> 701527.37 | ... AB67: =SUM($E$66:AB66) -> 1117362.1
C68: Payback flag | D68: =IFERROR(MATCH(1,E68:AB68,0),"n/a") -> 5 | E68: =IF(MIN(E67:$AB$67)>0,1,0) -> 0 | F68: =IF(MIN(F67:$AB$67)>0,1,0) -> 0 | G68: =IF(MIN(G67:$AB$67)>0,1,0) -> 0 | H68: =IF(MIN(H67:$AB$67)>0,1,0) -> 0 | I68: =IF(MIN(I67:$AB$67)>0,1,0) -> 1 | J68: =IF(MIN(J67:$AB$67)>0,1,0) -> 1 | K68: =IF(MIN(K67:$AB$67)>0,1,0) -> 1 | L68: =IF(MIN(L67:$AB$67)>0,1,0) -> 1 | ... AB68: =IF(MIN(AB67:$AB$67)>0,1,0) -> 1
A71: DEAL STRUCTURE COMPARISON
A72: Measure | C72: A - Fixed licence fee | D72: B - Minimum guarantee plus revenue share | E72: C - Performance fee with earn-outs
A73: Total expected platform licence cost - Base ($) | C73: ='Deal Structures'!$D$30 -> 1498516.7 | D73: ='Deal Structures'!$D$38 -> 1351903 | E73: ='Deal Structures'!$D$44 -> 1350000
A74: PV of licence payments - Base ($) | C74: =SUMPRODUCT('Deal Structures'!$E$30:$AB$30,'Title Economics'!$E$6:$AB$6) -> 1443543.4 | D74: =SUMPRODUCT('Deal Structures'!$E$38:$AB$38,'Title Economics'!$E$6:$AB$6) -> 1292294.2 | E74: =SUMPRODUCT('Deal Structures'!$E$44:$AB$44,'Title Economics'!$E$6:$AB$6) -> 1276142.3
A75: Base-case NPV ($) | C75: ='Title Economics'!$D$107-SUMPRODUCT('Deal Structures'!$E$30:$AB$30,'Title Economics'!$E$6:$AB$6) -> 496418.04 | D75: ='Title Economics'!$D$107-SUMPRODUCT('Deal Structures'!$E$38:$AB$38,'Title Economics'!$E$6:$AB$6) -> 647667.31 | E75: ='Title Economics'!$D$107-SUMPRODUCT('Deal Structures'!$E$44:$AB$44,'Title Economics'!$E$6:$AB$6) -> 663819.16
A76: Base-case ROI | C76: =('Title Economics'!$D$105-('Title Economics'!$D$106+SUMPRODUCT('Deal Structures'!$E$30:$AB$30,'Title Economics'!$E$6:$AB$6)))/('Title Economics'!$D$106+SUMPRODUCT('Deal Structures'!$E$30:$AB$30,'Title Economics'!$E$6:$AB$6)) -> 0.2 | D76: =('Title Economics'!$D$105-('Title Economics'!$D$106+SUMPRODUCT('Deal Structures'!$E$38:$AB$38,'Title Economics'!$E$6:$AB$6)))/('Title Economics'!$D$106+SUMPRODUCT('Deal Structures'!$E$38:$AB$38,'Title Economics'!$E$6:$AB$6)) -> 0.27786851 | E76: =('Title Economics'!$D$105-('Title Economics'!$D$106+SUMPRODUCT('Deal Structures'!$E$44:$AB$44,'Title Economics'!$E$6:$AB$6)))/('Title Economics'!$D$106+SUMPRODUCT('Deal Structures'!$E$44:$AB$44,'Title Economics'!$E$6:$AB$6)) -> 0.28678545
A77: Total licence cost - Downside ($) | C77: ='Deal Structures'!$D$9 -> 1498516.7 | D77: ='Deal Structures'!$D$17 -> 1156796 | E77: ='Deal Structures'!$D$23 -> 850000
A78: Downside NPV ($) | C78: ='Title Economics'!$D$54-SUMPRODUCT('Deal Structures'!$E$9:$AB$9,'Title Economics'!$E$6:$AB$6) -> 15172.812 | D78: ='Title Economics'!$D$54-SUMPRODUCT('Deal Structures'!$E$17:$AB$17,'Title Economics'!$E$6:$AB$6) -> 340355.89 | E78: ='Title Economics'!$D$54-SUMPRODUCT('Deal Structures'!$E$23:$AB$23,'Title Economics'!$E$6:$AB$6) -> 616705.89
A79: Upside NPV ($) | C79: ='Title Economics'!$D$160-SUMPRODUCT('Deal Structures'!$E$51:$AB$51,'Title Economics'!$E$6:$AB$6) -> 1101352.9 | D79: ='Title Economics'!$D$160-SUMPRODUCT('Deal Structures'!$E$59:$AB$59,'Title Economics'!$E$6:$AB$6) -> 1027198.9 | E79: ='Title Economics'!$D$160-SUMPRODUCT('Deal Structures'!$E$65:$AB$65,'Title Economics'!$E$6:$AB$6) -> 1029595.8
A80: Downside exposure - fall in NPV from Base ($) | C80: =C75-C78 -> 481245.23 | D80: =D75-D78 -> 307311.42 | E80: =E75-E78 -> 47113.271
A81: Break-even viewing hours - Base cost profile | C81: =Scenarios!$D$50*('Title Economics'!$D$111+C74)/('Title Economics'!$D$108+'Title Economics'!$D$109-'Title Economics'!$D$110) -> 13028127 | D81: =Scenarios!$D$50*('Title Economics'!$D$111+D74)/('Title Economics'!$D$108+'Title Economics'!$D$109-'Title Economics'!$D$110) -> 12131552 | E81: =Scenarios!$D$50*('Title Economics'!$D$111+E74)/('Title Economics'!$D$108+'Title Economics'!$D$109-'Title Economics'!$D$110) -> 12035807
A82: Payback period (months, Base) | C82: ='Deal Structures'!$D$33 -> 11 | D82: ='Deal Structures'!$D$41 -> 7 | E82: ='Deal Structures'!$D$47 -> 6
A83: Economic alignment with the seller | C83: Low. The buyer carries all performance risk once the fee is fixed. | D83: High. The seller participates directly in realised advertising revenue. | E83: Moderate to high. The seller is paid more only if viewing thresholds are met.
A84: Operational complexity | C84: Low. Two instalments and no ongoing reporting obligation. | D84: High. Requires audited monthly revenue reporting and a credit mechanism. | E84: Moderate. Requires agreed viewing definitions and an audit right at three test dates.
A85: Recommended negotiating position | C85: Acceptable only at or below the target price. Reject at the ask. | D85: Acceptable fallback. Cap total payments at the walk-away ceiling. | E85: Preferred. Open here; it prices the disagreement about viewing rather than arguing it.
A87: Break-even viewing hours for Structures B and C hold the Base-case payment profile constant; under those structures a viewing shortfall also reduces the fee, so the true break-even is lower.
A88: Payback is the first month after which cumulative net cash flow stays positive to the end of the term.

Sheet Scenarios
A1: PROJECT NIGHTFALL
A2: Scenario definitions, drivers and results
A3: Independent analytical case study using synthetic assumptions. Not based on proprietary company information.
A5: SCENARIO SELECTOR
A6: Active scenario | C6: Base | E6: Change this cell to re-run the whole model. Every downstream sheet responds.
A7: Scenario index | C7: =MATCH($C$6,$C$10:$E$10,0) -> 2
A9: SCENARIO DRIVERS
A10: Operating driver | C10: Downside | D10: Base | E10: Upside | F10: Active | G10: Basis
A11: Unique viewers (multiplier on lifetime viewers) | C11: 0.98 | D11: 1 | E11: 1.04 | F11: =INDEX($C11:$E11,1,$C$7) -> 1 | G11: Reach of the package on the service
A12: Completion rate (multiplier) | C12: 0.98 | D12: 1 | E12: 1.02 | F12: =INDEX($C12:$E12,1,$C$7) -> 1 | G12: Engagement per start
A13: Monthly viewing decay (delta, percentage points) | C13: 0.008 | D13: 0 | E13: -0.008 | F13: =INDEX($C13:$E13,1,$C$7) -> 0 | G13: Steeper decay shortens the earning life
A14: Ad fill rate (multiplier) | C14: 0.98 | D14: 1 | E14: 1.02 | F14: =INDEX($C14:$E14,1,$C$7) -> 1 | G14: Advertiser demand against available inventory
A15: Net advertising CPM (multiplier) | C15: 0.96 | D15: 1 | E15: 1.035 | F15: =INDEX($C15:$E15,1,$C$7) -> 1 | G15: Pricing in the ad market
A16: Incrementality (multiplier) | C16: 0.97 | D16: 1 | E16: 1.03 | F16: =INDEX($C16:$E16,1,$C$7) -> 1 | G16: Share of viewing that is genuinely additive
A17: Marketing cost per unit of reach (multiplier) | C17: 1.05 | D17: 1 | E17: 0.97 | F17: =INDEX($C17:$E17,1,$C$7) -> 1 | G17: Efficiency of promotional support
A18: Scenarios move operating drivers only. No output is overridden.
A20: SCENARIO-ADJUSTED TITLE DRIVERS
A21: Downside | C21: Nightfall Protocol | D21: Ash Ridge | E21: Cold Harbor | F21: The Quiet Depth | G21: Vector Nine
A22: Monthly viewing decay rate | C22: ='Title Inputs'!$C$20+Scenarios!$C$13 -> 0.123 | D22: ='Title Inputs'!$D$20+Scenarios!$C$13 -> 0.128 | E22: ='Title Inputs'!$E$20+Scenarios!$C$13 -> 0.136 | F22: ='Title Inputs'!$F$20+Scenarios!$C$13 -> 0.148 | G22: ='Title Inputs'!$G$20+Scenarios!$C$13 -> 0.158
A23: Month-1 unique viewers | C23: ='Title Inputs'!$C$15*Scenarios!$C$11/'Title Inputs'!$C$21 -> 428557.45 | D23: ='Title Inputs'!$D$15*Scenarios!$C$11/'Title Inputs'!$D$21 -> 376177.54 | E23: ='Title Inputs'!$E$15*Scenarios!$C$11/'Title Inputs'!$E$21 -> 325770.47 | F23: ='Title Inputs'!$F$15*Scenarios!$C$11/'Title Inputs'!$F$21 -> 232611.52 | G23: ='Title Inputs'!$G$15*Scenarios!$C$11/'Title Inputs'!$G$21 -> 127530.28
A24: Completion rate | C24: ='Title Inputs'!$C$18*Scenarios!$C$12 -> 0.6272 | D24: ='Title Inputs'!$D$18*Scenarios!$C$12 -> 0.5978 | E24: ='Title Inputs'!$E$18*Scenarios!$C$12 -> 0.5782 | F24: ='Title Inputs'!$F$18*Scenarios!$C$12 -> 0.4998 | G24: ='Title Inputs'!$G$18*Scenarios!$C$12 -> 0.441
A25: Ad fill rate | C25: ='Title Inputs'!$C$25*Scenarios!$C$14 -> 0.8036 | D25: ='Title Inputs'!$D$25*Scenarios!$C$14 -> 0.7938 | E25: ='Title Inputs'!$E$25*Scenarios!$C$14 -> 0.784 | F25: ='Title Inputs'!$F$25*Scenarios!$C$14 -> 0.7546 | G25: ='Title Inputs'!$G$25*Scenarios!$C$14 -> 0.735
A26: Net advertising CPM ($) | C26: ='Title Inputs'!$C$26*Scenarios!$C$15 -> 24.48 | D26: ='Title Inputs'!$D$26*Scenarios!$C$15 -> 23.04 | E26: ='Title Inputs'!$E$26*Scenarios!$C$15 -> 22.08 | F26: ='Title Inputs'!$F$26*Scenarios!$C$15 -> 20.16 | G26: ='Title Inputs'!$G$26*Scenarios!$C$15 -> 18.72
A27: Incrementality rate | C27: ='Title Inputs'!$C$27*Scenarios!$C$16 -> 0.6014 | D27: ='Title Inputs'!$D$27*Scenarios!$C$16 -> 0.5626 | E27: ='Title Inputs'!$E$27*Scenarios!$C$16 -> 0.5335 | F27: ='Title Inputs'!$F$27*Scenarios!$C$16 -> 0.4559 | G27: ='Title Inputs'!$G$27*Scenarios!$C$16 -> 0.388
A28: Marketing support ($) | C28: ='Title Inputs'!$C$31*Scenarios!$C$17 -> 173250 | D28: ='Title Inputs'!$D$31*Scenarios!$C$17 -> 136500 | E28: ='Title Inputs'!$E$31*Scenarios!$C$17 -> 105000 | F28: ='Title Inputs'!$F$31*Scenarios!$C$17 -> 75600 | G28: ='Title Inputs'!$G$31*Scenarios!$C$17 -> 60900
A30: Base | C30: Nightfall Protocol | D30: Ash Ridge | E30: Cold Harbor | F30: The Quiet Depth | G30: Vector Nine
A31: Monthly viewing decay rate | C31: ='Title Inputs'!$C$20+Scenarios!$D$13 -> 0.115 | D31: ='Title Inputs'!$D$20+Scenarios!$D$13 -> 0.12 | E31: ='Title Inputs'!$E$20+Scenarios!$D$13 -> 0.128 | F31: ='Title Inputs'!$F$20+Scenarios!$D$13 -> 0.14 | G31: ='Title Inputs'!$G$20+Scenarios!$D$13 -> 0.15
A32: Month-1 unique viewers | C32: ='Title Inputs'!$C$15*Scenarios!$D$11/'Title Inputs'!$C$21 -> 437303.52 | D32: ='Title Inputs'!$D$15*Scenarios!$D$11/'Title Inputs'!$D$21 -> 383854.63 | E32: ='Title Inputs'!$E$15*Scenarios!$D$11/'Title Inputs'!$E$21 -> 332418.85 | F32: ='Title Inputs'!$F$15*Scenarios!$D$11/'Title Inputs'!$F$21 -> 237358.69 | G32: ='Title Inputs'!$G$15*Scenarios!$D$11/'Title Inputs'!$G$21 -> 130132.94
A33: Completion rate | C33: ='Title Inputs'!$C$18*Scenarios!$D$12 -> 0.64 | D33: ='Title Inputs'!$D$18*Scenarios!$D$12 -> 0.61 | E33: ='Title Inputs'!$E$18*Scenarios!$D$12 -> 0.59 | F33: ='Title Inputs'!$F$18*Scenarios!$D$12 -> 0.51 | G33: ='Title Inputs'!$G$18*Scenarios!$D$12 -> 0.45
A34: Ad fill rate | C34: ='Title Inputs'!$C$25*Scenarios!$D$14 -> 0.82 | D34: ='Title Inputs'!$D$25*Scenarios!$D$14 -> 0.81 | E34: ='Title Inputs'!$E$25*Scenarios!$D$14 -> 0.8 | F34: ='Title Inputs'!$F$25*Scenarios!$D$14 -> 0.77 | G34: ='Title Inputs'!$G$25*Scenarios!$D$14 -> 0.75
A35: Net advertising CPM ($) | C35: ='Title Inputs'!$C$26*Scenarios!$D$15 -> 25.5 | D35: ='Title Inputs'!$D$26*Scenarios!$D$15 -> 24 | E35: ='Title Inputs'!$E$26*Scenarios!$D$15 -> 23 | F35: ='Title Inputs'!$F$26*Scenarios!$D$15 -> 21 | G35: ='Title Inputs'!$G$26*Scenarios!$D$15 -> 19.5
A36: Incrementality rate | C36: ='Title Inputs'!$C$27*Scenarios!$D$16 -> 0.62 | D36: ='Title Inputs'!$D$27*Scenarios!$D$16 -> 0.58 | E36: ='Title Inputs'!$E$27*Scenarios!$D$16 -> 0.55 | F36: ='Title Inputs'!$F$27*Scenarios!$D$16 -> 0.47 | G36: ='Title Inputs'!$G$27*Scenarios!$D$16 -> 0.4
A37: Marketing support ($) | C37: ='Title Inputs'!$C$31*Scenarios!$D$17 -> 165000 | D37: ='Title Inputs'!$D$31*Scenarios!$D$17 -> 130000 | E37: ='Title Inputs'!$E$31*Scenarios!$D$17 -> 100000 | F37: ='Title Inputs'!$F$31*Scenarios!$D$17 -> 72000 | G37: ='Title Inputs'!$G$31*Scenarios!$D$17 -> 58000
A39: Upside | C39: Nightfall Protocol | D39: Ash Ridge | E39: Cold Harbor | F39: The Quiet Depth | G39: Vector Nine
A40: Monthly viewing decay rate | C40: ='Title Inputs'!$C$20+Scenarios!$E$13 -> 0.107 | D40: ='Title Inputs'!$D$20+Scenarios!$E$13 -> 0.112 | E40: ='Title Inputs'!$E$20+Scenarios!$E$13 -> 0.12 | F40: ='Title Inputs'!$F$20+Scenarios!$E$13 -> 0.132 | G40: ='Title Inputs'!$G$20+Scenarios!$E$13 -> 0.142
A41: Month-1 unique viewers | C41: ='Title Inputs'!$C$15*Scenarios!$E$11/'Title Inputs'!$C$21 -> 454795.66 | D41: ='Title Inputs'!$D$15*Scenarios!$E$11/'Title Inputs'!$D$21 -> 399208.82 | E41: ='Title Inputs'!$E$15*Scenarios!$E$11/'Title Inputs'!$E$21 -> 345715.6 | F41: ='Title Inputs'!$F$15*Scenarios!$E$11/'Title Inputs'!$F$21 -> 246853.04 | G41: ='Title Inputs'!$G$15*Scenarios!$E$11/'Title Inputs'!$G$21 -> 135338.26
A42: Completion rate | C42: ='Title Inputs'!$C$18*Scenarios!$E$12 -> 0.6528 | D42: ='Title Inputs'!$D$18*Scenarios!$E$12 -> 0.6222 | E42: ='Title Inputs'!$E$18*Scenarios!$E$12 -> 0.6018 | F42: ='Title Inputs'!$F$18*Scenarios!$E$12 -> 0.5202 | G42: ='Title Inputs'!$G$18*Scenarios!$E$12 -> 0.459
A43: Ad fill rate | C43: ='Title Inputs'!$C$25*Scenarios!$E$14 -> 0.8364 | D43: ='Title Inputs'!$D$25*Scenarios!$E$14 -> 0.8262 | E43: ='Title Inputs'!$E$25*Scenarios!$E$14 -> 0.816 | F43: ='Title Inputs'!$F$25*Scenarios!$E$14 -> 0.7854 | G43: ='Title Inputs'!$G$25*Scenarios!$E$14 -> 0.765
A44: Net advertising CPM ($) | C44: ='Title Inputs'!$C$26*Scenarios!$E$15 -> 26.3925 | D44: ='Title Inputs'!$D$26*Scenarios!$E$15 -> 24.84 | E44: ='Title Inputs'!$E$26*Scenarios!$E$15 -> 23.805 | F44: ='Title Inputs'!$F$26*Scenarios!$E$15 -> 21.735 | G44: ='Title Inputs'!$G$26*Scenarios!$E$15 -> 20.1825
A45: Incrementality rate | C45: ='Title Inputs'!$C$27*Scenarios!$E$16 -> 0.6386 | D45: ='Title Inputs'!$D$27*Scenarios!$E$16 -> 0.5974 | E45: ='Title Inputs'!$E$27*Scenarios!$E$16 -> 0.5665 | F45: ='Title Inputs'!$F$27*Scenarios!$E$16 -> 0.4841 | G45: ='Title Inputs'!$G$27*Scenarios!$E$16 -> 0.412
A46: Marketing support ($) | C46: ='Title Inputs'!$C$31*Scenarios!$E$17 -> 160050 | D46: ='Title Inputs'!$D$31*Scenarios!$E$17 -> 126100 | E46: ='Title Inputs'!$E$31*Scenarios!$E$17 -> 97000 | F46: ='Title Inputs'!$F$31*Scenarios!$E$17 -> 69840 | G46: ='Title Inputs'!$G$31*Scenarios!$E$17 -> 56260
A48: SCENARIO RESULTS
A49: Portfolio outcome | C49: Downside | D49: Base | E49: Upside | G49: Definition
A50: Viewing hours | C50: ='Monthly Viewing Forecast'!$D$38 -> 14529862 | D50: ='Monthly Viewing Forecast'!$D$77 -> 15970795 | E50: ='Monthly Viewing Forecast'!$D$116 -> 17921711 | G50: Sum of monthly title-level viewing hours
A51: Gross advertising revenue ($) | C51: ='Monthly Viewing Forecast'!$D$40 -> 4131414.2 | D51: ='Monthly Viewing Forecast'!$D$79 -> 4828224.8 | E51: ='Monthly Viewing Forecast'!$D$118 -> 5721451.7 | G51: Monetised impressions divided by 1,000, multiplied by net CPM
A52: Incremental advertising revenue ($) | C52: ='Title Economics'!$D$44 -> 2301203.1 | D52: ='Title Economics'!$D$97 -> 2773098.3 | E52: ='Title Economics'!$D$150 -> 3385460.9 | G52: Gross advertising revenue multiplied by the incrementality rate
A53: Follow-on engagement value ($) | C53: ='Title Economics'!$D$45 -> 359936.51 | D53: ='Title Economics'!$D$98 -> 407970.58 | E53: ='Title Economics'!$D$151 -> 471663.75 | G53: Modelled incremental benefit, reported separately from ad revenue
A54: Total support costs ($) | C54: ='Title Economics'!$D$50 -> 1067317.4 | D54: ='Title Economics'!$D$103 -> 1068445.1 | E54: ='Title Economics'!$D$156 -> 1089762.5 | G54: Marketing, delivery and QC, and variable serving costs
A55: Contribution before licence fee ($) | C55: ='Title Economics'!$D$51 -> 1593822.3 | D55: ='Title Economics'!$D$104 -> 2112623.8 | E55: ='Title Economics'!$D$157 -> 2767362.1 | G55: Benefits less support costs, before any payment to the seller
A56: PV of modelled benefits ($) | C56: ='Title Economics'!$D$52 -> 2498097.6 | D56: ='Title Economics'!$D$105 -> 2978508.3 | E56: ='Title Economics'!$D$158 -> 3601828.1 | G56: Discounted at the monthly required return
A57: PV of support costs ($) | C57: ='Title Economics'!$D$53 -> 1039381.4 | D57: ='Title Economics'!$D$106 -> 1038546.8 | E57: ='Title Economics'!$D$159 -> 1056931.8 | G57: Discounted at the monthly required return
A58: PV of contribution before licence fee ($) | C58: ='Title Economics'!$D$54 -> 1458716.2 | D58: ='Title Economics'!$D$107 -> 1939961.5 | E58: ='Title Economics'!$D$160 -> 2544896.3 | G58: Capital available to pay the seller and still earn the required return
A59: Bid ceiling - maximum fixed fee at the required return ($) | C59: =C58/Assumptions!$C$34 -> 1514267.3 | D59: =D58/Assumptions!$C$34 -> 2013839.4 | E59: =E58/Assumptions!$C$34 -> 2641811.4 | G59: PV of contribution before fee divided by the PV factor on one dollar of fee
A61: PRICING CONCLUSIONS
A62: Seller initial ask ($) | C62: =Assumptions!$C$10 -> 2500000 | G62: Linked to Assumptions
A63: Walk-away ceiling - Base bid ceiling ($) | C63: =$D$59 -> 2013839.4 | G63: Above this price the Base case fails the required return
A64: Downside break-even fee ($) | C64: =$C$59 -> 1514267.3 | G64: Price at which the Downside case is exactly break-even
A65: Fee at the target portfolio ROI ($) | C65: =('Title Economics'!$D$105/(1+Assumptions!$C$15)-'Title Economics'!$D$106)/Assumptions!$C$34 -> 1498516.7 | G65: Price at which the Base case earns the target ROI
A66: Recommended target price ($) | C66: =MIN($C$64,$C$65) -> 1498516.7 | G66: The more binding of the two pricing tests
A67: Recommended opening offer ($) | C67: =$C$66*Assumptions!$C$16 -> 1318694.7 | G67: Target price less the negotiating margin set on Assumptions
A68: Seller ask premium to the walk-away ceiling | C68: =$C$62/$C$63-1 -> 0.24140984
A69: Viewing uplift required to justify the ask | C69: =($C$62*Assumptions!$C$34+'Title Economics'!$D$111)/('Title Economics'!$D$108+'Title Economics'!$D$109-'Title Economics'!$D$110)-1 -> 0.17382619 | G69: Uniform uplift to Base viewing needed for the ask to clear the required return
A70: Discount to the ask implied by the target price | C70: =1-$C$66/$C$62 -> 0.40059334
A72: OUTCOMES AT THE ASK AND AT THE TARGET PRICE (FIXED-FEE STRUCTURE)
A73: Measure | C73: Downside | D73: Base | E73: Upside
A74: NPV at the seller ask ($) | C74: =C58-Scenarios!$C$62*Assumptions!$C$34 -> -949571.01 | D74: =D58-Scenarios!$C$62*Assumptions!$C$34 -> -468325.78 | E74: =E58-Scenarios!$C$62*Assumptions!$C$34 -> 136609.06
A75: ROI at the seller ask | C75: =(C56-(C57+Scenarios!$C$62*Assumptions!$C$34))/(C57+Scenarios!$C$62*Assumptions!$C$34) -> -0.2754241 | D75: =(D56-(D57+Scenarios!$C$62*Assumptions!$C$34))/(D57+Scenarios!$C$62*Assumptions!$C$34) -> -0.13587129 | E75: =(E56-(E57+Scenarios!$C$62*Assumptions!$C$34))/(E57+Scenarios!$C$62*Assumptions!$C$34) -> 0.039422922
A76: NPV at the target price ($) | C76: =C58-Scenarios!$C$66*Assumptions!$C$34 -> 15172.812 | D76: =D58-Scenarios!$C$66*Assumptions!$C$34 -> 496418.04 | E76: =E58-Scenarios!$C$66*Assumptions!$C$34 -> 1101352.9
A77: ROI at the target price | C77: =(C56-(C57+Scenarios!$C$66*Assumptions!$C$34))/(C57+Scenarios!$C$66*Assumptions!$C$34) -> 0.0061108625 | D77: =(D56-(D57+Scenarios!$C$66*Assumptions!$C$34))/(D57+Scenarios!$C$66*Assumptions!$C$34) -> 0.2 | E77: =(E56-(E57+Scenarios!$C$66*Assumptions!$C$34))/(E57+Scenarios!$C$66*Assumptions!$C$34) -> 0.44045743
A79: ROI is stated on a present-value basis for both benefits and costs so that it is timing-consistent with NPV.
A80: All figures are illustrative outputs of a synthetic model.

Sheet Sensitivities
A1: PROJECT NIGHTFALL
A2: Sensitivity, break-even and portfolio concentration analysis
A3: Independent analytical case study using synthetic assumptions. Not based on proprietary company information.
A5: BASE-CASE VALUE COMPONENTS USED IN THE SENSITIVITY GRIDS
A6: PV of incremental advertising revenue - Base ($) | D6: ='Title Economics'!$D$108 -> 2596414
A7: PV of follow-on engagement value - Base ($) | D7: ='Title Economics'!$D$109 -> 382094.23
A8: PV of variable serving costs - Base ($) | D8: ='Title Economics'!$D$110 -> 284289.52
A9: PV of fixed support costs - Base ($) | D9: ='Title Economics'!$D$111 -> 754257.28
A10: PV factor on one dollar of fixed fee | D10: =Assumptions!$C$34 -> 0.9633149
A11: Recommended target price ($) | D11: =Scenarios!$C$66 -> 1498516.7
A12: Seller ask ($) | D12: =Scenarios!$C$62 -> 2500000
A13: Base viewing hours | D13: =Scenarios!$D$50 -> 15970795
A14: Base weighted-average net CPM ($) | D14: =Scenarios!$D$51/'Monthly Viewing Forecast'!$D$78*1000 -> 23.874162 | F14: Gross advertising revenue per thousand monetised impressions
A16: TWO-WAY SENSITIVITY 1 - PORTFOLIO NPV AT THE TARGET PRICE ($)
A17: Rows: viewing versus Base. Columns: net CPM versus Base.
C18: Viewing / CPM | D18: 0.85 | E18: 0.9 | F18: 0.95 | G18: 1 | H18: 1.05 | I18: 1.1 | J18: 1.15
C19: 0.8 | D19: =Sensitivities!$D$6*$C19*D$18+Sensitivities!$D$7*$C19-Sensitivities!$D$8*$C19-Sensitivities!$D$9-Sensitivities!$D$11*Sensitivities!$D$10 -> -353995.39 | E19: =Sensitivities!$D$6*$C19*E$18+Sensitivities!$D$7*$C19-Sensitivities!$D$8*$C19-Sensitivities!$D$9-Sensitivities!$D$11*Sensitivities!$D$10 -> -250138.83 | F19: =Sensitivities!$D$6*$C19*F$18+Sensitivities!$D$7*$C19-Sensitivities!$D$8*$C19-Sensitivities!$D$9-Sensitivities!$D$11*Sensitivities!$D$10 -> -146282.27 | G19: =Sensitivities!$D$6*$C19*G$18+Sensitivities!$D$7*$C19-Sensitivities!$D$8*$C19-Sensitivities!$D$9-Sensitivities!$D$11*Sensitivities!$D$10 -> -42425.704 | H19: =Sensitivities!$D$6*$C19*H$18+Sensitivities!$D$7*$C19-Sensitivities!$D$8*$C19-Sensitivities!$D$9-Sensitivities!$D$11*Sensitivities!$D$10 -> 61430.857 | I19: =Sensitivities!$D$6*$C19*I$18+Sensitivities!$D$7*$C19-Sensitivities!$D$8*$C19-Sensitivities!$D$9-Sensitivities!$D$11*Sensitivities!$D$10 -> 165287.42 | J19: =Sensitivities!$D$6*$C19*J$18+Sensitivities!$D$7*$C19-Sensitivities!$D$8*$C19-Sensitivities!$D$9-Sensitivities!$D$11*Sensitivities!$D$10 -> 269143.98
C20: 0.85 | D20: =Sensitivities!$D$6*$C20*D$18+Sensitivities!$D$7*$C20-Sensitivities!$D$8*$C20-Sensitivities!$D$9-Sensitivities!$D$11*Sensitivities!$D$10 -> -238757.56 | E20: =Sensitivities!$D$6*$C20*E$18+Sensitivities!$D$7*$C20-Sensitivities!$D$8*$C20-Sensitivities!$D$9-Sensitivities!$D$11*Sensitivities!$D$10 -> -128409.96 | F20: =Sensitivities!$D$6*$C20*F$18+Sensitivities!$D$7*$C20-Sensitivities!$D$8*$C20-Sensitivities!$D$9-Sensitivities!$D$11*Sensitivities!$D$10 -> -18062.363 | G20: =Sensitivities!$D$6*$C20*G$18+Sensitivities!$D$7*$C20-Sensitivities!$D$8*$C20-Sensitivities!$D$9-Sensitivities!$D$11*Sensitivities!$D$10 -> 92285.233 | H20: =Sensitivities!$D$6*$C20*H$18+Sensitivities!$D$7*$C20-Sensitivities!$D$8*$C20-Sensitivities!$D$9-Sensitivities!$D$11*Sensitivities!$D$10 -> 202632.83 | I20: =Sensitivities!$D$6*$C20*I$18+Sensitivities!$D$7*$C20-Sensitivities!$D$8*$C20-Sensitivities!$D$9-Sensitivities!$D$11*Sensitivities!$D$10 -> 312980.43 | J20: =Sensitivities!$D$6*$C20*J$18+Sensitivities!$D$7*$C20-Sensitivities!$D$8*$C20-Sensitivities!$D$9-Sensitivities!$D$11*Sensitivities!$D$10 -> 423328.02
C21: 0.9 | D21: =Sensitivities!$D$6*$C21*D$18+Sensitivities!$D$7*$C21-Sensitivities!$D$8*$C21-Sensitivities!$D$9-Sensitivities!$D$11*Sensitivities!$D$10 -> -123519.72 | E21: =Sensitivities!$D$6*$C21*E$18+Sensitivities!$D$7*$C21-Sensitivities!$D$8*$C21-Sensitivities!$D$9-Sensitivities!$D$11*Sensitivities!$D$10 -> -6681.0932 | F21: =Sensitivities!$D$6*$C21*F$18+Sensitivities!$D$7*$C21-Sensitivities!$D$8*$C21-Sensitivities!$D$9-Sensitivities!$D$11*Sensitivities!$D$10 -> 110157.54 | G21: =Sensitivities!$D$6*$C21*G$18+Sensitivities!$D$7*$C21-Sensitivities!$D$8*$C21-Sensitivities!$D$9-Sensitivities!$D$11*Sensitivities!$D$10 -> 226996.17 | H21: =Sensitivities!$D$6*$C21*H$18+Sensitivities!$D$7*$C21-Sensitivities!$D$8*$C21-Sensitivities!$D$9-Sensitivities!$D$11*Sensitivities!$D$10 -> 343834.8 | I21: =Sensitivities!$D$6*$C21*I$18+Sensitivities!$D$7*$C21-Sensitivities!$D$8*$C21-Sensitivities!$D$9-Sensitivities!$D$11*Sensitivities!$D$10 -> 460673.43 | J21: =Sensitivities!$D$6*$C21*J$18+Sensitivities!$D$7*$C21-Sensitivities!$D$8*$C21-Sensitivities!$D$9-Sensitivities!$D$11*Sensitivities!$D$10 -> 577512.06
C22: 0.95 | D22: =Sensitivities!$D$6*$C22*D$18+Sensitivities!$D$7*$C22-Sensitivities!$D$8*$C22-Sensitivities!$D$9-Sensitivities!$D$11*Sensitivities!$D$10 -> -8281.8931 | E22: =Sensitivities!$D$6*$C22*E$18+Sensitivities!$D$7*$C22-Sensitivities!$D$8*$C22-Sensitivities!$D$9-Sensitivities!$D$11*Sensitivities!$D$10 -> 115047.77 | F22: =Sensitivities!$D$6*$C22*F$18+Sensitivities!$D$7*$C22-Sensitivities!$D$8*$C22-Sensitivities!$D$9-Sensitivities!$D$11*Sensitivities!$D$10 -> 238377.44 | G22: =Sensitivities!$D$6*$C22*G$18+Sensitivities!$D$7*$C22-Sensitivities!$D$8*$C22-Sensitivities!$D$9-Sensitivities!$D$11*Sensitivities!$D$10 -> 361707.11 | H22: =Sensitivities!$D$6*$C22*H$18+Sensitivities!$D$7*$C22-Sensitivities!$D$8*$C22-Sensitivities!$D$9-Sensitivities!$D$11*Sensitivities!$D$10 -> 485036.77 | I22: =Sensitivities!$D$6*$C22*I$18+Sensitivities!$D$7*$C22-Sensitivities!$D$8*$C22-Sensitivities!$D$9-Sensitivities!$D$11*Sensitivities!$D$10 -> 608366.44 | J22: =Sensitivities!$D$6*$C22*J$18+Sensitivities!$D$7*$C22-Sensitivities!$D$8*$C22-Sensitivities!$D$9-Sensitivities!$D$11*Sensitivities!$D$10 -> 731696.11
C23: 1 | D23: =Sensitivities!$D$6*$C23*D$18+Sensitivities!$D$7*$C23-Sensitivities!$D$8*$C23-Sensitivities!$D$9-Sensitivities!$D$11*Sensitivities!$D$10 -> 106955.94 | E23: =Sensitivities!$D$6*$C23*E$18+Sensitivities!$D$7*$C23-Sensitivities!$D$8*$C23-Sensitivities!$D$9-Sensitivities!$D$11*Sensitivities!$D$10 -> 236776.64 | F23: =Sensitivities!$D$6*$C23*F$18+Sensitivities!$D$7*$C23-Sensitivities!$D$8*$C23-Sensitivities!$D$9-Sensitivities!$D$11*Sensitivities!$D$10 -> 366597.34 | G23: =Sensitivities!$D$6*$C23*G$18+Sensitivities!$D$7*$C23-Sensitivities!$D$8*$C23-Sensitivities!$D$9-Sensitivities!$D$11*Sensitivities!$D$10 -> 496418.04 | H23: =Sensitivities!$D$6*$C23*H$18+Sensitivities!$D$7*$C23-Sensitivities!$D$8*$C23-Sensitivities!$D$9-Sensitivities!$D$11*Sensitivities!$D$10 -> 626238.74 | I23: =Sensitivities!$D$6*$C23*I$18+Sensitivities!$D$7*$C23-Sensitivities!$D$8*$C23-Sensitivities!$D$9-Sensitivities!$D$11*Sensitivities!$D$10 -> 756059.45 | J23: =Sensitivities!$D$6*$C23*J$18+Sensitivities!$D$7*$C23-Sensitivities!$D$8*$C23-Sensitivities!$D$9-Sensitivities!$D$11*Sensitivities!$D$10 -> 885880.15
C24: 1.05 | D24: =Sensitivities!$D$6*$C24*D$18+Sensitivities!$D$7*$C24-Sensitivities!$D$8*$C24-Sensitivities!$D$9-Sensitivities!$D$11*Sensitivities!$D$10 -> 222193.77 | E24: =Sensitivities!$D$6*$C24*E$18+Sensitivities!$D$7*$C24-Sensitivities!$D$8*$C24-Sensitivities!$D$9-Sensitivities!$D$11*Sensitivities!$D$10 -> 358505.51 | F24: =Sensitivities!$D$6*$C24*F$18+Sensitivities!$D$7*$C24-Sensitivities!$D$8*$C24-Sensitivities!$D$9-Sensitivities!$D$11*Sensitivities!$D$10 -> 494817.24 | G24: =Sensitivities!$D$6*$C24*G$18+Sensitivities!$D$7*$C24-Sensitivities!$D$8*$C24-Sensitivities!$D$9-Sensitivities!$D$11*Sensitivities!$D$10 -> 631128.98 | H24: =Sensitivities!$D$6*$C24*H$18+Sensitivities!$D$7*$C24-Sensitivities!$D$8*$C24-Sensitivities!$D$9-Sensitivities!$D$11*Sensitivities!$D$10 -> 767440.72 | I24: =Sensitivities!$D$6*$C24*I$18+Sensitivities!$D$7*$C24-Sensitivities!$D$8*$C24-Sensitivities!$D$9-Sensitivities!$D$11*Sensitivities!$D$10 -> 903752.45 | J24: =Sensitivities!$D$6*$C24*J$18+Sensitivities!$D$7*$C24-Sensitivities!$D$8*$C24-Sensitivities!$D$9-Sensitivities!$D$11*Sensitivities!$D$10 -> 1040064.2
C25: 1.1 | D25: =Sensitivities!$D$6*$C25*D$18+Sensitivities!$D$7*$C25-Sensitivities!$D$8*$C25-Sensitivities!$D$9-Sensitivities!$D$11*Sensitivities!$D$10 -> 337431.6 | E25: =Sensitivities!$D$6*$C25*E$18+Sensitivities!$D$7*$C25-Sensitivities!$D$8*$C25-Sensitivities!$D$9-Sensitivities!$D$11*Sensitivities!$D$10 -> 480234.37 | F25: =Sensitivities!$D$6*$C25*F$18+Sensitivities!$D$7*$C25-Sensitivities!$D$8*$C25-Sensitivities!$D$9-Sensitivities!$D$11*Sensitivities!$D$10 -> 623037.14 | G25: =Sensitivities!$D$6*$C25*G$18+Sensitivities!$D$7*$C25-Sensitivities!$D$8*$C25-Sensitivities!$D$9-Sensitivities!$D$11*Sensitivities!$D$10 -> 765839.92 | H25: =Sensitivities!$D$6*$C25*H$18+Sensitivities!$D$7*$C25-Sensitivities!$D$8*$C25-Sensitivities!$D$9-Sensitivities!$D$11*Sensitivities!$D$10 -> 908642.69 | I25: =Sensitivities!$D$6*$C25*I$18+Sensitivities!$D$7*$C25-Sensitivities!$D$8*$C25-Sensitivities!$D$9-Sensitivities!$D$11*Sensitivities!$D$10 -> 1051445.5 | J25: =Sensitivities!$D$6*$C25*J$18+Sensitivities!$D$7*$C25-Sensitivities!$D$8*$C25-Sensitivities!$D$9-Sensitivities!$D$11*Sensitivities!$D$10 -> 1194248.2
C26: 1.15 | D26: =Sensitivities!$D$6*$C26*D$18+Sensitivities!$D$7*$C26-Sensitivities!$D$8*$C26-Sensitivities!$D$9-Sensitivities!$D$11*Sensitivities!$D$10 -> 452669.43 | E26: =Sensitivities!$D$6*$C26*E$18+Sensitivities!$D$7*$C26-Sensitivities!$D$8*$C26-Sensitivities!$D$9-Sensitivities!$D$11*Sensitivities!$D$10 -> 601963.24 | F26: =Sensitivities!$D$6*$C26*F$18+Sensitivities!$D$7*$C26-Sensitivities!$D$8*$C26-Sensitivities!$D$9-Sensitivities!$D$11*Sensitivities!$D$10 -> 751257.05 | G26: =Sensitivities!$D$6*$C26*G$18+Sensitivities!$D$7*$C26-Sensitivities!$D$8*$C26-Sensitivities!$D$9-Sensitivities!$D$11*Sensitivities!$D$10 -> 900550.85 | H26: =Sensitivities!$D$6*$C26*H$18+Sensitivities!$D$7*$C26-Sensitivities!$D$8*$C26-Sensitivities!$D$9-Sensitivities!$D$11*Sensitivities!$D$10 -> 1049844.7 | I26: =Sensitivities!$D$6*$C26*I$18+Sensitivities!$D$7*$C26-Sensitivities!$D$8*$C26-Sensitivities!$D$9-Sensitivities!$D$11*Sensitivities!$D$10 -> 1199138.5 | J26: =Sensitivities!$D$6*$C26*J$18+Sensitivities!$D$7*$C26-Sensitivities!$D$8*$C26-Sensitivities!$D$9-Sensitivities!$D$11*Sensitivities!$D$10 -> 1348432.3
C27: 1.2 | D27: =Sensitivities!$D$6*$C27*D$18+Sensitivities!$D$7*$C27-Sensitivities!$D$8*$C27-Sensitivities!$D$9-Sensitivities!$D$11*Sensitivities!$D$10 -> 567907.26 | E27: =Sensitivities!$D$6*$C27*E$18+Sensitivities!$D$7*$C27-Sensitivities!$D$8*$C27-Sensitivities!$D$9-Sensitivities!$D$11*Sensitivities!$D$10 -> 723692.11 | F27: =Sensitivities!$D$6*$C27*F$18+Sensitivities!$D$7*$C27-Sensitivities!$D$8*$C27-Sensitivities!$D$9-Sensitivities!$D$11*Sensitivities!$D$10 -> 879476.95 | G27: =Sensitivities!$D$6*$C27*G$18+Sensitivities!$D$7*$C27-Sensitivities!$D$8*$C27-Sensitivities!$D$9-Sensitivities!$D$11*Sensitivities!$D$10 -> 1035261.8 | H27: =Sensitivities!$D$6*$C27*H$18+Sensitivities!$D$7*$C27-Sensitivities!$D$8*$C27-Sensitivities!$D$9-Sensitivities!$D$11*Sensitivities!$D$10 -> 1191046.6 | I27: =Sensitivities!$D$6*$C27*I$18+Sensitivities!$D$7*$C27-Sensitivities!$D$8*$C27-Sensitivities!$D$9-Sensitivities!$D$11*Sensitivities!$D$10 -> 1346831.5 | J27: =Sensitivities!$D$6*$C27*J$18+Sensitivities!$D$7*$C27-Sensitivities!$D$8*$C27-Sensitivities!$D$9-Sensitivities!$D$11*Sensitivities!$D$10 -> 1502616.3
A29: TWO-WAY SENSITIVITY 2 - PORTFOLIO NPV BY LICENCE FEE AND INCREMENTALITY ($)
A30: Rows: fixed licence fee. Columns: incrementality versus Base. Follow-on value scales with incrementality because it is earned only on incremental viewing.
C31: Fee / incrementality | D31: 0.9 | E31: 0.95 | F31: 1 | G31: 1.05 | H31: 1.1
C32: 1100000 | D32: =(Sensitivities!$D$6+Sensitivities!$D$7)*D$31-Sensitivities!$D$8-Sensitivities!$D$9-$C32*Sensitivities!$D$10 -> 582464.25 | E32: =(Sensitivities!$D$6+Sensitivities!$D$7)*E$31-Sensitivities!$D$8-Sensitivities!$D$9-$C32*Sensitivities!$D$10 -> 731389.66 | F32: =(Sensitivities!$D$6+Sensitivities!$D$7)*F$31-Sensitivities!$D$8-Sensitivities!$D$9-$C32*Sensitivities!$D$10 -> 880315.07 | G32: =(Sensitivities!$D$6+Sensitivities!$D$7)*G$31-Sensitivities!$D$8-Sensitivities!$D$9-$C32*Sensitivities!$D$10 -> 1029240.5 | H32: =(Sensitivities!$D$6+Sensitivities!$D$7)*H$31-Sensitivities!$D$8-Sensitivities!$D$9-$C32*Sensitivities!$D$10 -> 1178165.9
C33: 1300000 | D33: =(Sensitivities!$D$6+Sensitivities!$D$7)*D$31-Sensitivities!$D$8-Sensitivities!$D$9-$C33*Sensitivities!$D$10 -> 389801.27 | E33: =(Sensitivities!$D$6+Sensitivities!$D$7)*E$31-Sensitivities!$D$8-Sensitivities!$D$9-$C33*Sensitivities!$D$10 -> 538726.68 | F33: =(Sensitivities!$D$6+Sensitivities!$D$7)*F$31-Sensitivities!$D$8-Sensitivities!$D$9-$C33*Sensitivities!$D$10 -> 687652.09 | G33: =(Sensitivities!$D$6+Sensitivities!$D$7)*G$31-Sensitivities!$D$8-Sensitivities!$D$9-$C33*Sensitivities!$D$10 -> 836577.51 | H33: =(Sensitivities!$D$6+Sensitivities!$D$7)*H$31-Sensitivities!$D$8-Sensitivities!$D$9-$C33*Sensitivities!$D$10 -> 985502.92
C34: 1500000 | D34: =(Sensitivities!$D$6+Sensitivities!$D$7)*D$31-Sensitivities!$D$8-Sensitivities!$D$9-$C34*Sensitivities!$D$10 -> 197138.29 | E34: =(Sensitivities!$D$6+Sensitivities!$D$7)*E$31-Sensitivities!$D$8-Sensitivities!$D$9-$C34*Sensitivities!$D$10 -> 346063.7 | F34: =(Sensitivities!$D$6+Sensitivities!$D$7)*F$31-Sensitivities!$D$8-Sensitivities!$D$9-$C34*Sensitivities!$D$10 -> 494989.12 | G34: =(Sensitivities!$D$6+Sensitivities!$D$7)*G$31-Sensitivities!$D$8-Sensitivities!$D$9-$C34*Sensitivities!$D$10 -> 643914.53 | H34: =(Sensitivities!$D$6+Sensitivities!$D$7)*H$31-Sensitivities!$D$8-Sensitivities!$D$9-$C34*Sensitivities!$D$10 -> 792839.94
C35: 1700000 | D35: =(Sensitivities!$D$6+Sensitivities!$D$7)*D$31-Sensitivities!$D$8-Sensitivities!$D$9-$C35*Sensitivities!$D$10 -> 4475.3106 | E35: =(Sensitivities!$D$6+Sensitivities!$D$7)*E$31-Sensitivities!$D$8-Sensitivities!$D$9-$C35*Sensitivities!$D$10 -> 153400.72 | F35: =(Sensitivities!$D$6+Sensitivities!$D$7)*F$31-Sensitivities!$D$8-Sensitivities!$D$9-$C35*Sensitivities!$D$10 -> 302326.14 | G35: =(Sensitivities!$D$6+Sensitivities!$D$7)*G$31-Sensitivities!$D$8-Sensitivities!$D$9-$C35*Sensitivities!$D$10 -> 451251.55 | H35: =(Sensitivities!$D$6+Sensitivities!$D$7)*H$31-Sensitivities!$D$8-Sensitivities!$D$9-$C35*Sensitivities!$D$10 -> 600176.96
C36: 1900000 | D36: =(Sensitivities!$D$6+Sensitivities!$D$7)*D$31-Sensitivities!$D$8-Sensitivities!$D$9-$C36*Sensitivities!$D$10 -> -188187.67 | E36: =(Sensitivities!$D$6+Sensitivities!$D$7)*E$31-Sensitivities!$D$8-Sensitivities!$D$9-$C36*Sensitivities!$D$10 -> -39262.256 | F36: =(Sensitivities!$D$6+Sensitivities!$D$7)*F$31-Sensitivities!$D$8-Sensitivities!$D$9-$C36*Sensitivities!$D$10 -> 109663.16 | G36: =(Sensitivities!$D$6+Sensitivities!$D$7)*G$31-Sensitivities!$D$8-Sensitivities!$D$9-$C36*Sensitivities!$D$10 -> 258588.57 | H36: =(Sensitivities!$D$6+Sensitivities!$D$7)*H$31-Sensitivities!$D$8-Sensitivities!$D$9-$C36*Sensitivities!$D$10 -> 407513.98
C37: 2100000 | D37: =(Sensitivities!$D$6+Sensitivities!$D$7)*D$31-Sensitivities!$D$8-Sensitivities!$D$9-$C37*Sensitivities!$D$10 -> -380850.65 | E37: =(Sensitivities!$D$6+Sensitivities!$D$7)*E$31-Sensitivities!$D$8-Sensitivities!$D$9-$C37*Sensitivities!$D$10 -> -231925.23 | F37: =(Sensitivities!$D$6+Sensitivities!$D$7)*F$31-Sensitivities!$D$8-Sensitivities!$D$9-$C37*Sensitivities!$D$10 -> -82999.822 | G37: =(Sensitivities!$D$6+Sensitivities!$D$7)*G$31-Sensitivities!$D$8-Sensitivities!$D$9-$C37*Sensitivities!$D$10 -> 65925.591 | H37: =(Sensitivities!$D$6+Sensitivities!$D$7)*H$31-Sensitivities!$D$8-Sensitivities!$D$9-$C37*Sensitivities!$D$10 -> 214851
C38: 2300000 | D38: =(Sensitivities!$D$6+Sensitivities!$D$7)*D$31-Sensitivities!$D$8-Sensitivities!$D$9-$C38*Sensitivities!$D$10 -> -573513.63 | E38: =(Sensitivities!$D$6+Sensitivities!$D$7)*E$31-Sensitivities!$D$8-Sensitivities!$D$9-$C38*Sensitivities!$D$10 -> -424588.21 | F38: =(Sensitivities!$D$6+Sensitivities!$D$7)*F$31-Sensitivities!$D$8-Sensitivities!$D$9-$C38*Sensitivities!$D$10 -> -275662.8 | G38: =(Sensitivities!$D$6+Sensitivities!$D$7)*G$31-Sensitivities!$D$8-Sensitivities!$D$9-$C38*Sensitivities!$D$10 -> -126737.39 | H38: =(Sensitivities!$D$6+Sensitivities!$D$7)*H$31-Sensitivities!$D$8-Sensitivities!$D$9-$C38*Sensitivities!$D$10 -> 22188.025
C39: 2500000 | D39: =(Sensitivities!$D$6+Sensitivities!$D$7)*D$31-Sensitivities!$D$8-Sensitivities!$D$9-$C39*Sensitivities!$D$10 -> -766176.61 | E39: =(Sensitivities!$D$6+Sensitivities!$D$7)*E$31-Sensitivities!$D$8-Sensitivities!$D$9-$C39*Sensitivities!$D$10 -> -617251.19 | F39: =(Sensitivities!$D$6+Sensitivities!$D$7)*F$31-Sensitivities!$D$8-Sensitivities!$D$9-$C39*Sensitivities!$D$10 -> -468325.78 | G39: =(Sensitivities!$D$6+Sensitivities!$D$7)*G$31-Sensitivities!$D$8-Sensitivities!$D$9-$C39*Sensitivities!$D$10 -> -319400.37 | H39: =(Sensitivities!$D$6+Sensitivities!$D$7)*H$31-Sensitivities!$D$8-Sensitivities!$D$9-$C39*Sensitivities!$D$10 -> -170474.95
A41: BREAK-EVEN AND MAXIMUM SUPPORTABLE PRICE
A42: Break-even viewing hours at the target price | D42: =Sensitivities!$D$13*(Sensitivities!$D$9+Sensitivities!$D$11*Sensitivities!$D$10)/(Sensitivities!$D$6+Sensitivities!$D$7-Sensitivities!$D$8) -> 13028127 | F42: Uniform scaling of the Base viewing profile that sets NPV to zero
A43: Break-even viewing hours at the seller ask | D43: =Sensitivities!$D$13*(Sensitivities!$D$9+Sensitivities!$D$12*Sensitivities!$D$10)/(Sensitivities!$D$6+Sensitivities!$D$7-Sensitivities!$D$8) -> 18746938
A44: Viewing headroom at the target price | D44: =1-Sensitivities!$D$42/Sensitivities!$D$13 -> 0.18425306 | F44: Share of Base viewing that can be lost before the deal stops clearing the required return
A45: Additional viewing required at the seller ask | D45: =Sensitivities!$D$43/Sensitivities!$D$13-1 -> 0.17382619
A46: Break-even weighted-average net CPM at the target price ($) | D46: =Sensitivities!$D$14*(Sensitivities!$D$9+Sensitivities!$D$11*Sensitivities!$D$10+Sensitivities!$D$8-Sensitivities!$D$7)/Sensitivities!$D$6 -> 19.309573
A47: Break-even weighted-average net CPM at the seller ask ($) | D47: =Sensitivities!$D$14*(Sensitivities!$D$9+Sensitivities!$D$12*Sensitivities!$D$10+Sensitivities!$D$8-Sensitivities!$D$7)/Sensitivities!$D$6 -> 28.180442
A48: Maximum supportable licence fee - Base ($) | D48: =Scenarios!$D$59 -> 2013839.4 | F48: Walk-away ceiling
A49: Maximum supportable licence fee - Downside ($) | D49: =Scenarios!$C$59 -> 1514267.3
A50: Maximum supportable licence fee - Upside ($) | D50: =Scenarios!$E$59 -> 2641811.4
A52: TITLE CONTRIBUTION RANKING AND CONCENTRATION
A53: Rank | B53: Title | C53: Contribution before fee ($) | D53: Share of portfolio | E53: Cumulative share | F53: Contribution after fee ($) | G53: Downside contribution after fee ($)
A54: 1 | B54: =INDEX('Title Inputs'!$C$7:$G$7,MATCH(LARGE('Title Economics'!$C$177:$G$177,$A54),'Title Economics'!$C$177:$G$177,0)) -> Nightfall Protocol | C54: =LARGE('Title Economics'!$C$177:$G$177,$A54) -> 1051288.4 | D54: =$C54/SUM('Title Economics'!$C$177:$G$177) -> 0.49762214 | E54: =SUM($C$54:$C54)/SUM('Title Economics'!$C$177:$G$177) -> 0.49762214 | F54: =INDEX('Title Economics'!$C$181:$G$181,MATCH(LARGE('Title Economics'!$C$177:$G$177,$A54),'Title Economics'!$C$177:$G$177,0)) -> 571763.02 | G54: =INDEX('Title Economics'!$C$191:$G$191,MATCH(LARGE('Title Economics'!$C$177:$G$177,$A54),'Title Economics'!$C$177:$G$177,0)) -> 344614.37
A55: 2 | B55: =INDEX('Title Inputs'!$C$7:$G$7,MATCH(LARGE('Title Economics'!$C$177:$G$177,$A55),'Title Economics'!$C$177:$G$177,0)) -> Ash Ridge | C55: =LARGE('Title Economics'!$C$177:$G$177,$A55) -> 625470.78 | D55: =$C55/SUM('Title Economics'!$C$177:$G$177) -> 0.2960635 | E55: =SUM($C$54:$C55)/SUM('Title Economics'!$C$177:$G$177) -> 0.79368564 | F55: =INDEX('Title Economics'!$C$181:$G$181,MATCH(LARGE('Title Economics'!$C$177:$G$177,$A55),'Title Economics'!$C$177:$G$177,0)) -> 235856.45 | G55: =INDEX('Title Economics'!$C$191:$G$191,MATCH(LARGE('Title Economics'!$C$177:$G$177,$A55),'Title Economics'!$C$177:$G$177,0)) -> 91087.663
A56: 3 | B56: =INDEX('Title Inputs'!$C$7:$G$7,MATCH(LARGE('Title Economics'!$C$177:$G$177,$A56),'Title Economics'!$C$177:$G$177,0)) -> Cold Harbor | C56: =LARGE('Title Economics'!$C$177:$G$177,$A56) -> 362481.47 | D56: =$C56/SUM('Title Economics'!$C$177:$G$177) -> 0.17157881 | E56: =SUM($C$54:$C56)/SUM('Title Economics'!$C$177:$G$177) -> 0.96526444 | F56: =INDEX('Title Economics'!$C$181:$G$181,MATCH(LARGE('Title Economics'!$C$177:$G$177,$A56),'Title Economics'!$C$177:$G$177,0)) -> 62778.139 | G56: =INDEX('Title Economics'!$C$191:$G$191,MATCH(LARGE('Title Economics'!$C$177:$G$177,$A56),'Title Economics'!$C$177:$G$177,0)) -> -28718.513
A57: 4 | B57: =INDEX('Title Inputs'!$C$7:$G$7,MATCH(LARGE('Title Economics'!$C$177:$G$177,$A57),'Title Economics'!$C$177:$G$177,0)) -> The Quiet Depth | C57: =LARGE('Title Economics'!$C$177:$G$177,$A57) -> 112253.06 | D57: =$C57/SUM('Title Economics'!$C$177:$G$177) -> 0.053134429 | E57: =SUM($C$54:$C57)/SUM('Title Economics'!$C$177:$G$177) -> 1.0183989 | F57: =INDEX('Title Economics'!$C$181:$G$181,MATCH(LARGE('Title Economics'!$C$177:$G$177,$A57),'Title Economics'!$C$177:$G$177,0)) -> -82554.108 | G57: =INDEX('Title Economics'!$C$191:$G$191,MATCH(LARGE('Title Economics'!$C$177:$G$177,$A57),'Title Economics'!$C$177:$G$177,0)) -> -124926.01
A58: 5 | B58: =INDEX('Title Inputs'!$C$7:$G$7,MATCH(LARGE('Title Economics'!$C$177:$G$177,$A58),'Title Economics'!$C$177:$G$177,0)) -> Vector Nine | C58: =LARGE('Title Economics'!$C$177:$G$177,$A58) -> -38869.899 | D58: =$C58/SUM('Title Economics'!$C$177:$G$177) -> -0.018398874 | E58: =SUM($C$54:$C58)/SUM('Title Economics'!$C$177:$G$177) -> 1 | F58: =INDEX('Title Economics'!$C$181:$G$181,MATCH(LARGE('Title Economics'!$C$177:$G$177,$A58),'Title Economics'!$C$177:$G$177,0)) -> -173736.4 | G58: =INDEX('Title Economics'!$C$191:$G$191,MATCH(LARGE('Title Economics'!$C$177:$G$177,$A58),'Title Economics'!$C$177:$G$177,0)) -> -186751.9
A60: Largest title share of portfolio contribution | D60: =$D$54 -> 0.49762214
A61: Top two titles share of portfolio contribution | D61: =$E$55 -> 0.79368564
A62: Top three titles share of portfolio contribution | D62: =$E$56 -> 0.96526444
A63: Contribution concentration index (sum of squared shares) | D63: =SUMPRODUCT($D$54:$D$58,$D$54:$D$58) -> 0.36788246 | F63: 1.00 is a single-title package; 0.20 is five equal titles
A64: Titles that do not cover their allocated licence fee | D64: =COUNTIF($F$54:$F$58,"<0") -> 2
A65: Titles with negative contribution before any licence fee | D65: =COUNTIF($C$54:$C$58,"<0") -> 1
A66: Titles loss-making in the Downside after the allocated fee | D66: =COUNTIF($G$54:$G$58,"<0") -> 3
A68: PORTFOLIO CASH FLOW - ACTIVE SCENARIO, PREFERRED STRUCTURE C
C69: Month | D69: Total | E69: 1 | F69: 2 | G69: 3 | H69: 4 | I69: 5 | J69: 6 | K69: 7 | L69: 8 | M69: 9 | N69: 10 | O69: 11 | P69: 12 | Q69: 13 | R69: 14 | S69: 15 | T69: 16 | U69: 17 | V69: 18 | W69: 19 | X69: 20 | Y69: 21 | Z69: 22 | AA69: 23 | AB69: 24
C70: Viewing hours | D70: =SUM(E70:AB70) -> 15970795 | E70: =CHOOSE(Scenarios!$C$7,'Monthly Viewing Forecast'!E38,'Monthly Viewing Forecast'!E77,'Monthly Viewing Forecast'!E116) -> 2060369.5 | F70: =CHOOSE(Scenarios!$C$7,'Monthly Viewing Forecast'!F38,'Monthly Viewing Forecast'!F77,'Monthly Viewing Forecast'!F116) -> 1804592 | G70: =CHOOSE(Scenarios!$C$7,'Monthly Viewing Forecast'!G38,'Monthly Viewing Forecast'!G77,'Monthly Viewing Forecast'!G116) -> 1580783.2 | H70: =CHOOSE(Scenarios!$C$7,'Monthly Viewing Forecast'!H38,'Monthly Viewing Forecast'!H77,'Monthly Viewing Forecast'!H116) -> 1384918.6 | I70: =CHOOSE(Scenarios!$C$7,'Monthly Viewing Forecast'!I38,'Monthly Viewing Forecast'!I77,'Monthly Viewing Forecast'!I116) -> 1213483.9 | J70: =CHOOSE(Scenarios!$C$7,'Monthly Viewing Forecast'!J38,'Monthly Viewing Forecast'!J77,'Monthly Viewing Forecast'!J116) -> 1063410.4 | K70: =CHOOSE(Scenarios!$C$7,'Monthly Viewing Forecast'!K38,'Monthly Viewing Forecast'!K77,'Monthly Viewing Forecast'!K116) -> 932017.56 | L70: =CHOOSE(Scenarios!$C$7,'Monthly Viewing Forecast'!L38,'Monthly Viewing Forecast'!L77,'Monthly Viewing Forecast'!L116) -> 816963.91 | ... AB70: =CHOOSE(Scenarios!$C$7,'Monthly Viewing Forecast'!AB38,'Monthly Viewing Forecast'!AB77,'Monthly Viewing Forecast'!AB116) -> 100836.89
C71: Contribution before licence fee ($) | D71: =SUM(E71:AB71) -> 2112623.8 | E71: =CHOOSE(Scenarios!$C$7,'Title Economics'!E51,'Title Economics'!E104,'Title Economics'!E157) -> -162835.44 | F71: =CHOOSE(Scenarios!$C$7,'Title Economics'!F51,'Title Economics'!F104,'Title Economics'!F157) -> 190059.6 | G71: =CHOOSE(Scenarios!$C$7,'Title Economics'!G51,'Title Economics'!G104,'Title Economics'!G157) -> 219170.13 | H71: =CHOOSE(Scenarios!$C$7,'Title Economics'!H51,'Title Economics'!H104,'Title Economics'!H157) -> 205822.7 | I71: =CHOOSE(Scenarios!$C$7,'Title Economics'!I51,'Title Economics'!I104,'Title Economics'!I157) -> 217677.33 | J71: =CHOOSE(Scenarios!$C$7,'Title Economics'!J51,'Title Economics'!J104,'Title Economics'!J157) -> 191217.1 | K71: =CHOOSE(Scenarios!$C$7,'Title Economics'!K51,'Title Economics'!K104,'Title Economics'!K157) -> 167989.09 | L71: =CHOOSE(Scenarios!$C$7,'Title Economics'!L51,'Title Economics'!L104,'Title Economics'!L157) -> 147596.36 | ... AB71: =CHOOSE(Scenarios!$C$7,'Title Economics'!AB51,'Title Economics'!AB104,'Title Economics'!AB157) -> 18827.071
C72: Licence payments - Structure C ($) | D72: =SUM(E72:AB72) -> 1350000 | E72: =CHOOSE(Scenarios!$C$7,'Deal Structures'!E23,'Deal Structures'!E44,'Deal Structures'!E65) -> 850000 | F72: =CHOOSE(Scenarios!$C$7,'Deal Structures'!F23,'Deal Structures'!F44,'Deal Structures'!F65) -> 0 | G72: =CHOOSE(Scenarios!$C$7,'Deal Structures'!G23,'Deal Structures'!G44,'Deal Structures'!G65) -> 0 | H72: =CHOOSE(Scenarios!$C$7,'Deal Structures'!H23,'Deal Structures'!H44,'Deal Structures'!H65) -> 0 | I72: =CHOOSE(Scenarios!$C$7,'Deal Structures'!I23,'Deal Structures'!I44,'Deal Structures'!I65) -> 0 | J72: =CHOOSE(Scenarios!$C$7,'Deal Structures'!J23,'Deal Structures'!J44,'Deal Structures'!J65) -> 0 | K72: =CHOOSE(Scenarios!$C$7,'Deal Structures'!K23,'Deal Structures'!K44,'Deal Structures'!K65) -> 0 | L72: =CHOOSE(Scenarios!$C$7,'Deal Structures'!L23,'Deal Structures'!L44,'Deal Structures'!L65) -> 0 | ... AB72: =CHOOSE(Scenarios!$C$7,'Deal Structures'!AB23,'Deal Structures'!AB44,'Deal Structures'!AB65) -> 0
C73: Net cash flow ($) | D73: =SUM(E73:AB73) -> 762623.76 | E73: =E71-E72 -> -1012835.4 | F73: =F71-F72 -> 190059.6 | G73: =G71-G72 -> 219170.13 | H73: =H71-H72 -> 205822.7 | I73: =I71-I72 -> 217677.33 | J73: =J71-J72 -> 191217.1 | K73: =K71-K72 -> 167989.09 | L73: =L71-L72 -> 147596.36 | ... AB73: =AB71-AB72 -> 18827.071
C74: Cumulative net cash flow ($) | D74: =AB74 -> 762623.76 | E74: =SUM($E$73:E73) -> -1012835.4 | F74: =SUM($E$73:F73) -> -822775.85 | G74: =SUM($E$73:G73) -> -603605.71 | H74: =SUM($E$73:H73) -> -397783.01 | I74: =SUM($E$73:I73) -> -180105.68 | J74: =SUM($E$73:J73) -> 11111.423 | K74: =SUM($E$73:K73) -> 179100.52 | L74: =SUM($E$73:L73) -> 326696.87 | ... AB74: =SUM($E$73:AB73) -> 762623.76
C75: Payback flag | D75: =IFERROR(MATCH(1,E75:AB75,0),"n/a") -> 6 | E75: =IF(MIN(E74:$AB$74)>0,1,0) -> 0 | F75: =IF(MIN(F74:$AB$74)>0,1,0) -> 0 | G75: =IF(MIN(G74:$AB$74)>0,1,0) -> 0 | H75: =IF(MIN(H74:$AB$74)>0,1,0) -> 0 | I75: =IF(MIN(I74:$AB$74)>0,1,0) -> 0 | J75: =IF(MIN(J74:$AB$74)>0,1,0) -> 1 | K75: =IF(MIN(K74:$AB$74)>0,1,0) -> 1 | L75: =IF(MIN(L74:$AB$74)>0,1,0) -> 1 | ... AB75: =IF(MIN(AB74:$AB$74)>0,1,0) -> 1
A77: The cash flow above excludes any terminal or renewal value. The licence expires at month 24.

Sheet Executive Summary
A1: PROJECT NIGHTFALL
A2: Recommendation and key model outputs
A3: Independent analytical case study using synthetic assumptions. Not based on proprietary company information.
A5: Recommendation | C5: =IF(AND(Scenarios!$D$74<0,Scenarios!$D$76>0),"Acquire only if repriced or restructured",IF(Scenarios!$D$74>=0,"Acquire at the ask","Decline")) -> Acquire only if repriced or restructured
A7: PRICE
A8: Seller initial ask - fixed fee ($) | C8: =Scenarios!$C$62 -> 2500000
A9: Modelled bid ceiling, Base case ($) | C9: =Scenarios!$D$59 -> 2013839.4 | E9: Maximum fixed fee that still earns the required return
A10: Recommended opening offer ($) | C10: =Scenarios!$C$67 -> 1318694.7
A11: Target price ($) | C11: =Scenarios!$C$66 -> 1498516.7
A12: Walk-away ceiling ($) | C12: =Scenarios!$C$63 -> 2013839.4
A13: Ask premium to the walk-away ceiling | C13: =Scenarios!$C$68 -> 0.24140984
A14: Viewing uplift required to justify the ask | C14: =Scenarios!$C$69 -> 0.17382619
A16: RETURNS
A17: Base-case ROI at the target price | C17: =Scenarios!$D$77 -> 0.2
A18: Base-case NPV at the target price ($) | C18: =Scenarios!$D$76 -> 496418.04
A19: Downside NPV at the target price ($) | C19: =Scenarios!$C$76 -> 15172.812
A20: Upside NPV at the target price ($) | C20: =Scenarios!$E$76 -> 1101352.9
A21: Downside NPV at the seller ask ($) | C21: =Scenarios!$C$74 -> -949571.01
A22: Base-case NPV at the seller ask ($) | C22: =Scenarios!$D$74 -> -468325.78
A23: Upside NPV at the seller ask ($) | C23: =Scenarios!$E$74 -> 136609.06
A25: PREFERRED STRUCTURE
A26: Preferred deal structure | C26: =INDEX('Deal Structures'!$C$72:$E$72,MATCH(MAX('Deal Structures'!$C$78:$E$78),'Deal Structures'!$C$78:$E$78,0)) -> C - Performance fee with earn-outs | E26: Selected because it produces the highest Downside NPV and strongest downside protection under its modeled contractual terms.
A27: Expected licence cost, Structure C, Base ($) | C27: ='Deal Structures'!$E$73 -> 1350000
A28: Base-case NPV, Structure C ($) | C28: ='Deal Structures'!$E$75 -> 663819.16
A29: Downside NPV, Structure C ($) | C29: ='Deal Structures'!$E$78 -> 616705.89
A30: Upside NPV, Structure C ($) | C30: ='Deal Structures'!$E$79 -> 1029595.8
A31: Payback period, Structure C, Base (months) | C31: ='Deal Structures'!$E$82 -> 6
A33: VALUE BRIDGE - ACTIVE SCENARIO
A34: Modelled lifetime unique viewers | C34: ='Title Economics'!$H$170 -> 11650000
A35: Viewing hours | C35: ='Title Economics'!$H$171 -> 15970795
A36: Monetised ad impressions | C36: ='Title Economics'!$H$172 -> 2.0223641e+08
A37: Gross advertising revenue ($) | C37: ='Title Economics'!$H$173 -> 4828224.8
A38: Incremental advertising revenue ($) | C38: ='Title Economics'!$H$174 -> 2773098.3
A39: Follow-on engagement value ($) | C39: ='Title Economics'!$H$175 -> 407970.58
A40: Support costs ($) | C40: ='Title Economics'!$H$176 -> 1068445.1
A41: Contribution before licence fee ($) | C41: ='Title Economics'!$H$177 -> 2112623.8
A43: PORTFOLIO SHAPE AND RISK
A44: Top two titles share of contribution | C44: =Sensitivities!$D$61 -> 0.79368564
A45: Titles not covering their allocated fee | C45: =Sensitivities!$D$64 -> 2
A46: Titles loss-making in the Downside after fee | C46: =Sensitivities!$D$66 -> 3
A47: Break-even viewing hours at the target price | C47: =Sensitivities!$D$42 -> 13028127
A48: Viewing headroom at the target price | C48: =Sensitivities!$D$44 -> 0.18425306
A49: Break-even weighted-average net CPM at the target price ($) | C49: =Sensitivities!$D$46 -> 19.309573
A51: Independent analytical case study using synthetic assumptions. Not based on proprietary company information.

Sheet QA Controls
A1: PROJECT NIGHTFALL
A2: Automated reconciliation and integrity controls
A3: Independent analytical case study using synthetic assumptions. Not based on proprietary company information.
A5: Overall status | C5: =IF(COUNTIF($F$8:$F$21,"FAIL")=0,"ALL CONTROLS PASS","CONTROL FAILURE - DO NOT RELY ON OUTPUTS") -> ALL CONTROLS PASS | F5: =COUNTIF($F$8:$F$21,"PASS")&" of "&COUNTA($F$8:$F$21)&" controls pass" -> 14 of 14 controls pass
A7: # | B7: Control | C7: Test | D7: Difference | E7: Tolerance | F7: Result
A8: 1 | B8: Title licence allocations tie to the package fee | C8: Sum of title allocation shares equals 100% and allocated fees equal the target price | D8: =MAX(ABS(SUM('Title Inputs'!$C$35:$G$35)-1)*Scenarios!$C$66,ABS(SUM('Title Economics'!$C$180:$G$180)-Scenarios!$C$66)) -> 0 | E8: 1 | F8: =IF($D8<=$E8,"PASS","FAIL") -> PASS
A9: 2 | B9: Monthly viewing ties to lifetime viewing | C9: Sum of monthly unique viewers equals the lifetime input for every title in the Base case | D9: =MAX(ABS(('Monthly Viewing Forecast'!$D$46)-('Title Inputs'!$C$15)),ABS(('Monthly Viewing Forecast'!$D$52)-('Title Inputs'!$D$15)),ABS(('Monthly Viewing Forecast'!$D$58)-('Title Inputs'!$E$15)),ABS(('Monthly Viewing Forecast'!$D$64)-('Title Inputs'!$F$15)),ABS(('Monthly Viewing Forecast'!$D$70)-('Title Inputs'!$G$15))) -> 0 | E9: 1 | F9: =IF($D9<=$E9,"PASS","FAIL") -> PASS
A10: 3 | B10: Viewing hours tie to title-level totals | C10: Portfolio viewing hours equal the sum of the five title rows in every scenario | D10: =MAX(ABS(('Monthly Viewing Forecast'!$D$38)-('Monthly Viewing Forecast'!$D$9+'Monthly Viewing Forecast'!$D$15+'Monthly Viewing Forecast'!$D$21+'Monthly Viewing Forecast'!$D$27+'Monthly Viewing Forecast'!$D$33)),ABS(('Monthly Viewing Forecast'!$D$77)-('Monthly Viewing Forecast'!$D$48+'Monthly Viewing Forecast'!$D$54+'Monthly Viewing Forecast'!$D$60+'Monthly Viewing Forecast'!$D$66+'Monthly Viewing Forecast'!$D$72)),ABS(('Monthly Viewing Forecast'!$D$116)-('Monthly Viewing Forecast'!$D$87+'Monthly Viewing Forecast'!$D$93+'Monthly Viewing Forecast'!$D$99+'Monthly Viewing Forecast'!$D$105+'Monthly Viewing Forecast'!$D$111))) -> 0 | E10: 1 | F10: =IF($D10<=$E10,"PASS","FAIL") -> PASS
A11: 4 | B11: Impressions reconcile to hours, ad load and fill | C11: Title impressions equal viewing hours multiplied by ad opportunities and fill rate | D11: =MAX(ABS(('Monthly Viewing Forecast'!$D$10)-('Monthly Viewing Forecast'!$D$9*'Title Inputs'!$C$24*Scenarios!$C$25)),ABS(('Monthly Viewing Forecast'!$D$16)-('Monthly Viewing Forecast'!$D$15*'Title Inputs'!$D$24*Scenarios!$D$25)),ABS(('Monthly Viewing Forecast'!$D$22)-('Monthly Viewing Forecast'!$D$21*'Title Inputs'!$E$24*Scenarios!$E$25)),ABS(('Monthly Viewing Forecast'!$D$28)-('Monthly Viewing Forecast'!$D$27*'Title Inputs'!$F$24*Scenarios!$F$25)),ABS(('Monthly Viewing Forecast'!$D$34)-('Monthly Viewing Forecast'!$D$33*'Title Inputs'!$G$24*Scenarios!$G$25)),ABS(('Monthly Viewing Forecast'!$D$49)-('Monthly Viewing Forecast'!$D$48*'Title Inputs'!$C$24*Scenarios!$C$34)),ABS(('Monthly Viewing Forecast'!$D$55)-('Monthly Viewing Forecast'!$D$54*'Title Inputs'!$D$24*Scenarios!$D$34)),ABS(('Monthly Viewing Forecast'!$D$61)-('Monthly Viewing Forecast'!$D$60*'Title Inputs'!$E$24*Scenarios!$E$34)),ABS(('Monthly Viewing Forecast'!$D$67)-('Monthly Viewing Forecast'!$D$66*'Title Inputs'!$F$24*Scenarios!$F$34)),ABS(('Monthly Viewing Forecast'!$D$73)-('Monthly Viewing Forecast'!$D$72*'Title Inputs'!$G$24*Scenarios!$G$34)),ABS(('Monthly Viewing Forecast'!$D$88)-('Monthly Viewing Forecast'!$D$87*'Title Inputs'!$C$24*Scenarios!$C$43)),ABS(('Monthly Viewing Forecast'!$D$94)-('Monthly Viewing Forecast'!$D$93*'Title Inputs'!$D$24*Scenarios!$D$43)),ABS(('Monthly Viewing Forecast'!$D$100)-('Monthly Viewing Forecast'!$D$99*'Title Inputs'!$E$24*Scenarios!$E$43)),ABS(('Monthly Viewing Forecast'!$D$106)-('Monthly Viewing Forecast'!$D$105*'Title Inputs'!$F$24*Scenarios!$F$43)),ABS(('Monthly Viewing Forecast'!$D$112)-('Monthly Viewing Forecast'!$D$111*'Title Inputs'!$G$24*Scenarios!$G$43))) -> 0 | E11: 1 | F11: =IF($D11<=$E11,"PASS","FAIL") -> PASS
