Workbook

Sheet Cover
B2: U.S. Streaming Subscription Pricing Analysis, 2018–2026
B3: What has actually risen since 2018, in nominal and real terms, and whether ad tiers and bundles are absorbing it
B5: Work sample · Subscription & pricing analytics
B6: Tanmay Srivastava · srivasta@mail.uc.edu · linkedin.com/in/srivasta26
B7: Version 2.0 · Prices as of 29 July 2026 · All current prices re-verified 29–30 July 2026
B9: WHAT'S IN THIS WORKBOOK
B10: Standalone subscriber growth has matured, so price and packaging are the levers services pull to manage revenue and churn. This workbook quantifies (1) how U.S. list prices have moved since each service launched, nominal and real; (2) whether the ad-supported tier is functioning as the cheap entry point the industry narrative assumes; and (3) how far bundles discount against standalone pricing. Every headline figure is derived in-sheet from the Price History table.
B13: Tab | C13: Contents
B14: Price History | C14: 67 dated price points, 8 services, 17 tiers, 2018–2026. Every row carries a clickable source link, a publication date and a confidence flag.
B15: Panel | C15: Year-end price for every tracked tier, derived by formula from Price History. Everything downstream reads from here.
B16: Price Analysis | C16: Total change and CAGR per flagship tier, over each service's own window and a common 2022–2026 window. Mean, median and n.
B17: Real vs Nominal | C17: Each endpoint deflated by the CPI-U index of its own period.
B18: Ad vs No-Ad | C18: Category-average price by tier type, averaged from the Panel — no typed figures.
B19: Bundles | C19: Bundle price vs. component standalone prices at a stated date, split by archetype, with eligibility noted.
B20: Price Event Cadence | C20: Price changes per year, counted from Price History with COUNTIFS, and normalized per active tier.
B21: Subscriber & ARPU | C21: Company-reported figures where disclosed, with the scope of each metric recorded. Not used in any calculation.
B22: CPI Deflator | C22: BLS CPI-U annual averages to 2024; 2025 and 2026 are flagged provisional inputs with a sensitivity note.
B23: Methodology | C23: Definitions, limitations and a changelog of every correction made across two revisions.
B25: METHODOLOGY & CAVEATS
B26: • | C26: All figures are U.S. list prices, monthly, in USD, for a new direct subscriber. Promotional, annual, student, partner and app-store prices are excluded.
B27: • | C27: The panel is not claimed to be exhaustive. It records every price change that could be sourced and dated for the tracked tiers. Where a step could not be tied to a contemporaneous report it is flagged Medium confidence.
B28: • | C28: CAGR windows differ by service (5.4 to 8.3 years) and are not directly comparable. The common 2022–2026 window exists for that comparison. Mean, median, range and n are shown together.
B29: • | C29: Real figures deflate each price by the CPI-U index of the year it took effect, at both ends.
B30: • | C30: ESPN Select has no ad-free tier. Its ad-supported plan is its flagship and is excluded from all ad-free category averages.
B31: • | C31: 2025 and 2026 CPI values are provisional. BLS did not publish an October 2025 index, so any 2025 annual average is non-standard; see the CPI Deflator tab for the sensitivity.
B32: • | C32: Subscriber and ARPU figures are reported values only, with the scope of each recorded. They feed no calculation in this workbook.
B33: • | C33: Nothing here measures churn, retention, elasticity, ad ARPU or contribution margin, and no claim in this workbook depends on them.

Sheet Dashboard
B2: Dashboard
B3: Every figure on this tab is a link or a formula. Nothing here is typed.
B5: Mean CAGR, common window | C5: CPI-U, same window | D5: Mean real price change | E5: Price points tracked
B6: ='Price Analysis'!G29 -> 0.1115279 | C6: ='Price Analysis'!G31 -> 0.037122115 | D6: ='Real vs Nominal'!I14 -> 0.4813177 | E6: =COUNTA('Price History'!B6:B72) -> 67
B7: ="All prices as of "&TEXT('Price Analysis'!$C$4,"dd mmm yyyy")&". Median CAGR over the same window is "&TEXT('Price Analysis'!G30,"0.0%")&", across "&COUNTA('Price Analysis'!B7:B14)&" services." -> All prices as of 29 Jul 2026. Median CAGR over the same window is 8.7%, across 8 services.
B9: Flagship tier inflation summary
B10: Service | C10: Launch | D10: Total % chg | E10: CAGR | F10: Real % chg
B11: ='Price Analysis'!B7 -> Netflix | C11: ='Price Analysis'!D7 -> 43480 | D11: ='Price Analysis'!H7 -> 0.53887606 | E11: ='Price Analysis'!I7 -> 0.058878128 | F11: ='Real vs Nominal'!I6 -> 0.1800373
B12: ='Price Analysis'!B8 -> Disney+ | C12: ='Price Analysis'!D8 -> 43781 | D12: ='Price Analysis'!H8 -> 1.7167382 | E12: ='Price Analysis'!I8 -> 0.16059889 | F12: ='Real vs Nominal'!I7 -> 1.0832428
B13: ='Price Analysis'!B9 -> Hulu | C13: ='Price Analysis'!D9 -> 43466 | D13: ='Price Analysis'!H9 -> 0.58381985 | E13: ='Price Analysis'!I9 -> 0.062603218 | F13: ='Real vs Nominal'!I8 -> 0.21450099
B14: ='Price Analysis'!B10 -> HBO Max | C14: ='Price Analysis'!D10 -> 43978 | D14: ='Price Analysis'!H10 -> 0.23348899 | E14: ='Price Analysis'!I10 -> 0.034592875 | F14: ='Real vs Nominal'!I9 -> -0.042469947
B15: ='Price Analysis'!B11 -> Peacock | C15: ='Price Analysis'!D11 -> 44027 | D15: ='Price Analysis'!H11 -> 0.7007007 | E15: ='Price Analysis'!I11 -> 0.091959127 | F15: ='Real vs Nominal'!I10 -> 0.3202161
B16: ='Price Analysis'!B12 -> Paramount+ | C16: ='Price Analysis'!D12 -> 44259 | D16: ='Price Analysis'!H12 -> 0.4004004 | E16: ='Price Analysis'!I12 -> 0.064311233 | F16: ='Real vs Nominal'!I11 -> 0.13817186
B17: ='Price Analysis'!B13 -> Apple TV | C17: ='Price Analysis'!D13 -> 43770 | D17: ='Price Analysis'!H13 -> 1.6032064 | E17: ='Price Analysis'!I13 -> 0.15250489 | F17: ='Real vs Nominal'!I12 -> 0.99618459
B18: ='Price Analysis'!B14 -> ESPN Select | C18: ='Price Analysis'!D14 -> 43202 | D18: ='Price Analysis'!H14 -> 1.6032064 | E18: ='Price Analysis'!I14 -> 0.12223418 | F18: ='Real vs Nominal'!I13 -> 0.96065793
B20: What the panel shows
B21: 1. | C21: Flagship prices rose at roughly three times CPI over the common 2022–2026 window, and about half the increase survives deflation.
B23: 2. | C23: The growth is concentrated. Three of the eight services account for almost all of the real increase; two are flat or negative in real terms.
B25: 3. | C25: The ad tier has risen slightly faster than the ad-free tier since end-2022, and the implied discount has held flat near 36%.
B27: 4. | C27: Bundles discount roughly a third to two thirds against standalone pricing, so list price is a weak proxy for realized revenue.
B29: 5. | C29: Services that launched cheapest have compounded fastest. That is descriptive across eight observations; no convergence test is performed.
B31: Not tested | C31: Whether ad tiers or bundles protect retention. This panel cannot show it, and churn, cohort and ad-ARPU data would be the next input.
B34: Automation (VBA)
B35: RunDataAudit | C35: Checks all 67 price points and writes a timestamped Audit Log sheet: missing source URLs, Medium-confidence rows, bad dates, duplicate service/tier/date rows, formula errors on any sheet, and any tier whose current price is over 24 months old.
B37: AddPriceChange | C37: Adds a price point in sort order inside the existing data block, so the absolute ranges the Panel depends on expand with it, then rebuilds the Event type column and offers to move the as-of date.
B39: RebuildEventTypes | C39: Re-flags each tier's first observed price as Baseline and the rest as Change. The cadence counts read this column.
B41: SetAsOfDate | C41: Moves the single as-of date cell, forces a full rebuild and reports the refreshed headline figures.
B43: Alt+F8 to run. Modules mPriceModel and mAudit; source is readable in the VBA editor (Alt+F11).

Sheet Price History
B2: Price History — U.S. Monthly List Prices
B3: One row per service, tier and effective date. Dates are true date values and drive every calculation downstream. Blue text marks a sourced hardcoded input. Event type separates a tier's first observed price (Baseline) from a subsequent change.
B5: Service | C5: Tier | D5: Effective date | E5: Price $/mo | F5: Event type | G5: Source | H5: URL | I5: Published | J5: Confidence
B6: Apple TV | C6: Standard (no ads) | D6: 43770 | E6: 4.99 | F6: Baseline | G6: Launch price (company) | H6: https://variety.com/2023/digital/news/apple-tv-plus-increases-monthly-price-1235768060/ | I6: 25 Oct 2023 | J6: High
B7: Apple TV | C7: Standard (no ads) | D7: 44858 | E7: 6.99 | F7: Change | G7: Oct 2022 increase (company) | H7: https://variety.com/2023/digital/news/apple-tv-plus-increases-monthly-price-1235768060/ | I7: 25 Oct 2023 | J7: High
B8: Apple TV | C8: Standard (no ads) | D8: 45224 | E8: 9.99 | F8: Change | G8: Oct 2023 increase (company) | H8: https://www.cnbc.com/2023/10/25/apple-raises-price-of-apple-tv-to-9point99-a-month.html | I8: 25 Oct 2023 | J8: High
B9: Apple TV | C9: Standard (no ads) | D9: 45890 | E9: 12.99 | F9: Change | G9: Aug 2025 increase, +30% (eMarketer; trade press) | H9: https://www.macrumors.com/2025/08/21/apple-tv-plus-price-increase-announced/ | I9: 21 Aug 2025 | J9: High
B10: Disney+ | C10: Basic w/ ads | D10: 44903 | E10: 7.99 | F10: Baseline | G10: Ad tier launch (TechCrunch) | H10: https://variety.com/2022/digital/news/disney-plus-ads-launch-price-increase-hulu-1235338148/ | I10: 10 Aug 2022 | J10: High
B11: Disney+ | C11: Basic w/ ads | D11: 45582 | E11: 9.99 | F11: Change | G11: Oct 2024 increase (TechCrunch) | H11: https://variety.com/2023/digital/news/disney-plus-price-increase-hulu-espn-plus-1235692057/ | I11: 9 Aug 2023 | J11: High
B12: Disney+ | C12: Basic w/ ads | D12: 45951 | E12: 11.99 | F12: Change | G12: Oct 2025 increase, +$2 (Variety; TechCrunch) | H12: https://variety.com/2025/digital/news/disney-plus-hulu-price-increases-october-2025-1236527241/ | I12: 23 Sep 2025 | J12: High
B13: Disney+ | C13: Premium (no ads) | D13: 43781 | E13: 6.99 | F13: Baseline | G13: US launch price (company announcement) | H13: https://variety.com/2023/digital/news/disney-plus-price-increase-hulu-espn-plus-1235692057/ | I13: 9 Aug 2023 | J13: High
B14: Disney+ | C14: Premium (no ads) | D14: 44281 | E14: 7.99 | F14: Change | G14: First increase, Mar 2021 (company) | H14: https://www.tvline.com/news/disney-plus-with-ads-price-launch-date-hulu-cost-increase-1234860250/ | I14: 10 Aug 2022 | J14: High
B15: Disney+ | C15: Premium (no ads) | D15: 44903 | E15: 10.99 | F15: Change | G15: Ad tier launch; Premium repriced (TechCrunch) | H15: https://variety.com/2022/digital/news/disney-plus-ads-launch-price-increase-hulu-1235338148/ | I15: 10 Aug 2022 | J15: High
B16: Disney+ | C16: Premium (no ads) | D16: 45211 | E16: 13.99 | F16: Change | G16: Oct 2023 increase (CNBC/NBC News) | H16: https://www.nbcnews.com/business/business-news/disney-raise-monthly-price-ad-free-disney-1399-rcna99126 | I16: 3 Aug 2023 | J16: High
B17: Disney+ | C17: Premium (no ads) | D17: 45582 | E17: 15.99 | F17: Change | G17: Oct 2024 increase (TechCrunch) | H17: https://techcrunch.com/2025/09/23/disney-is-raising-the-price-of-disney-hulu-subscriptions-next-month/ | I17: 23 Sep 2025 | J17: High
... B72: Peacock | C72: Select w/ ads | D72: 45861 | E72: 7.99 | F72: Baseline | G72: New low tier introduced (Variety) | H72: https://www.aol.com/entertainment/nbcuniversal-peacock-hiking-prices-3-182638817.html | I72: 17 Jul 2025 | J72: High
B74: ="Records: "&COUNTA(B6:B72)&" · Services: "&SUMPRODUCT((COUNTIF(B6:B72,B6:B72)>0)/COUNTIF(B6:B72,B6:B72))&" · As-of date: "&TEXT('Price Analysis'!$C$4,"dd mmm yyyy") -> Records: 67 · Services: 8 · As-of date: 29 Jul 2026
B75: Every row carries a live source link. Confidence: High means the change is confirmed in a dated company announcement or a contemporaneous trade-press report covering that specific change. Medium means the date or amount was corroborated from a later report or a price-history aggregator rather than reporting published at the time; those rows are all intermediate steps, never an endpoint used in the analysis.

Sheet Panel
B2: Panel — Year-End Price by Tier
B3: Every cell is the last documented price on or before 31 December of that year (or the as-of date for 2026), looked up from Price History by formula. Blank means the tier did not exist yet. This is the single source for every category average in the workbook.
B5: Service | C5: Tier | D5: Tier type | E5: 2019 | F5: 2020 | G5: 2021 | H5: 2022 | I5: 2023 | J5: 2024 | K5: 2025 | L5: 2026
B6: Netflix | C6: Standard (no ads) | D6: Ad-free | E6: =IF(SUMPRODUCT(MAX(('Price History'!$B$6:$B$72=$B6)*('Price History'!$C$6:$C$72=$C6)*('Price History'!$D$6:$D$72<=MIN(DATE(2019,12,31),'Price Analysis'!$C$4))*ROW('Price History'!$E$6:$E$72)))=0,"",INDEX('Price History'!$E$6:$E$72,SUMPRODUCT(MAX(('Price History'!$B$6:$B$72=$B6)*('Price History'!$C$6:$C$72=$C6)*('Price History'!$D$6:$D$72<=MIN(DATE(2019,12,31),'Price Analysis'!$C$4))*ROW('Price History'!$E$6:$E$72)))-5)) -> 12.99 | F6: =IF(SUMPRODUCT(MAX(('Price History'!$B$6:$B$72=$B6)*('Price History'!$C$6:$C$72=$C6)*('Price History'!$D$6:$D$72<=MIN(DATE(2020,12,31),'Price Analysis'!$C$4))*ROW('Price History'!$E$6:$E$72)))=0,"",INDEX('Price History'!$E$6:$E$72,SUMPRODUCT(MAX(('Price History'!$B$6:$B$72=$B6)*('Price History'!$C$6:$C$72=$C6)*('Price History'!$D$6:$D$72<=MIN(DATE(2020,12,31),'Price Analysis'!$C$4))*ROW('Price History'!$E$6:$E$72)))-5)) -> 13.99 | G6: =IF(SUMPRODUCT(MAX(('Price History'!$B$6:$B$72=$B6)*('Price History'!$C$6:$C$72=$C6)*('Price History'!$D$6:$D$72<=MIN(DATE(2021,12,31),'Price Analysis'!$C$4))*ROW('Price History'!$E$6:$E$72)))=0,"",INDEX('Price History'!$E$6:$E$72,SUMPRODUCT(MAX(('Price History'!$B$6:$B$72=$B6)*('Price History'!$C$6:$C$72=$C6)*('Price History'!$D$6:$D$72<=MIN(DATE(2021,12,31),'Price Analysis'!$C$4))*ROW('Price History'!$E$6:$E$72)))-5)) -> 13.99 | H6: =IF(SUMPRODUCT(MAX(('Price History'!$B$6:$B$72=$B6)*('Price History'!$C$6:$C$72=$C6)*('Price History'!$D$6:$D$72<=MIN(DATE(2022,12,31),'Price Analysis'!$C$4))*ROW('Price History'!$E$6:$E$72)))=0,"",INDEX('Price History'!$E$6:$E$72,SUMPRODUCT(MAX(('Price History'!$B$6:$B$72=$B6)*('Price History'!$C$6:$C$72=$C6)*('Price History'!$D$6:$D$72<=MIN(DATE(2022,12,31),'Price Analysis'!$C$4))*ROW('Price History'!$E$6:$E$72)))-5)) -> 15.49 | I6: =IF(SUMPRODUCT(MAX(('Price History'!$B$6:$B$72=$B6)*('Price History'!$C$6:$C$72=$C6)*('Price History'!$D$6:$D$72<=MIN(DATE(2023,12,31),'Price Analysis'!$C$4))*ROW('Price History'!$E$6:$E$72)))=0,"",INDEX('Price History'!$E$6:$E$72,SUMPRODUCT(MAX(('Price History'!$B$6:$B$72=$B6)*('Price History'!$C$6:$C$72=$C6)*('Price History'!$D$6:$D$72<=MIN(DATE(2023,12,31),'Price Analysis'!$C$4))*ROW('Price History'!$E$6:$E$72)))-5)) -> 15.49 | J6: =IF(SUMPRODUCT(MAX(('Price History'!$B$6:$B$72=$B6)*('Price History'!$C$6:$C$72=$C6)*('Price History'!$D$6:$D$72<=MIN(DATE(2024,12,31),'Price Analysis'!$C$4))*ROW('Price History'!$E$6:$E$72)))=0,"",INDEX('Price History'!$E$6:$E$72,SUMPRODUCT(MAX(('Price History'!$B$6:$B$72=$B6)*('Price History'!$C$6:$C$72=$C6)*('Price History'!$D$6:$D$72<=MIN(DATE(2024,12,31),'Price Analysis'!$C$4))*ROW('Price History'!$E$6:$E$72)))-5)) -> 15.49 | K6: =IF(SUMPRODUCT(MAX(('Price History'!$B$6:$B$72=$B6)*('Price History'!$C$6:$C$72=$C6)*('Price History'!$D$6:$D$72<=MIN(DATE(2025,12,31),'Price Analysis'!$C$4))*ROW('Price History'!$E$6:$E$72)))=0,"",INDEX('Price History'!$E$6:$E$72,SUMPRODUCT(MAX(('Price History'!$B$6:$B$72=$B6)*('Price History'!$C$6:$C$72=$C6)*('Price History'!$D$6:$D$72<=MIN(DATE(2025,12,31),'Price Analysis'!$C$4))*ROW('Price History'!$E$6:$E$72)))-5)) -> 17.99 | L6: =IF(SUMPRODUCT(MAX(('Price History'!$B$6:$B$72=$B6)*('Price History'!$C$6:$C$72=$C6)*('Price History'!$D$6:$D$72<=MIN(DATE(2026,12,31),'Price Analysis'!$C$4))*ROW('Price History'!$E$6:$E$72)))=0,"",INDEX('Price History'!$E$6:$E$72,SUMPRODUCT(MAX(('Price History'!$B$6:$B$72=$B6)*('Price History'!$C$6:$C$72=$C6)*('Price History'!$D$6:$D$72<=MIN(DATE(2026,12,31),'Price Analysis'!$C$4))*ROW('Price History'!$E$6:$E$72)))-5)) -> 19.99
B7: Disney+ | C7: Premium (no ads) | D7: Ad-free | E7: =IF(SUMPRODUCT(MAX(('Price History'!$B$6:$B$72=$B7)*('Price History'!$C$6:$C$72=$C7)*('Price History'!$D$6:$D$72<=MIN(DATE(2019,12,31),'Price Analysis'!$C$4))*ROW('Price History'!$E$6:$E$72)))=0,"",INDEX('Price History'!$E$6:$E$72,SUMPRODUCT(MAX(('Price History'!$B$6:$B$72=$B7)*('Price History'!$C$6:$C$72=$C7)*('Price History'!$D$6:$D$72<=MIN(DATE(2019,12,31),'Price Analysis'!$C$4))*ROW('Price History'!$E$6:$E$72)))-5)) -> 6.99 | F7: =IF(SUMPRODUCT(MAX(('Price History'!$B$6:$B$72=$B7)*('Price History'!$C$6:$C$72=$C7)*('Price History'!$D$6:$D$72<=MIN(DATE(2020,12,31),'Price Analysis'!$C$4))*ROW('Price History'!$E$6:$E$72)))=0,"",INDEX('Price History'!$E$6:$E$72,SUMPRODUCT(MAX(('Price History'!$B$6:$B$72=$B7)*('Price History'!$C$6:$C$72=$C7)*('Price History'!$D$6:$D$72<=MIN(DATE(2020,12,31),'Price Analysis'!$C$4))*ROW('Price History'!$E$6:$E$72)))-5)) -> 6.99 | G7: =IF(SUMPRODUCT(MAX(('Price History'!$B$6:$B$72=$B7)*('Price History'!$C$6:$C$72=$C7)*('Price History'!$D$6:$D$72<=MIN(DATE(2021,12,31),'Price Analysis'!$C$4))*ROW('Price History'!$E$6:$E$72)))=0,"",INDEX('Price History'!$E$6:$E$72,SUMPRODUCT(MAX(('Price History'!$B$6:$B$72=$B7)*('Price History'!$C$6:$C$72=$C7)*('Price History'!$D$6:$D$72<=MIN(DATE(2021,12,31),'Price Analysis'!$C$4))*ROW('Price History'!$E$6:$E$72)))-5)) -> 7.99 | H7: =IF(SUMPRODUCT(MAX(('Price History'!$B$6:$B$72=$B7)*('Price History'!$C$6:$C$72=$C7)*('Price History'!$D$6:$D$72<=MIN(DATE(2022,12,31),'Price Analysis'!$C$4))*ROW('Price History'!$E$6:$E$72)))=0,"",INDEX('Price History'!$E$6:$E$72,SUMPRODUCT(MAX(('Price History'!$B$6:$B$72=$B7)*('Price History'!$C$6:$C$72=$C7)*('Price History'!$D$6:$D$72<=MIN(DATE(2022,12,31),'Price Analysis'!$C$4))*ROW('Price History'!$E$6:$E$72)))-5)) -> 10.99 | I7: =IF(SUMPRODUCT(MAX(('Price History'!$B$6:$B$72=$B7)*('Price History'!$C$6:$C$72=$C7)*('Price History'!$D$6:$D$72<=MIN(DATE(2023,12,31),'Price Analysis'!$C$4))*ROW('Price History'!$E$6:$E$72)))=0,"",INDEX('Price History'!$E$6:$E$72,SUMPRODUCT(MAX(('Price History'!$B$6:$B$72=$B7)*('Price History'!$C$6:$C$72=$C7)*('Price History'!$D$6:$D$72<=MIN(DATE(2023,12,31),'Price Analysis'!$C$4))*ROW('Price History'!$E$6:$E$72)))-5)) -> 13.99 | J7: =IF(SUMPRODUCT(MAX(('Price History'!$B$6:$B$72=$B7)*('Price History'!$C$6:$C$72=$C7)*('Price History'!$D$6:$D$72<=MIN(DATE(2024,12,31),'Price Analysis'!$C$4))*ROW('Price History'!$E$6:$E$72)))=0,"",INDEX('Price History'!$E$6:$E$72,SUMPRODUCT(MAX(('Price History'!$B$6:$B$72=$B7)*('Price History'!$C$6:$C$72=$C7)*('Price History'!$D$6:$D$72<=MIN(DATE(2024,12,31),'Price Analysis'!$C$4))*ROW('Price History'!$E$6:$E$72)))-5)) -> 15.99 | K7: =IF(SUMPRODUCT(MAX(('Price History'!$B$6:$B$72=$B7)*('Price History'!$C$6:$C$72=$C7)*('Price History'!$D$6:$D$72<=MIN(DATE(2025,12,31),'Price Analysis'!$C$4))*ROW('Price History'!$E$6:$E$72)))=0,"",INDEX('Price History'!$E$6:$E$72,SUMPRODUCT(MAX(('Price History'!$B$6:$B$72=$B7)*('Price History'!$C$6:$C$72=$C7)*('Price History'!$D$6:$D$72<=MIN(DATE(2025,12,31),'Price Analysis'!$C$4))*ROW('Price History'!$E$6:$E$72)))-5)) -> 18.99 | L7: =IF(SUMPRODUCT(MAX(('Price History'!$B$6:$B$72=$B7)*('Price History'!$C$6:$C$72=$C7)*('Price History'!$D$6:$D$72<=MIN(DATE(2026,12,31),'Price Analysis'!$C$4))*ROW('Price History'!$E$6:$E$72)))=0,"",INDEX('Price History'!$E$6:$E$72,SUMPRODUCT(MAX(('Price History'!$B$6:$B$72=$B7)*('Price History'!$C$6:$C$72=$C7)*('Price History'!$D$6:$D$72<=MIN(DATE(2026,12,31),'Price Analysis'!$C$4))*ROW('Price History'!$E$6:$E$72)))-5)) -> 18.99
B8: Hulu | C8: No ads | D8: Ad-free | E8: =IF(SUMPRODUCT(MAX(('Price History'!$B$6:$B$72=$B8)*('Price History'!$C$6:$C$72=$C8)*('Price History'!$D$6:$D$72<=MIN(DATE(2019,12,31),'Price Analysis'!$C$4))*ROW('Price History'!$E$6:$E$72)))=0,"",INDEX('Price History'!$E$6:$E$72,SUMPRODUCT(MAX(('Price History'!$B$6:$B$72=$B8)*('Price History'!$C$6:$C$72=$C8)*('Price History'!$D$6:$D$72<=MIN(DATE(2019,12,31),'Price Analysis'!$C$4))*ROW('Price History'!$E$6:$E$72)))-5)) -> 11.99 | F8: =IF(SUMPRODUCT(MAX(('Price History'!$B$6:$B$72=$B8)*('Price History'!$C$6:$C$72=$C8)*('Price History'!$D$6:$D$72<=MIN(DATE(2020,12,31),'Price Analysis'!$C$4))*ROW('Price History'!$E$6:$E$72)))=0,"",INDEX('Price History'!$E$6:$E$72,SUMPRODUCT(MAX(('Price History'!$B$6:$B$72=$B8)*('Price History'!$C$6:$C$72=$C8)*('Price History'!$D$6:$D$72<=MIN(DATE(2020,12,31),'Price Analysis'!$C$4))*ROW('Price History'!$E$6:$E$72)))-5)) -> 11.99 | G8: =IF(SUMPRODUCT(MAX(('Price History'!$B$6:$B$72=$B8)*('Price History'!$C$6:$C$72=$C8)*('Price History'!$D$6:$D$72<=MIN(DATE(2021,12,31),'Price Analysis'!$C$4))*ROW('Price History'!$E$6:$E$72)))=0,"",INDEX('Price History'!$E$6:$E$72,SUMPRODUCT(MAX(('Price History'!$B$6:$B$72=$B8)*('Price History'!$C$6:$C$72=$C8)*('Price History'!$D$6:$D$72<=MIN(DATE(2021,12,31),'Price Analysis'!$C$4))*ROW('Price History'!$E$6:$E$72)))-5)) -> 11.99 | H8: =IF(SUMPRODUCT(MAX(('Price History'!$B$6:$B$72=$B8)*('Price History'!$C$6:$C$72=$C8)*('Price History'!$D$6:$D$72<=MIN(DATE(2022,12,31),'Price Analysis'!$C$4))*ROW('Price History'!$E$6:$E$72)))=0,"",INDEX('Price History'!$E$6:$E$72,SUMPRODUCT(MAX(('Price History'!$B$6:$B$72=$B8)*('Price History'!$C$6:$C$72=$C8)*('Price History'!$D$6:$D$72<=MIN(DATE(2022,12,31),'Price Analysis'!$C$4))*ROW('Price History'!$E$6:$E$72)))-5)) -> 14.99 | I8: =IF(SUMPRODUCT(MAX(('Price History'!$B$6:$B$72=$B8)*('Price History'!$C$6:$C$72=$C8)*('Price History'!$D$6:$D$72<=MIN(DATE(2023,12,31),'Price Analysis'!$C$4))*ROW('Price History'!$E$6:$E$72)))=0,"",INDEX('Price History'!$E$6:$E$72,SUMPRODUCT(MAX(('Price History'!$B$6:$B$72=$B8)*('Price History'!$C$6:$C$72=$C8)*('Price History'!$D$6:$D$72<=MIN(DATE(2023,12,31),'Price Analysis'!$C$4))*ROW('Price History'!$E$6:$E$72)))-5)) -> 17.99 | J8: =IF(SUMPRODUCT(MAX(('Price History'!$B$6:$B$72=$B8)*('Price History'!$C$6:$C$72=$C8)*('Price History'!$D$6:$D$72<=MIN(DATE(2024,12,31),'Price Analysis'!$C$4))*ROW('Price History'!$E$6:$E$72)))=0,"",INDEX('Price History'!$E$6:$E$72,SUMPRODUCT(MAX(('Price History'!$B$6:$B$72=$B8)*('Price History'!$C$6:$C$72=$C8)*('Price History'!$D$6:$D$72<=MIN(DATE(2024,12,31),'Price Analysis'!$C$4))*ROW('Price History'!$E$6:$E$72)))-5)) -> 18.99 | K8: =IF(SUMPRODUCT(MAX(('Price History'!$B$6:$B$72=$B8)*('Price History'!$C$6:$C$72=$C8)*('Price History'!$D$6:$D$72<=MIN(DATE(2025,12,31),'Price Analysis'!$C$4))*ROW('Price History'!$E$6:$E$72)))=0,"",INDEX('Price History'!$E$6:$E$72,SUMPRODUCT(MAX(('Price History'!$B$6:$B$72=$B8)*('Price History'!$C$6:$C$72=$C8)*('Price History'!$D$6:$D$72<=MIN(DATE(2025,12,31),'Price Analysis'!$C$4))*ROW('Price History'!$E$6:$E$72)))-5)) -> 18.99 | L8: =IF(SUMPRODUCT(MAX(('Price History'!$B$6:$B$72=$B8)*('Price History'!$C$6:$C$72=$C8)*('Price History'!$D$6:$D$72<=MIN(DATE(2026,12,31),'Price Analysis'!$C$4))*ROW('Price History'!$E$6:$E$72)))=0,"",INDEX('Price History'!$E$6:$E$72,SUMPRODUCT(MAX(('Price History'!$B$6:$B$72=$B8)*('Price History'!$C$6:$C$72=$C8)*('Price History'!$D$6:$D$72<=MIN(DATE(2026,12,31),'Price Analysis'!$C$4))*ROW('Price History'!$E$6:$E$72)))-5)) -> 18.99
B9: HBO Max | C9: Standard (no ads) | D9: Ad-free | E9: =IF(SUMPRODUCT(MAX(('Price History'!$B$6:$B$72=$B9)*('Price History'!$C$6:$C$72=$C9)*('Price History'!$D$6:$D$72<=MIN(DATE(2019,12,31),'Price Analysis'!$C$4))*ROW('Price History'!$E$6:$E$72)))=0,"",INDEX('Price History'!$E$6:$E$72,SUMPRODUCT(MAX(('Price History'!$B$6:$B$72=$B9)*('Price History'!$C$6:$C$72=$C9)*('Price History'!$D$6:$D$72<=MIN(DATE(2019,12,31),'Price Analysis'!$C$4))*ROW('Price History'!$E$6:$E$72)))-5)) | F9: =IF(SUMPRODUCT(MAX(('Price History'!$B$6:$B$72=$B9)*('Price History'!$C$6:$C$72=$C9)*('Price History'!$D$6:$D$72<=MIN(DATE(2020,12,31),'Price Analysis'!$C$4))*ROW('Price History'!$E$6:$E$72)))=0,"",INDEX('Price History'!$E$6:$E$72,SUMPRODUCT(MAX(('Price History'!$B$6:$B$72=$B9)*('Price History'!$C$6:$C$72=$C9)*('Price History'!$D$6:$D$72<=MIN(DATE(2020,12,31),'Price Analysis'!$C$4))*ROW('Price History'!$E$6:$E$72)))-5)) -> 14.99 | G9: =IF(SUMPRODUCT(MAX(('Price History'!$B$6:$B$72=$B9)*('Price History'!$C$6:$C$72=$C9)*('Price History'!$D$6:$D$72<=MIN(DATE(2021,12,31),'Price Analysis'!$C$4))*ROW('Price History'!$E$6:$E$72)))=0,"",INDEX('Price History'!$E$6:$E$72,SUMPRODUCT(MAX(('Price History'!$B$6:$B$72=$B9)*('Price History'!$C$6:$C$72=$C9)*('Price History'!$D$6:$D$72<=MIN(DATE(2021,12,31),'Price Analysis'!$C$4))*ROW('Price History'!$E$6:$E$72)))-5)) -> 14.99 | H9: =IF(SUMPRODUCT(MAX(('Price History'!$B$6:$B$72=$B9)*('Price History'!$C$6:$C$72=$C9)*('Price History'!$D$6:$D$72<=MIN(DATE(2022,12,31),'Price Analysis'!$C$4))*ROW('Price History'!$E$6:$E$72)))=0,"",INDEX('Price History'!$E$6:$E$72,SUMPRODUCT(MAX(('Price History'!$B$6:$B$72=$B9)*('Price History'!$C$6:$C$72=$C9)*('Price History'!$D$6:$D$72<=MIN(DATE(2022,12,31),'Price Analysis'!$C$4))*ROW('Price History'!$E$6:$E$72)))-5)) -> 14.99 | I9: =IF(SUMPRODUCT(MAX(('Price History'!$B$6:$B$72=$B9)*('Price History'!$C$6:$C$72=$C9)*('Price History'!$D$6:$D$72<=MIN(DATE(2023,12,31),'Price Analysis'!$C$4))*ROW('Price History'!$E$6:$E$72)))=0,"",INDEX('Price History'!$E$6:$E$72,SUMPRODUCT(MAX(('Price History'!$B$6:$B$72=$B9)*('Price History'!$C$6:$C$72=$C9)*('Price History'!$D$6:$D$72<=MIN(DATE(2023,12,31),'Price Analysis'!$C$4))*ROW('Price History'!$E$6:$E$72)))-5)) -> 15.99 | J9: =IF(SUMPRODUCT(MAX(('Price History'!$B$6:$B$72=$B9)*('Price History'!$C$6:$C$72=$C9)*('Price History'!$D$6:$D$72<=MIN(DATE(2024,12,31),'Price Analysis'!$C$4))*ROW('Price History'!$E$6:$E$72)))=0,"",INDEX('Price History'!$E$6:$E$72,SUMPRODUCT(MAX(('Price History'!$B$6:$B$72=$B9)*('Price History'!$C$6:$C$72=$C9)*('Price History'!$D$6:$D$72<=MIN(DATE(2024,12,31),'Price Analysis'!$C$4))*ROW('Price History'!$E$6:$E$72)))-5)) -> 16.99 | K9: =IF(SUMPRODUCT(MAX(('Price History'!$B$6:$B$72=$B9)*('Price History'!$C$6:$C$72=$C9)*('Price History'!$D$6:$D$72<=MIN(DATE(2025,12,31),'Price Analysis'!$C$4))*ROW('Price History'!$E$6:$E$72)))=0,"",INDEX('Price History'!$E$6:$E$72,SUMPRODUCT(MAX(('Price History'!$B$6:$B$72=$B9)*('Price History'!$C$6:$C$72=$C9)*('Price History'!$D$6:$D$72<=MIN(DATE(2025,12,31),'Price Analysis'!$C$4))*ROW('Price History'!$E$6:$E$72)))-5)) -> 18.49 | L9: =IF(SUMPRODUCT(MAX(('Price History'!$B$6:$B$72=$B9)*('Price History'!$C$6:$C$72=$C9)*('Price History'!$D$6:$D$72<=MIN(DATE(2026,12,31),'Price Analysis'!$C$4))*ROW('Price History'!$E$6:$E$72)))=0,"",INDEX('Price History'!$E$6:$E$72,SUMPRODUCT(MAX(('Price History'!$B$6:$B$72=$B9)*('Price History'!$C$6:$C$72=$C9)*('Price History'!$D$6:$D$72<=MIN(DATE(2026,12,31),'Price Analysis'!$C$4))*ROW('Price History'!$E$6:$E$72)))-5)) -> 18.49
B10: Peacock | C10: Premium Plus (no ads) | D10: Ad-free | E10: =IF(SUMPRODUCT(MAX(('Price History'!$B$6:$B$72=$B10)*('Price History'!$C$6:$C$72=$C10)*('Price History'!$D$6:$D$72<=MIN(DATE(2019,12,31),'Price Analysis'!$C$4))*ROW('Price History'!$E$6:$E$72)))=0,"",INDEX('Price History'!$E$6:$E$72,SUMPRODUCT(MAX(('Price History'!$B$6:$B$72=$B10)*('Price History'!$C$6:$C$72=$C10)*('Price History'!$D$6:$D$72<=MIN(DATE(2019,12,31),'Price Analysis'!$C$4))*ROW('Price History'!$E$6:$E$72)))-5)) | F10: =IF(SUMPRODUCT(MAX(('Price History'!$B$6:$B$72=$B10)*('Price History'!$C$6:$C$72=$C10)*('Price History'!$D$6:$D$72<=MIN(DATE(2020,12,31),'Price Analysis'!$C$4))*ROW('Price History'!$E$6:$E$72)))=0,"",INDEX('Price History'!$E$6:$E$72,SUMPRODUCT(MAX(('Price History'!$B$6:$B$72=$B10)*('Price History'!$C$6:$C$72=$C10)*('Price History'!$D$6:$D$72<=MIN(DATE(2020,12,31),'Price Analysis'!$C$4))*ROW('Price History'!$E$6:$E$72)))-5)) -> 9.99 | G10: =IF(SUMPRODUCT(MAX(('Price History'!$B$6:$B$72=$B10)*('Price History'!$C$6:$C$72=$C10)*('Price History'!$D$6:$D$72<=MIN(DATE(2021,12,31),'Price Analysis'!$C$4))*ROW('Price History'!$E$6:$E$72)))=0,"",INDEX('Price History'!$E$6:$E$72,SUMPRODUCT(MAX(('Price History'!$B$6:$B$72=$B10)*('Price History'!$C$6:$C$72=$C10)*('Price History'!$D$6:$D$72<=MIN(DATE(2021,12,31),'Price Analysis'!$C$4))*ROW('Price History'!$E$6:$E$72)))-5)) -> 9.99 | H10: =IF(SUMPRODUCT(MAX(('Price History'!$B$6:$B$72=$B10)*('Price History'!$C$6:$C$72=$C10)*('Price History'!$D$6:$D$72<=MIN(DATE(2022,12,31),'Price Analysis'!$C$4))*ROW('Price History'!$E$6:$E$72)))=0,"",INDEX('Price History'!$E$6:$E$72,SUMPRODUCT(MAX(('Price History'!$B$6:$B$72=$B10)*('Price History'!$C$6:$C$72=$C10)*('Price History'!$D$6:$D$72<=MIN(DATE(2022,12,31),'Price Analysis'!$C$4))*ROW('Price History'!$E$6:$E$72)))-5)) -> 9.99 | I10: =IF(SUMPRODUCT(MAX(('Price History'!$B$6:$B$72=$B10)*('Price History'!$C$6:$C$72=$C10)*('Price History'!$D$6:$D$72<=MIN(DATE(2023,12,31),'Price Analysis'!$C$4))*ROW('Price History'!$E$6:$E$72)))=0,"",INDEX('Price History'!$E$6:$E$72,SUMPRODUCT(MAX(('Price History'!$B$6:$B$72=$B10)*('Price History'!$C$6:$C$72=$C10)*('Price History'!$D$6:$D$72<=MIN(DATE(2023,12,31),'Price Analysis'!$C$4))*ROW('Price History'!$E$6:$E$72)))-5)) -> 11.99 | J10: =IF(SUMPRODUCT(MAX(('Price History'!$B$6:$B$72=$B10)*('Price History'!$C$6:$C$72=$C10)*('Price History'!$D$6:$D$72<=MIN(DATE(2024,12,31),'Price Analysis'!$C$4))*ROW('Price History'!$E$6:$E$72)))=0,"",INDEX('Price History'!$E$6:$E$72,SUMPRODUCT(MAX(('Price History'!$B$6:$B$72=$B10)*('Price History'!$C$6:$C$72=$C10)*('Price History'!$D$6:$D$72<=MIN(DATE(2024,12,31),'Price Analysis'!$C$4))*ROW('Price History'!$E$6:$E$72)))-5)) -> 13.99 | K10: =IF(SUMPRODUCT(MAX(('Price History'!$B$6:$B$72=$B10)*('Price History'!$C$6:$C$72=$C10)*('Price History'!$D$6:$D$72<=MIN(DATE(2025,12,31),'Price Analysis'!$C$4))*ROW('Price History'!$E$6:$E$72)))=0,"",INDEX('Price History'!$E$6:$E$72,SUMPRODUCT(MAX(('Price History'!$B$6:$B$72=$B10)*('Price History'!$C$6:$C$72=$C10)*('Price History'!$D$6:$D$72<=MIN(DATE(2025,12,31),'Price Analysis'!$C$4))*ROW('Price History'!$E$6:$E$72)))-5)) -> 16.99 | L10: =IF(SUMPRODUCT(MAX(('Price History'!$B$6:$B$72=$B10)*('Price History'!$C$6:$C$72=$C10)*('Price History'!$D$6:$D$72<=MIN(DATE(2026,12,31),'Price Analysis'!$C$4))*ROW('Price History'!$E$6:$E$72)))=0,"",INDEX('Price History'!$E$6:$E$72,SUMPRODUCT(MAX(('Price History'!$B$6:$B$72=$B10)*('Price History'!$C$6:$C$72=$C10)*('Price History'!$D$6:$D$72<=MIN(DATE(2026,12,31),'Price Analysis'!$C$4))*ROW('Price History'!$E$6:$E$72)))-5)) -> 16.99
B11: Paramount+ | C11: Premium (no ads) | D11: Ad-free | E11: =IF(SUMPRODUCT(MAX(('Price History'!$B$6:$B$72=$B11)*('Price History'!$C$6:$C$72=$C11)*('Price History'!$D$6:$D$72<=MIN(DATE(2019,12,31),'Price Analysis'!$C$4))*ROW('Price History'!$E$6:$E$72)))=0,"",INDEX('Price History'!$E$6:$E$72,SUMPRODUCT(MAX(('Price History'!$B$6:$B$72=$B11)*('Price History'!$C$6:$C$72=$C11)*('Price History'!$D$6:$D$72<=MIN(DATE(2019,12,31),'Price Analysis'!$C$4))*ROW('Price History'!$E$6:$E$72)))-5)) | F11: =IF(SUMPRODUCT(MAX(('Price History'!$B$6:$B$72=$B11)*('Price History'!$C$6:$C$72=$C11)*('Price History'!$D$6:$D$72<=MIN(DATE(2020,12,31),'Price Analysis'!$C$4))*ROW('Price History'!$E$6:$E$72)))=0,"",INDEX('Price History'!$E$6:$E$72,SUMPRODUCT(MAX(('Price History'!$B$6:$B$72=$B11)*('Price History'!$C$6:$C$72=$C11)*('Price History'!$D$6:$D$72<=MIN(DATE(2020,12,31),'Price Analysis'!$C$4))*ROW('Price History'!$E$6:$E$72)))-5)) | G11: =IF(SUMPRODUCT(MAX(('Price History'!$B$6:$B$72=$B11)*('Price History'!$C$6:$C$72=$C11)*('Price History'!$D$6:$D$72<=MIN(DATE(2021,12,31),'Price Analysis'!$C$4))*ROW('Price History'!$E$6:$E$72)))=0,"",INDEX('Price History'!$E$6:$E$72,SUMPRODUCT(MAX(('Price History'!$B$6:$B$72=$B11)*('Price History'!$C$6:$C$72=$C11)*('Price History'!$D$6:$D$72<=MIN(DATE(2021,12,31),'Price Analysis'!$C$4))*ROW('Price History'!$E$6:$E$72)))-5)) -> 9.99 | H11: =IF(SUMPRODUCT(MAX(('Price History'!$B$6:$B$72=$B11)*('Price History'!$C$6:$C$72=$C11)*('Price History'!$D$6:$D$72<=MIN(DATE(2022,12,31),'Price Analysis'!$C$4))*ROW('Price History'!$E$6:$E$72)))=0,"",INDEX('Price History'!$E$6:$E$72,SUMPRODUCT(MAX(('Price History'!$B$6:$B$72=$B11)*('Price History'!$C$6:$C$72=$C11)*('Price History'!$D$6:$D$72<=MIN(DATE(2022,12,31),'Price Analysis'!$C$4))*ROW('Price History'!$E$6:$E$72)))-5)) -> 9.99 | I11: =IF(SUMPRODUCT(MAX(('Price History'!$B$6:$B$72=$B11)*('Price History'!$C$6:$C$72=$C11)*('Price History'!$D$6:$D$72<=MIN(DATE(2023,12,31),'Price Analysis'!$C$4))*ROW('Price History'!$E$6:$E$72)))=0,"",INDEX('Price History'!$E$6:$E$72,SUMPRODUCT(MAX(('Price History'!$B$6:$B$72=$B11)*('Price History'!$C$6:$C$72=$C11)*('Price History'!$D$6:$D$72<=MIN(DATE(2023,12,31),'Price Analysis'!$C$4))*ROW('Price History'!$E$6:$E$72)))-5)) -> 11.99 | J11: =IF(SUMPRODUCT(MAX(('Price History'!$B$6:$B$72=$B11)*('Price History'!$C$6:$C$72=$C11)*('Price History'!$D$6:$D$72<=MIN(DATE(2024,12,31),'Price Analysis'!$C$4))*ROW('Price History'!$E$6:$E$72)))=0,"",INDEX('Price History'!$E$6:$E$72,SUMPRODUCT(MAX(('Price History'!$B$6:$B$72=$B11)*('Price History'!$C$6:$C$72=$C11)*('Price History'!$D$6:$D$72<=MIN(DATE(2024,12,31),'Price Analysis'!$C$4))*ROW('Price History'!$E$6:$E$72)))-5)) -> 12.99 | K11: =IF(SUMPRODUCT(MAX(('Price History'!$B$6:$B$72=$B11)*('Price History'!$C$6:$C$72=$C11)*('Price History'!$D$6:$D$72<=MIN(DATE(2025,12,31),'Price Analysis'!$C$4))*ROW('Price History'!$E$6:$E$72)))=0,"",INDEX('Price History'!$E$6:$E$72,SUMPRODUCT(MAX(('Price History'!$B$6:$B$72=$B11)*('Price History'!$C$6:$C$72=$C11)*('Price History'!$D$6:$D$72<=MIN(DATE(2025,12,31),'Price Analysis'!$C$4))*ROW('Price History'!$E$6:$E$72)))-5)) -> 12.99 | L11: =IF(SUMPRODUCT(MAX(('Price History'!$B$6:$B$72=$B11)*('Price History'!$C$6:$C$72=$C11)*('Price History'!$D$6:$D$72<=MIN(DATE(2026,12,31),'Price Analysis'!$C$4))*ROW('Price History'!$E$6:$E$72)))=0,"",INDEX('Price History'!$E$6:$E$72,SUMPRODUCT(MAX(('Price History'!$B$6:$B$72=$B11)*('Price History'!$C$6:$C$72=$C11)*('Price History'!$D$6:$D$72<=MIN(DATE(2026,12,31),'Price Analysis'!$C$4))*ROW('Price History'!$E$6:$E$72)))-5)) -> 13.99
B12: Apple TV | C12: Standard (no ads) | D12: Ad-free | E12: =IF(SUMPRODUCT(MAX(('Price History'!$B$6:$B$72=$B12)*('Price History'!$C$6:$C$72=$C12)*('Price History'!$D$6:$D$72<=MIN(DATE(2019,12,31),'Price Analysis'!$C$4))*ROW('Price History'!$E$6:$E$72)))=0,"",INDEX('Price History'!$E$6:$E$72,SUMPRODUCT(MAX(('Price History'!$B$6:$B$72=$B12)*('Price History'!$C$6:$C$72=$C12)*('Price History'!$D$6:$D$72<=MIN(DATE(2019,12,31),'Price Analysis'!$C$4))*ROW('Price History'!$E$6:$E$72)))-5)) -> 4.99 | F12: =IF(SUMPRODUCT(MAX(('Price History'!$B$6:$B$72=$B12)*('Price History'!$C$6:$C$72=$C12)*('Price History'!$D$6:$D$72<=MIN(DATE(2020,12,31),'Price Analysis'!$C$4))*ROW('Price History'!$E$6:$E$72)))=0,"",INDEX('Price History'!$E$6:$E$72,SUMPRODUCT(MAX(('Price History'!$B$6:$B$72=$B12)*('Price History'!$C$6:$C$72=$C12)*('Price History'!$D$6:$D$72<=MIN(DATE(2020,12,31),'Price Analysis'!$C$4))*ROW('Price History'!$E$6:$E$72)))-5)) -> 4.99 | G12: =IF(SUMPRODUCT(MAX(('Price History'!$B$6:$B$72=$B12)*('Price History'!$C$6:$C$72=$C12)*('Price History'!$D$6:$D$72<=MIN(DATE(2021,12,31),'Price Analysis'!$C$4))*ROW('Price History'!$E$6:$E$72)))=0,"",INDEX('Price History'!$E$6:$E$72,SUMPRODUCT(MAX(('Price History'!$B$6:$B$72=$B12)*('Price History'!$C$6:$C$72=$C12)*('Price History'!$D$6:$D$72<=MIN(DATE(2021,12,31),'Price Analysis'!$C$4))*ROW('Price History'!$E$6:$E$72)))-5)) -> 4.99 | H12: =IF(SUMPRODUCT(MAX(('Price History'!$B$6:$B$72=$B12)*('Price History'!$C$6:$C$72=$C12)*('Price History'!$D$6:$D$72<=MIN(DATE(2022,12,31),'Price Analysis'!$C$4))*ROW('Price History'!$E$6:$E$72)))=0,"",INDEX('Price History'!$E$6:$E$72,SUMPRODUCT(MAX(('Price History'!$B$6:$B$72=$B12)*('Price History'!$C$6:$C$72=$C12)*('Price History'!$D$6:$D$72<=MIN(DATE(2022,12,31),'Price Analysis'!$C$4))*ROW('Price History'!$E$6:$E$72)))-5)) -> 6.99 | I12: =IF(SUMPRODUCT(MAX(('Price History'!$B$6:$B$72=$B12)*('Price History'!$C$6:$C$72=$C12)*('Price History'!$D$6:$D$72<=MIN(DATE(2023,12,31),'Price Analysis'!$C$4))*ROW('Price History'!$E$6:$E$72)))=0,"",INDEX('Price History'!$E$6:$E$72,SUMPRODUCT(MAX(('Price History'!$B$6:$B$72=$B12)*('Price History'!$C$6:$C$72=$C12)*('Price History'!$D$6:$D$72<=MIN(DATE(2023,12,31),'Price Analysis'!$C$4))*ROW('Price History'!$E$6:$E$72)))-5)) -> 9.99 | J12: =IF(SUMPRODUCT(MAX(('Price History'!$B$6:$B$72=$B12)*('Price History'!$C$6:$C$72=$C12)*('Price History'!$D$6:$D$72<=MIN(DATE(2024,12,31),'Price Analysis'!$C$4))*ROW('Price History'!$E$6:$E$72)))=0,"",INDEX('Price History'!$E$6:$E$72,SUMPRODUCT(MAX(('Price History'!$B$6:$B$72=$B12)*('Price History'!$C$6:$C$72=$C12)*('Price History'!$D$6:$D$72<=MIN(DATE(2024,12,31),'Price Analysis'!$C$4))*ROW('Price History'!$E$6:$E$72)))-5)) -> 9.99 | K12: =IF(SUMPRODUCT(MAX(('Price History'!$B$6:$B$72=$B12)*('Price History'!$C$6:$C$72=$C12)*('Price History'!$D$6:$D$72<=MIN(DATE(2025,12,31),'Price Analysis'!$C$4))*ROW('Price History'!$E$6:$E$72)))=0,"",INDEX('Price History'!$E$6:$E$72,SUMPRODUCT(MAX(('Price History'!$B$6:$B$72=$B12)*('Price History'!$C$6:$C$72=$C12)*('Price History'!$D$6:$D$72<=MIN(DATE(2025,12,31),'Price Analysis'!$C$4))*ROW('Price History'!$E$6:$E$72)))-5)) -> 12.99 | L12: =IF(SUMPRODUCT(MAX(('Price History'!$B$6:$B$72=$B12)*('Price History'!$C$6:$C$72=$C12)*('Price History'!$D$6:$D$72<=MIN(DATE(2026,12,31),'Price Analysis'!$C$4))*ROW('Price History'!$E$6:$E$72)))=0,"",INDEX('Price History'!$E$6:$E$72,SUMPRODUCT(MAX(('Price History'!$B$6:$B$72=$B12)*('Price History'!$C$6:$C$72=$C12)*('Price History'!$D$6:$D$72<=MIN(DATE(2026,12,31),'Price Analysis'!$C$4))*ROW('Price History'!$E$6:$E$72)))-5)) -> 12.99
B13: ESPN Select | C13: Standard w/ ads | D13: Ad-supported | E13: =IF(SUMPRODUCT(MAX(('Price History'!$B$6:$B$72=$B13)*('Price History'!$C$6:$C$72=$C13)*('Price History'!$D$6:$D$72<=MIN(DATE(2019,12,31),'Price Analysis'!$C$4))*ROW('Price History'!$E$6:$E$72)))=0,"",INDEX('Price History'!$E$6:$E$72,SUMPRODUCT(MAX(('Price History'!$B$6:$B$72=$B13)*('Price History'!$C$6:$C$72=$C13)*('Price History'!$D$6:$D$72<=MIN(DATE(2019,12,31),'Price Analysis'!$C$4))*ROW('Price History'!$E$6:$E$72)))-5)) -> 4.99 | F13: =IF(SUMPRODUCT(MAX(('Price History'!$B$6:$B$72=$B13)*('Price History'!$C$6:$C$72=$C13)*('Price History'!$D$6:$D$72<=MIN(DATE(2020,12,31),'Price Analysis'!$C$4))*ROW('Price History'!$E$6:$E$72)))=0,"",INDEX('Price History'!$E$6:$E$72,SUMPRODUCT(MAX(('Price History'!$B$6:$B$72=$B13)*('Price History'!$C$6:$C$72=$C13)*('Price History'!$D$6:$D$72<=MIN(DATE(2020,12,31),'Price Analysis'!$C$4))*ROW('Price History'!$E$6:$E$72)))-5)) -> 5.99 | G13: =IF(SUMPRODUCT(MAX(('Price History'!$B$6:$B$72=$B13)*('Price History'!$C$6:$C$72=$C13)*('Price History'!$D$6:$D$72<=MIN(DATE(2021,12,31),'Price Analysis'!$C$4))*ROW('Price History'!$E$6:$E$72)))=0,"",INDEX('Price History'!$E$6:$E$72,SUMPRODUCT(MAX(('Price History'!$B$6:$B$72=$B13)*('Price History'!$C$6:$C$72=$C13)*('Price History'!$D$6:$D$72<=MIN(DATE(2021,12,31),'Price Analysis'!$C$4))*ROW('Price History'!$E$6:$E$72)))-5)) -> 6.99 | H13: =IF(SUMPRODUCT(MAX(('Price History'!$B$6:$B$72=$B13)*('Price History'!$C$6:$C$72=$C13)*('Price History'!$D$6:$D$72<=MIN(DATE(2022,12,31),'Price Analysis'!$C$4))*ROW('Price History'!$E$6:$E$72)))=0,"",INDEX('Price History'!$E$6:$E$72,SUMPRODUCT(MAX(('Price History'!$B$6:$B$72=$B13)*('Price History'!$C$6:$C$72=$C13)*('Price History'!$D$6:$D$72<=MIN(DATE(2022,12,31),'Price Analysis'!$C$4))*ROW('Price History'!$E$6:$E$72)))-5)) -> 9.99 | I13: =IF(SUMPRODUCT(MAX(('Price History'!$B$6:$B$72=$B13)*('Price History'!$C$6:$C$72=$C13)*('Price History'!$D$6:$D$72<=MIN(DATE(2023,12,31),'Price Analysis'!$C$4))*ROW('Price History'!$E$6:$E$72)))=0,"",INDEX('Price History'!$E$6:$E$72,SUMPRODUCT(MAX(('Price History'!$B$6:$B$72=$B13)*('Price History'!$C$6:$C$72=$C13)*('Price History'!$D$6:$D$72<=MIN(DATE(2023,12,31),'Price Analysis'!$C$4))*ROW('Price History'!$E$6:$E$72)))-5)) -> 10.99 | J13: =IF(SUMPRODUCT(MAX(('Price History'!$B$6:$B$72=$B13)*('Price History'!$C$6:$C$72=$C13)*('Price History'!$D$6:$D$72<=MIN(DATE(2024,12,31),'Price Analysis'!$C$4))*ROW('Price History'!$E$6:$E$72)))=0,"",INDEX('Price History'!$E$6:$E$72,SUMPRODUCT(MAX(('Price History'!$B$6:$B$72=$B13)*('Price History'!$C$6:$C$72=$C13)*('Price History'!$D$6:$D$72<=MIN(DATE(2024,12,31),'Price Analysis'!$C$4))*ROW('Price History'!$E$6:$E$72)))-5)) -> 11.99 | K13: =IF(SUMPRODUCT(MAX(('Price History'!$B$6:$B$72=$B13)*('Price History'!$C$6:$C$72=$C13)*('Price History'!$D$6:$D$72<=MIN(DATE(2025,12,31),'Price Analysis'!$C$4))*ROW('Price History'!$E$6:$E$72)))=0,"",INDEX('Price History'!$E$6:$E$72,SUMPRODUCT(MAX(('Price History'!$B$6:$B$72=$B13)*('Price History'!$C$6:$C$72=$C13)*('Price History'!$D$6:$D$72<=MIN(DATE(2025,12,31),'Price Analysis'!$C$4))*ROW('Price History'!$E$6:$E$72)))-5)) -> 12.99 | L13: =IF(SUMPRODUCT(MAX(('Price History'!$B$6:$B$72=$B13)*('Price History'!$C$6:$C$72=$C13)*('Price History'!$D$6:$D$72<=MIN(DATE(2026,12,31),'Price Analysis'!$C$4))*ROW('Price History'!$E$6:$E$72)))=0,"",INDEX('Price History'!$E$6:$E$72,SUMPRODUCT(MAX(('Price History'!$B$6:$B$72=$B13)*('Price History'!$C$6:$C$72=$C13)*('Price History'!$D$6:$D$72<=MIN(DATE(2026,12,31),'Price Analysis'!$C$4))*ROW('Price History'!$E$6:$E$72)))-5)) -> 12.99
B14: Netflix | C14: Standard w/ ads | D14: Ad-supported | E14: =IF(SUMPRODUCT(MAX(('Price History'!$B$6:$B$72=$B14)*('Price History'!$C$6:$C$72=$C14)*('Price History'!$D$6:$D$72<=MIN(DATE(2019,12,31),'Price Analysis'!$C$4))*ROW('Price History'!$E$6:$E$72)))=0,"",INDEX('Price History'!$E$6:$E$72,SUMPRODUCT(MAX(('Price History'!$B$6:$B$72=$B14)*('Price History'!$C$6:$C$72=$C14)*('Price History'!$D$6:$D$72<=MIN(DATE(2019,12,31),'Price Analysis'!$C$4))*ROW('Price History'!$E$6:$E$72)))-5)) | F14: =IF(SUMPRODUCT(MAX(('Price History'!$B$6:$B$72=$B14)*('Price History'!$C$6:$C$72=$C14)*('Price History'!$D$6:$D$72<=MIN(DATE(2020,12,31),'Price Analysis'!$C$4))*ROW('Price History'!$E$6:$E$72)))=0,"",INDEX('Price History'!$E$6:$E$72,SUMPRODUCT(MAX(('Price History'!$B$6:$B$72=$B14)*('Price History'!$C$6:$C$72=$C14)*('Price History'!$D$6:$D$72<=MIN(DATE(2020,12,31),'Price Analysis'!$C$4))*ROW('Price History'!$E$6:$E$72)))-5)) | G14: =IF(SUMPRODUCT(MAX(('Price History'!$B$6:$B$72=$B14)*('Price History'!$C$6:$C$72=$C14)*('Price History'!$D$6:$D$72<=MIN(DATE(2021,12,31),'Price Analysis'!$C$4))*ROW('Price History'!$E$6:$E$72)))=0,"",INDEX('Price History'!$E$6:$E$72,SUMPRODUCT(MAX(('Price History'!$B$6:$B$72=$B14)*('Price History'!$C$6:$C$72=$C14)*('Price History'!$D$6:$D$72<=MIN(DATE(2021,12,31),'Price Analysis'!$C$4))*ROW('Price History'!$E$6:$E$72)))-5)) | H14: =IF(SUMPRODUCT(MAX(('Price History'!$B$6:$B$72=$B14)*('Price History'!$C$6:$C$72=$C14)*('Price History'!$D$6:$D$72<=MIN(DATE(2022,12,31),'Price Analysis'!$C$4))*ROW('Price History'!$E$6:$E$72)))=0,"",INDEX('Price History'!$E$6:$E$72,SUMPRODUCT(MAX(('Price History'!$B$6:$B$72=$B14)*('Price History'!$C$6:$C$72=$C14)*('Price History'!$D$6:$D$72<=MIN(DATE(2022,12,31),'Price Analysis'!$C$4))*ROW('Price History'!$E$6:$E$72)))-5)) -> 6.99 | I14: =IF(SUMPRODUCT(MAX(('Price History'!$B$6:$B$72=$B14)*('Price History'!$C$6:$C$72=$C14)*('Price History'!$D$6:$D$72<=MIN(DATE(2023,12,31),'Price Analysis'!$C$4))*ROW('Price History'!$E$6:$E$72)))=0,"",INDEX('Price History'!$E$6:$E$72,SUMPRODUCT(MAX(('Price History'!$B$6:$B$72=$B14)*('Price History'!$C$6:$C$72=$C14)*('Price History'!$D$6:$D$72<=MIN(DATE(2023,12,31),'Price Analysis'!$C$4))*ROW('Price History'!$E$6:$E$72)))-5)) -> 6.99 | J14: =IF(SUMPRODUCT(MAX(('Price History'!$B$6:$B$72=$B14)*('Price History'!$C$6:$C$72=$C14)*('Price History'!$D$6:$D$72<=MIN(DATE(2024,12,31),'Price Analysis'!$C$4))*ROW('Price History'!$E$6:$E$72)))=0,"",INDEX('Price History'!$E$6:$E$72,SUMPRODUCT(MAX(('Price History'!$B$6:$B$72=$B14)*('Price History'!$C$6:$C$72=$C14)*('Price History'!$D$6:$D$72<=MIN(DATE(2024,12,31),'Price Analysis'!$C$4))*ROW('Price History'!$E$6:$E$72)))-5)) -> 6.99 | K14: =IF(SUMPRODUCT(MAX(('Price History'!$B$6:$B$72=$B14)*('Price History'!$C$6:$C$72=$C14)*('Price History'!$D$6:$D$72<=MIN(DATE(2025,12,31),'Price Analysis'!$C$4))*ROW('Price History'!$E$6:$E$72)))=0,"",INDEX('Price History'!$E$6:$E$72,SUMPRODUCT(MAX(('Price History'!$B$6:$B$72=$B14)*('Price History'!$C$6:$C$72=$C14)*('Price History'!$D$6:$D$72<=MIN(DATE(2025,12,31),'Price Analysis'!$C$4))*ROW('Price History'!$E$6:$E$72)))-5)) -> 7.99 | L14: =IF(SUMPRODUCT(MAX(('Price History'!$B$6:$B$72=$B14)*('Price History'!$C$6:$C$72=$C14)*('Price History'!$D$6:$D$72<=MIN(DATE(2026,12,31),'Price Analysis'!$C$4))*ROW('Price History'!$E$6:$E$72)))=0,"",INDEX('Price History'!$E$6:$E$72,SUMPRODUCT(MAX(('Price History'!$B$6:$B$72=$B14)*('Price History'!$C$6:$C$72=$C14)*('Price History'!$D$6:$D$72<=MIN(DATE(2026,12,31),'Price Analysis'!$C$4))*ROW('Price History'!$E$6:$E$72)))-5)) -> 8.99
B15: Disney+ | C15: Basic w/ ads | D15: Ad-supported | E15: =IF(SUMPRODUCT(MAX(('Price History'!$B$6:$B$72=$B15)*('Price History'!$C$6:$C$72=$C15)*('Price History'!$D$6:$D$72<=MIN(DATE(2019,12,31),'Price Analysis'!$C$4))*ROW('Price History'!$E$6:$E$72)))=0,"",INDEX('Price History'!$E$6:$E$72,SUMPRODUCT(MAX(('Price History'!$B$6:$B$72=$B15)*('Price History'!$C$6:$C$72=$C15)*('Price History'!$D$6:$D$72<=MIN(DATE(2019,12,31),'Price Analysis'!$C$4))*ROW('Price History'!$E$6:$E$72)))-5)) | F15: =IF(SUMPRODUCT(MAX(('Price History'!$B$6:$B$72=$B15)*('Price History'!$C$6:$C$72=$C15)*('Price History'!$D$6:$D$72<=MIN(DATE(2020,12,31),'Price Analysis'!$C$4))*ROW('Price History'!$E$6:$E$72)))=0,"",INDEX('Price History'!$E$6:$E$72,SUMPRODUCT(MAX(('Price History'!$B$6:$B$72=$B15)*('Price History'!$C$6:$C$72=$C15)*('Price History'!$D$6:$D$72<=MIN(DATE(2020,12,31),'Price Analysis'!$C$4))*ROW('Price History'!$E$6:$E$72)))-5)) | G15: =IF(SUMPRODUCT(MAX(('Price History'!$B$6:$B$72=$B15)*('Price History'!$C$6:$C$72=$C15)*('Price History'!$D$6:$D$72<=MIN(DATE(2021,12,31),'Price Analysis'!$C$4))*ROW('Price History'!$E$6:$E$72)))=0,"",INDEX('Price History'!$E$6:$E$72,SUMPRODUCT(MAX(('Price History'!$B$6:$B$72=$B15)*('Price History'!$C$6:$C$72=$C15)*('Price History'!$D$6:$D$72<=MIN(DATE(2021,12,31),'Price Analysis'!$C$4))*ROW('Price History'!$E$6:$E$72)))-5)) | H15: =IF(SUMPRODUCT(MAX(('Price History'!$B$6:$B$72=$B15)*('Price History'!$C$6:$C$72=$C15)*('Price History'!$D$6:$D$72<=MIN(DATE(2022,12,31),'Price Analysis'!$C$4))*ROW('Price History'!$E$6:$E$72)))=0,"",INDEX('Price History'!$E$6:$E$72,SUMPRODUCT(MAX(('Price History'!$B$6:$B$72=$B15)*('Price History'!$C$6:$C$72=$C15)*('Price History'!$D$6:$D$72<=MIN(DATE(2022,12,31),'Price Analysis'!$C$4))*ROW('Price History'!$E$6:$E$72)))-5)) -> 7.99 | I15: =IF(SUMPRODUCT(MAX(('Price History'!$B$6:$B$72=$B15)*('Price History'!$C$6:$C$72=$C15)*('Price History'!$D$6:$D$72<=MIN(DATE(2023,12,31),'Price Analysis'!$C$4))*ROW('Price History'!$E$6:$E$72)))=0,"",INDEX('Price History'!$E$6:$E$72,SUMPRODUCT(MAX(('Price History'!$B$6:$B$72=$B15)*('Price History'!$C$6:$C$72=$C15)*('Price History'!$D$6:$D$72<=MIN(DATE(2023,12,31),'Price Analysis'!$C$4))*ROW('Price History'!$E$6:$E$72)))-5)) -> 7.99 | J15: =IF(SUMPRODUCT(MAX(('Price History'!$B$6:$B$72=$B15)*('Price History'!$C$6:$C$72=$C15)*('Price History'!$D$6:$D$72<=MIN(DATE(2024,12,31),'Price Analysis'!$C$4))*ROW('Price History'!$E$6:$E$72)))=0,"",INDEX('Price History'!$E$6:$E$72,SUMPRODUCT(MAX(('Price History'!$B$6:$B$72=$B15)*('Price History'!$C$6:$C$72=$C15)*('Price History'!$D$6:$D$72<=MIN(DATE(2024,12,31),'Price Analysis'!$C$4))*ROW('Price History'!$E$6:$E$72)))-5)) -> 9.99 | K15: =IF(SUMPRODUCT(MAX(('Price History'!$B$6:$B$72=$B15)*('Price History'!$C$6:$C$72=$C15)*('Price History'!$D$6:$D$72<=MIN(DATE(2025,12,31),'Price Analysis'!$C$4))*ROW('Price History'!$E$6:$E$72)))=0,"",INDEX('Price History'!$E$6:$E$72,SUMPRODUCT(MAX(('Price History'!$B$6:$B$72=$B15)*('Price History'!$C$6:$C$72=$C15)*('Price History'!$D$6:$D$72<=MIN(DATE(2025,12,31),'Price Analysis'!$C$4))*ROW('Price History'!$E$6:$E$72)))-5)) -> 11.99 | L15: =IF(SUMPRODUCT(MAX(('Price History'!$B$6:$B$72=$B15)*('Price History'!$C$6:$C$72=$C15)*('Price History'!$D$6:$D$72<=MIN(DATE(2026,12,31),'Price Analysis'!$C$4))*ROW('Price History'!$E$6:$E$72)))=0,"",INDEX('Price History'!$E$6:$E$72,SUMPRODUCT(MAX(('Price History'!$B$6:$B$72=$B15)*('Price History'!$C$6:$C$72=$C15)*('Price History'!$D$6:$D$72<=MIN(DATE(2026,12,31),'Price Analysis'!$C$4))*ROW('Price History'!$E$6:$E$72)))-5)) -> 11.99
B16: Hulu | C16: With ads | D16: Ad-supported | E16: =IF(SUMPRODUCT(MAX(('Price History'!$B$6:$B$72=$B16)*('Price History'!$C$6:$C$72=$C16)*('Price History'!$D$6:$D$72<=MIN(DATE(2019,12,31),'Price Analysis'!$C$4))*ROW('Price History'!$E$6:$E$72)))=0,"",INDEX('Price History'!$E$6:$E$72,SUMPRODUCT(MAX(('Price History'!$B$6:$B$72=$B16)*('Price History'!$C$6:$C$72=$C16)*('Price History'!$D$6:$D$72<=MIN(DATE(2019,12,31),'Price Analysis'!$C$4))*ROW('Price History'!$E$6:$E$72)))-5)) -> 5.99 | F16: =IF(SUMPRODUCT(MAX(('Price History'!$B$6:$B$72=$B16)*('Price History'!$C$6:$C$72=$C16)*('Price History'!$D$6:$D$72<=MIN(DATE(2020,12,31),'Price Analysis'!$C$4))*ROW('Price History'!$E$6:$E$72)))=0,"",INDEX('Price History'!$E$6:$E$72,SUMPRODUCT(MAX(('Price History'!$B$6:$B$72=$B16)*('Price History'!$C$6:$C$72=$C16)*('Price History'!$D$6:$D$72<=MIN(DATE(2020,12,31),'Price Analysis'!$C$4))*ROW('Price History'!$E$6:$E$72)))-5)) -> 5.99 | G16: =IF(SUMPRODUCT(MAX(('Price History'!$B$6:$B$72=$B16)*('Price History'!$C$6:$C$72=$C16)*('Price History'!$D$6:$D$72<=MIN(DATE(2021,12,31),'Price Analysis'!$C$4))*ROW('Price History'!$E$6:$E$72)))=0,"",INDEX('Price History'!$E$6:$E$72,SUMPRODUCT(MAX(('Price History'!$B$6:$B$72=$B16)*('Price History'!$C$6:$C$72=$C16)*('Price History'!$D$6:$D$72<=MIN(DATE(2021,12,31),'Price Analysis'!$C$4))*ROW('Price History'!$E$6:$E$72)))-5)) -> 6.99 | H16: =IF(SUMPRODUCT(MAX(('Price History'!$B$6:$B$72=$B16)*('Price History'!$C$6:$C$72=$C16)*('Price History'!$D$6:$D$72<=MIN(DATE(2022,12,31),'Price Analysis'!$C$4))*ROW('Price History'!$E$6:$E$72)))=0,"",INDEX('Price History'!$E$6:$E$72,SUMPRODUCT(MAX(('Price History'!$B$6:$B$72=$B16)*('Price History'!$C$6:$C$72=$C16)*('Price History'!$D$6:$D$72<=MIN(DATE(2022,12,31),'Price Analysis'!$C$4))*ROW('Price History'!$E$6:$E$72)))-5)) -> 7.99 | I16: =IF(SUMPRODUCT(MAX(('Price History'!$B$6:$B$72=$B16)*('Price History'!$C$6:$C$72=$C16)*('Price History'!$D$6:$D$72<=MIN(DATE(2023,12,31),'Price Analysis'!$C$4))*ROW('Price History'!$E$6:$E$72)))=0,"",INDEX('Price History'!$E$6:$E$72,SUMPRODUCT(MAX(('Price History'!$B$6:$B$72=$B16)*('Price History'!$C$6:$C$72=$C16)*('Price History'!$D$6:$D$72<=MIN(DATE(2023,12,31),'Price Analysis'!$C$4))*ROW('Price History'!$E$6:$E$72)))-5)) -> 7.99 | J16: =IF(SUMPRODUCT(MAX(('Price History'!$B$6:$B$72=$B16)*('Price History'!$C$6:$C$72=$C16)*('Price History'!$D$6:$D$72<=MIN(DATE(2024,12,31),'Price Analysis'!$C$4))*ROW('Price History'!$E$6:$E$72)))=0,"",INDEX('Price History'!$E$6:$E$72,SUMPRODUCT(MAX(('Price History'!$B$6:$B$72=$B16)*('Price History'!$C$6:$C$72=$C16)*('Price History'!$D$6:$D$72<=MIN(DATE(2024,12,31),'Price Analysis'!$C$4))*ROW('Price History'!$E$6:$E$72)))-5)) -> 9.99 | K16: =IF(SUMPRODUCT(MAX(('Price History'!$B$6:$B$72=$B16)*('Price History'!$C$6:$C$72=$C16)*('Price History'!$D$6:$D$72<=MIN(DATE(2025,12,31),'Price Analysis'!$C$4))*ROW('Price History'!$E$6:$E$72)))=0,"",INDEX('Price History'!$E$6:$E$72,SUMPRODUCT(MAX(('Price History'!$B$6:$B$72=$B16)*('Price History'!$C$6:$C$72=$C16)*('Price History'!$D$6:$D$72<=MIN(DATE(2025,12,31),'Price Analysis'!$C$4))*ROW('Price History'!$E$6:$E$72)))-5)) -> 11.99 | L16: =IF(SUMPRODUCT(MAX(('Price History'!$B$6:$B$72=$B16)*('Price History'!$C$6:$C$72=$C16)*('Price History'!$D$6:$D$72<=MIN(DATE(2026,12,31),'Price Analysis'!$C$4))*ROW('Price History'!$E$6:$E$72)))=0,"",INDEX('Price History'!$E$6:$E$72,SUMPRODUCT(MAX(('Price History'!$B$6:$B$72=$B16)*('Price History'!$C$6:$C$72=$C16)*('Price History'!$D$6:$D$72<=MIN(DATE(2026,12,31),'Price Analysis'!$C$4))*ROW('Price History'!$E$6:$E$72)))-5)) -> 11.99
B17: HBO Max | C17: Basic w/ ads | D17: Ad-supported | E17: =IF(SUMPRODUCT(MAX(('Price History'!$B$6:$B$72=$B17)*('Price History'!$C$6:$C$72=$C17)*('Price History'!$D$6:$D$72<=MIN(DATE(2019,12,31),'Price Analysis'!$C$4))*ROW('Price History'!$E$6:$E$72)))=0,"",INDEX('Price History'!$E$6:$E$72,SUMPRODUCT(MAX(('Price History'!$B$6:$B$72=$B17)*('Price History'!$C$6:$C$72=$C17)*('Price History'!$D$6:$D$72<=MIN(DATE(2019,12,31),'Price Analysis'!$C$4))*ROW('Price History'!$E$6:$E$72)))-5)) | F17: =IF(SUMPRODUCT(MAX(('Price History'!$B$6:$B$72=$B17)*('Price History'!$C$6:$C$72=$C17)*('Price History'!$D$6:$D$72<=MIN(DATE(2020,12,31),'Price Analysis'!$C$4))*ROW('Price History'!$E$6:$E$72)))=0,"",INDEX('Price History'!$E$6:$E$72,SUMPRODUCT(MAX(('Price History'!$B$6:$B$72=$B17)*('Price History'!$C$6:$C$72=$C17)*('Price History'!$D$6:$D$72<=MIN(DATE(2020,12,31),'Price Analysis'!$C$4))*ROW('Price History'!$E$6:$E$72)))-5)) | G17: =IF(SUMPRODUCT(MAX(('Price History'!$B$6:$B$72=$B17)*('Price History'!$C$6:$C$72=$C17)*('Price History'!$D$6:$D$72<=MIN(DATE(2021,12,31),'Price Analysis'!$C$4))*ROW('Price History'!$E$6:$E$72)))=0,"",INDEX('Price History'!$E$6:$E$72,SUMPRODUCT(MAX(('Price History'!$B$6:$B$72=$B17)*('Price History'!$C$6:$C$72=$C17)*('Price History'!$D$6:$D$72<=MIN(DATE(2021,12,31),'Price Analysis'!$C$4))*ROW('Price History'!$E$6:$E$72)))-5)) -> 9.99 | H17: =IF(SUMPRODUCT(MAX(('Price History'!$B$6:$B$72=$B17)*('Price History'!$C$6:$C$72=$C17)*('Price History'!$D$6:$D$72<=MIN(DATE(2022,12,31),'Price Analysis'!$C$4))*ROW('Price History'!$E$6:$E$72)))=0,"",INDEX('Price History'!$E$6:$E$72,SUMPRODUCT(MAX(('Price History'!$B$6:$B$72=$B17)*('Price History'!$C$6:$C$72=$C17)*('Price History'!$D$6:$D$72<=MIN(DATE(2022,12,31),'Price Analysis'!$C$4))*ROW('Price History'!$E$6:$E$72)))-5)) -> 9.99 | I17: =IF(SUMPRODUCT(MAX(('Price History'!$B$6:$B$72=$B17)*('Price History'!$C$6:$C$72=$C17)*('Price History'!$D$6:$D$72<=MIN(DATE(2023,12,31),'Price Analysis'!$C$4))*ROW('Price History'!$E$6:$E$72)))=0,"",INDEX('Price History'!$E$6:$E$72,SUMPRODUCT(MAX(('Price History'!$B$6:$B$72=$B17)*('Price History'!$C$6:$C$72=$C17)*('Price History'!$D$6:$D$72<=MIN(DATE(2023,12,31),'Price Analysis'!$C$4))*ROW('Price History'!$E$6:$E$72)))-5)) -> 9.99 | J17: =IF(SUMPRODUCT(MAX(('Price History'!$B$6:$B$72=$B17)*('Price History'!$C$6:$C$72=$C17)*('Price History'!$D$6:$D$72<=MIN(DATE(2024,12,31),'Price Analysis'!$C$4))*ROW('Price History'!$E$6:$E$72)))=0,"",INDEX('Price History'!$E$6:$E$72,SUMPRODUCT(MAX(('Price History'!$B$6:$B$72=$B17)*('Price History'!$C$6:$C$72=$C17)*('Price History'!$D$6:$D$72<=MIN(DATE(2024,12,31),'Price Analysis'!$C$4))*ROW('Price History'!$E$6:$E$72)))-5)) -> 9.99 | K17: =IF(SUMPRODUCT(MAX(('Price History'!$B$6:$B$72=$B17)*('Price History'!$C$6:$C$72=$C17)*('Price History'!$D$6:$D$72<=MIN(DATE(2025,12,31),'Price Analysis'!$C$4))*ROW('Price History'!$E$6:$E$72)))=0,"",INDEX('Price History'!$E$6:$E$72,SUMPRODUCT(MAX(('Price History'!$B$6:$B$72=$B17)*('Price History'!$C$6:$C$72=$C17)*('Price History'!$D$6:$D$72<=MIN(DATE(2025,12,31),'Price Analysis'!$C$4))*ROW('Price History'!$E$6:$E$72)))-5)) -> 10.99 | L17: =IF(SUMPRODUCT(MAX(('Price History'!$B$6:$B$72=$B17)*('Price History'!$C$6:$C$72=$C17)*('Price History'!$D$6:$D$72<=MIN(DATE(2026,12,31),'Price Analysis'!$C$4))*ROW('Price History'!$E$6:$E$72)))=0,"",INDEX('Price History'!$E$6:$E$72,SUMPRODUCT(MAX(('Price History'!$B$6:$B$72=$B17)*('Price History'!$C$6:$C$72=$C17)*('Price History'!$D$6:$D$72<=MIN(DATE(2026,12,31),'Price Analysis'!$C$4))*ROW('Price History'!$E$6:$E$72)))-5)) -> 10.99
... B19: Paramount+ | C19: Essential w/ ads | D19: Ad-supported | E19: =IF(SUMPRODUCT(MAX(('Price History'!$B$6:$B$72=$B19)*('Price History'!$C$6:$C$72=$C19)*('Price History'!$D$6:$D$72<=MIN(DATE(2019,12,31),'Price Analysis'!$C$4))*ROW('Price History'!$E$6:$E$72)))=0,"",INDEX('Price History'!$E$6:$E$72,SUMPRODUCT(MAX(('Price History'!$B$6:$B$72=$B19)*('Price History'!$C$6:$C$72=$C19)*('Price History'!$D$6:$D$72<=MIN(DATE(2019,12,31),'Price Analysis'!$C$4))*ROW('Price History'!$E$6:$E$72)))-5)) | F19: =IF(SUMPRODUCT(MAX(('Price History'!$B$6:$B$72=$B19)*('Price History'!$C$6:$C$72=$C19)*('Price History'!$D$6:$D$72<=MIN(DATE(2020,12,31),'Price Analysis'!$C$4))*ROW('Price History'!$E$6:$E$72)))=0,"",INDEX('Price History'!$E$6:$E$72,SUMPRODUCT(MAX(('Price History'!$B$6:$B$72=$B19)*('Price History'!$C$6:$C$72=$C19)*('Price History'!$D$6:$D$72<=MIN(DATE(2020,12,31),'Price Analysis'!$C$4))*ROW('Price History'!$E$6:$E$72)))-5)) | G19: =IF(SUMPRODUCT(MAX(('Price History'!$B$6:$B$72=$B19)*('Price History'!$C$6:$C$72=$C19)*('Price History'!$D$6:$D$72<=MIN(DATE(2021,12,31),'Price Analysis'!$C$4))*ROW('Price History'!$E$6:$E$72)))=0,"",INDEX('Price History'!$E$6:$E$72,SUMPRODUCT(MAX(('Price History'!$B$6:$B$72=$B19)*('Price History'!$C$6:$C$72=$C19)*('Price History'!$D$6:$D$72<=MIN(DATE(2021,12,31),'Price Analysis'!$C$4))*ROW('Price History'!$E$6:$E$72)))-5)) -> 4.99 | H19: =IF(SUMPRODUCT(MAX(('Price History'!$B$6:$B$72=$B19)*('Price History'!$C$6:$C$72=$C19)*('Price History'!$D$6:$D$72<=MIN(DATE(2022,12,31),'Price Analysis'!$C$4))*ROW('Price History'!$E$6:$E$72)))=0,"",INDEX('Price History'!$E$6:$E$72,SUMPRODUCT(MAX(('Price History'!$B$6:$B$72=$B19)*('Price History'!$C$6:$C$72=$C19)*('Price History'!$D$6:$D$72<=MIN(DATE(2022,12,31),'Price Analysis'!$C$4))*ROW('Price History'!$E$6:$E$72)))-5)) -> 4.99 | I19: =IF(SUMPRODUCT(MAX(('Price History'!$B$6:$B$72=$B19)*('Price History'!$C$6:$C$72=$C19)*('Price History'!$D$6:$D$72<=MIN(DATE(2023,12,31),'Price Analysis'!$C$4))*ROW('Price History'!$E$6:$E$72)))=0,"",INDEX('Price History'!$E$6:$E$72,SUMPRODUCT(MAX(('Price History'!$B$6:$B$72=$B19)*('Price History'!$C$6:$C$72=$C19)*('Price History'!$D$6:$D$72<=MIN(DATE(2023,12,31),'Price Analysis'!$C$4))*ROW('Price History'!$E$6:$E$72)))-5)) -> 5.99 | J19: =IF(SUMPRODUCT(MAX(('Price History'!$B$6:$B$72=$B19)*('Price History'!$C$6:$C$72=$C19)*('Price History'!$D$6:$D$72<=MIN(DATE(2024,12,31),'Price Analysis'!$C$4))*ROW('Price History'!$E$6:$E$72)))=0,"",INDEX('Price History'!$E$6:$E$72,SUMPRODUCT(MAX(('Price History'!$B$6:$B$72=$B19)*('Price History'!$C$6:$C$72=$C19)*('Price History'!$D$6:$D$72<=MIN(DATE(2024,12,31),'Price Analysis'!$C$4))*ROW('Price History'!$E$6:$E$72)))-5)) -> 7.99 | K19: =IF(SUMPRODUCT(MAX(('Price History'!$B$6:$B$72=$B19)*('Price History'!$C$6:$C$72=$C19)*('Price History'!$D$6:$D$72<=MIN(DATE(2025,12,31),'Price Analysis'!$C$4))*ROW('Price History'!$E$6:$E$72)))=0,"",INDEX('Price History'!$E$6:$E$72,SUMPRODUCT(MAX(('Price History'!$B$6:$B$72=$B19)*('Price History'!$C$6:$C$72=$C19)*('Price History'!$D$6:$D$72<=MIN(DATE(2025,12,31),'Price Analysis'!$C$4))*ROW('Price History'!$E$6:$E$72)))-5)) -> 7.99 | L19: =IF(SUMPRODUCT(MAX(('Price History'!$B$6:$B$72=$B19)*('Price History'!$C$6:$C$72=$C19)*('Price History'!$D$6:$D$72<=MIN(DATE(2026,12,31),'Price Analysis'!$C$4))*ROW('Price History'!$E$6:$E$72)))=0,"",INDEX('Price History'!$E$6:$E$72,SUMPRODUCT(MAX(('Price History'!$B$6:$B$72=$B19)*('Price History'!$C$6:$C$72=$C19)*('Price History'!$D$6:$D$72<=MIN(DATE(2026,12,31),'Price Analysis'!$C$4))*ROW('Price History'!$E$6:$E$72)))-5)) -> 8.99
B21: Ad-free rows are averaged on the Ad vs No-Ad tab; ESPN Select is classified Ad-supported and never enters an ad-free average.

Sheet Price Analysis
B2: Price Analysis — Flagship Tier Inflation
B3: Flagship means the ad-free consumer plan, except at ESPN Select, which has never offered one. Launch date and launch price are read from Price History and elapsed years are computed with YEARFRAC rather than typed. Windows differ by service, so read CAGR next to the launch date and alongside the median.
B4: As-of date | C4: 46232 | D4: Single input governing every current-price comparison and the 2026 column of the Panel.
B6: Service | C6: Flagship tier | D6: Launch date | E6: Launch $ | F6: Current $ | G6: Years | H6: Total % chg | I6: CAGR
B7: Netflix | C7: Standard (no ads) | D7: =INDEX('Price History'!$D$6:$D$72,MATCH(1,INDEX(('Price History'!$B$6:$B$72=$B7)*('Price History'!$C$6:$C$72=$C7),0),0)) -> 43480 | E7: =INDEX('Price History'!$E$6:$E$72,MATCH(1,INDEX(('Price History'!$B$6:$B$72=$B7)*('Price History'!$C$6:$C$72=$C7),0),0)) -> 12.99 | F7: =INDEX('Price History'!$E$6:$E$72,SUMPRODUCT(MAX(('Price History'!$B$6:$B$72=$B7)*('Price History'!$C$6:$C$72=$C7)*('Price History'!$D$6:$D$72<=$C$4)*ROW('Price History'!$E$6:$E$72))) -5) -> 19.99 | G7: =YEARFRAC(D7,$C$4,1) -> 7.5345654 | H7: =F7/E7-1 -> 0.53887606 | I7: =(F7/E7)^(1/G7)-1 -> 0.058878128
B8: Disney+ | C8: Premium (no ads) | D8: =INDEX('Price History'!$D$6:$D$72,MATCH(1,INDEX(('Price History'!$B$6:$B$72=$B8)*('Price History'!$C$6:$C$72=$C8),0),0)) -> 43781 | E8: =INDEX('Price History'!$E$6:$E$72,MATCH(1,INDEX(('Price History'!$B$6:$B$72=$B8)*('Price History'!$C$6:$C$72=$C8),0),0)) -> 6.99 | F8: =INDEX('Price History'!$E$6:$E$72,SUMPRODUCT(MAX(('Price History'!$B$6:$B$72=$B8)*('Price History'!$C$6:$C$72=$C8)*('Price History'!$D$6:$D$72<=$C$4)*ROW('Price History'!$E$6:$E$72))) -5) -> 18.99 | G8: =YEARFRAC(D8,$C$4,1) -> 6.7104723 | H8: =F8/E8-1 -> 1.7167382 | I8: =(F8/E8)^(1/G8)-1 -> 0.16059889
B9: Hulu | C9: No ads | D9: =INDEX('Price History'!$D$6:$D$72,MATCH(1,INDEX(('Price History'!$B$6:$B$72=$B9)*('Price History'!$C$6:$C$72=$C9),0),0)) -> 43466 | E9: =INDEX('Price History'!$E$6:$E$72,MATCH(1,INDEX(('Price History'!$B$6:$B$72=$B9)*('Price History'!$C$6:$C$72=$C9),0),0)) -> 11.99 | F9: =INDEX('Price History'!$E$6:$E$72,SUMPRODUCT(MAX(('Price History'!$B$6:$B$72=$B9)*('Price History'!$C$6:$C$72=$C9)*('Price History'!$D$6:$D$72<=$C$4)*ROW('Price History'!$E$6:$E$72))) -5) -> 18.99 | G9: =YEARFRAC(D9,$C$4,1) -> 7.5728953 | H9: =F9/E9-1 -> 0.58381985 | I9: =(F9/E9)^(1/G9)-1 -> 0.062603218
B10: HBO Max | C10: Standard (no ads) | D10: =INDEX('Price History'!$D$6:$D$72,MATCH(1,INDEX(('Price History'!$B$6:$B$72=$B10)*('Price History'!$C$6:$C$72=$C10),0),0)) -> 43978 | E10: =INDEX('Price History'!$E$6:$E$72,MATCH(1,INDEX(('Price History'!$B$6:$B$72=$B10)*('Price History'!$C$6:$C$72=$C10),0),0)) -> 14.99 | F10: =INDEX('Price History'!$E$6:$E$72,SUMPRODUCT(MAX(('Price History'!$B$6:$B$72=$B10)*('Price History'!$C$6:$C$72=$C10)*('Price History'!$D$6:$D$72<=$C$4)*ROW('Price History'!$E$6:$E$72))) -5) -> 18.49 | G10: =YEARFRAC(D10,$C$4,1) -> 6.1705123 | H10: =F10/E10-1 -> 0.23348899 | I10: =(F10/E10)^(1/G10)-1 -> 0.034592875
B11: Peacock | C11: Premium Plus (no ads) | D11: =INDEX('Price History'!$D$6:$D$72,MATCH(1,INDEX(('Price History'!$B$6:$B$72=$B11)*('Price History'!$C$6:$C$72=$C11),0),0)) -> 44027 | E11: =INDEX('Price History'!$E$6:$E$72,MATCH(1,INDEX(('Price History'!$B$6:$B$72=$B11)*('Price History'!$C$6:$C$72=$C11),0),0)) -> 9.99 | F11: =INDEX('Price History'!$E$6:$E$72,SUMPRODUCT(MAX(('Price History'!$B$6:$B$72=$B11)*('Price History'!$C$6:$C$72=$C11)*('Price History'!$D$6:$D$72<=$C$4)*ROW('Price History'!$E$6:$E$72))) -5) -> 16.99 | G11: =YEARFRAC(D11,$C$4,1) -> 6.0363707 | H11: =F11/E11-1 -> 0.7007007 | I11: =(F11/E11)^(1/G11)-1 -> 0.091959127
B12: Paramount+ | C12: Premium (no ads) | D12: =INDEX('Price History'!$D$6:$D$72,MATCH(1,INDEX(('Price History'!$B$6:$B$72=$B12)*('Price History'!$C$6:$C$72=$C12),0),0)) -> 44259 | E12: =INDEX('Price History'!$E$6:$E$72,MATCH(1,INDEX(('Price History'!$B$6:$B$72=$B12)*('Price History'!$C$6:$C$72=$C12),0),0)) -> 9.99 | F12: =INDEX('Price History'!$E$6:$E$72,SUMPRODUCT(MAX(('Price History'!$B$6:$B$72=$B12)*('Price History'!$C$6:$C$72=$C12)*('Price History'!$D$6:$D$72<=$C$4)*ROW('Price History'!$E$6:$E$72))) -5) -> 13.99 | G12: =YEARFRAC(D12,$C$4,1) -> 5.4030123 | H12: =F12/E12-1 -> 0.4004004 | I12: =(F12/E12)^(1/G12)-1 -> 0.064311233
B13: Apple TV | C13: Standard (no ads) | D13: =INDEX('Price History'!$D$6:$D$72,MATCH(1,INDEX(('Price History'!$B$6:$B$72=$B13)*('Price History'!$C$6:$C$72=$C13),0),0)) -> 43770 | E13: =INDEX('Price History'!$E$6:$E$72,MATCH(1,INDEX(('Price History'!$B$6:$B$72=$B13)*('Price History'!$C$6:$C$72=$C13),0),0)) -> 4.99 | F13: =INDEX('Price History'!$E$6:$E$72,SUMPRODUCT(MAX(('Price History'!$B$6:$B$72=$B13)*('Price History'!$C$6:$C$72=$C13)*('Price History'!$D$6:$D$72<=$C$4)*ROW('Price History'!$E$6:$E$72))) -5) -> 12.99 | G13: =YEARFRAC(D13,$C$4,1) -> 6.7405886 | H13: =F13/E13-1 -> 1.6032064 | I13: =(F13/E13)^(1/G13)-1 -> 0.15250489
B14: ESPN Select | C14: Standard w/ ads | D14: =INDEX('Price History'!$D$6:$D$72,MATCH(1,INDEX(('Price History'!$B$6:$B$72=$B14)*('Price History'!$C$6:$C$72=$C14),0),0)) -> 43202 | E14: =INDEX('Price History'!$E$6:$E$72,MATCH(1,INDEX(('Price History'!$B$6:$B$72=$B14)*('Price History'!$C$6:$C$72=$C14),0),0)) -> 4.99 | F14: =INDEX('Price History'!$E$6:$E$72,SUMPRODUCT(MAX(('Price History'!$B$6:$B$72=$B14)*('Price History'!$C$6:$C$72=$C14)*('Price History'!$D$6:$D$72<=$C$4)*ROW('Price History'!$E$6:$E$72))) -5) -> 12.99 | G14: =YEARFRAC(D14,$C$4,1) -> 8.2963188 | H14: =F14/E14-1 -> 1.6032064 | I14: =(F14/E14)^(1/G14)-1 -> 0.12223418
B15: Mean | H15: =AVERAGE(H7:H14) -> 0.92255463 | I15: =AVERAGE(I7:I14) -> 0.093460318
B16: Median | H16: =MEDIAN(H7:H14) -> 0.64226028 | I16: =MEDIAN(I7:I14) -> 0.07813518
B17: Range (min–max CAGR) | H17: =COUNT(I7:I14)&" services" -> 8 services | I17: =TEXT(MIN(I7:I14),"0.0%")&" – "&TEXT(MAX(I7:I14),"0.0%") -> 3.5% – 16.1%
B19: Common window: year-end 2022 → as-of date. All eight services were in market throughout, so this is the like-for-like comparison; the table above ranks each service on its own history.
B20: Service | C20: YE2022 $ | D20: Current $ | E20: Years | F20: Total % chg | G20: CAGR
B21: Netflix | C21: =Panel!H6 -> 15.49 | D21: =Panel!L6 -> 19.99 | E21: =YEARFRAC(DATE(2022,12,31),$C$4,1) -> 3.5761227 | F21: =D21/C21-1 -> 0.29051001 | G21: =(D21/C21)^(1/E21)-1 -> 0.073921351
B22: Disney+ | C22: =Panel!H7 -> 10.99 | D22: =Panel!L7 -> 18.99 | E22: =YEARFRAC(DATE(2022,12,31),$C$4,1) -> 3.5761227 | F22: =D22/C22-1 -> 0.72793449 | G22: =(D22/C22)^(1/E22)-1 -> 0.16525329
B23: Hulu | C23: =Panel!H8 -> 14.99 | D23: =Panel!L8 -> 18.99 | E23: =YEARFRAC(DATE(2022,12,31),$C$4,1) -> 3.5761227 | F23: =D23/C23-1 -> 0.26684456 | G23: =(D23/C23)^(1/E23)-1 -> 0.068377612
B24: HBO Max | C24: =Panel!H9 -> 14.99 | D24: =Panel!L9 -> 18.49 | E24: =YEARFRAC(DATE(2022,12,31),$C$4,1) -> 3.5761227 | F24: =D24/C24-1 -> 0.23348899 | G24: =(D24/C24)^(1/E24)-1 -> 0.060435804
B25: Peacock | C25: =Panel!H10 -> 9.99 | D25: =Panel!L10 -> 16.99 | E25: =YEARFRAC(DATE(2022,12,31),$C$4,1) -> 3.5761227 | F25: =D25/C25-1 -> 0.7007007 | G25: =(D25/C25)^(1/E25)-1 -> 0.1600883
B26: Paramount+ | C26: =Panel!H11 -> 9.99 | D26: =Panel!L11 -> 13.99 | E26: =YEARFRAC(DATE(2022,12,31),$C$4,1) -> 3.5761227 | F26: =D26/C26-1 -> 0.4004004 | G26: =(D26/C26)^(1/E26)-1 -> 0.098744896
B27: Apple TV | C27: =Panel!H12 -> 6.99 | D27: =Panel!L12 -> 12.99 | E27: =YEARFRAC(DATE(2022,12,31),$C$4,1) -> 3.5761227 | F27: =D27/C27-1 -> 0.8583691 | G27: =(D27/C27)^(1/E27)-1 -> 0.18920859
B28: ESPN Select | C28: =Panel!H13 -> 9.99 | D28: =Panel!L13 -> 12.99 | E28: =YEARFRAC(DATE(2022,12,31),$C$4,1) -> 3.5761227 | F28: =D28/C28-1 -> 0.3003003 | G28: =(D28/C28)^(1/E28)-1 -> 0.076193366
B29: Mean | F29: =AVERAGE(F21:F28) -> 0.47231857 | G29: =AVERAGE(G21:G28) -> 0.1115279
B30: Median | F30: =MEDIAN(F21:F28) -> 0.35035035 | G30: =MEDIAN(G21:G28) -> 0.087469131
B31: CPI-U, same window | F31: ='CPI Deflator'!D13/'CPI Deflator'!D9-1 -> 0.13922537 | G31: =('CPI Deflator'!D13/'CPI Deflator'!D9)^(1/E21)-1 -> 0.037122115
B32: Ratio: category mean ÷ CPI | G32: =G29/G31 -> 3.004352
B34: Takeaway
B35: Over the common 2022–2026 window, flagship prices rose at roughly three times the rate of general inflation. The spread tracks starting position. Disney+, Apple TV and Peacock all launched cheap and have compounded fastest; HBO Max and Hulu launched at or near the category ceiling and have moved least. Treat that as a pattern across eight observations, not a market law. It also says nothing about profitability, which would need cost and margin data this workbook does not have.
B68: Source: Price History tab. Windows differ by service (5.4 to 8.3 years), so this ranks each service on its own history. See the common-window table above for the like-for-like comparison.

Sheet Real vs Nominal
B2: Real vs. Nominal — Is 'Streamflation' Real?
B3: Both endpoints are converted to constant 2019 dollars using the CPI-U index of their own period. Deflating only the current price, which is the common shortcut, overstates real growth for every service that launched after 2019.
B5: Service | C5: Launch yr | D5: Launch $ nominal | E5: Launch $ real (2019) | F5: Current $ nominal | G5: Current $ real (2019) | H5: Nominal % chg | I5: Real % chg
B6: ='Price Analysis'!B7 -> Netflix | C6: =YEAR('Price Analysis'!D7) -> 2019 | D6: ='Price Analysis'!E7 -> 12.99 | E6: =D6/(INDEX('CPI Deflator'!$D$6:$D$14,MATCH(C6,'CPI Deflator'!$B$6:$B$14,0))/100) -> 12.99 | F6: ='Price Analysis'!F7 -> 19.99 | G6: =F6/('CPI Deflator'!$D$13/100) -> 15.328685 | H6: =F6/D6-1 -> 0.53887606 | I6: =G6/E6-1 -> 0.1800373
B7: ='Price Analysis'!B8 -> Disney+ | C7: =YEAR('Price Analysis'!D8) -> 2019 | D7: ='Price Analysis'!E8 -> 6.99 | E7: =D7/(INDEX('CPI Deflator'!$D$6:$D$14,MATCH(C7,'CPI Deflator'!$B$6:$B$14,0))/100) -> 6.99 | F7: ='Price Analysis'!F8 -> 18.99 | G7: =F7/('CPI Deflator'!$D$13/100) -> 14.561867 | H7: =F7/D7-1 -> 1.7167382 | I7: =G7/E7-1 -> 1.0832428
B8: ='Price Analysis'!B9 -> Hulu | C8: =YEAR('Price Analysis'!D9) -> 2019 | D8: ='Price Analysis'!E9 -> 11.99 | E8: =D8/(INDEX('CPI Deflator'!$D$6:$D$14,MATCH(C8,'CPI Deflator'!$B$6:$B$14,0))/100) -> 11.99 | F8: ='Price Analysis'!F9 -> 18.99 | G8: =F8/('CPI Deflator'!$D$13/100) -> 14.561867 | H8: =F8/D8-1 -> 0.58381985 | I8: =G8/E8-1 -> 0.21450099
B9: ='Price Analysis'!B10 -> HBO Max | C9: =YEAR('Price Analysis'!D10) -> 2020 | D9: ='Price Analysis'!E10 -> 14.99 | E9: =D9/(INDEX('CPI Deflator'!$D$6:$D$14,MATCH(C9,'CPI Deflator'!$B$6:$B$14,0))/100) -> 14.807324 | F9: ='Price Analysis'!F10 -> 18.49 | G9: =F9/('CPI Deflator'!$D$13/100) -> 14.178458 | H9: =F9/D9-1 -> 0.23348899 | I9: =G9/E9-1 -> -0.042469947
B10: ='Price Analysis'!B11 -> Peacock | C10: =YEAR('Price Analysis'!D11) -> 2020 | D10: ='Price Analysis'!E11 -> 9.99 | E10: =D10/(INDEX('CPI Deflator'!$D$6:$D$14,MATCH(C10,'CPI Deflator'!$B$6:$B$14,0))/100) -> 9.8682569 | F10: ='Price Analysis'!F11 -> 16.99 | G10: =F10/('CPI Deflator'!$D$13/100) -> 13.028232 | H10: =F10/D10-1 -> 0.7007007 | I10: =G10/E10-1 -> 0.3202161
B11: ='Price Analysis'!B12 -> Paramount+ | C11: =YEAR('Price Analysis'!D12) -> 2021 | D11: ='Price Analysis'!E12 -> 9.99 | E11: =D11/(INDEX('CPI Deflator'!$D$6:$D$14,MATCH(C11,'CPI Deflator'!$B$6:$B$14,0))/100) -> 9.4254472 | F11: ='Price Analysis'!F12 -> 13.99 | G11: =F11/('CPI Deflator'!$D$13/100) -> 10.727779 | H11: =F11/D11-1 -> 0.4004004 | I11: =G11/E11-1 -> 0.13817186
B12: ='Price Analysis'!B13 -> Apple TV | C12: =YEAR('Price Analysis'!D13) -> 2019 | D12: ='Price Analysis'!E13 -> 4.99 | E12: =D12/(INDEX('CPI Deflator'!$D$6:$D$14,MATCH(C12,'CPI Deflator'!$B$6:$B$14,0))/100) -> 4.99 | F12: ='Price Analysis'!F13 -> 12.99 | G12: =F12/('CPI Deflator'!$D$13/100) -> 9.9609611 | H12: =F12/D12-1 -> 1.6032064 | I12: =G12/E12-1 -> 0.99618459
B13: ='Price Analysis'!B14 -> ESPN Select | C13: =YEAR('Price Analysis'!D14) -> 2018 | D13: ='Price Analysis'!E14 -> 4.99 | E13: =D13/(INDEX('CPI Deflator'!$D$6:$D$14,MATCH(C13,'CPI Deflator'!$B$6:$B$14,0))/100) -> 5.0804176 | F13: ='Price Analysis'!F14 -> 12.99 | G13: =F13/('CPI Deflator'!$D$13/100) -> 9.9609611 | H13: =F13/D13-1 -> 1.6032064 | I13: =G13/E13-1 -> 0.96065793
B14: Mean | H14: =AVERAGE(H6:H13) -> 0.92255463 | I14: =AVERAGE(I6:I13) -> 0.4813177
B15: Median | H15: =MEDIAN(H6:H13) -> 0.64226028 | I15: =MEDIAN(I6:I13) -> 0.26735855
B17: Takeaway
B18: Roughly half the headline increase survives deflation. These are real increases, not CPI drift, but they are concentrated rather than category-wide. Disney+, Apple TV and ESPN Select account for almost all of the real growth. HBO Max has gone backwards in real terms and Paramount+ has barely moved. The mean of about +48% describes almost none of the eight services individually, which is why the median sits next to it. Sustained real increases are consistent with pricing power. Proving pricing power would take volume, churn or margin evidence, and none of that is here.
B53: Source: Price History and CPI Deflator tabs. Both endpoints are deflated by the CPI-U index of their own period. The 2026 index is provisional.

Sheet Ad vs No-Ad
B2: Ad vs. No-Ad Price Divergence
B3: Both averages are AVERAGE() over the Panel rows for that year, unweighted, with the sample size shown beside each. No figure on this tab is typed.
B5: Year | C5: Avg no-ad $ | D5: n | E5: Avg ad-tier $ | F5: n | G5: Gap $ | H5: Ad as % of no-ad | I5: Discount | J5: Note
B6: 2019 | C6: =AVERAGE(Panel!E6:E12) -> 9.24 | D6: =COUNT(Panel!E6:E12) -> 4 | E6: =IFERROR(AVERAGE(Panel!E13:E19),"—") -> 5.49 | F6: =COUNT(Panel!E13:E19) -> 2 | G6: =IFERROR(C6-E6,"—") -> 3.75 | H6: =IFERROR(E6/C6,"—") -> 0.59415584 | I6: =IFERROR(1-E6/C6,"—") -> 0.40584416 | J6: Only Hulu and ESPN+ have an ad plan
B7: 2020 | C7: =AVERAGE(Panel!F6:F12) -> 10.49 | D7: =COUNT(Panel!F6:F12) -> 6 | E7: =IFERROR(AVERAGE(Panel!F13:F19),"—") -> 5.6566667 | F7: =COUNT(Panel!F13:F19) -> 3 | G7: =IFERROR(C7-E7,"—") -> 4.8333333 | H7: =IFERROR(E7/C7,"—") -> 0.53924372 | I7: =IFERROR(1-E7/C7,"—") -> 0.46075628 | J7: Peacock launches with both tiers
B8: 2021 | C8: =AVERAGE(Panel!G6:G12) -> 10.561429 | D8: =COUNT(Panel!G6:G12) -> 7 | E8: =IFERROR(AVERAGE(Panel!G13:G19),"—") -> 6.79 | F8: =COUNT(Panel!G13:G19) -> 5 | G8: =IFERROR(C8-E8,"—") -> 3.7714286 | H8: =IFERROR(E8/C8,"—") -> 0.64290545 | I8: =IFERROR(1-E8/C8,"—") -> 0.35709455 | J8: HBO Max adds an ad tier
B9: 2022 | C9: =AVERAGE(Panel!H6:H12) -> 11.918571 | D9: =COUNT(Panel!H6:H12) -> 7 | E9: =IFERROR(AVERAGE(Panel!H13:H19),"—") -> 7.5614286 | F9: =COUNT(Panel!H13:H19) -> 7 | G9: =IFERROR(C9-E9,"—") -> 4.3571429 | H9: =IFERROR(E9/C9,"—") -> 0.63442407 | I9: =IFERROR(1-E9/C9,"—") -> 0.36557593 | J9: Netflix and Disney+ launch ad tiers — all seven present
B10: 2023 | C10: =AVERAGE(Panel!I6:I12) -> 13.918571 | D10: =COUNT(Panel!I6:I12) -> 7 | E10: =IFERROR(AVERAGE(Panel!I13:I19),"—") -> 7.99 | F10: =COUNT(Panel!I13:I19) -> 7 | G10: =IFERROR(C10-E10,"—") -> 5.9285714 | H10: =IFERROR(E10/C10,"—") -> 0.57405317 | I10: =IFERROR(1-E10/C10,"—") -> 0.42594683 | J10: First broad round of no-ad increases
B11: 2024 | C11: =AVERAGE(Panel!J6:J12) -> 14.918571 | D11: =COUNT(Panel!J6:J12) -> 7 | E11: =IFERROR(AVERAGE(Panel!J13:J19),"—") -> 9.2757143 | F11: =COUNT(Panel!J13:J19) -> 7 | G11: =IFERROR(C11-E11,"—") -> 5.6428571 | H11: =IFERROR(E11/C11,"—") -> 0.6217562 | I11: =IFERROR(1-E11/C11,"—") -> 0.3782438 | J11: Both tiers rise together
B12: 2025 | C12: =AVERAGE(Panel!K6:K12) -> 16.775714 | D12: =COUNT(Panel!K6:K12) -> 7 | E12: =IFERROR(AVERAGE(Panel!K13:K19),"—") -> 10.704286 | F12: =COUNT(Panel!K13:K19) -> 7 | G12: =IFERROR(C12-E12,"—") -> 6.0714286 | H12: =IFERROR(E12/C12,"—") -> 0.63808226 | I12: =IFERROR(1-E12/C12,"—") -> 0.36191774 | J12: Largest single year of increases in the panel
B13: 2026 | C13: =AVERAGE(Panel!L6:L12) -> 17.204286 | D13: =COUNT(Panel!L6:L12) -> 7 | E13: =IFERROR(AVERAGE(Panel!L13:L19),"—") -> 10.99 | F13: =COUNT(Panel!L13:L19) -> 7 | G13: =IFERROR(C13-E13,"—") -> 6.2142857 | H13: =IFERROR(E13/C13,"—") -> 0.63879432 | I13: =IFERROR(1-E13/C13,"—") -> 0.36120568 | J13: As of the as-of date; Netflix and Paramount+ have already moved
B15: Takeaway — the ad tier is not holding the line
B16: The standard claim is that the ad tier stays cheap while no-ad prices climb, widening the discount and steering price-sensitive subscribers down rather than out. This panel does not support it. Since end-2022, with all seven ad tiers in market, the ad-supported average has risen slightly faster than the ad-free average and the implied discount has held flat near 36%. The entry point itself has nearly doubled since 2020. The dollar gap widens only because both lines are rising together off different bases. Whether ad tiers help retention is not tested here; that would need ad ARPU and cohort data. If they do help, it is not through a widening price advantage.
B53: Source: Panel tab, unweighted means. Sample size for each year is in the n columns above. 2026 is measured at the as-of date, not a full year.

Sheet Bundles
B2: Bundles — Savings Computed Against the Price Panel
B3: Bundle price vs. the sum of its components' standalone prices, both measured at the same stated date. Component prices are pulled from Price History, so each figure is reproducible. Archetypes differ in eligibility and are not averaged together as if they were one market.
B5: Bundle | C5: Archetype | D5: Priced as of | E5: Bundle $ | F5: Standalone $ | G5: Savings % | H5: Source | I5: Eligibility / caveat
B6: Disney+ / Hulu / HBO Max | C6: Streamer-to-streamer | D6: 46232 | E6: 19.99 | F6: =INDEX('Price History'!$E$6:$E$72,SUMPRODUCT(MAX(('Price History'!$B$6:$B$72="Disney+")*('Price History'!$C$6:$C$72="Basic w/ ads")*('Price History'!$D$6:$D$72<=DATE(2026,7,29))*ROW('Price History'!$E$6:$E$72)))-5)+INDEX('Price History'!$E$6:$E$72,SUMPRODUCT(MAX(('Price History'!$B$6:$B$72="Hulu")*('Price History'!$C$6:$C$72="With ads")*('Price History'!$D$6:$D$72<=DATE(2026,7,29))*ROW('Price History'!$E$6:$E$72)))-5)+INDEX('Price History'!$E$6:$E$72,SUMPRODUCT(MAX(('Price History'!$B$6:$B$72="HBO Max")*('Price History'!$C$6:$C$72="Basic w/ ads")*('Price History'!$D$6:$D$72<=DATE(2026,7,29))*ROW('Price History'!$E$6:$E$72)))-5) -> 34.97 | G6: =1-E6/F6 -> 0.42836717 | H6: hulu.com/disney-hulu-hbomax-bundle | I6: Open to anyone; direct-billed only. Ad-free version is $32.99.
B7: Apple TV / Peacock | C7: Streamer-to-streamer | D7: 45951 | E7: 14.99 | F7: =INDEX('Price History'!$E$6:$E$72,SUMPRODUCT(MAX(('Price History'!$B$6:$B$72="Apple TV")*('Price History'!$C$6:$C$72="Standard (no ads)")*('Price History'!$D$6:$D$72<=DATE(2025,10,21))*ROW('Price History'!$E$6:$E$72)))-5)+INDEX('Price History'!$E$6:$E$72,SUMPRODUCT(MAX(('Price History'!$B$6:$B$72="Peacock")*('Price History'!$C$6:$C$72="Premium w/ ads")*('Price History'!$D$6:$D$72<=DATE(2025,10,21))*ROW('Price History'!$E$6:$E$72)))-5) -> 23.98 | G7: =1-E7/F7 -> 0.37489575 | H7: Company announcements, Oct 2025 | I7: Launch pricing; not re-verified as current.
B8: Xfinity StreamSaver | C8: Cable distributor | D8: 45413 | E8: 15 | F8: =INDEX('Price History'!$E$6:$E$72,SUMPRODUCT(MAX(('Price History'!$B$6:$B$72="Netflix")*('Price History'!$C$6:$C$72="Standard w/ ads")*('Price History'!$D$6:$D$72<=DATE(2024,5,1))*ROW('Price History'!$E$6:$E$72)))-5)+INDEX('Price History'!$E$6:$E$72,SUMPRODUCT(MAX(('Price History'!$B$6:$B$72="Apple TV")*('Price History'!$C$6:$C$72="Standard (no ads)")*('Price History'!$D$6:$D$72<=DATE(2024,5,1))*ROW('Price History'!$E$6:$E$72)))-5)+INDEX('Price History'!$E$6:$E$72,SUMPRODUCT(MAX(('Price History'!$B$6:$B$72="Peacock")*('Price History'!$C$6:$C$72="Premium w/ ads")*('Price History'!$D$6:$D$72<=DATE(2024,5,1))*ROW('Price History'!$E$6:$E$72)))-5) -> 22.97 | G8: =1-E8/F8 -> 0.34697431 | H8: Comcast announcement, May 2024 | I8: Requires an existing Xfinity TV/internet subscription. Launch pricing.
B9: Verizon myPlan: Netflix & HBO Max | C9: Telecom perk | D9: 45261 | E9: 10 | F9: =INDEX('Price History'!$E$6:$E$72,SUMPRODUCT(MAX(('Price History'!$B$6:$B$72="Netflix")*('Price History'!$C$6:$C$72="Standard w/ ads")*('Price History'!$D$6:$D$72<=DATE(2023,12,1))*ROW('Price History'!$E$6:$E$72)))-5)+INDEX('Price History'!$E$6:$E$72,SUMPRODUCT(MAX(('Price History'!$B$6:$B$72="HBO Max")*('Price History'!$C$6:$C$72="Basic w/ ads")*('Price History'!$D$6:$D$72<=DATE(2023,12,1))*ROW('Price History'!$E$6:$E$72)))-5) -> 16.98 | G9: =1-E9/F9 -> 0.41107185 | H9: Verizon announcement, Dec 2023 | I9: Perk requires an eligible myPlan line. Launch pricing.
B10: Verizon myPlan: Disney bundle | C10: Telecom perk | D10: 45261 | E10: 10 | F10: =INDEX('Price History'!$E$6:$E$72,SUMPRODUCT(MAX(('Price History'!$B$6:$B$72="Disney+")*('Price History'!$C$6:$C$72="Basic w/ ads")*('Price History'!$D$6:$D$72<=DATE(2023,12,1))*ROW('Price History'!$E$6:$E$72)))-5)+INDEX('Price History'!$E$6:$E$72,SUMPRODUCT(MAX(('Price History'!$B$6:$B$72="Hulu")*('Price History'!$C$6:$C$72="With ads")*('Price History'!$D$6:$D$72<=DATE(2023,12,1))*ROW('Price History'!$E$6:$E$72)))-5)+INDEX('Price History'!$E$6:$E$72,SUMPRODUCT(MAX(('Price History'!$B$6:$B$72="ESPN Select")*('Price History'!$C$6:$C$72="Standard w/ ads")*('Price History'!$D$6:$D$72<=DATE(2023,12,1))*ROW('Price History'!$E$6:$E$72)))-5) -> 26.97 | G10: =1-E10/F10 -> 0.62921765 | H10: Verizon announcement, Dec 2023 | I10: Perk requires an eligible myPlan line. Launch pricing.
B11: Median, all five | G11: =MEDIAN(G6:G10) -> 0.41107185
B12: Range | G12: =TEXT(MIN(G6:G10),"0.0%")&" – "&TEXT(MAX(G6:G10),"0.0%") -> 34.7% – 62.9%
B13: Telecom perks (mean) | G13: =AVERAGE(G9:G10) -> 0.52014475
B14: Streamer / distributor (mean) | G14: =AVERAGE(G6:G8) -> 0.38341241
B16: Takeaway
B17: Discounts run from about a third to two thirds off standalone, and they deepen as the distributor moves further from the content. Telecom perks are steepest because the carrier is buying retention on its own subscription rather than the streamer's. These are five different products with different eligibility rules, so read the median and range rather than the mean. Only the top row is verified as current; the others are launch-date snapshots, labeled as such.
B51: Source: Price History tab. Five different products with different eligibility rules, so read the median and range rather than the mean. Only the top row is verified as current.

Sheet Price Event Cadence
B2: Price-Change Cadence
B3: Counts are COUNTIFS over Price History: rows of Event type "Change", by calendar year. A tier's first observed price is a Baseline and is excluded. Because the tracked tier count grows over time, changes per active tier is the comparable series.
B5: Year | C5: # price changes | D5: Active tiers | E5: Changes per tier | F5: Notable moves
B6: 2020 | C6: =COUNTIFS('Price History'!$F$6:$F$72,"Change",'Price History'!$D$6:$D$72,">="&DATE(2020,1,1),'Price History'!$D$6:$D$72,"<="&DATE(2020,12,31)) -> 3 | D6: =COUNT(Panel!F6:F19) -> 9 | E6: =IFERROR(C6/D6,"—") -> 0.33333333 | F6: Netflix; ESPN+ first increase
B7: 2021 | C7: =COUNTIFS('Price History'!$F$6:$F$72,"Change",'Price History'!$D$6:$D$72,">="&DATE(2021,1,1),'Price History'!$D$6:$D$72,"<="&DATE(2021,12,31)) -> 3 | D7: =COUNT(Panel!G6:G19) -> 12 | E7: =IFERROR(C7/D7,"—") -> 0.25 | F7: Disney+ to $7.99; Hulu ad tier; ESPN+
B8: 2022 | C8: =COUNTIFS('Price History'!$F$6:$F$72,"Change",'Price History'!$D$6:$D$72,">="&DATE(2022,1,1),'Price History'!$D$6:$D$72,"<="&DATE(2022,12,31)) -> 7 | D8: =COUNT(Panel!H6:H19) -> 14 | E8: =IFERROR(C8/D8,"—") -> 0.5 | F8: Netflix; Hulu both tiers; Apple TV; ESPN+ +43%; Disney+ Premium repriced alongside its ad-tier launch
B9: 2023 | C9: =COUNTIFS('Price History'!$F$6:$F$72,"Change",'Price History'!$D$6:$D$72,">="&DATE(2023,1,1),'Price History'!$D$6:$D$72,"<="&DATE(2023,12,31)) -> 10 | D9: =COUNT(Panel!I6:I19) -> 14 | E9: =IFERROR(C9/D9,"—") -> 0.71428571 | F9: Disney+ and Hulu October round; HBO Max first increase; Peacock first increase; Paramount+ with SHOWTIME; Apple TV; Netflix Premium
B10: 2024 | C10: =COUNTIFS('Price History'!$F$6:$F$72,"Change",'Price History'!$D$6:$D$72,">="&DATE(2024,1,1),'Price History'!$D$6:$D$72,"<="&DATE(2024,12,31)) -> 10 | D10: =COUNT(Panel!J6:J19) -> 14 | E10: =IFERROR(C10/D10,"—") -> 0.71428571 | F10: Disney+ and Hulu; HBO Max; Peacock both tiers; Paramount+ both tiers; ESPN+
B11: 2025 | C11: =COUNTIFS('Price History'!$F$6:$F$72,"Change",'Price History'!$D$6:$D$72,">="&DATE(2025,1,1),'Price History'!$D$6:$D$72,"<="&DATE(2025,12,31)) -> 12 | D11: =COUNT(Panel!K6:K19) -> 14 | E11: =IFERROR(C11/D11,"—") -> 0.85714286 | F11: Netflix all tiers; Disney+ and Hulu ad tiers; HBO Max all tiers; Peacock +$3; Apple TV +30%; ESPN Select rebrand
B12: 2026 | C12: =COUNTIFS('Price History'!$F$6:$F$72,"Change",'Price History'!$D$6:$D$72,">="&DATE(2026,1,1),'Price History'!$D$6:$D$72,"<="&DATE(2026,12,31)) -> 5 | D12: =COUNT(Panel!L6:L19) -> 14 | E12: =IFERROR(C12/D12,"—") -> 0.35714286 | F12: Netflix all tiers (Mar); Paramount+ both tiers (Jan) — year-to-date through July
B13: Total | C13: =SUM(C6:C12) -> 50
B15: 2026 covers seven months of twelve. Five changes to 29 July annualizes to roughly nine, which puts it in line with 2025 rather than below it, so the fall at the right edge is a partial year and not a slowdown. Changes per active tier controls for the panel widening as services added tiers. On that basis the acceleration from 2021 to 2025 is smaller than the raw count implies, but still clear.
B49: Source: Price History tab, COUNTIFS on rows of Event type "Change". 2026 is year-to-date through July. See changes per active tier for the series adjusted for panel width.

Sheet Subscriber & ARPU
B2: Subscriber & ARPU — Reported Figures Only
B3: Reported values with the scope of each metric recorded, because subscriber and ARPU definitions differ by company. These figures feed no calculation elsewhere in this workbook and are not charted as a panel. n/d means not disclosed and is never filled with an estimate.
B5: Service | C5: Period | D5: Subs (M) | E5: ARPU $/mo | F5: Scope | G5: Type | H5: Note
B6: Netflix | C6: Q3 2023 | D6: 247.15 | E6: n/d | F6: Global paid subs | G6: Reported | H6: +8.76M in the quarter
B7: Netflix | C7: Q4 2024 | D7: 301.6 | E7: 17.26 | F7: Global paid subs; US/Can ARPU | G7: Reported | H7: Last disclosure before reporting was discontinued
B8: Netflix | C8: Q2 2025 | D8: n/d | E8: n/d | F8: — | G8: Not disclosed | H8: No longer reports subscribers or ARPU
B9: Disney+ | C9: Q1 2024 | D9: 117.6 | E9: 7.28 | F9: Core Disney+ global; global ARPU | G9: Reported
B10: Disney+ | C10: Q1 2025 | D10: n/d | E10: 8.09 | F10: Domestic ARPU | G10: Reported | H10: Not comparable with the global figure above
B11: Disney+ | C11: Q2 2025 | D11: n/d | E11: 7.99 | F11: Domestic ARPU | G11: Reported | H11: Subscriber reporting ends from Q1 FY26
B12: HBO Max | C12: Q4 2023 | D12: 97.7 | E12: n/d | F12: Global paid subs | G12: Reported | H12: Blended with legacy linear HBO
B13: HBO Max | C13: Q1 2024 | D13: 99.6 | E13: n/d | F13: Global paid subs | G13: Reported
B14: HBO Max | C14: Q4 2024 | D14: n/d | E14: 11.77 | F14: Global ARPU | G14: Reported
B15: Peacock | C15: Q1 2023 | D15: 22 | E15: n/d | F15: US paid subs | G15: Reported | H15: +60% YoY
B16: Peacock | C16: Q4 2023 | D16: 31 | E16: 10 | F16: US paid subs; US ARPU | G16: Reported
B17: Peacock | C17: Q2 2025 | D17: 41 | E17: n/d | F17: US paid subs | G17: Reported | H17: Flat in a seasonally light quarter
B18: Paramount+ | C18: Q4 2023 | D18: 67.5 | E18: n/d | F18: Global subs | G18: Reported | H18: +11.6M across 2023
B19: Paramount+ | C19: Q2 2025 | D19: 77.7 | E19: n/d | F19: Global subs | G19: Reported | H19: −1.3M on international hard-bundle expiry
B20: Paramount+ | C20: Q3 2025 | D20: 79.1 | E20: n/d | F20: Global subs | G20: Reported | H20: Per Q3 2025 shareholder letter
B21: Apple TV | C21: — | D21: n/d | E21: n/d | F21: — | G21: Not disclosed | H21: Apple has never reported subscribers or ARPU
B22: Amazon Prime Video | C22: — | D22: n/d | E22: n/d | F22: — | G22: Not comparable | H22: Not a standalone subscription; no equivalent figure exists
B24: Takeaway
B25: The observable picture is thinning as the category consolidates. Netflix stopped reporting after Q4 2024, Disney is winding down subscriber disclosure, and Apple and Amazon have never disclosed at all. What remains is not a panel: global subscribers sit beside domestic ARPU, definitions of a paid subscriber differ by company, and bundle subscribers are attributed inconsistently. That is why these rows carry their scope, stay out of every calculation, and are not charted. Price is public, dated and verifiable, which is why the analysis anchors there instead.

Sheet CPI Deflator
B2: CPI Deflator — BLS CPI-U
B3: U.S. city average, all items, annual averages, rebased to 2019 = 100. Values through 2024 are published annual averages. 2025 and 2026 are provisional and shaded, so read the note below before quoting any real figure to two decimal places.
B5: Year | C5: CPI-U | D5: Index (2019=100) | E5: Status | F5: Note
B6: 2019 | C6: 255.657 | D6: =C6/$C$6*100 -> 100 | E6: Published | F6: Published BLS annual average
B7: 2020 | C7: 258.811 | D7: =C7/$C$6*100 -> 101.23368 | E7: Published | F7: Published BLS annual average
B8: 2021 | C8: 270.97 | D8: =C8/$C$6*100 -> 105.98967 | E8: Published | F8: Published BLS annual average
B9: 2022 | C9: 292.655 | D9: =C9/$C$6*100 -> 114.47173 | E9: Published | F9: Published BLS annual average (40-year-high inflation)
B10: 2023 | C10: 304.702 | D10: =C10/$C$6*100 -> 119.18391 | E10: Published | F10: Published BLS annual average
B11: 2024 | C11: 313.689 | D11: =C11/$C$6*100 -> 122.69916 | E11: Published | F11: Published BLS annual average
B12: 2025 | C12: 323.1 | D12: =C12/$C$6*100 -> 126.38027 | E12: Provisional | F12: Provisional. BLS did not publish an October 2025 index owing to the appropriations lapse, so a 2025 annual average is non-standard. Verify against the BLS annual-average table before publication.
B13: 2026 | C13: 333.4 | D13: =C13/$C$6*100 -> 130.4091 | E13: Provisional | F13: Provisional. Year-to-date only — not an annual average. Real 2026 figures are indicative.
B14: 2018 | C14: 251.107 | D14: =C14/$C$6*100 -> 98.220272 | E14: Published | F14: Needed to deflate the ESPN+ 2018 launch price
B16: Sensitivity: an independent review puts the 2025 annual average at 321.943 rather than the 323.100 used here. Substituting it moves the average real price change by under one percentage point and changes no conclusion on any tab. The 2025 and 2026 cells are the only two inputs on this tab that are not published annual averages; both are shaded, and every real figure in the workbook flows from them, so they are the first cells to update when BLS publishes.

Sheet Audit Log
B2: Data Quality Audit | H2: Summary
B3: Output of the RunDataAudit macro over 67 price points, as-of 29 Jul 2026. Press Alt+F8 and run RunDataAudit to regenerate this sheet with a live timestamp. | H3: Price points | I3: 67
H4: Rows with a source URL | I4: 67
H5: Rows with no URL | I5: 0
B6: Issue | C6: Service / sheet | D6: Tier / detail | E6: Note | F6: Row | H6: Medium confidence | I6: 7
B7: Medium confidence | C7: ESPN Select | D7: Standard w/ ads | E7: Corroborated from later reporting rather than a contemporaneous announcement | F7: 23 | H7: Possibly stale current price | I7: 0
B8: Medium confidence | C8: ESPN Select | D8: Standard w/ ads | E8: Corroborated from later reporting rather than a contemporaneous announcement | F8: 24 | H8: Bad dates | I8: 0
B9: Medium confidence | C9: Hulu | D9: No ads | E9: Corroborated from later reporting rather than a contemporaneous announcement | F9: 33 | H9: Bad prices | I9: 0
B10: Medium confidence | C10: Hulu | D10: With ads | E10: Corroborated from later reporting rather than a contemporaneous announcement | F10: 37 | H10: Duplicate service+tier+date | I10: 0
B11: Medium confidence | C11: Hulu | D11: With ads | E11: Corroborated from later reporting rather than a contemporaneous announcement | F11: 38 | H11: Formula errors | I11: 0
B12: Medium confidence | C12: Paramount+ | D12: Essential w/ ads | E12: Corroborated from later reporting rather than a contemporaneous announcement | F12: 57
B13: Medium confidence | C13: Paramount+ | D13: Premium (no ads) | E13: Corroborated from later reporting rather than a contemporaneous announcement | F13: 61

Sheet Methodology
B2: Methodology, Limitations & Changelog
B3: How every figure is constructed, what it cannot support, and what changed across two revisions.
B5: Universe | C5: Eight U.S. subscription services: Netflix, Disney+, Hulu, HBO Max, Peacock, Paramount+, Apple TV and ESPN Select. Amazon Prime Video is excluded — it has no standalone comparable price.
B6: Price definition | C6: U.S. list price, monthly, USD, new direct subscriber. Excludes annual, promotional, student, partner and app-store pricing, taxes and fees.
B7: Flagship tier | C7: The ad-free consumer plan. ESPN Select has never offered one, so its single ad-supported tier is used and it is excluded from every ad-free average.
B8: Model architecture | C8: Price History is the only table with typed prices. The Panel derives year-end prices from it by formula; Price Analysis, Ad vs No-Ad, Bundles, Cadence and the Dashboard all read from those two. Changing a price or the as-of date updates every downstream figure.
B9: CAGR | C9: (P_end / P_start)^(1/years) − 1, with years from YEARFRAC on true date values. Windows differ by service; mean, median, range and n are reported together, and a common 2022–2026 window is provided for like-for-like comparison.
B10: Real terms | C10: Each endpoint is divided by the CPI-U index of its own period before comparison. 2025 and 2026 CPI inputs are provisional and flagged on that tab.
B11: Averages | C11: Unweighted means, with medians alongside. No subscriber weighting is applied because subscriber counts are not disclosed consistently enough to build one. These describe the price set on offer, not the price the average subscriber pays.
B12: What this cannot support | C12: No churn, retention, elasticity, ad ARPU, engagement or margin data is used anywhere. Statements about retention or profitability are labeled as hypotheses on the Dashboard, not findings. Bundles and promotions mean a growing share of subscribers never pays list price.
B13: Revision 2.0 — architecture | C13: Dates converted to true date values; elapsed years now computed with YEARFRAC rather than typed. New Panel tab derives every year-end price from Price History by formula. Ad-tier averages, cadence counts, bundle standalone sums and the record count are now derived, not typed. A single as-of date cell governs all current-price comparisons.
B14: Revision 2.0 — evidence | C14: Source URLs and publication dates added where captured; rows without a URL are flagged and are never an endpoint used in the analysis. Bundle rows carry eligibility conditions and an as-of date. Subscriber rows carry the scope of each metric. Analyst estimates removed from a sheet that claims to hold reported figures only.
B15: Revision 2.0 — claims | C15: 'Genuine pricing power', 'sustainable pricing' and 'loss-leader normalization' softened to what the data shows. Findings, observations and hypotheses are now visually separated on the Dashboard. Median and range accompany every mean.
B16: Revision 1.0 — corrections | C16: Current prices re-verified: HBO Max Standard $18.49 (Oct 2025, not $17.99); Disney+ Premium $18.99 effective Oct 2025; Paramount+ Premium $13.99 (Jan 2026, not $12.99); ESPN Select $12.99 (Oct 2025, not $11.99); Peacock Premium w/ ads $10.99 (Jul 2025, not $8.99). Netflix's 2011 streaming-only price removed as a baseline. The series now starts Jan 2019, so its CAGR is no longer a 15-year figure presented as seven.
B17: Revision 1.0 — corrections | C17: Real-price method corrected to deflate both endpoints. ESPN Select removed from the ad-free cohort. Launch prices for Peacock Premium Plus and Paramount+ Premium, previously used in analysis without appearing in the price table, added as sourced rows. The claim that the ad/no-ad gap 'roughly doubled' was false on the workbook's own figures and is removed; rebuilding the averages from the panel reversed the finding. A claim that the slowest riser outpaced wage growth was removed. No wage series is used here, and HBO Max in fact trailed both CPI and average hourly earnings.
